Workbook

Sheet 提出物チェックリスト
A2: 自主点検 提出物チェックリスト（構成単位版）
A3: ■ 会社名: ________________________ ■ 実施期: ______________ ■ サイクル (年度末 / 四半期): __________ ■ 記入者: ________________________
A4: 【凡例】 ☑提出 → □ を記入 / 対象外・未実施 → 「該当なし」に □ 記入し、理由を記述のうえ提出可。全行チェックは必須ではありません。
A6: No | B6: 項目No | C6: 点検項目名 | D6: 提出物名 | E6: 提出物詳細 | F6: 区分 | G6: 提出区分 | H6: 適用の目安 （条件付き・代替・排他の場合） | I6: 年度末 | J6: 四半期 | K6: ☑提出 | L6: 該当なし | M6: 非該当・未提出の理由 | N6: 格納先フォルダパス | O6: 一次ソース | P6: 備考
A7: 1 | B7: 1 | C7: 売掛金の残高確認 | D7: 残高確認状の回収結果・差異調整結果 | F7: ①成果物本体 | G7: 必須 | I7: ○ | K7: □ | L7: □ | N7: 01_監査対応/[会社名]/05_自主点検成果物/01_残高確認状 | O7: input/01_監査対応_自主点検成果物_ファイルリスト_filtered.xlsx（構成単位・2026年3月期）
A8: 2 | B8: 1 | C8: 売掛金の残高確認 | D8: 代替手続実施結果 | E8: 代替手続チェックリスト・入金消込管理表の検証資料 | F8: ①成果物本体 | G8: 条件付き | H8: 確認状を回収できない/発送しない相手先(個人・官公庁等)がある場合 | I8: ○ | K8: □ | L8: □ | N8: 01_監査対応/[会社名]/05_自主点検成果物/01_残高確認状 | O8: input/01_監査対応_自主点検成果物_ファイルリスト_filtered.xlsx（構成単位・2026年3月期）
A9: 3 | B9: 1 | C9: 売掛金の残高確認 | D9: 追加サンプリング結果 | F9: ②根拠資料 | G9: 条件付き | H9: 2026年6月以降入金予定の3月末売掛金残高が閾値以上 | I9: ○ | K9: □ | L9: □ | N9: 01_監査対応/[会社名]/05_自主点検成果物/01_残高確認状 | O9: input/01_監査対応_自主点検成果物_ファイルリスト_filtered.xlsx（構成単位・2026年3月期）
A10: 4 | B10: 1 | C10: 売掛金の残高確認 | D10: 売掛金明細 | E10: 2026年3月末 | F10: ③共通添付 | G10: 必須 | I10: ○ | K10: □ | L10: □ | N10: 01_監査対応/[会社名]/05_自主点検成果物/01_残高確認状 | O10: input/01_監査対応_自主点検成果物_ファイルリスト_filtered.xlsx（構成単位・2026年3月期）
A11: 5 | B11: 1 | C11: 売掛金の残高確認 | D11: 試算表＋連結PKGまでの調整 | E11: 3月末 | F11: ③共通添付 | G11: 必須 | I11: ○ | K11: □ | L11: □ | N11: 01_監査対応/[会社名]/05_自主点検成果物/01_残高確認状 | O11: input/01_監査対応_自主点検成果物_ファイルリスト_filtered.xlsx（構成単位・2026年3月期）
A12: 6 | B12: 2 | C12: 在庫の実地棚卸 | D12: 実地棚卸の結果 | E12: 別途ガイダンスに従い提出 | F12: ①成果物本体 | G12: 必須 | I12: ○ | K12: □ | L12: □ | N12: 01_監査対応/[会社名]/05_自主点検成果物/02_在庫の実地棚卸 | O12: input/01_監査対応_自主点検成果物_ファイルリスト_filtered.xlsx（構成単位・2026年3月期）
A13: 7 | B13: 2 | C13: 在庫の実地棚卸 | D13: 預り売上に関する親会社への情報・検討内容 | F13: ①成果物本体 | G13: 条件付き | H13: 預り売上(請求済未出荷)を計上している場合(原則禁止) | I13: ○ | K13: □ | L13: □ | N13: 01_監査対応/[会社名]/05_自主点検成果物/02_在庫の実地棚卸 | O13: input/01_監査対応_自主点検成果物_ファイルリスト_filtered.xlsx（構成単位・2026年3月期）
A14: 8 | B14: 3 | C14: 固定資産の実査 | D14: 固定資産実査報告書 | E14: 確定版:エクセル＋部署長検印済PDF | F14: ①成果物本体 | G14: 必須 | I14: ○ | K14: □ | L14: □ | N14: 01_監査対応/[会社名]/05_自主点検成果物/03_固定資産実査 | O14: input/01_監査対応_自主点検成果物_ファイルリスト_filtered.xlsx（構成単位・2026年3月期）
A15: 9 | B15: 3 | C15: 固定資産の実査 | D15: 現物照合の写真 | F15: ②根拠資料 | G15: 必須 | I15: ○ | K15: □ | L15: □ | N15: 01_監査対応/[会社名]/05_自主点検成果物/03_固定資産実査 | O15: input/01_監査対応_自主点検成果物_ファイルリスト_filtered.xlsx（構成単位・2026年3月期）
A16: 10 | B16: 3 | C16: 固定資産の実査 | D16: 代替証跡 | E16: 登記簿・リース契約書・使用実績資料等 | F16: ②根拠資料 | G16: 代替 | H16: 現物カウントが困難な資産がある場合 | I16: ○ | K16: □ | L16: □ | N16: 01_監査対応/[会社名]/05_自主点検成果物/03_固定資産実査 | O16: input/01_監査対応_自主点検成果物_ファイルリスト_filtered.xlsx（構成単位・2026年3月期）
A17: 11 | B17: 3 | C17: 固定資産の実査 | D17: 固定資産訂正仕訳が必要な資産の報告書 | F17: ①成果物本体 | G17: 条件付き | H17: 現物照合で訂正(除却漏れ・資産性等)が発覚した場合 | I17: ○ | K17: □ | L17: □ | N17: 01_監査対応/[会社名]/05_自主点検成果物/03_固定資産実査 | O17: input/01_監査対応_自主点検成果物_ファイルリスト_filtered.xlsx（構成単位・2026年3月期）
A18: 12 | B18: 3 | C18: 固定資産の実査 | D18: 修正仕訳のエビデンス | E18: Proplusモニターシート・Biz∫仕訳 | F18: ②根拠資料 | G18: 条件付き | H18: 修正仕訳を起票した場合 | I18: ○ | K18: □ | L18: □ | N18: 01_監査対応/[会社名]/05_自主点検成果物/03_固定資産実査 | O18: input/01_監査対応_自主点検成果物_ファイルリスト_filtered.xlsx（構成単位・2026年3月期）
A19: 13 | B19: 3 | C19: 固定資産の実査 | D19: 独立立会人による実査立会結果 | F19: ①成果物本体 | G19: 条件付き | H19: 第2線立会対象(規模条件) | I19: ○ | K19: □ | L19: □ | N19: 01_監査対応/[会社名]/05_自主点検成果物/03_固定資産実査 | O19: input/01_監査対応_自主点検成果物_ファイルリスト_filtered.xlsx（構成単位・2026年3月期）
A20: 14 | B20: 4 | C20: 滞留債権の分析 | D20: 期末滞留債権一覧 | E20: 回収遅延理由・最新回収予定日 | F20: ①成果物本体 | G20: 必須 | I20: ○ | J20: ○ | K20: □ | L20: □ | N20: 01_監査対応/[会社名]/05_自主点検成果物/04_滞留債権 | O20: input/01_監査対応_自主点検成果物_ファイルリスト_filtered.xlsx（構成単位・2026年3月期）
A21: 15 | B21: 4 | C21: 滞留債権の分析 | D21: 売掛金明細・試算表の一致 | E21: データソース・抽出条件 | F21: ③共通添付 | G21: 必須 | I21: ○ | J21: ○ | K21: □ | L21: □ | N21: 01_監査対応/[会社名]/05_自主点検成果物/04_滞留債権 | O21: input/01_監査対応_自主点検成果物_ファイルリスト_filtered.xlsx（構成単位・2026年3月期）
A22: 16 | B22: 4 | C22: 滞留債権の分析 | D22: 回収遅延理由の承認証跡 | F22: ②根拠資料 | G22: 代替 | H22: 部門責任者等の承認(チェックリスト承認で代替可) | I22: ○ | J22: ○ | K22: □ | L22: □ | N22: 01_監査対応/[会社名]/05_自主点検成果物/04_滞留債権 | O22: input/01_監査対応_自主点検成果物_ファイルリスト_filtered.xlsx（構成単位・2026年3月期）
A23: 17 | B23: 4 | C23: 滞留債権の分析 | D23: 外部証憑 | E23: 契約書・注文書・納品書 等 | F23: ②根拠資料 | G23: 条件付き | H23: 回収遅延理由が合理的でない債権がある場合 | I23: ○ | J23: ○ | K23: □ | L23: □ | N23: 01_監査対応/[会社名]/05_自主点検成果物/04_滞留債権 | O23: input/01_監査対応_自主点検成果物_ファイルリスト_filtered.xlsx（構成単位・2026年3月期）
A24: 18 | B24: 5 | C24: 異常取引の分析 | D24: 年間取引データ | E24: 取引先別・案件別ソート,マイナス理由記載 | F24: ①成果物本体 | G24: 必須 | I24: ○ | J24: ○ | K24: □ | L24: □ | N24: 01_監査対応/[会社名]/05_自主点検成果物/05_売上マイナスデータ・取り消し仕訳 | O24: input/01_監査対応_自主点検成果物_ファイルリスト_filtered.xlsx（構成単位・2026年3月期）
A25: 19 | B25: 5 | C25: 異常取引の分析 | D25: 翌期4月分の二次提出データ | F25: ①成果物本体 | G25: 必須 | I25: ○ | J25: ○ | K25: □ | L25: □ | N25: 01_監査対応/[会社名]/05_自主点検成果物/05_売上マイナスデータ・取り消し仕訳 | O25: input/01_監査対応_自主点検成果物_ファイルリスト_filtered.xlsx（構成単位・2026年3月期）
A26: 20 | B26: 5 | C26: 異常取引の分析 | D26: データソース・抽出条件 | E26: 全明細と試算表の一致 | F26: ③共通添付 | G26: 必須 | I26: ○ | J26: ○ | K26: □ | L26: □ | N26: 01_監査対応/[会社名]/05_自主点検成果物/05_売上マイナスデータ・取り消し仕訳 | O26: input/01_監査対応_自主点検成果物_ファイルリスト_filtered.xlsx（構成単位・2026年3月期）
A27: 21 | B27: 5 | C27: 異常取引の分析 | D27: マイナス取引の根拠資料 | E27: ①計上妥当②取消妥当 | F27: ②根拠資料 | G27: 条件付き | H27: 2次レビューで確認が必要な取引 | I27: ○ | J27: ○ | K27: □ | L27: □ | N27: 01_監査対応/[会社名]/05_自主点検成果物/05_売上マイナスデータ・取り消し仕訳 | O27: input/01_監査対応_自主点検成果物_ファイルリスト_filtered.xlsx（構成単位・2026年3月期）
A28: 22 | B28: 6 | C28: 売上の期末変動分析 | D28: 月次の売上・粗利推移データ | E28: グラフ・増減分析コメント | F28: ①成果物本体 | G28: 必須 | I28: ○ | J28: ○ | K28: □ | L28: □ | N28: 01_監査対応/[会社名]/05_自主点検成果物/06_売上・粗利月次推移分析 | O28: input/01_監査対応_自主点検成果物_ファイルリスト_filtered.xlsx（構成単位・2026年3月期）
A29: 23 | B29: 6 | C29: 売上の期末変動分析 | D29: データソース・抽出条件 | E29: 試算表との一致 | F29: ③共通添付 | G29: 必須 | I29: ○ | J29: ○ | K29: □ | L29: □ | N29: 01_監査対応/[会社名]/05_自主点検成果物/06_売上・粗利月次推移分析 | O29: input/01_監査対応_自主点検成果物_ファイルリスト_filtered.xlsx（構成単位・2026年3月期）
A30: 24 | B30: 6 | C30: 売上の期末変動分析 | D30: 増減要因の根拠証憑 | F30: ②根拠資料 | G30: 条件付き | H30: 四半期末月に上昇傾向・重要変動がある場合 | I30: ○ | J30: ○ | K30: □ | L30: □ | N30: 01_監査対応/[会社名]/05_自主点検成果物/06_売上・粗利月次推移分析 | O30: input/01_監査対応_自主点検成果物_ファイルリスト_filtered.xlsx（構成単位・2026年3月期）
A31: 25 | B31: 7 | C31: 収益認識アンケート（証憑提出含む） | D31: 収益認識アンケート回答 | E31: SPファイル直接更新/メール返信 | F31: ①成果物本体 | G31: 必須 | I31: ○ | J31: ○ | K31: □ | L31: □ | N31: 01_監査対応/[会社名]/05_自主点検成果物/07_収益認識アンケート | O31: input/01_監査対応_自主点検成果物_ファイルリスト_filtered.xlsx（構成単位・2026年3月期）
A32: 26 | B32: 7 | C32: 収益認識アンケート（証憑提出含む） | D32: 契約書PDF | E32: 取引基本契約書等 | F32: ②根拠資料 | G32: 条件付き | H32: 年間売上金額が閾値以上の取引(半期提出済は再提出不要) | I32: ○ | J32: ○ | K32: □ | L32: □ | N32: 01_監査対応/[会社名]/05_自主点検成果物/07_収益認識アンケート | O32: input/01_監査対応_自主点検成果物_ファイルリスト_filtered.xlsx（構成単位・2026年3月期）
A33: 27 | B33: 7 | C33: 収益認識アンケート（証憑提出含む） | D33: 当期の売上明細データ | E33: 試算表との一致を事前確認 | F33: ③共通添付 | G33: 必須 | I33: ○ | J33: ○ | K33: □ | L33: □ | N33: 01_監査対応/[会社名]/05_自主点検成果物/07_収益認識アンケート | O33: input/01_監査対応_自主点検成果物_ファイルリスト_filtered.xlsx（構成単位・2026年3月期）
A34: 28 | B34: 8 | C34: 売上のカットオフテスト | D34: 売上明細データ | E34: 検証結果コメント付 | F34: ①成果物本体 | G34: 必須 | I34: ○ | J34: ○ | K34: □ | L34: □ | N34: 01_監査対応/[会社名]/05_自主点検成果物/08_売上明細データ | O34: input/01_監査対応_自主点検成果物_ファイルリスト_filtered.xlsx（構成単位・2026年3月期）
A35: 29 | B35: 8 | C35: 売上のカットオフテスト | D35: データソース・抽出条件 | E35: 3月単月の試算表一致 | F35: ③共通添付 | G35: 必須 | I35: ○ | J35: ○ | K35: □ | L35: □ | N35: 01_監査対応/[会社名]/05_自主点検成果物/08_売上明細データ | O35: input/01_監査対応_自主点検成果物_ファイルリスト_filtered.xlsx（構成単位・2026年3月期）
A36: 30 | B36: 8 | C36: 売上のカットオフテスト | D36: 収益認識の根拠資料 | F36: ②根拠資料 | G36: 条件付き | H36: 一定金額以上の取引に限る | I36: ○ | J36: ○ | K36: □ | L36: □ | N36: 01_監査対応/[会社名]/05_自主点検成果物/08_売上明細データ | O36: input/01_監査対応_自主点検成果物_ファイルリスト_filtered.xlsx（構成単位・2026年3月期）
A37: 31 | B37: 9 | C37: 長期請負工事案件の洗い出し | D37: 進行基準適用案件リスト | E37: 履行義務毎の判断根拠 | F37: ①成果物本体 | G37: 必須 | I37: ○ | J37: ○ | K37: □ | L37: □ | N37: 01_監査対応/[会社名]/05_自主点検成果物/09_工事案件の収益認識会計基準あてはめ | O37: input/01_監査対応_自主点検成果物_ファイルリスト_filtered.xlsx（構成単位・2026年3月期）
A38: 32 | B38: 9 | C38: 長期請負工事案件の洗い出し | D38: データソース・抽出条件 | E38: PKG進行基準売上との一致 | F38: ③共通添付 | G38: 必須 | I38: ○ | J38: ○ | K38: □ | L38: □ | N38: 01_監査対応/[会社名]/05_自主点検成果物/09_工事案件の収益認識会計基準あてはめ | O38: input/01_監査対応_自主点検成果物_ファイルリスト_filtered.xlsx（構成単位・2026年3月期）
A39: 33 | B39: 9 | C39: 長期請負工事案件の洗い出し | D39: 契約書 | E39: 請負高5億円超の案件 | F39: ②根拠資料 | G39: 条件付き | H39: 請負高が閾値超の案件(No.7で提出済を確認) | I39: ○ | J39: ○ | K39: □ | L39: □ | N39: 01_監査対応/[会社名]/05_自主点検成果物/09_工事案件の収益認識会計基準あてはめ | O39: input/01_監査対応_自主点検成果物_ファイルリスト_filtered.xlsx（構成単位・2026年3月期）
A40: 34 | B40: 10 | C40: 実行予算の取得・確認 | D40: 進行基準適用案件毎の実行予算 月次推移 | E40: グラフ・増減コメント | F40: ①成果物本体 | G40: 必須 | I40: ○ | J40: ○ | K40: □ | L40: □ | N40: 01_監査対応/[会社名]/05_自主点検成果物/10_工事案件実効予算分析 | O40: input/01_監査対応_自主点検成果物_ファイルリスト_filtered.xlsx（構成単位・2026年3月期）
A41: 35 | B41: 10 | C41: 実行予算の取得・確認 | D41: データソース・抽出条件 | E41: No.9リストとの整合 | F41: ③共通添付 | G41: 必須 | I41: ○ | J41: ○ | K41: □ | L41: □ | N41: 01_監査対応/[会社名]/05_自主点検成果物/10_工事案件実効予算分析 | O41: input/01_監査対応_自主点検成果物_ファイルリスト_filtered.xlsx（構成単位・2026年3月期）
A42: 36 | B42: 11 | C42: 材料費の実際発生原価の確認 | D42: 原材料購買データと入庫データの月次比較表 | F42: ①成果物本体 | G42: 必須 | I42: ○ | J42: ○ | K42: □ | L42: □ | N42: 01_監査対応/[会社名]/05_自主点検成果物/11_工事案件購買・原材料入出庫分析 | O42: input/01_監査対応_自主点検成果物_ファイルリスト_filtered.xlsx（構成単位・2026年3月期）
A43: 37 | B43: 11 | C43: 材料費の実際発生原価の確認 | D43: 工事案件原価明細と出庫データの紐づけ | E43: 案件毎シート | F43: ①成果物本体 | G43: 必須 | I43: ○ | J43: ○ | K43: □ | L43: □ | N43: 01_監査対応/[会社名]/05_自主点検成果物/11_工事案件購買・原材料入出庫分析 | O43: input/01_監査対応_自主点検成果物_ファイルリスト_filtered.xlsx（構成単位・2026年3月期）
A44: 38 | B44: 11 | C44: 材料費の実際発生原価の確認 | D44: 差異取引の外部根拠証憑 | F44: ②根拠資料 | G44: 条件付き | H44: 入出庫と整合しない購買・原価明細がある場合 | I44: ○ | J44: ○ | K44: □ | L44: □ | N44: 01_監査対応/[会社名]/05_自主点検成果物/11_工事案件購買・原材料入出庫分析 | O44: input/01_監査対応_自主点検成果物_ファイルリスト_filtered.xlsx（構成単位・2026年3月期）
A45: 39 | B45: 12 | C45: 進捗率の算定根拠の確認 | D45: 進行基準適用案件毎の進捗率 月次推移表 | E45: 要因コメント | F45: ①成果物本体 | G45: 必須 | I45: ○ | J45: ○ | K45: □ | L45: □ | N45: 01_監査対応/[会社名]/05_自主点検成果物/12_工事案件進捗率分析 | O45: input/01_監査対応_自主点検成果物_ファイルリスト_filtered.xlsx（構成単位・2026年3月期）
A46: 40 | B46: 12 | C46: 進捗率の算定根拠の確認 | D46: 進捗率の算定根拠資料 | E46: 実行予算書・原価明細 | F46: ②根拠資料 | G46: 必須 | I46: ○ | J46: ○ | K46: □ | L46: □ | N46: 01_監査対応/[会社名]/05_自主点検成果物/12_工事案件進捗率分析 | O46: input/01_監査対応_自主点検成果物_ファイルリスト_filtered.xlsx（構成単位・2026年3月期）
A47: 41 | B47: 12 | C47: 進捗率の算定根拠の確認 | D47: データソース・抽出条件 | E47: No.9整合 | F47: ③共通添付 | G47: 必須 | I47: ○ | J47: ○ | K47: □ | L47: □ | N47: 01_監査対応/[会社名]/05_自主点検成果物/12_工事案件進捗率分析 | O47: input/01_監査対応_自主点検成果物_ファイルリスト_filtered.xlsx（構成単位・2026年3月期）
A48: 42 | B48: 13 | C48: 経費の実際発生原価の確認 | D48: 滞留未成工事支出金一覧 | E48: 滞留要因・初回原価発生日・振替予定日 | F48: ①成果物本体 | G48: 必須 | I48: ○ | J48: ○ | K48: □ | L48: □ | N48: 01_監査対応/[会社名]/05_自主点検成果物/13_未成工事支出金滞留チェック | O48: input/01_監査対応_自主点検成果物_ファイルリスト_filtered.xlsx（構成単位・2026年3月期）
A49: 43 | B49: 13 | C49: 経費の実際発生原価の確認 | D49: データソース・抽出条件 | E49: 試算表との一致 | F49: ③共通添付 | G49: 必須 | I49: ○ | J49: ○ | K49: □ | L49: □ | N49: 01_監査対応/[会社名]/05_自主点検成果物/13_未成工事支出金滞留チェック | O49: input/01_監査対応_自主点検成果物_ファイルリスト_filtered.xlsx（構成単位・2026年3月期）
A50: 44 | B50: 13 | C50: 経費の実際発生原価の確認 | D50: 滞留要因の根拠証憑 | F50: ②根拠資料 | G50: 条件付き | H50: 2次レビューで必要に応じ依頼 | I50: ○ | J50: ○ | K50: □ | L50: □ | N50: 01_監査対応/[会社名]/05_自主点検成果物/13_未成工事支出金滞留チェック | O50: input/01_監査対応_自主点検成果物_ファイルリスト_filtered.xlsx（構成単位・2026年3月期）
A51: 45 | B51: 14 | C51: 原価振替取引の要因説明 | D51: 案件毎原価明細のマイナス取引と取消・振替理由 | F51: ①成果物本体 | G51: 必須 | I51: ○ | J51: ○ | K51: □ | L51: □ | N51: 01_監査対応/[会社名]/05_自主点検成果物/14_個別原価計算適用原価振替取引要因説明 | O51: input/01_監査対応_自主点検成果物_ファイルリスト_filtered.xlsx（構成単位・2026年3月期）
A52: 46 | B52: 14 | C52: 原価振替取引の要因説明 | D52: データソース・抽出基準/手順 | E52: 発生原価合計との一致 | F52: ③共通添付 | G52: 必須 | I52: ○ | J52: ○ | K52: □ | L52: □ | N52: 01_監査対応/[会社名]/05_自主点検成果物/14_個別原価計算適用原価振替取引要因説明 | O52: input/01_監査対応_自主点検成果物_ファイルリスト_filtered.xlsx（構成単位・2026年3月期）
A53: 47 | B53: 14 | C53: 原価振替取引の要因説明 | D53: 原価マイナス取引の根拠証憑 | E53: 承認証跡含む | F53: ②根拠資料 | G53: 条件付き | H53: 請負高が閾値以上の案件 | I53: ○ | J53: ○ | K53: □ | L53: □ | N53: 01_監査対応/[会社名]/05_自主点検成果物/14_個別原価計算適用原価振替取引要因説明 | O53: input/01_監査対応_自主点検成果物_ファイルリスト_filtered.xlsx（構成単位・2026年3月期）
A54: 48 | B54: 15 | C54: 低粗利案件の分析 | D54: 案件毎の利益率 月次推移表 | E54: 全案件 | F54: ①成果物本体 | G54: 必須 | I54: ○ | J54: ○ | K54: □ | L54: □ | N54: 01_監査対応/[会社名]/05_自主点検成果物/15_個別原価計算適用粗利率分析 | O54: input/01_監査対応_自主点検成果物_ファイルリスト_filtered.xlsx（構成単位・2026年3月期）
A55: 49 | B55: 15 | C55: 低粗利案件の分析 | D55: 原価振替有無の調査結果と根拠資料 | F55: ①成果物本体 | G55: 条件付き | H55: 請負高1億円以上＆利益率5%以下＆一定期間変動なしの案件 | I55: ○ | J55: ○ | K55: □ | L55: □ | N55: 01_監査対応/[会社名]/05_自主点検成果物/15_個別原価計算適用粗利率分析 | O55: input/01_監査対応_自主点検成果物_ファイルリスト_filtered.xlsx（構成単位・2026年3月期）
A56: 50 | B56: 15 | C56: 低粗利案件の分析 | D56: データソース・抽出条件 | E56: No.14原価明細との整合 | F56: ③共通添付 | G56: 必須 | I56: ○ | J56: ○ | K56: □ | L56: □ | N56: 01_監査対応/[会社名]/05_自主点検成果物/15_個別原価計算適用粗利率分析 | O56: input/01_監査対応_自主点検成果物_ファイルリスト_filtered.xlsx（構成単位・2026年3月期）
A57: 51 | B57: 16 | C57: 社内/会社間取引の価格設定の妥当性チェック | D57: 価格設定の妥当性確認資料 | F57: ①成果物本体 | G57: 条件付き | H57: 親会社が別途指定(個別ルール) | I57: ○ | J57: ○ | K57: □ | L57: □ | N57: 01_監査対応/[会社名]/05_自主点検成果物/16_社内・関係間取引価格設定の妥当性 | O57: input/01_監査対応_自主点検成果物_ファイルリスト_filtered.xlsx（構成単位・2026年3月期）
A58: 52 | B58: 17 | C58: 費用振替取引の要因説明 | D58: 費用振替の承認者・理由の記録 | F58: ①成果物本体 | G58: 条件付き | H58: 親会社が別途指定(個別ルール) | I58: ○ | J58: ○ | K58: □ | L58: □ | N58: 01_監査対応/[会社名]/05_自主点検成果物/17_費用振替取引要因説明 | O58: input/01_監査対応_自主点検成果物_ファイルリスト_filtered.xlsx（構成単位・2026年3月期）
A59: 53 | B59: 18 | C59: 各費用月次推移分析 | D59: 販管費の月次推移データ | E59: グラフ・期末月増加の分析コメント | F59: ①成果物本体 | G59: 必須 | I59: ○ | J59: ○ | K59: □ | L59: □ | N59: 01_監査対応/[会社名]/05_自主点検成果物/18_各費用月次推移分析 | O59: input/01_監査対応_自主点検成果物_ファイルリスト_filtered.xlsx（構成単位・2026年3月期）
A60: 54 | B60: 18 | C60: 各費用月次推移分析 | D60: データソース・抽出条件 | E60: 試算表との一致 | F60: ③共通添付 | G60: 必須 | I60: ○ | J60: ○ | K60: □ | L60: □ | N60: 01_監査対応/[会社名]/05_自主点検成果物/18_各費用月次推移分析 | O60: input/01_監査対応_自主点検成果物_ファイルリスト_filtered.xlsx（構成単位・2026年3月期）
A61: 55 | B61: 18 | C61: 各費用月次推移分析 | D61: 著しい増加の根拠資料 | F61: ②根拠資料 | G61: 条件付き | H61: 期末月に著しい増加がある場合 | I61: ○ | J61: ○ | K61: □ | L61: □ | N61: 01_監査対応/[会社名]/05_自主点検成果物/18_各費用月次推移分析 | O61: input/01_監査対応_自主点検成果物_ファイルリスト_filtered.xlsx（構成単位・2026年3月期）
A62: 56 | B62: 19 | C62: 翌期取引の確認 | D62: 翌期4月計上仕訳データ一覧 | E62: 3月計上すべき費用の顛末 | F62: ①成果物本体 | G62: 必須 | I62: ○ | J62: ○ | K62: □ | L62: □ | N62: 01_監査対応/[会社名]/05_自主点検成果物/19_費用計上すべき請求書有無 | O62: input/01_監査対応_自主点検成果物_ファイルリスト_filtered.xlsx（構成単位・2026年3月期）
A63: 57 | B63: 19 | C63: 翌期取引の確認 | D63: データソース・抽出条件 | E63: 試算表との一致 | F63: ③共通添付 | G63: 必須 | I63: ○ | J63: ○ | K63: □ | L63: □ | N63: 01_監査対応/[会社名]/05_自主点検成果物/19_費用計上すべき請求書有無 | O63: input/01_監査対応_自主点検成果物_ファイルリスト_filtered.xlsx（構成単位・2026年3月期）
A64: 58 | B64: 19 | C64: 翌期取引の確認 | D64: 3月分として計上すべき費用の根拠資料 | F64: ②根拠資料 | G64: 条件付き | H64: 当期3月計上すべき費用が見つかった場合 | I64: ○ | J64: ○ | K64: □ | L64: □ | N64: 01_監査対応/[会社名]/05_自主点検成果物/19_費用計上すべき請求書有無 | O64: input/01_監査対応_自主点検成果物_ファイルリスト_filtered.xlsx（構成単位・2026年3月期）
A65: 59 | B65: 20 | C65: 非経常的取引の識別と説明 | D65: 管理部門が各部署から情報収集したことが分かる資料 | E65: メール・アンケート | F65: ①成果物本体 | G65: 必須 | I65: ○ | J65: ○ | K65: □ | L65: □ | N65: 01_監査対応/[会社名]/05_自主点検成果物/20_非経常的な事象 | O65: input/01_監査対応_自主点検成果物_ファイルリスト_filtered.xlsx（構成単位・2026年3月期）
A66: 60 | B66: 20 | C66: 非経常的取引の識別と説明 | D66: 収集情報を基に会計処理を検討したことが分かる資料 | F66: ①成果物本体 | G66: 条件付き | H66: 非経常的な取引・事象がある場合 | I66: ○ | J66: ○ | K66: □ | L66: □ | N66: 01_監査対応/[会社名]/05_自主点検成果物/20_非経常的な事象 | O66: input/01_監査対応_自主点検成果物_ファイルリスト_filtered.xlsx（構成単位・2026年3月期）
A67: 61 | B67: 21 | C67: 見積計上費用：計上根拠 | D67: 当期3月の見積計上費用リスト | E67: 会計処理の顛末 | F67: ①成果物本体 | G67: 必須 | I67: ○ | J67: ○ | K67: □ | L67: □ | N67: 01_監査対応/[会社名]/05_自主点検成果物/21_見積計上費用計上根拠整理 | O67: input/01_監査対応_自主点検成果物_ファイルリスト_filtered.xlsx（構成単位・2026年3月期）
A68: 62 | B68: 21 | C68: 見積計上費用：計上根拠 | D68: 見積根拠資料 | E68: 契約書・正式見積書・検針データ等 | F68: ②根拠資料 | G68: 必須 | I68: ○ | J68: ○ | K68: □ | L68: □ | N68: 01_監査対応/[会社名]/05_自主点検成果物/21_見積計上費用計上根拠整理 | O68: input/01_監査対応_自主点検成果物_ファイルリスト_filtered.xlsx（構成単位・2026年3月期）
A69: 63 | B69: 21 | C69: 見積計上費用：計上根拠 | D69: データソース・網羅性の確認 | F69: ③共通添付 | G69: 必須 | I69: ○ | J69: ○ | K69: □ | L69: □ | N69: 01_監査対応/[会社名]/05_自主点検成果物/21_見積計上費用計上根拠整理 | O69: input/01_監査対応_自主点検成果物_ファイルリスト_filtered.xlsx（構成単位・2026年3月期）
A70: 64 | B70: 22 | C70: 固定資産除却損の計上確認 | D70: 総勘定元帳から抽出した当期の除却取引 | E70: コメント付 | F70: ①成果物本体 | G70: 必須 | I70: ○ | J70: ○ | K70: □ | L70: □ | N70: 01_監査対応/[会社名]/05_自主点検成果物/22_固定資産除去取引 | O70: input/01_監査対応_自主点検成果物_ファイルリスト_filtered.xlsx（構成単位・2026年3月期）
A71: 65 | B71: 22 | C71: 固定資産除却損の計上確認 | D71: データソース／試算表との一致 | E71: 総勘定元帳 | F71: ③共通添付 | G71: 必須 | I71: ○ | J71: ○ | K71: □ | L71: □ | N71: 01_監査対応/[会社名]/05_自主点検成果物/22_固定資産除去取引 | O71: input/01_監査対応_自主点検成果物_ファイルリスト_filtered.xlsx（構成単位・2026年3月期）
A72: 66 | B72: 22 | C72: 固定資産除却損の計上確認 | D72: 除却の根拠資料 | E72: 除却申請書・廃棄証明書 等 | F72: ②根拠資料 | G72: 必須 | I72: ○ | J72: ○ | K72: □ | L72: □ | N72: 01_監査対応/[会社名]/05_自主点検成果物/22_固定資産除去取引 | O72: input/01_監査対応_自主点検成果物_ファイルリスト_filtered.xlsx（構成単位・2026年3月期）
A73: 67 | B73: 23 | C73: 固定資産の資産性確認 | D73: 固定資産台帳でフラグ付けした明細＋資産計上妥当性コメント | F73: ①成果物本体 | G73: 必須 | I73: ○ | J73: ○ | K73: □ | L73: □ | N73: 01_監査対応/[会社名]/05_自主点検成果物/23_修繕費・研究費資産計上項目 | O73: input/01_監査対応_自主点検成果物_ファイルリスト_filtered.xlsx（構成単位・2026年3月期）
A74: 68 | B74: 23 | C74: 固定資産の資産性確認 | D74: データソース・抽出条件 | E74: 台帳簿価と試算表の一致 | F74: ③共通添付 | G74: 必須 | I74: ○ | J74: ○ | K74: □ | L74: □ | N74: 01_監査対応/[会社名]/05_自主点検成果物/23_修繕費・研究費資産計上項目 | O74: input/01_監査対応_自主点検成果物_ファイルリスト_filtered.xlsx（構成単位・2026年3月期）
A75: 69 | B75: 23 | C75: 固定資産の資産性確認 | D75: 資産計上の根拠資料 | E75: 見積書・仕様書・請求書・稟議書 | F75: ②根拠資料 | G75: 必須 | I75: ○ | J75: ○ | K75: □ | L75: □ | N75: 01_監査対応/[会社名]/05_自主点検成果物/23_修繕費・研究費資産計上項目 | O75: input/01_監査対応_自主点検成果物_ファイルリスト_filtered.xlsx（構成単位・2026年3月期）
A76: 70 | B76: 24 | C76: 資産除去債務の計上要否の判断を証憑に基づいて整理（証憑提出含む） | D76: 「資産除去債務に関するアンケート」回答済みエクセル | F76: ①成果物本体 | G76: 必須 | I76: ○ | K76: □ | L76: □ | N76: 01_監査対応/[会社名]/05_自主点検成果物/24_資産除去債務 | O76: input/01_監査対応_自主点検成果物_ファイルリスト_filtered.xlsx（構成単位・2026年3月期）
A77: 71 | B77: 24 | C77: 資産除去債務の計上要否の判断を証憑に基づいて整理（証憑提出含む） | D77: アンケートに記載の必要資料 | F77: ②根拠資料 | G77: 条件付き | H77: 該当固定資産を保有(質問Ⅰ・Ⅱに該当)する場合 | I77: ○ | K77: □ | L77: □ | N77: 01_監査対応/[会社名]/05_自主点検成果物/24_資産除去債務 | O77: input/01_監査対応_自主点検成果物_ファイルリスト_filtered.xlsx（構成単位・2026年3月期）
A78: 72 | B78: 25 | C78: 減損テスト | D78: 各CGUの減損判定資料 | F78: ①成果物本体 | G78: 必須 | I78: ○ | J78: ○ | K78: □ | L78: □ | N78: 01_監査対応/[会社名]/05_自主点検成果物/25_減損判定資料 | O78: input/01_監査対応_自主点検成果物_ファイルリスト_filtered.xlsx（構成単位・2026年3月期）
A79: 73 | B79: 25 | C79: 減損テスト | D79: 割引前・割引後 将来CF算定資料 | F79: ②根拠資料 | G79: 条件付き | H79: 減損の兆候に抵触したCGUがある場合(IFRS含め検討) | I79: ○ | J79: ○ | K79: □ | L79: □ | N79: 01_監査対応/[会社名]/05_自主点検成果物/25_減損判定資料 | O79: input/01_監査対応_自主点検成果物_ファイルリスト_filtered.xlsx（構成単位・2026年3月期）
A80: 74 | B80: 25 | C80: 減損テスト | D80: 固定資産領域の内部統制・減損処理アンケート | E80: フォーム回答 | F80: ①成果物本体 | G80: 必須 | I80: ○ | J80: ○ | K80: □ | L80: □ | N80: 01_監査対応/[会社名]/05_自主点検成果物/25_減損判定資料 | O80: input/01_監査対応_自主点検成果物_ファイルリスト_filtered.xlsx（構成単位・2026年3月期）
A81: 75 | B81: 25 | C81: 減損テスト | D81: データソース | E81: CGU営業損益と全社TBの一致 | F81: ③共通添付 | G81: 必須 | I81: ○ | J81: ○ | K81: □ | L81: □ | N81: 01_監査対応/[会社名]/05_自主点検成果物/25_減損判定資料 | O81: input/01_監査対応_自主点検成果物_ファイルリスト_filtered.xlsx（構成単位・2026年3月期）
A82: 76 | B82: 26 | C82: 賞与引当金の計上確認 | D82: 計上根拠資料 | E82: 繰入額の計算根拠 | F82: ②根拠資料 | G82: 排他 | H82: 賞与引当金を計上している場合 | I82: ○ | J82: ○ | K82: □ | L82: □ | N82: 01_監査対応/[会社名]/05_自主点検成果物/26_賞与引当金 | O82: input/01_監査対応_自主点検成果物_ファイルリスト_filtered.xlsx（構成単位・2026年3月期）
A83: 77 | B83: 26 | C83: 賞与引当金の計上確認 | D83: 取崩時の支払証跡＋当初計上額と支払額の比較分析 | F83: ①成果物本体 | G83: 条件付き | H83: 計上・取崩がある場合 | I83: ○ | J83: ○ | K83: □ | L83: □ | N83: 01_監査対応/[会社名]/05_自主点検成果物/26_賞与引当金 | O83: input/01_監査対応_自主点検成果物_ファイルリスト_filtered.xlsx（構成単位・2026年3月期）
A84: 78 | B84: 26 | C84: 賞与引当金の計上確認 | D84: 計上不要とした理由コメント | F84: ①成果物本体 | G84: 排他 | H84: 賞与引当金を計上していない場合 | I84: ○ | J84: ○ | K84: □ | L84: □ | N84: 01_監査対応/[会社名]/05_自主点検成果物/26_賞与引当金 | O84: input/01_監査対応_自主点検成果物_ファイルリスト_filtered.xlsx（構成単位・2026年3月期）
A85: 79 | B85: 26 | C85: 賞与引当金の計上確認 | D85: 月次推移表／繰入額・残高と試算表の一致 | E85: PL | F85: ③共通添付 | G85: 必須 | I85: ○ | J85: ○ | K85: □ | L85: □ | N85: 01_監査対応/[会社名]/05_自主点検成果物/26_賞与引当金 | O85: input/01_監査対応_自主点検成果物_ファイルリスト_filtered.xlsx（構成単位・2026年3月期）
A86: 80 | B86: 27 | C86: 自主点検チェックリスト | D86: 自主点検チェックリスト | E86: No.1〜26の自己評価 | F86: ①成果物本体 | G86: 必須 | I86: ○ | J86: ○ | K86: □ | L86: □ | N86: 01_監査対応/[会社名]/05_自主点検成果物/27_自主点検チェックリスト | O86: input/01_監査対応_自主点検成果物_ファイルリスト_filtered.xlsx（構成単位・2026年3月期）
A87: 81 | B87: 28 | C87: 財務分析 | D87: 連結PKG上の増減分析 | F87: ①成果物本体 | G87: 必須 | I87: ○ | J87: ○ | K87: □ | L87: □ | N87: 01_監査対応/[会社名]/05_自主点検成果物/28_財務分析 | O87: input/01_監査対応_自主点検成果物_ファイルリスト_filtered.xlsx（構成単位・2026年3月期）
A88: 82 | B88: 28 | C88: 財務分析 | D88: 個社別の財務分析用ファイル | F88: ①成果物本体 | G88: 条件付き | H88: 個社別財務分析の対象会社 | I88: ○ | J88: ○ | K88: □ | L88: □ | N88: 01_監査対応/[会社名]/05_自主点検成果物/28_財務分析 | O88: input/01_監査対応_自主点検成果物_ファイルリスト_filtered.xlsx（構成単位・2026年3月期）

Sheet チェックポイント確認
A2: 自主点検 チェックポイント確認リスト（構成単位版）
A3: ■ 会社名: ________________________ ■ 実施期: ______________ ■ サイクル (年度末 / 四半期): __________ ■ 記入者: ________________________
A4: 【凡例】 ☑提出 → □ を記入 / 対象外・未実施 → 「該当なし」に □ 記入し、理由を記述のうえ提出可。全行チェックは必須ではありません。
A6: No | B6: 項目No | C6: 点検項目名 | D6: CP_ID | E6: チェックポイント内容 | F6: 年度末 | G6: 四半期 | H6: ☑確認 | I6: 該当なし | J6: 非該当・未確認の理由 | K6: 過去の差し戻し注意 （頻出パターン） | L6: 一次ソース | M6: 備考
A7: 1 | B7: 1 | C7: 売掛金の残高確認 | D7: 01-001 | E7: データソースと抽出条件（手順）の記録が成果物として提出されている | F7: ○ | H7: □ | I7: □ | L7: 統合マスタ v1（内製作成 2026.6）
A8: 2 | B8: 1 | C8: 売掛金の残高確認 | D8: 01-002 | E8: 網羅性が確認できる情報が記載又は提出されている（売掛金残高明細と試算表BSの一致が確認できる） | F8: ○ | H8: □ | I8: □ | L8: 統合マスタ v1（内製作成 2026.6）
A9: 3 | B9: 1 | C9: 売掛金の残高確認 | D9: 01-003 | E9: 残高確認状の発送先一覧と回収結果が提出されている（確認状未発送先・未回収先の区分が明確になっている） | F9: ○ | H9: □ | I9: □ | L9: 統合マスタ v1（内製作成 2026.6）
A10: 4 | B10: 1 | C10: 売掛金の残高確認 | D10: 01-004 | E10: 確認状を回収できなかった相手先について代替手続（入金消込チェックリスト・追加サンプリング等）の実施結果が提出されている | F10: ○ | H10: □ | I10: □ | L10: 統合マスタ v1（内製作成 2026.6）
A11: 5 | B11: 1 | C11: 売掛金の残高確認 | D11: 01-005 | E11: 担当者の確認結果に対し上席者（部門責任者等）のレビュー証跡がある | F11: ○ | H11: □ | I11: □ | L11: 統合マスタ v1（内製作成 2026.6）
A12: 6 | B12: 1 | C12: 売掛金の残高確認 | D12: 01-006 | E12: 差異調整の内容が合理的であり、未入金残高の回収見込みが具体的に説明されている | F12: ○ | H12: □ | I12: □ | L12: 統合マスタ v1（内製作成 2026.6）
A13: 7 | B13: 1 | C13: 売掛金の残高確認 | D13: 01-007 | E13: 代替手続に使用した証憑（注文書・請求書・入金確認等）が適切な外部証憑である（内部帳票のみでの確認は不可） | F13: ○ | H13: □ | I13: □ | L13: 統合マスタ v1（内製作成 2026.6）
A14: 8 | B14: 2 | C14: 在庫の実地棚卸 | D14: 02-001 | E14: データソースと抽出条件（手順）の記録が成果物として提出されている | F14: ○ | H14: □ | I14: □ | L14: 統合マスタ v1（内製作成 2026.6）
A15: 9 | B15: 2 | C15: 在庫の実地棚卸 | D15: 02-002 | E15: 網羅性が確認できる情報が記載又は提出されている（棚卸残高と試算表の一致が確認できる） | F15: ○ | H15: □ | I15: □ | L15: 統合マスタ v1（内製作成 2026.6）
A16: 10 | B16: 2 | C16: 在庫の実地棚卸 | D16: 02-003 | E16: 棚卸実施記録（実施日・実施者・対象品目・数量・差異）が提出されている | F16: ○ | H16: □ | I16: □ | L16: 統合マスタ v1（内製作成 2026.6）
A17: 11 | B17: 2 | C17: 在庫の実地棚卸 | D17: 02-004 | E17: 棚卸差異（帳簿残高との差異）の調整内容と理由が記録されている | F17: ○ | H17: □ | I17: □ | L17: 統合マスタ v1（内製作成 2026.6）
A18: 12 | B18: 2 | C18: 在庫の実地棚卸 | D18: 02-005 | E18: 在庫評価損の計上要否を検討した記録がある（低価法適用対象の確認含む） | F18: ○ | H18: □ | I18: □ | L18: 統合マスタ v1（内製作成 2026.6）
... A27: 21 | B27: 3 | C27: 固定資産の実査 | D27: 03-008 | E27: 第2線立会対象拠点（有形固定資産期末残高1億円以上の拠点）では管理部門担当者の立会証跡が残っている | F27: ○ | H27: □ | I27: □ | L27: 統合マスタ v1（内製作成 2026.6）
A28: 22 | B28: 4 | C28: 滞留債権の分析 | D28: 04-001 | E28: データソースと抽出条件（手順）の記録が成果物として提出されている | F28: ○ | G28: ○ | H28: □ | I28: □ | K28: 計199件指摘 ▶網羅性・試算表不一致(100件): 例)「・網羅性が確認できる資料（試算表との一致確認）の送付をお願いします…」 ▶根拠資料不足(45件): 例)「・自己点検説明資料に記載の金額と試算表の一致がわかる資料の送付をお願いします…」 【構成単位固有】計90件 ▶網羅性・試算表不一致(64件): 例)「・データソース及び抽出条件が分かる資料（画面コピーなど）の送付をお願いします ・網羅性が確認できる資料（試算表との一致確…」 ▶その他(14件): 例)「・データソース及び抽出条件が分かる資料（画面コピーなど）の送付をお願いします」 ▶根拠資料不足(8件): 例)「・No255（カインズホームFC大曲店）の取引発生日が2024/10/29のため、売上計上の妥当性について、補足説明と根…」 ▶コメント・説明不足(4件): 例)「成果物である「04_滞留債権_(札幌デンタル).xlsx」に記載された2先の抽出過程が分かる資料をご提示頂けますでしょう…」 | L28: レビュー指針 No.4（input/自主点検_レビュー指針.xlsx）
A29: 23 | B29: 4 | C29: 滞留債権の分析 | D29: 04-002 | E29: 網羅性が確認できる情報が記載又は提出されている（試算表との一致が確認できる） | F29: ○ | G29: ○ | H29: □ | I29: □ | K29: 計199件指摘 ▶網羅性・試算表不一致(100件): 例)「・網羅性が確認できる資料（試算表との一致確認）の送付をお願いします…」 ▶根拠資料不足(45件): 例)「・自己点検説明資料に記載の金額と試算表の一致がわかる資料の送付をお願いします…」 | L29: レビュー指針 No.4（input/自主点検_レビュー指針.xlsx）
A30: 24 | B30: 4 | C30: 滞留債権の分析 | D30: 04-003 | E30: 回収が遅延している債権全てにつき、回収遅延理由が記載されている | F30: ○ | G30: ○ | H30: □ | I30: □ | K30: 計199件指摘 ▶網羅性・試算表不一致(100件): 例)「・網羅性が確認できる資料（試算表との一致確認）の送付をお願いします…」 ▶根拠資料不足(45件): 例)「・自己点検説明資料に記載の金額と試算表の一致がわかる資料の送付をお願いします…」 | L30: レビュー指針 No.4（input/自主点検_レビュー指針.xlsx）
A31: 25 | B31: 4 | C31: 滞留債権の分析 | D31: 04-004 | E31: 回収遅延理由について、部門責任者等の適切な承認者の承認を得ている | F31: ○ | G31: ○ | H31: □ | I31: □ | K31: 計199件指摘 ▶網羅性・試算表不一致(100件): 例)「・網羅性が確認できる資料（試算表との一致確認）の送付をお願いします…」 ▶根拠資料不足(45件): 例)「・自己点検説明資料に記載の金額と試算表の一致がわかる資料の送付をお願いします…」 | L31: レビュー指針 No.4（input/自主点検_レビュー指針.xlsx）
A32: 26 | B32: 4 | C32: 滞留債権の分析 | D32: 04-005 | E32: 回収遅延理由が合理的である | F32: ○ | G32: ○ | H32: □ | I32: □ | K32: 計199件指摘 ▶網羅性・試算表不一致(100件): 例)「・網羅性が確認できる資料（試算表との一致確認）の送付をお願いします…」 ▶根拠資料不足(45件): 例)「・自己点検説明資料に記載の金額と試算表の一致がわかる資料の送付をお願いします…」 | L32: レビュー指針 No.4（input/自主点検_レビュー指針.xlsx）
A33: 27 | B33: 4 | C33: 滞留債権の分析 | D33: 04-006 | E33: 回収遅延理由が合理的でない場合、売上計上の妥当性に関するコメントが記載されている | F33: ○ | G33: ○ | H33: □ | I33: □ | K33: 計199件指摘 ▶網羅性・試算表不一致(100件): 例)「・網羅性が確認できる資料（試算表との一致確認）の送付をお願いします…」 ▶根拠資料不足(45件): 例)「・自己点検説明資料に記載の金額と試算表の一致がわかる資料の送付をお願いします…」 | L33: レビュー指針 No.4（input/自主点検_レビュー指針.xlsx）
A34: 28 | B34: 4 | C34: 滞留債権の分析 | D34: 04-007 | E34: 注文書などの外部証憑を確認したうえで、適切に売上計上の妥当性をコメントできている | F34: ○ | G34: ○ | H34: □ | I34: □ | K34: 計199件指摘 ▶網羅性・試算表不一致(100件): 例)「・網羅性が確認できる資料（試算表との一致確認）の送付をお願いします…」 ▶根拠資料不足(45件): 例)「・自己点検説明資料に記載の金額と試算表の一致がわかる資料の送付をお願いします…」 | L34: レビュー指針 No.4（input/自主点検_レビュー指針.xlsx）
A35: 29 | B35: 5 | C35: 異常取引の分析 | D35: 05-001 | E35: データソースと抽出条件（手順）の記録が成果物として提出されている | F35: ○ | G35: ○ | H35: □ | I35: □ | K35: 計350件指摘 ▶網羅性・試算表不一致(182件): 例)「・網羅性及び売上伝票/明細と試算表の整合性を確認するため、25年4月~26年3月の全ての売上明細（マイナス含む）の提出をお願い出来ますでしょうか ・マイナスの売…」 ▶根拠資料不足(97件): 例)「下記、売上マイナス仕訳の根拠証憑のご提示をお願いいたします。 ・計上日：20260331 仕訳検索テキスト：022502903161 売上額：△26,759,0…」 【構成単位固有】計123件 ▶網羅性・試算表不一致(100件): 例)「・データソース及び抽出条件が分かる資料（抽出する際の条件を記載した画面スクショなど）の提出をお願い出来ますでしょうか。 …」 ▶コメント・説明不足(12件): 例)「・データソース及び抽出条件が分かる資料（抽出する際の条件を記載した画面スクショなど）の提出をお願い出来ますでしょうか。 …」 ▶根拠資料不足(7件): 例)「証跡フォルダにてご提示いただいております”コンポーネンツ機器部関係 証跡 260427小澤_1”Excelに関しまして、…」 ▶その他(4件): 例)「2025年4月～2026年3月までは確認済みであり、問題ありませんでした。 お聞きになっておられるかと思いますが、202…」 | L35: レビュー指針 No.5（input/自主点検_レビュー指針.xlsx）
A36: 30 | B36: 5 | C36: 異常取引の分析 | D36: 05-002 | E36: 25年4月~26年3月の全ての売上明細（マイナス含む）が提出されている（試算表との一致が確認できる） | F36: ○ | G36: ○ | H36: □ | I36: □ | K36: 計350件指摘 ▶網羅性・試算表不一致(182件): 例)「・網羅性及び売上伝票/明細と試算表の整合性を確認するため、25年4月~26年3月の全ての売上明細（マイナス含む）の提出をお願い出来ますでしょうか ・マイナスの売…」 ▶根拠資料不足(97件): 例)「下記、売上マイナス仕訳の根拠証憑のご提示をお願いいたします。 ・計上日：20260331 仕訳検索テキスト：022502903161 売上額：△26,759,0…」 | L36: レビュー指針 No.5（input/自主点検_レビュー指針.xlsx）
A37: 31 | B37: 5 | C37: 異常取引の分析 | D37: 05-003 | E37: マイナスの売上がある場合、売上計上の妥当性（収益認識基準を満たしているか）を検討したコメントが残されている | F37: ○ | G37: ○ | H37: □ | I37: □ | K37: 計350件指摘 ▶網羅性・試算表不一致(182件): 例)「・網羅性及び売上伝票/明細と試算表の整合性を確認するため、25年4月~26年3月の全ての売上明細（マイナス含む）の提出をお願い出来ますでしょうか ・マイナスの売…」 ▶根拠資料不足(97件): 例)「下記、売上マイナス仕訳の根拠証憑のご提示をお願いいたします。 ・計上日：20260331 仕訳検索テキスト：022502903161 売上額：△26,759,0…」 | L37: レビュー指針 No.5（input/自主点検_レビュー指針.xlsx）
A38: 32 | B38: 5 | C38: 異常取引の分析 | D38: 05-004 | E38: マイナス売上の売上は収益認識基準を満たした売上計上である（例えば、リスクの高いマイナス取引については、根拠資料を確認したうえで①売上計上と②取消それぞれの観点で合理的なコメントが出来ているかの確認が必要） | F38: ○ | G38: ○ | H38: □ | I38: □ | K38: 計350件指摘 ▶網羅性・試算表不一致(182件): 例)「・網羅性及び売上伝票/明細と試算表の整合性を確認するため、25年4月~26年3月の全ての売上明細（マイナス含む）の提出をお願い出来ますでしょうか ・マイナスの売…」 ▶根拠資料不足(97件): 例)「下記、売上マイナス仕訳の根拠証憑のご提示をお願いいたします。 ・計上日：20260331 仕訳検索テキスト：022502903161 売上額：△26,759,0…」 | L38: レビュー指針 No.5（input/自主点検_レビュー指針.xlsx） | M38: 【構成単位】2次レビュー対象閾値：金額2,000万円以上・最低5件（非構成単位は3件）
A39: 33 | B39: 5 | C39: 異常取引の分析 | D39: 05-005 | E39: 収益認識基準を満たさない売上計上の場合は、会計処理の顛末が記載されている | F39: ○ | G39: ○ | H39: □ | I39: □ | K39: 計350件指摘 ▶網羅性・試算表不一致(182件): 例)「・網羅性及び売上伝票/明細と試算表の整合性を確認するため、25年4月~26年3月の全ての売上明細（マイナス含む）の提出をお願い出来ますでしょうか ・マイナスの売…」 ▶根拠資料不足(97件): 例)「下記、売上マイナス仕訳の根拠証憑のご提示をお願いいたします。 ・計上日：20260331 仕訳検索テキスト：022502903161 売上額：△26,759,0…」 | L39: レビュー指針 No.5（input/自主点検_レビュー指針.xlsx） | M39: 【構成単位】2次レビュー対象閾値：金額2,000万円以上・最低5件（非構成単位は3件）
A40: 34 | B40: 6 | C40: 売上の期末変動分析 | D40: 06-001 | E40: データソースと抽出条件（手順）の記録が成果物として提出されている | F40: ○ | G40: ○ | H40: □ | I40: □ | K40: 計199件指摘 ▶網羅性・試算表不一致(95件): 例)「・データソース及び抽出条件が分かる資料（画面コピーなど）の送付をお願いします ・網羅性が確認できる資料（試算表との一致確認）の送付をお願いします…」 ▶根拠資料不足(51件): 例)「・データソース及び抽出条件が分かる資料（画面コピーなど）の提出してください ・網羅性が確認できる資料（試算表との一致確認）の提出してください ・特に四半期末月に…」 【構成単位固有】計88件 ▶網羅性・試算表不一致(71件): 例)「・データソース及び抽出条件が分かる資料（画面コピーなど）の送付をお願いします ・網羅性が確認できる資料（試算表との一致確…」 ▶コメント・説明不足(9件): 例)「増減のコメントに関し、前月比で+-20%の増減がある場合のコメントが不足しているように見受けられましたので、ご確認をお願…」 ▶その他(7件): 例)「・Please send us documentation that shows the data sources an…」 ▶根拠資料不足(1件): 例)「・データソース及び抽出条件が分かる資料（画面コピーなど）の送付をお願いします ・前年度同月比較だけでなく、前月比の増減検…」 | L40: レビュー指針 No.6（input/自主点検_レビュー指針.xlsx）
A41: 35 | B41: 6 | C41: 売上の期末変動分析 | D41: 06-002 | E41: 網羅性が確認できる情報が記載又は提出されている（試算表との一致が確認できる） | F41: ○ | G41: ○ | H41: □ | I41: □ | K41: 計199件指摘 ▶網羅性・試算表不一致(95件): 例)「・データソース及び抽出条件が分かる資料（画面コピーなど）の送付をお願いします ・網羅性が確認できる資料（試算表との一致確認）の送付をお願いします…」 ▶根拠資料不足(51件): 例)「・データソース及び抽出条件が分かる資料（画面コピーなど）の提出してください ・網羅性が確認できる資料（試算表との一致確認）の提出してください ・特に四半期末月に…」 | L41: レビュー指針 No.6（input/自主点検_レビュー指針.xlsx）
A42: 36 | B42: 6 | C42: 売上の期末変動分析 | D42: 06-003 | E42: 前年同期・前月比較ともに、10百万円の変動、かつ、20%以上の変動がある場合、増減コメントがされている | F42: ○ | G42: ○ | H42: □ | I42: □ | K42: 計199件指摘 ▶網羅性・試算表不一致(95件): 例)「・データソース及び抽出条件が分かる資料（画面コピーなど）の送付をお願いします ・網羅性が確認できる資料（試算表との一致確認）の送付をお願いします…」 ▶根拠資料不足(51件): 例)「・データソース及び抽出条件が分かる資料（画面コピーなど）の提出してください ・網羅性が確認できる資料（試算表との一致確認）の提出してください ・特に四半期末月に…」 | L42: レビュー指針 No.6（input/自主点検_レビュー指針.xlsx）
A43: 37 | B43: 6 | C43: 売上の期末変動分析 | D43: 06-004 | E43: 増減分析コメントにて、要因毎の影響金額を記載している（最低限、6割～7割程度） | F43: ○ | G43: ○ | H43: □ | I43: □ | K43: 計199件指摘 ▶網羅性・試算表不一致(95件): 例)「・データソース及び抽出条件が分かる資料（画面コピーなど）の送付をお願いします ・網羅性が確認できる資料（試算表との一致確認）の送付をお願いします…」 ▶根拠資料不足(51件): 例)「・データソース及び抽出条件が分かる資料（画面コピーなど）の提出してください ・網羅性が確認できる資料（試算表との一致確認）の提出してください ・特に四半期末月に…」 ▶【構成単位固有要件】要因毎の影響金額記載（6〜7割以上）は構成単位の1次レビュー要件（非構成単位は定量記載不要） | L43: レビュー指針 No.6（input/自主点検_レビュー指針.xlsx）
A44: 38 | B44: 6 | C44: 売上の期末変動分析 | D44: 06-005 | E44: 特に四半期末月に上昇傾向があった場合に、根拠資料に基づいて売上計上の妥当性を検証している。また、検証した旨がコメントされている。 | F44: ○ | G44: ○ | H44: □ | I44: □ | K44: 計199件指摘 ▶網羅性・試算表不一致(95件): 例)「・データソース及び抽出条件が分かる資料（画面コピーなど）の送付をお願いします ・網羅性が確認できる資料（試算表との一致確認）の送付をお願いします…」 ▶根拠資料不足(51件): 例)「・データソース及び抽出条件が分かる資料（画面コピーなど）の提出してください ・網羅性が確認できる資料（試算表との一致確認）の提出してください ・特に四半期末月に…」 | L44: レビュー指針 No.6（input/自主点検_レビュー指針.xlsx）
A45: 39 | B45: 6 | C45: 売上の期末変動分析 | D45: 06-006 | E45: 増減分析コメントにて、増減内容の説明になっている | F45: ○ | G45: ○ | H45: □ | I45: □ | K45: 計199件指摘 ▶網羅性・試算表不一致(95件): 例)「・データソース及び抽出条件が分かる資料（画面コピーなど）の送付をお願いします ・網羅性が確認できる資料（試算表との一致確認）の送付をお願いします…」 ▶根拠資料不足(51件): 例)「・データソース及び抽出条件が分かる資料（画面コピーなど）の提出してください ・網羅性が確認できる資料（試算表との一致確認）の提出してください ・特に四半期末月に…」 | L45: レビュー指針 No.6（input/自主点検_レビュー指針.xlsx）
A46: 40 | B46: 6 | C46: 売上の期末変動分析 | D46: 06-007 | E46: 増減分析コメントにて、金額推移と整合した説明になっている | F46: ○ | G46: ○ | H46: □ | I46: □ | K46: 計199件指摘 ▶網羅性・試算表不一致(95件): 例)「・データソース及び抽出条件が分かる資料（画面コピーなど）の送付をお願いします ・網羅性が確認できる資料（試算表との一致確認）の送付をお願いします…」 ▶根拠資料不足(51件): 例)「・データソース及び抽出条件が分かる資料（画面コピーなど）の提出してください ・網羅性が確認できる資料（試算表との一致確認）の提出してください ・特に四半期末月に…」 | L46: レビュー指針 No.6（input/自主点検_レビュー指針.xlsx）
A47: 41 | B47: 6 | C47: 売上の期末変動分析 | D47: 06-008 | E47: 前年同期・前月比較ともに、10百万円の変動、かつ、20%以上の変動がある場合、増減コメントがされている 特に四半期末月に上昇傾向があった場合に、増減分析コメントにて、要因を記載している | F47: ○ | G47: ○ | H47: □ | I47: □ | K47: 計199件指摘 ▶網羅性・試算表不一致(95件): 例)「・データソース及び抽出条件が分かる資料（画面コピーなど）の送付をお願いします ・網羅性が確認できる資料（試算表との一致確認）の送付をお願いします…」 ▶根拠資料不足(51件): 例)「・データソース及び抽出条件が分かる資料（画面コピーなど）の提出してください ・網羅性が確認できる資料（試算表との一致確認）の提出してください ・特に四半期末月に…」 | L47: レビュー指針 No.6（input/自主点検_レビュー指針.xlsx） | M47: 【非構成単位専用】構成単位版では06-003〜06-005が適用（定量要件・四半期末月妥当性検証あり）。
A48: 42 | B48: 7 | C48: 収益認識アンケート（証憑提出含む） | D48: 07-001 | E48: データソースと抽出条件（手順）の記録が成果物として提出されている | F48: ○ | G48: ○ | H48: □ | I48: □ | L48: 統合マスタ v1（内製作成 2026.6）
A49: 43 | B49: 7 | C49: 収益認識アンケート（証憑提出含む） | D49: 07-002 | E49: 網羅性が確認できる情報が記載又は提出されている（売上明細データと試算表PLの一致が事前確認されている） | F49: ○ | G49: ○ | H49: □ | I49: □ | L49: 統合マスタ v1（内製作成 2026.6）
A50: 44 | B50: 7 | C50: 収益認識アンケート（証憑提出含む） | D50: 07-003 | E50: アンケートの全4セクション（概要整理・商流図・チェックシート・PL金額）が記入・提出されている | F50: ○ | G50: ○ | H50: □ | I50: □ | L50: 統合マスタ v1（内製作成 2026.6）
A51: 45 | B51: 7 | C51: 収益認識アンケート（証憑提出含む） | D51: 07-004 | E51: 年間売上金額1億円以上の取引がすべて記載されている（1億円未満のみの場合はその旨が明記されている） | F51: ○ | G51: ○ | H51: □ | I51: □ | L51: 統合マスタ v1（内製作成 2026.6）
A52: 46 | B52: 7 | C52: 収益認識アンケート（証憑提出含む） | D52: 07-005 | E52: 年間売上金額5億円以上の取引について取引基本契約書（PDF）が提出されている | F52: ○ | G52: ○ | H52: □ | I52: □ | L52: 統合マスタ v1（内製作成 2026.6）
A53: 47 | B53: 7 | C53: 収益認識アンケート（証憑提出含む） | D53: 07-006 | E53: 売上計上基準（出荷/着荷/検収等）がチェックシートに記載され実態と整合している | F53: ○ | G53: ○ | H53: □ | I53: □ | L53: 統合マスタ v1（内製作成 2026.6）
A54: 48 | B54: 7 | C54: 収益認識アンケート（証憑提出含む） | D54: 07-007 | E54: 代理人取引・スルー取引・二重売上リスク・預かり在庫に関する確認事項がチェックシートに回答されている | F54: ○ | G54: ○ | H54: □ | I54: □ | L54: 統合マスタ v1（内製作成 2026.6）
A55: 49 | B55: 8 | C55: 売上のカットオフテスト | D55: 08-001 | E55: データソースと抽出条件（手順）の記録が成果物として提出されている | F55: ○ | G55: ○ | H55: □ | I55: □ | K55: 計285件指摘 ▶根拠資料不足(156件): 例)「・1,000万円以上の売上の根拠として契約書を提出いただいておりますが単価のみの記載のため請求額の根拠資料となる数量が分かる資料の送付をお願いします…」 ▶網羅性・試算表不一致(73件): 例)「・データソース及び抽出条件が分かる資料（画面コピーなど）の提出してください ・網羅性が確認できる資料（試算表との一致確認）の提出してください…」 【構成単位固有】計109件 ▶網羅性・試算表不一致(64件): 例)「・売上明細のデータソースと抽出条件が分かる資料（画面コピーなど）の送付をお願いします ・網羅性が確認できる資料（試算表と…」 ▶根拠資料不足(18件): 例)「・データソース及び抽出条件が分かる資料（画面コピーなど）の提出してください ・10百万円以上の取引について、根拠資料（数…」 ▶コメント・説明不足(16件): 例)「・10百万円以上の2件については、収益計上の妥当性の検証を終えました。ただ、全ての売上について、売上計上の妥当性（収益認…」 ▶その他(11件): 例)「物販(ECサイトを通る売上高)について、ヤマト/佐川等の外部サイトから取得した2026年3月分の伝票番号データをご提出く…」 | L55: レビュー指針 No.8（input/自主点検_レビュー指針.xlsx）
A56: 50 | B56: 8 | C56: 売上のカットオフテスト | D56: 08-002 | E56: 26年3月単月の全ての売上明細が提出されている（試算表との一致が確認できる） | F56: ○ | G56: ○ | H56: □ | I56: □ | K56: 計285件指摘 ▶根拠資料不足(156件): 例)「・1,000万円以上の売上の根拠として契約書を提出いただいておりますが単価のみの記載のため請求額の根拠資料となる数量が分かる資料の送付をお願いします…」 ▶網羅性・試算表不一致(73件): 例)「・データソース及び抽出条件が分かる資料（画面コピーなど）の提出してください ・網羅性が確認できる資料（試算表との一致確認）の提出してください…」 | L56: レビュー指針 No.8（input/自主点検_レビュー指針.xlsx）
A57: 51 | B57: 8 | C57: 売上のカットオフテスト | D57: 08-003 | E57: 全ての明細に対して売上計上の妥当性（収益認識基準を満たしているか）を検討したコメントが残されている | F57: ○ | G57: ○ | H57: □ | I57: □ | K57: 計285件指摘 ▶根拠資料不足(156件): 例)「・1,000万円以上の売上の根拠として契約書を提出いただいておりますが単価のみの記載のため請求額の根拠資料となる数量が分かる資料の送付をお願いします…」 ▶網羅性・試算表不一致(73件): 例)「・データソース及び抽出条件が分かる資料（画面コピーなど）の提出してください ・網羅性が確認できる資料（試算表との一致確認）の提出してください…」 | L57: レビュー指針 No.8（input/自主点検_レビュー指針.xlsx）
A58: 52 | B58: 8 | C58: 売上のカットオフテスト | D58: 08-004 | E58: 1,000万円以上の取引について、根拠資料が提出されている | F58: ○ | G58: ○ | H58: □ | I58: □ | K58: 計285件指摘 ▶根拠資料不足(156件): 例)「・1,000万円以上の売上の根拠として契約書を提出いただいておりますが単価のみの記載のため請求額の根拠資料となる数量が分かる資料の送付をお願いします…」 ▶網羅性・試算表不一致(73件): 例)「・データソース及び抽出条件が分かる資料（画面コピーなど）の提出してください ・網羅性が確認できる資料（試算表との一致確認）の提出してください…」 | L58: レビュー指針 No.8（input/自主点検_レビュー指針.xlsx）
A59: 53 | B59: 8 | C59: 売上のカットオフテスト | D59: 08-005 | E59: 根拠資料は第三者により作成または承認されたものである | F59: ○ | G59: ○ | H59: □ | I59: □ | K59: 計285件指摘 ▶根拠資料不足(156件): 例)「・1,000万円以上の売上の根拠として契約書を提出いただいておりますが単価のみの記載のため請求額の根拠資料となる数量が分かる資料の送付をお願いします…」 ▶網羅性・試算表不一致(73件): 例)「・データソース及び抽出条件が分かる資料（画面コピーなど）の提出してください ・網羅性が確認できる資料（試算表との一致確認）の提出してください…」 | L59: レビュー指針 No.8（input/自主点検_レビュー指針.xlsx） | M59: 【構成単位】2次レビュー対象閾値：金額2,000万円以上・最低5件（非構成単位は3件）
A60: 54 | B60: 8 | C60: 売上のカットオフテスト | D60: 08-006 | E60: 収益認識基準を満たした売上計上である（根拠資料により、製品・サービス、数量が確認できる） | F60: ○ | G60: ○ | H60: □ | I60: □ | K60: 計285件指摘 ▶根拠資料不足(156件): 例)「・1,000万円以上の売上の根拠として契約書を提出いただいておりますが単価のみの記載のため請求額の根拠資料となる数量が分かる資料の送付をお願いします…」 ▶網羅性・試算表不一致(73件): 例)「・データソース及び抽出条件が分かる資料（画面コピーなど）の提出してください ・網羅性が確認できる資料（試算表との一致確認）の提出してください…」 | L60: レビュー指針 No.8（input/自主点検_レビュー指針.xlsx） | M60: 【構成単位】2次レビュー対象閾値：金額2,000万円以上・最低5件（非構成単位は3件）
A61: 55 | B61: 8 | C61: 売上のカットオフテスト | D61: 08-007 | E61: 収益認識基準を満たした売上計上である（根拠資料により、売上計上日の妥当性が確認できる） | F61: ○ | G61: ○ | H61: □ | I61: □ | K61: 計285件指摘 ▶根拠資料不足(156件): 例)「・1,000万円以上の売上の根拠として契約書を提出いただいておりますが単価のみの記載のため請求額の根拠資料となる数量が分かる資料の送付をお願いします…」 ▶網羅性・試算表不一致(73件): 例)「・データソース及び抽出条件が分かる資料（画面コピーなど）の提出してください ・網羅性が確認できる資料（試算表との一致確認）の提出してください…」 | L61: レビュー指針 No.8（input/自主点検_レビュー指針.xlsx） | M61: 【構成単位】2次レビュー対象閾値：金額2,000万円以上・最低5件（非構成単位は3件）
A62: 56 | B62: 8 | C62: 売上のカットオフテスト | D62: 08-008 | E62: 収益認識基準を満たさない売上計上の場合は、売上計上の可否を検討し、会計処理の顛末が記載されている | F62: ○ | G62: ○ | H62: □ | I62: □ | K62: 計285件指摘 ▶根拠資料不足(156件): 例)「・1,000万円以上の売上の根拠として契約書を提出いただいておりますが単価のみの記載のため請求額の根拠資料となる数量が分かる資料の送付をお願いします…」 ▶網羅性・試算表不一致(73件): 例)「・データソース及び抽出条件が分かる資料（画面コピーなど）の提出してください ・網羅性が確認できる資料（試算表との一致確認）の提出してください…」 | L62: レビュー指針 No.8（input/自主点検_レビュー指針.xlsx） | M62: 【構成単位】2次レビュー対象閾値：金額2,000万円以上・最低5件（非構成単位は3件）
A63: 57 | B63: 9 | C63: 長期請負工事案件の洗い出し | D63: 09-001 | E63: データソースと抽出条件（手順）の記録が成果物として提出されている | F63: ○ | G63: ○ | H63: □ | I63: □ | K63: 計22件指摘 ▶網羅性・試算表不一致(11件): 例)「・網羅性を確認できる資料（試算表等）の提出をお願い出来ますでしょうか。…」 ▶その他(6件): 例)「工事進行基準取り崩し_MARUWAのExcelファイルが見当たりませんでした…」 【構成単位固有】計15件 ▶網羅性・試算表不一致(13件): 例)「・網羅性を確認できる資料（試算表等）の提出をお願い出来ますでしょうか。」 ▶その他(1件): 例)「工事進行基準取り崩し_MARUWAのExcelファイルが見当たりませんでした」 ▶根拠資料不足(1件): 例)「・データソース及び抽出条件が分かる資料（画面コピーなど）の送付をお願いします。具体的には、データソースだけでなく、抽出基…」 | L63: レビュー指針 No.9（input/自主点検_レビュー指針.xlsx）
A64: 58 | B64: 9 | C64: 長期請負工事案件の洗い出し | D64: 09-002 | E64: 網羅性が確認できる情報が記載又は提出されている（例：PKGの進行基準売上との一致） | F64: ○ | G64: ○ | H64: □ | I64: □ | K64: 計22件指摘 ▶網羅性・試算表不一致(11件): 例)「・網羅性を確認できる資料（試算表等）の提出をお願い出来ますでしょうか。…」 ▶その他(6件): 例)「工事進行基準取り崩し_MARUWAのExcelファイルが見当たりませんでした…」 | L64: レビュー指針 No.9（input/自主点検_レビュー指針.xlsx）
A65: 59 | B65: 9 | C65: 長期請負工事案件の洗い出し | D65: 09-003 | E65: 全ての取引について進行基準の適用可否に関する判断根拠が記載されている | F65: ○ | G65: ○ | H65: □ | I65: □ | K65: 計22件指摘 ▶網羅性・試算表不一致(11件): 例)「・網羅性を確認できる資料（試算表等）の提出をお願い出来ますでしょうか。…」 ▶その他(6件): 例)「工事進行基準取り崩し_MARUWAのExcelファイルが見当たりませんでした…」 | L65: レビュー指針 No.9（input/自主点検_レビュー指針.xlsx）
A66: 60 | B66: 9 | C66: 長期請負工事案件の洗い出し | D66: 09-004 | E66: 判断根拠が会計基準の要求事項に沿う内容になっている | F66: ○ | G66: ○ | H66: □ | I66: □ | K66: 計22件指摘 ▶網羅性・試算表不一致(11件): 例)「・網羅性を確認できる資料（試算表等）の提出をお願い出来ますでしょうか。…」 ▶その他(6件): 例)「工事進行基準取り崩し_MARUWAのExcelファイルが見当たりませんでした…」 | L66: レビュー指針 No.9（input/自主点検_レビュー指針.xlsx）
A67: 61 | B67: 9 | C67: 長期請負工事案件の洗い出し | D67: 09-005 | E67: 会社の判断根拠によれば、一定期間にわたって収益を認識することが妥当である | F67: ○ | G67: ○ | H67: □ | I67: □ | K67: 計22件指摘 ▶網羅性・試算表不一致(11件): 例)「・網羅性を確認できる資料（試算表等）の提出をお願い出来ますでしょうか。…」 ▶その他(6件): 例)「工事進行基準取り崩し_MARUWAのExcelファイルが見当たりませんでした…」 | L67: レビュー指針 No.9（input/自主点検_レビュー指針.xlsx）
A68: 62 | B68: 9 | C68: 長期請負工事案件の洗い出し | D68: 09-006 | E68: 請負高が5億円を超える工事案件は、会社の判断根拠の適切性を確認する | F68: ○ | G68: ○ | H68: □ | I68: □ | K68: 計22件指摘 ▶網羅性・試算表不一致(11件): 例)「・網羅性を確認できる資料（試算表等）の提出をお願い出来ますでしょうか。…」 ▶その他(6件): 例)「工事進行基準取り崩し_MARUWAのExcelファイルが見当たりませんでした…」 | L68: レビュー指針 No.9（input/自主点検_レビュー指針.xlsx）
A69: 63 | B69: 10 | C69: 実行予算の取得・確認 | D69: 10-001 | E69: データソースと抽出条件（手順）の記録が成果物として提出されている | F69: ○ | G69: ○ | H69: □ | I69: □ | K69: 計19件指摘 ▶網羅性・試算表不一致(8件): 例)「・データソース及び抽出条件が分かる資料（画面コピーなど）の送付をお願いします ・網羅性を確認できる資料（試算表等）の提出をお願い出来ますでしょうか。そのうえで、…」 ▶根拠資料不足(8件): 例)「・各工事案件の月ごとの実行予算について、提出いただいた成果物と試算表などの根拠資料等もしくは提出成果物とNo.9の整合を確認して頂き、その旨を提出物内で記載して…」 【構成単位固有】計16件 ▶網羅性・試算表不一致(11件): 例)「・データソース及び抽出条件が分かる資料（画面コピーなど）の送付をお願いします ・網羅性を確認できる資料（試算表等）の提出…」 ▶コメント・説明不足(2件): 例)「実行予算に著増減がある場合、コメントを記載がありませんでした」 ▶その他(2件): 例)「財務資料、工事案件リスト確認できました。その上で以下ご確認をお願いします。 ・四半期毎にPKGを通じて工事進行売上を計上…」 ▶根拠資料不足(1件): 例)「（青字5/18加筆） 関連資料「WIP」をリンクにて根拠資料フォルダを確認しました。以下青字の追加「WIP」資料を提出い…」 | L69: レビュー指針 No.10（input/自主点検_レビュー指針.xlsx）
A70: 64 | B70: 10 | C70: 実行予算の取得・確認 | D70: 10-002 | E70: 網羅性が確認できる情報が記載又は提出されている（試算表との一致を確認できる） | F70: ○ | G70: ○ | H70: □ | I70: □ | K70: 計19件指摘 ▶網羅性・試算表不一致(8件): 例)「・データソース及び抽出条件が分かる資料（画面コピーなど）の送付をお願いします ・網羅性を確認できる資料（試算表等）の提出をお願い出来ますでしょうか。そのうえで、…」 ▶根拠資料不足(8件): 例)「・各工事案件の月ごとの実行予算について、提出いただいた成果物と試算表などの根拠資料等もしくは提出成果物とNo.9の整合を確認して頂き、その旨を提出物内で記載して…」 | L70: レビュー指針 No.10（input/自主点検_レビュー指針.xlsx）
A71: 65 | B71: 10 | C71: 実行予算の取得・確認 | D71: 10-003 | E71: 実行予算に著増減がある場合、コメントを記載している | F71: ○ | G71: ○ | H71: □ | I71: □ | K71: 計19件指摘 ▶網羅性・試算表不一致(8件): 例)「・データソース及び抽出条件が分かる資料（画面コピーなど）の送付をお願いします ・網羅性を確認できる資料（試算表等）の提出をお願い出来ますでしょうか。そのうえで、…」 ▶根拠資料不足(8件): 例)「・各工事案件の月ごとの実行予算について、提出いただいた成果物と試算表などの根拠資料等もしくは提出成果物とNo.9の整合を確認して頂き、その旨を提出物内で記載して…」 | L71: レビュー指針 No.10（input/自主点検_レビュー指針.xlsx）
A72: 66 | B72: 10 | C72: 実行予算の取得・確認 | D72: 10-004 | E72: 増減コメントが変動要因の説明になっている | F72: ○ | G72: ○ | H72: □ | I72: □ | K72: 計19件指摘 ▶網羅性・試算表不一致(8件): 例)「・データソース及び抽出条件が分かる資料（画面コピーなど）の送付をお願いします ・網羅性を確認できる資料（試算表等）の提出をお願い出来ますでしょうか。そのうえで、…」 ▶根拠資料不足(8件): 例)「・各工事案件の月ごとの実行予算について、提出いただいた成果物と試算表などの根拠資料等もしくは提出成果物とNo.9の整合を確認して頂き、その旨を提出物内で記載して…」 | L72: レビュー指針 No.10（input/自主点検_レビュー指針.xlsx）
A73: 67 | B73: 10 | C73: 実行予算の取得・確認 | D73: 10-005 | E73: 増減コメントにより、予算の信頼性が低いと判断される場合、進行基準の適用可否を検討できている | F73: ○ | G73: ○ | H73: □ | I73: □ | K73: 計19件指摘 ▶網羅性・試算表不一致(8件): 例)「・データソース及び抽出条件が分かる資料（画面コピーなど）の送付をお願いします ・網羅性を確認できる資料（試算表等）の提出をお願い出来ますでしょうか。そのうえで、…」 ▶根拠資料不足(8件): 例)「・各工事案件の月ごとの実行予算について、提出いただいた成果物と試算表などの根拠資料等もしくは提出成果物とNo.9の整合を確認して頂き、その旨を提出物内で記載して…」 | L73: レビュー指針 No.10（input/自主点検_レビュー指針.xlsx）
A74: 68 | B74: 11 | C74: 材料費の実際発生原価の確認 | D74: 11-001 | E74: データソースと抽出条件（手順）の記録が成果物として提出されている | F74: ○ | G74: ○ | H74: □ | I74: □ | K74: 計17件指摘 ▶網羅性・試算表不一致(9件): 例)「・データソース及び抽出条件が分かる資料（画面コピーなど）の送付をお願いします ・網羅性を確認できる資料（試算表等）の提出をお願い出来ますでしょうか。そのうえで、…」 ▶根拠資料不足(6件): 例)「・原材料購買データと原材料入庫データの月次比較表、工事案件の原価明細をベースにどの原材料出庫データと紐づくかを記載した資料のご送付をお願いします（※詳細は№11…」 【構成単位固有】計12件 ▶網羅性・試算表不一致(11件): 例)「・データソース及び抽出条件が分かる資料（画面コピーなど）の送付をお願いします ・網羅性を確認できる資料（試算表等）の提出…」 ▶その他(1件): 例)「No.9で提出いただいている資料と比較し、提出いただいている購買・入庫・出庫・原価の各データにつき、対応するプロジェクト…」 | L74: レビュー指針 No.11（input/自主点検_レビュー指針.xlsx）
... A101: 95 | B101: 15 | C101: 低粗利案件の分析 | D101: 15-007 | E101: 請負高1億円以上で、利益率5%以下、かつ、一定期間変動がない案件全てについて、利益率悪化の要因のコメントや残工事予算と実績の突合などから、要因を説明できている | F101: ○ | G101: ○ | H101: □ | I101: □ | K101: 計18件指摘 ▶根拠資料不足(10件): 例)「No.42のご質問の返信になります。 他案件に原価付替をしているかどうかを聞いておりますか？⇒はい。インストラクション上「請負高1億円以上で、利益率5%以下、か…」 ▶網羅性・試算表不一致(4件): 例)「・データソース、手順及び抽出条件が分かる資料（画面コピーなど）の送付をお願いします ・提出物の整合性を確認するため、試算表を提出して頂けないでしょうか。そのうえ…」 | L101: レビュー指針 No.15（input/自主点検_レビュー指針.xlsx）
A102: 96 | B102: 16 | C102: 社内/会社間取引の価格設定の妥当性チェック | D102: 16-001 | E102: データソースと抽出条件（手順）の記録が成果物として提出されている | F102: ○ | G102: ○ | H102: □ | I102: □ | L102: 統合マスタ v1（内製作成 2026.6）
A103: 97 | B103: 16 | C103: 社内/会社間取引の価格設定の妥当性チェック | D103: 16-002 | E103: 対象となるすべての社内・会社間取引が一覧化されており網羅性が確認できる | F103: ○ | G103: ○ | H103: □ | I103: □ | L103: 統合マスタ v1（内製作成 2026.6）
A104: 98 | B104: 16 | C104: 社内/会社間取引の価格設定の妥当性チェック | D104: 16-003 | E104: 価格設定が市場価格・原価ベース等の合理的な基準に基づいていることが具体的に説明されている | F104: ○ | G104: ○ | H104: □ | I104: □ | L104: 統合マスタ v1（内製作成 2026.6）
A105: 99 | B105: 16 | C105: 社内/会社間取引の価格設定の妥当性チェック | D105: 16-004 | E105: セグメント間・会社間で恣意的な利益移動が行われていないことを確認している | F105: ○ | G105: ○ | H105: □ | I105: □ | L105: 統合マスタ v1（内製作成 2026.6）
A106: 100 | B106: 17 | C106: 費用振替取引の要因説明 | D106: 17-001 | E106: データソースと抽出条件（手順）の記録が成果物として提出されている | F106: ○ | G106: ○ | H106: □ | I106: □ | L106: 統合マスタ v1（内製作成 2026.6）
A107: 101 | B107: 17 | C107: 費用振替取引の要因説明 | D107: 17-002 | E107: 費用振替（部門間・案件間）の一覧が提出されており対象取引の網羅性が確認できる | F107: ○ | G107: ○ | H107: □ | I107: □ | L107: 統合マスタ v1（内製作成 2026.6）
A108: 102 | B108: 17 | C108: 費用振替取引の要因説明 | D108: 17-003 | E108: 各振替について承認者と振替理由が記録されており承認証跡（稟議・メール等）が確認できる | F108: ○ | G108: ○ | H108: □ | I108: □ | L108: 統合マスタ v1（内製作成 2026.6）
A109: 103 | B109: 17 | C109: 費用振替取引の要因説明 | D109: 17-004 | E109: 振替理由が合理的であり恣意的な利益移動の意図がないことが説明されている | F109: ○ | G109: ○ | H109: □ | I109: □ | L109: 統合マスタ v1（内製作成 2026.6）
A110: 104 | B110: 18 | C110: 各費用月次推移分析 | D110: 18-001 | E110: データソースと抽出条件（手順）の記録が成果物として提出されている | F110: ○ | G110: ○ | H110: □ | I110: □ | K110: 計245件指摘 ▶網羅性・試算表不一致(103件): 例)「・上記作成の上で必要となるデータソース及び抽出条件が分かる資料（画面コピーなど）の送付をお願いいたします ・網羅性が確認できる資料（残高試算表との一致確認）の送…」 ▶根拠資料不足(74件): 例)「2026年3月の販売費及び一般管理費の合計と自主点検06の根拠資料として格納されております月次推移表の3月の金額が一致していないかと存じますが、ご確認いただけま…」 【構成単位固有】計107件 ▶網羅性・試算表不一致(69件): 例)「(産業・医療・その他) ・販管科目の推移グラフの作成をお願いいたします (EN) ・データソース及び抽出条件手順)が分か…」 ▶根拠資料不足(19件): 例)「・根拠資料を確認すると、交際費や支払運賃費等成果物に未記載なものが見受けられるため追記いただきますようお願いいたします。」 ▶その他(13件): 例)「25年4月～26年3月の科目毎のグラフが作成されていません。」 ▶コメント・説明不足(6件): 例)「・グラフがおかしいかと思います（4月-3月ではなく、1-12ですし、マイナスの月もマイナスになっていません。正しいグラフ…」 | L110: レビュー指針 No.18（input/自主点検_レビュー指針.xlsx）
A111: 105 | B111: 18 | C111: 各費用月次推移分析 | D111: 18-002 | E111: 網羅性が確認できる情報が記載又は提出されている | F111: ○ | G111: ○ | H111: □ | I111: □ | K111: 計245件指摘 ▶網羅性・試算表不一致(103件): 例)「・上記作成の上で必要となるデータソース及び抽出条件が分かる資料（画面コピーなど）の送付をお願いいたします ・網羅性が確認できる資料（残高試算表との一致確認）の送…」 ▶根拠資料不足(74件): 例)「2026年3月の販売費及び一般管理費の合計と自主点検06の根拠資料として格納されております月次推移表の3月の金額が一致していないかと存じますが、ご確認いただけま…」 | L111: レビュー指針 No.18（input/自主点検_レビュー指針.xlsx）
A112: 106 | B112: 18 | C112: 各費用月次推移分析 | D112: 18-003 | E112: 25年4月～26年3月の科目毎の月次推移表及びグラフが作成されている | F112: ○ | G112: ○ | H112: □ | I112: □ | K112: 計245件指摘 ▶網羅性・試算表不一致(103件): 例)「・上記作成の上で必要となるデータソース及び抽出条件が分かる資料（画面コピーなど）の送付をお願いいたします ・網羅性が確認できる資料（残高試算表との一致確認）の送…」 ▶根拠資料不足(74件): 例)「2026年3月の販売費及び一般管理費の合計と自主点検06の根拠資料として格納されております月次推移表の3月の金額が一致していないかと存じますが、ご確認いただけま…」 ▶【構成単位固有要件】グラフ作成が1次レビュー要件（非構成単位はグラフ不要。適切コメントがあれば差し戻しとしない） | L112: レビュー指針 No.18（input/自主点検_レビュー指針.xlsx） | M112: 【構成単位1次レビュー要件】グラフ作成が必須（適切コメントがある場合は差し戻しとしない）
A113: 107 | B113: 18 | C113: 各費用月次推移分析 | D113: 18-004 | E113: 変動額と要因分析のコメントに記載されている影響金額が概ね整合している | F113: ○ | G113: ○ | H113: □ | I113: □ | K113: 計245件指摘 ▶網羅性・試算表不一致(103件): 例)「・上記作成の上で必要となるデータソース及び抽出条件が分かる資料（画面コピーなど）の送付をお願いいたします ・網羅性が確認できる資料（残高試算表との一致確認）の送…」 ▶根拠資料不足(74件): 例)「2026年3月の販売費及び一般管理費の合計と自主点検06の根拠資料として格納されております月次推移表の3月の金額が一致していないかと存じますが、ご確認いただけま…」 | L113: レビュー指針 No.18（input/自主点検_レビュー指針.xlsx）
A114: 108 | B114: 18 | C114: 各費用月次推移分析 | D114: 18-005 | E114: 変動の大きい科目について、要因の説明が十分にされている | F114: ○ | G114: ○ | H114: □ | I114: □ | K114: 計245件指摘 ▶網羅性・試算表不一致(103件): 例)「・上記作成の上で必要となるデータソース及び抽出条件が分かる資料（画面コピーなど）の送付をお願いいたします ・網羅性が確認できる資料（残高試算表との一致確認）の送…」 ▶根拠資料不足(74件): 例)「2026年3月の販売費及び一般管理費の合計と自主点検06の根拠資料として格納されております月次推移表の3月の金額が一致していないかと存じますが、ご確認いただけま…」 | L114: レビュー指針 No.18（input/自主点検_レビュー指針.xlsx）
A115: 109 | B115: 18 | C115: 各費用月次推移分析 | D115: 18-006 | E115: 変動の説明をサポートする適切な根拠資料が提出されている | F115: ○ | G115: ○ | H115: □ | I115: □ | K115: 計245件指摘 ▶網羅性・試算表不一致(103件): 例)「・上記作成の上で必要となるデータソース及び抽出条件が分かる資料（画面コピーなど）の送付をお願いいたします ・網羅性が確認できる資料（残高試算表との一致確認）の送…」 ▶根拠資料不足(74件): 例)「2026年3月の販売費及び一般管理費の合計と自主点検06の根拠資料として格納されております月次推移表の3月の金額が一致していないかと存じますが、ご確認いただけま…」 | L115: レビュー指針 No.18（input/自主点検_レビュー指針.xlsx）
A116: 110 | B116: 18 | C116: 各費用月次推移分析 | D116: 18-007 | E116: 25年4月～26年3月の科目毎の月次推移表が作成されている | F116: ○ | G116: ○ | H116: □ | I116: □ | K116: 計245件指摘 ▶網羅性・試算表不一致(103件): 例)「・上記作成の上で必要となるデータソース及び抽出条件が分かる資料（画面コピーなど）の送付をお願いいたします ・網羅性が確認できる資料（残高試算表との一致確認）の送…」 ▶根拠資料不足(74件): 例)「2026年3月の販売費及び一般管理費の合計と自主点検06の根拠資料として格納されております月次推移表の3月の金額が一致していないかと存じますが、ご確認いただけま…」 | L116: レビュー指針 No.18（input/自主点検_レビュー指針.xlsx） | M116: 【非構成単位専用】構成単位版は18-003が適用（グラフが1次レビュー要件）。
A117: 111 | B117: 18 | C117: 各費用月次推移分析 | D117: 18-008 | E117: 変動の大きい科目について、要因の説明がなされている | F117: ○ | G117: ○ | H117: □ | I117: □ | K117: 計245件指摘 ▶網羅性・試算表不一致(103件): 例)「・上記作成の上で必要となるデータソース及び抽出条件が分かる資料（画面コピーなど）の送付をお願いいたします ・網羅性が確認できる資料（残高試算表との一致確認）の送…」 ▶根拠資料不足(74件): 例)「2026年3月の販売費及び一般管理費の合計と自主点検06の根拠資料として格納されております月次推移表の3月の金額が一致していないかと存じますが、ご確認いただけま…」 | L117: レビュー指針 No.18（input/自主点検_レビュー指針.xlsx） | M117: 【非構成単位専用】構成単位版は18-004〜18-006が適用。
A118: 112 | B118: 19 | C118: 翌期取引の確認 | D118: 19-001 | E118: データソースと抽出条件（手順）の記録が成果物として提出されている | F118: ○ | G118: ○ | H118: □ | I118: □ | K118: 計195件指摘 ▶根拠資料不足(70件): 例)「貴社親会社が作成した自主点検の説明資料によると、確認方法（作業イメージ）は以下の通りです。 １．2026年4月に費用計上された仕訳の明細データを出⼒し、明細デー…」 ▶網羅性・試算表不一致(66件): 例)「・データソース及び抽出条件が分かる資料（画面コピーなど）の送付をお願いします ・網羅性が確認できる資料（試算表との一致確認）の送付をお願いします…」 【構成単位固有】計65件 ▶網羅性・試算表不一致(44件): 例)「貴社親会社が作成した自主点検の説明資料によると、確認方法（作業イメージ）は以下の通りです。 １．2026年4月に費用計上…」 ▶その他(13件): 例)「・4月の仕訳データから3月に計上すべき仕訳を抽出した際の抽出条件が分かる資料の送付をお願いします」 ▶根拠資料不足(6件): 例)「№19の「当期に費用計上すべき請求書の有無」について、成果物フォルダの一次レビュー及び二次レビューそれぞれにExcelを…」 ▶コメント・説明不足(2件): 例)「・4月の総勘定元帳から3月に計上すべき仕訳を抽出する際、例えば摘要欄に「3月」と記載がある仕訳を検索するなどされているか…」 | L118: レビュー指針 No.19（input/自主点検_レビュー指針.xlsx）
A119: 113 | B119: 19 | C119: 翌期取引の確認 | D119: 19-002 | E119: 網羅性が確認できる情報が記載又は提出されている | F119: ○ | G119: ○ | H119: □ | I119: □ | K119: 計195件指摘 ▶根拠資料不足(70件): 例)「貴社親会社が作成した自主点検の説明資料によると、確認方法（作業イメージ）は以下の通りです。 １．2026年4月に費用計上された仕訳の明細データを出⼒し、明細デー…」 ▶網羅性・試算表不一致(66件): 例)「・データソース及び抽出条件が分かる資料（画面コピーなど）の送付をお願いします ・網羅性が確認できる資料（試算表との一致確認）の送付をお願いします…」 | L119: レビュー指針 No.19（input/自主点検_レビュー指針.xlsx）
A120: 114 | B120: 19 | C120: 翌期取引の確認 | D120: 19-003 | E120: 仕訳明細データの摘要欄等から、26年3月以前に費用計上すべき費用の有無を確認している | F120: ○ | G120: ○ | H120: □ | I120: □ | K120: 計195件指摘 ▶根拠資料不足(70件): 例)「貴社親会社が作成した自主点検の説明資料によると、確認方法（作業イメージ）は以下の通りです。 １．2026年4月に費用計上された仕訳の明細データを出⼒し、明細デー…」 ▶網羅性・試算表不一致(66件): 例)「・データソース及び抽出条件が分かる資料（画面コピーなど）の送付をお願いします ・網羅性が確認できる資料（試算表との一致確認）の送付をお願いします…」 | L120: レビュー指針 No.19（input/自主点検_レビュー指針.xlsx）
A121: 115 | B121: 19 | C121: 翌期取引の確認 | D121: 19-004 | E121: 26年3月以前に費用計上すべきリスクのある費用について会計処理の顛末が適切に記載されている | F121: ○ | G121: ○ | H121: □ | I121: □ | K121: 計195件指摘 ▶根拠資料不足(70件): 例)「貴社親会社が作成した自主点検の説明資料によると、確認方法（作業イメージ）は以下の通りです。 １．2026年4月に費用計上された仕訳の明細データを出⼒し、明細デー…」 ▶網羅性・試算表不一致(66件): 例)「・データソース及び抽出条件が分かる資料（画面コピーなど）の送付をお願いします ・網羅性が確認できる資料（試算表との一致確認）の送付をお願いします…」 | L121: レビュー指針 No.19（input/自主点検_レビュー指針.xlsx）
A122: 116 | B122: 19 | C122: 翌期取引の確認 | D122: 19-005 | E122: 修正した場合、伝票番号等が記載され、第三者が確認できるようになっている | F122: ○ | G122: ○ | H122: □ | I122: □ | K122: 計195件指摘 ▶根拠資料不足(70件): 例)「貴社親会社が作成した自主点検の説明資料によると、確認方法（作業イメージ）は以下の通りです。 １．2026年4月に費用計上された仕訳の明細データを出⼒し、明細デー…」 ▶網羅性・試算表不一致(66件): 例)「・データソース及び抽出条件が分かる資料（画面コピーなど）の送付をお願いします ・網羅性が確認できる資料（試算表との一致確認）の送付をお願いします…」 | L122: レビュー指針 No.19（input/自主点検_レビュー指針.xlsx）
A123: 117 | B123: 20 | C123: 非経常的取引の識別と説明 | D123: 20-001 | E123: 管理部門により非経常的な取引について各部署から情報を収集している | F123: ○ | G123: ○ | H123: □ | I123: □ | K123: 計86件指摘 ▶根拠資料不足(37件): 例)「・該当なしのご回答をご提出されましたが、管理部門より各部署に情報収集を実施したことの証明できる証憑（メール、アンケート等）をご送付ください…」 ▶その他(15件): 例)「各部署アンケートで「非経常的取引：あり」と回答された内容について、 以下内容を示す資料のご提出をお願いいたします。 ①収集した情報を基に、管理部門が会計処理を検…」 【構成単位固有】計34件 ▶根拠資料不足(17件): 例)「・該当なしのご回答をご提出されましたが、管理部門より各部署に情報収集を実施したことの証明できる証憑（メール、アンケート等…」 ▶その他(10件): 例)「各部署アンケートで「非経常的取引：あり」と回答された内容について、 以下内容を示す資料のご提出をお願いいたします。 ①収…」 ▶コメント・説明不足(7件): 例)「東日本営業所にて修理案件が報告されていますが、会計処理についての顛末記載がありません。 成果物として「収集した情報を基に…」 | L123: レビュー指針 No.20（input/自主点検_レビュー指針.xlsx）
A124: 118 | B124: 20 | C124: 非経常的取引の識別と説明 | D124: 20-002 | E124: 収集した情報を基に、管理部門が会計処理を検討している | F124: ○ | G124: ○ | H124: □ | I124: □ | K124: 計86件指摘 ▶根拠資料不足(37件): 例)「・該当なしのご回答をご提出されましたが、管理部門より各部署に情報収集を実施したことの証明できる証憑（メール、アンケート等）をご送付ください…」 ▶その他(15件): 例)「各部署アンケートで「非経常的取引：あり」と回答された内容について、 以下内容を示す資料のご提出をお願いいたします。 ①収集した情報を基に、管理部門が会計処理を検…」 | L124: レビュー指針 No.20（input/自主点検_レビュー指針.xlsx）
A125: 119 | B125: 20 | C125: 非経常的取引の識別と説明 | D125: 20-003 | E125: 非経常的な取引がある場合、管理部門は収集情報に基づいて正しい会計処理を行っている | F125: ○ | G125: ○ | H125: □ | I125: □ | K125: 計86件指摘 ▶根拠資料不足(37件): 例)「・該当なしのご回答をご提出されましたが、管理部門より各部署に情報収集を実施したことの証明できる証憑（メール、アンケート等）をご送付ください…」 ▶その他(15件): 例)「各部署アンケートで「非経常的取引：あり」と回答された内容について、 以下内容を示す資料のご提出をお願いいたします。 ①収集した情報を基に、管理部門が会計処理を検…」 | L125: レビュー指針 No.20（input/自主点検_レビュー指針.xlsx）
A126: 120 | B126: 21 | C126: 見積計上費用：計上根拠 | D126: 21-001 | E126: データソースと抽出条件（手順）の記録が成果物として提出されている | F126: ○ | G126: ○ | H126: □ | I126: □ | K126: 計144件指摘 ▶網羅性・試算表不一致(57件): 例)「・データソース及び抽出条件が分かる資料（抽出する際の条件を記載した画面スクショなど）の提出をお願い出来ますでしょうか。 ・データの網羅性確認のため、試算表の提出…」 ▶根拠資料不足(40件): 例)「■販管費等の明細をご提出いただておりますが、こちらすべて見積に係る費用となりますでしょうか。 ①明細すべてが見積に係る費用の場合 ＞見積計上費用の根拠資料（一定…」 【構成単位固有】計52件 ▶網羅性・試算表不一致(30件): 例)「・データソース及び抽出条件が分かる資料（抽出する際の条件を記載した画面スクショなど）の提出をお願い出来ますでしょうか。 …」 ▶根拠資料不足(10件): 例)「総勘定元帳の格納ありがとうございました。 202603見積計上費用リスト（集計）Excelファイルを最終成果物として改め…」 ▶コメント・説明不足(7件): 例)「未払費用、賞与引当金、棚卸評価引当金の計上に際し、見積の要素(仮定や概算に基づく計上)はございませんでしょうか。見積の要…」 ▶その他(5件): 例)「・検討過程を確認するため、2026年3月の仕訳データに対する検討証跡を提出いただけますでしょうか。」 | L126: レビュー指針 No.21（input/自主点検_レビュー指針.xlsx）
A127: 121 | B127: 21 | C127: 見積計上費用：計上根拠 | D127: 21-002 | E127: 網羅性が確認できる情報が記載又は提出されている | F127: ○ | G127: ○ | H127: □ | I127: □ | K127: 計144件指摘 ▶網羅性・試算表不一致(57件): 例)「・データソース及び抽出条件が分かる資料（抽出する際の条件を記載した画面スクショなど）の提出をお願い出来ますでしょうか。 ・データの網羅性確認のため、試算表の提出…」 ▶根拠資料不足(40件): 例)「■販管費等の明細をご提出いただておりますが、こちらすべて見積に係る費用となりますでしょうか。 ①明細すべてが見積に係る費用の場合 ＞見積計上費用の根拠資料（一定…」 | L127: レビュー指針 No.21（input/自主点検_レビュー指針.xlsx）
A128: 122 | B128: 21 | C128: 見積計上費用：計上根拠 | D128: 21-003 | E128: 見積計上の根拠が十分に示されている | F128: ○ | G128: ○ | H128: □ | I128: □ | K128: 計144件指摘 ▶網羅性・試算表不一致(57件): 例)「・データソース及び抽出条件が分かる資料（抽出する際の条件を記載した画面スクショなど）の提出をお願い出来ますでしょうか。 ・データの網羅性確認のため、試算表の提出…」 ▶根拠資料不足(40件): 例)「■販管費等の明細をご提出いただておりますが、こちらすべて見積に係る費用となりますでしょうか。 ①明細すべてが見積に係る費用の場合 ＞見積計上費用の根拠資料（一定…」 | L128: レビュー指針 No.21（input/自主点検_レビュー指針.xlsx）
A129: 123 | B129: 22 | C129: 固定資産除却損の計上確認 | D129: 22-001 | E129: データソースと抽出条件（手順）の記録が成果物として提出されている | F129: ○ | G129: ○ | H129: □ | I129: □ | K129: 計148件指摘 ▶網羅性・試算表不一致(60件): 例)「・「22_固定資産の除却取引_成果物（AWLSol）」について、資産ごとの固定資産除却損を記載いただけますでしょうか。 ・資産ごとの固定資産除却損の合計額が試算…」 ▶根拠資料不足(55件): 例)「・除却取引全てについて根拠資料(仕訳伝票だけでなく、例えば、除却申請書や職務権限決裁報告書)が提出されていない ・除却売却明細1行ごとの証憑（除却申請書など）を…」 【構成単位固有】計74件 ▶網羅性・試算表不一致(48件): 例)「・「22_固定資産の除却取引_成果物（AWLSol）」について、資産ごとの固定資産除却損を記載いただけますでしょうか。 …」 ▶その他(15件): 例)「No.120 Follow-up： 成果物ファイルは更新されていません。3月単月ではなく、年間分のすべての固定資産除却取…」 ▶根拠資料不足(8件): 例)「・除却取引全てについて根拠資料(仕訳伝票だけでなく、例えば、除却申請書や職務権限決裁報告書)が提出されていない ・除却売…」 ▶コメント・説明不足(3件): 例)「No.111でのご対応ありがとうございました。 年間分の固定資産除却取引の記載が必要ですので、成果物の更新をお願いいたし…」 | L129: レビュー指針 No.22（input/自主点検_レビュー指針.xlsx）
... A136: 130 | B136: 23 | C136: 固定資産の資産性確認 | D136: 23-004 | E136: フラグが付された明細の固定資産計上に関する合理的な説明がされているか | F136: ○ | G136: ○ | H136: □ | I136: □ | K136: 計139件指摘 ▶網羅性・試算表不一致(74件): 例)「・試算表との一致が確認できる資料（一致の記載/画面コピー）をお願いします ・固定資産台帳の抽出条件が分かる資料（画面コピーなど）の送付をお願いします ・「自主点…」 ▶根拠資料不足(37件): 例)「車両運搬具で計上している「ボデー修理一式」について、資産計上の根拠となる追加証憑（稟議等で修理内容を説明されているものなど）のご提供をお願いいたします。 なお、…」 | L136: レビュー指針 No.23（input/自主点検_レビュー指針.xlsx）
A137: 131 | B137: 24 | C137: 資産除去債務の計上要否の判断を証憑に基づいて整理（証憑提出含む） | D137: 24-001 | E137: データソースと抽出条件（手順）の記録が成果物として提出されている | F137: ○ | H137: □ | I137: □ | K137: 計1件指摘 ▶根拠資料不足(1件): 例)「・25年7月支払い額と引当減資(2503時引当金)の差異の金額および差異が生じた要因についてコメントが記載されていませんでしたので、記載をお願いできますでしょう…」 | L137: 統合マスタ v1（内製作成 2026.6）
A138: 132 | B138: 24 | C138: 資産除去債務の計上要否の判断を証憑に基づいて整理（証憑提出含む） | D138: 24-002 | E138: 「資産除去債務に関するアンケート」（エクセル）の全設問（質問Ⅰ〜Ⅳ）が記入・提出されている | F138: ○ | H138: □ | I138: □ | K138: 計1件指摘 ▶根拠資料不足(1件): 例)「・25年7月支払い額と引当減資(2503時引当金)の差異の金額および差異が生じた要因についてコメントが記載されていませんでしたので、記載をお願いできますでしょう…」 | L138: 統合マスタ v1（内製作成 2026.6）
A139: 133 | B139: 24 | C139: 資産除去債務の計上要否の判断を証憑に基づいて整理（証憑提出含む） | D139: 24-003 | E139: アンケート記載の必要添付資料（賃貸借契約書・固定資産台帳等）が漏れなく提出されている | F139: ○ | H139: □ | I139: □ | K139: 計1件指摘 ▶根拠資料不足(1件): 例)「・25年7月支払い額と引当減資(2503時引当金)の差異の金額および差異が生じた要因についてコメントが記載されていませんでしたので、記載をお願いできますでしょう…」 | L139: 統合マスタ v1（内製作成 2026.6）
A140: 134 | B140: 24 | C140: 資産除去債務の計上要否の判断を証憑に基づいて整理（証憑提出含む） | D140: 24-004 | E140: 資産除去債務の計上要否の判断が証憑（賃貸借契約書・過去の固定資産除却損実績等）に基づき整理されている | F140: ○ | H140: □ | I140: □ | K140: 計1件指摘 ▶根拠資料不足(1件): 例)「・25年7月支払い額と引当減資(2503時引当金)の差異の金額および差異が生じた要因についてコメントが記載されていませんでしたので、記載をお願いできますでしょう…」 | L140: 統合マスタ v1（内製作成 2026.6）
A141: 135 | B141: 24 | C141: 資産除去債務の計上要否の判断を証憑に基づいて整理（証憑提出含む） | D141: 24-005 | E141: 計上すべき資産除去債務が漏れなく計上されており計上金額と見積根拠が整合している（差異がある場合は要因説明あり） | F141: ○ | H141: □ | I141: □ | K141: 計1件指摘 ▶根拠資料不足(1件): 例)「・25年7月支払い額と引当減資(2503時引当金)の差異の金額および差異が生じた要因についてコメントが記載されていませんでしたので、記載をお願いできますでしょう…」 | L141: 統合マスタ v1（内製作成 2026.6）
A142: 136 | B142: 25 | C142: 減損テスト | D142: 25-001 | E142: データソースと抽出条件（手順）の記録が成果物として提出されている | F142: ○ | G142: ○ | H142: □ | I142: □ | K142: 計169件指摘 ▶網羅性・試算表不一致(65件): 例)「2025年3月期全社TBの営業損益の一致が確認できる情報や資料のご提出をお願いします。…」 ▶根拠資料不足(45件): 例)「2025年3月期全社TBの営業損益との一致が確認できる資料の送付をお願いします。…」 【構成単位固有】計108件 ▶網羅性・試算表不一致(45件): 例)「2025年3月期全社TBの営業損益の一致が確認できる情報や資料のご提出をお願いします。」 ▶コメント・説明不足(33件): 例)「提出頂いた減損判定資料について、 ・検討基準日が2025年9月末の資料をご提出頂いているかと思いますが、今回2026年3…」 ▶その他(20件): 例)「・データソースと抽出条件（手順）の記録が成果物として提出されていない …数値のバックデータ（割引率、成長率、事業計画、事…」 ▶根拠資料不足(10件): 例)「ワークシートに入力されている土地・土地の固定資産税評価額・有形固定資産・無形資産の金額、前々期、前期、当期の営業損益の入…」 | L142: レビュー指針 No.25（input/自主点検_レビュー指針.xlsx）
...

Sheet 点検項目インデックス
A2: 自主点検 点検項目インデックス（28項目）
A3: ■ 会社名: ________________________ ■ 実施期: ______________ ■ サイクル (年度末 / 四半期): __________ ■ 記入者: ________________________
A4: 【凡例】 ☑提出 → □ を記入 / 対象外・未実施 → 「該当なし」に □ 記入し、理由を記述のうえ提出可。全行チェックは必須ではありません。
A6: No | B6: 点検項目名 | C6: 関連科目・取引 | D6: 提出物数 | E6: CP数 | F6: 年度末 対象 | G6: 四半期 対象 | H6: 過去事例 件数 | I6: 備考
A7: 1 | B7: 売掛金の残高確認 | C7: 売掛金、売上 | D7: =COUNTIF(提出物チェックリスト!$B$7:$B$88,$A7) -> 5 | E7: =COUNTIF(チェックポイント確認!$B$7:$B$169,$A7) -> 7 | F7: ○ | H7: 0
A8: 2 | B8: 在庫の実地棚卸 | C8: 棚卸資産、売上 | D8: =COUNTIF(提出物チェックリスト!$B$7:$B$88,$A8) -> 2 | E8: =COUNTIF(チェックポイント確認!$B$7:$B$169,$A8) -> 6 | F8: ○ | H8: 0
A9: 3 | B9: 固定資産の実査 | C9: 固定資産 | D9: =COUNTIF(提出物チェックリスト!$B$7:$B$88,$A9) -> 6 | E9: =COUNTIF(チェックポイント確認!$B$7:$B$169,$A9) -> 8 | F9: ○ | H9: 0
A10: 4 | B10: 滞留債権の分析 | C10: 売掛金 | D10: =COUNTIF(提出物チェックリスト!$B$7:$B$88,$A10) -> 4 | E10: =COUNTIF(チェックポイント確認!$B$7:$B$169,$A10) -> 7 | F10: ○ | G10: ○ | H10: 199
A11: 5 | B11: 異常取引の分析 | C11: 売上 | D11: =COUNTIF(提出物チェックリスト!$B$7:$B$88,$A11) -> 4 | E11: =COUNTIF(チェックポイント確認!$B$7:$B$169,$A11) -> 5 | F11: ○ | G11: ○ | H11: 350
A12: 6 | B12: 売上の期末変動分析 | C12: 売上 | D12: =COUNTIF(提出物チェックリスト!$B$7:$B$88,$A12) -> 3 | E12: =COUNTIF(チェックポイント確認!$B$7:$B$169,$A12) -> 8 | F12: ○ | G12: ○ | H12: 199
A13: 7 | B13: 収益認識アンケート（証憑提出含む） | C13: 売上 | D13: =COUNTIF(提出物チェックリスト!$B$7:$B$88,$A13) -> 3 | E13: =COUNTIF(チェックポイント確認!$B$7:$B$169,$A13) -> 7 | F13: ○ | G13: ○ | H13: 0
A14: 8 | B14: 売上のカットオフテスト | C14: 売上 | D14: =COUNTIF(提出物チェックリスト!$B$7:$B$88,$A14) -> 3 | E14: =COUNTIF(チェックポイント確認!$B$7:$B$169,$A14) -> 8 | F14: ○ | G14: ○ | H14: 285
A15: 9 | B15: 長期請負工事案件の洗い出し | C15: 売上、仕掛品 | D15: =COUNTIF(提出物チェックリスト!$B$7:$B$88,$A15) -> 3 | E15: =COUNTIF(チェックポイント確認!$B$7:$B$169,$A15) -> 6 | F15: ○ | G15: ○ | H15: 22
A16: 10 | B16: 実行予算の取得・確認 | C16: 売上、仕掛品 | D16: =COUNTIF(提出物チェックリスト!$B$7:$B$88,$A16) -> 2 | E16: =COUNTIF(チェックポイント確認!$B$7:$B$169,$A16) -> 5 | F16: ○ | G16: ○ | H16: 19
A17: 11 | B17: 材料費の実際発生原価の確認 | C17: 売上原価、仕掛品 | D17: =COUNTIF(提出物チェックリスト!$B$7:$B$88,$A17) -> 3 | E17: =COUNTIF(チェックポイント確認!$B$7:$B$169,$A17) -> 5 | F17: ○ | G17: ○ | H17: 17
A18: 12 | B18: 進捗率の算定根拠の確認 | C18: 売上、仕掛品 | D18: =COUNTIF(提出物チェックリスト!$B$7:$B$88,$A18) -> 3 | E18: =COUNTIF(チェックポイント確認!$B$7:$B$169,$A18) -> 7 | F18: ○ | G18: ○ | H18: 22
A19: 13 | B19: 経費の実際発生原価の確認 | C19: 売上原価、仕掛品 | D19: =COUNTIF(提出物チェックリスト!$B$7:$B$88,$A19) -> 3 | E19: =COUNTIF(チェックポイント確認!$B$7:$B$169,$A19) -> 4 | F19: ○ | G19: ○ | H19: 14
A20: 14 | B20: 原価振替取引の要因説明 | C20: 売上原価 | D20: =COUNTIF(提出物チェックリスト!$B$7:$B$88,$A20) -> 3 | E20: =COUNTIF(チェックポイント確認!$B$7:$B$169,$A20) -> 5 | F20: ○ | G20: ○ | H20: 20
A21: 15 | B21: 低粗利案件の分析 | C21: 売上原価 | D21: =COUNTIF(提出物チェックリスト!$B$7:$B$88,$A21) -> 3 | E21: =COUNTIF(チェックポイント確認!$B$7:$B$169,$A21) -> 7 | F21: ○ | G21: ○ | H21: 18
... A29: 23 | B29: 固定資産の資産性確認 | C29: 固定資産 | D29: =COUNTIF(提出物チェックリスト!$B$7:$B$88,$A29) -> 3 | E29: =COUNTIF(チェックポイント確認!$B$7:$B$169,$A29) -> 4 | F29: ○ | G29: ○ | H29: 139
A30: 24 | B30: 資産除去債務の計上要否の判断を証憑に基づいて整理（証憑提出含む） | C30: 固定資産、資産除去債務 | D30: =COUNTIF(提出物チェックリスト!$B$7:$B$88,$A30) -> 2 | E30: =COUNTIF(チェックポイント確認!$B$7:$B$169,$A30) -> 5 | F30: ○ | H30: 1
A31: 25 | B31: 減損テスト | C31: 固定資産、のれん、投資その他の資産 | D31: =COUNTIF(提出物チェックリスト!$B$7:$B$88,$A31) -> 4 | E31: =COUNTIF(チェックポイント確認!$B$7:$B$169,$A31) -> 6 | F31: ○ | G31: ○ | H31: 169
A32: 26 | B32: 賞与引当金の計上確認 | C32: 賞与引当金、賞与 | D32: =COUNTIF(提出物チェックリスト!$B$7:$B$88,$A32) -> 4 | E32: =COUNTIF(チェックポイント確認!$B$7:$B$169,$A32) -> 8 | F32: ○ | G32: ○ | H32: 193
A33: 27 | B33: 自主点検チェックリスト | C33: 全般 | D33: =COUNTIF(提出物チェックリスト!$B$7:$B$88,$A33) -> 1 | E33: =COUNTIF(チェックポイント確認!$B$7:$B$169,$A33) -> 7 | F33: ○ | G33: ○ | H33: 1
A34: 28 | B34: 財務分析 | C34: 全般 | D34: =COUNTIF(提出物チェックリスト!$B$7:$B$88,$A34) -> 2 | E34: =COUNTIF(チェックポイント確認!$B$7:$B$169,$A34) -> 7 | F34: ○ | G34: ○ | H34: 9
A35: 合計 | D35: =SUM(D7:D34) -> 82 | E35: =SUM(E7:E34) -> 163 | H35: =SUM(H7:H34) -> 2495
