Workbook

Sheet 自主点検項目
A1: No | B1: 自主点検項目名 | C1: 関連科目・取引 | D1: 備考
A2: 1 | B2: 売掛金の残高確認 | C2: 売掛金、売上
A3: 2 | B3: 在庫の実地棚卸 | C3: 棚卸資産、売上
A4: 3 | B4: 固定資産の実査 | C4: 固定資産
A5: 4 | B5: 滞留債権の分析 | C5: 売掛金
A6: 5 | B6: 異常取引の分析 | C6: 売上
A7: 6 | B7: 売上の期末変動分析 | C7: 売上
A8: 7 | B8: 収益認識アンケート（証憑提出含む） | C8: 売上
A9: 8 | B9: 売上のカットオフテスト | C9: 売上
A10: 9 | B10: 長期請負工事案件の洗い出し | C10: 売上、仕掛品
A11: 10 | B11: 実行予算の取得・確認 | C11: 売上、仕掛品
A12: 11 | B12: 材料費の実際発生原価の確認 | C12: 売上原価、仕掛品
A13: 12 | B13: 進捗率の算定根拠の確認 | C13: 売上、仕掛品
... A29: 28 | B29: 財務分析 | C29: 全般

Sheet 提出物
A1: No | B1: 自主点検項目No | C1: 自主点検項目名 | D1: 提出物名 | E1: 提出物詳細 | F1: 区分 | G1: 提出区分 | H1: 適用の目安（条件付き・代替・排他の場合） | I1: 提出 | J1: 該当なし | K1: 非該当・未提出の理由 | L1: 備考
A2: 1 | B2: 1 | C2: =IFERROR(INDEX(自主点検項目!$B:$B,MATCH(B2,自主点検項目!$A:$A,0)),"") -> 売掛金の残高確認 | D2: 残高確認状の回収結果・差異調整結果 | F2: ①成果物本体 | G2: 必須
A3: 2 | B3: 1 | C3: =IFERROR(INDEX(自主点検項目!$B:$B,MATCH(B3,自主点検項目!$A:$A,0)),"") -> 売掛金の残高確認 | D3: 代替手続実施結果 | E3: 代替手続チェックリスト・入金消込管理表の検証資料 | F3: ①成果物本体 | G3: 条件付き | H3: 確認状を回収できない/発送しない相手先(個人・官公庁等)がある場合
A4: 3 | B4: 1 | C4: =IFERROR(INDEX(自主点検項目!$B:$B,MATCH(B4,自主点検項目!$A:$A,0)),"") -> 売掛金の残高確認 | D4: 追加サンプリング結果 | F4: ②根拠資料 | G4: 条件付き | H4: 2026年6月以降入金予定の3月末売掛金残高が閾値以上
A5: 4 | B5: 1 | C5: =IFERROR(INDEX(自主点検項目!$B:$B,MATCH(B5,自主点検項目!$A:$A,0)),"") -> 売掛金の残高確認 | D5: 売掛金明細 | E5: 2026年3月末 | F5: ③共通添付 | G5: 必須
A6: 5 | B6: 1 | C6: =IFERROR(INDEX(自主点検項目!$B:$B,MATCH(B6,自主点検項目!$A:$A,0)),"") -> 売掛金の残高確認 | D6: 試算表＋連結PKGまでの調整 | E6: 3月末 | F6: ③共通添付 | G6: 必須
A7: 6 | B7: 2 | C7: =IFERROR(INDEX(自主点検項目!$B:$B,MATCH(B7,自主点検項目!$A:$A,0)),"") -> 在庫の実地棚卸 | D7: 実地棚卸の結果 | E7: 別途ガイダンスに従い提出 | F7: ①成果物本体 | G7: 必須
A8: 7 | B8: 2 | C8: =IFERROR(INDEX(自主点検項目!$B:$B,MATCH(B8,自主点検項目!$A:$A,0)),"") -> 在庫の実地棚卸 | D8: 預り売上に関する親会社への情報・検討内容 | F8: ①成果物本体 | G8: 条件付き | H8: 預り売上(請求済未出荷)を計上している場合(原則禁止)
A9: 8 | B9: 3 | C9: =IFERROR(INDEX(自主点検項目!$B:$B,MATCH(B9,自主点検項目!$A:$A,0)),"") -> 固定資産の実査 | D9: 固定資産実査報告書 | E9: 確定版:エクセル＋部署長検印済PDF | F9: ①成果物本体 | G9: 必須
A10: 9 | B10: 3 | C10: =IFERROR(INDEX(自主点検項目!$B:$B,MATCH(B10,自主点検項目!$A:$A,0)),"") -> 固定資産の実査 | D10: 現物照合の写真 | F10: ②根拠資料 | G10: 必須
A11: 10 | B11: 3 | C11: =IFERROR(INDEX(自主点検項目!$B:$B,MATCH(B11,自主点検項目!$A:$A,0)),"") -> 固定資産の実査 | D11: 代替証跡 | E11: 登記簿・リース契約書・使用実績資料等 | F11: ②根拠資料 | G11: 代替 | H11: 現物カウントが困難な資産がある場合
A12: 11 | B12: 3 | C12: =IFERROR(INDEX(自主点検項目!$B:$B,MATCH(B12,自主点検項目!$A:$A,0)),"") -> 固定資産の実査 | D12: 固定資産訂正仕訳が必要な資産の報告書 | F12: ①成果物本体 | G12: 条件付き | H12: 現物照合で訂正(除却漏れ・資産性等)が発覚した場合
A13: 12 | B13: 3 | C13: =IFERROR(INDEX(自主点検項目!$B:$B,MATCH(B13,自主点検項目!$A:$A,0)),"") -> 固定資産の実査 | D13: 修正仕訳のエビデンス | E13: Proplusモニターシート・Biz∫仕訳 | F13: ②根拠資料 | G13: 条件付き | H13: 修正仕訳を起票した場合
A14: 13 | B14: 3 | C14: =IFERROR(INDEX(自主点検項目!$B:$B,MATCH(B14,自主点検項目!$A:$A,0)),"") -> 固定資産の実査 | D14: 独立立会人による実査立会結果 | F14: ①成果物本体 | G14: 条件付き | H14: 第2線立会対象(規模条件)
A15: 14 | B15: 4 | C15: =IFERROR(INDEX(自主点検項目!$B:$B,MATCH(B15,自主点検項目!$A:$A,0)),"") -> 滞留債権の分析 | D15: 期末滞留債権一覧 | E15: 回収遅延理由・最新回収予定日 | F15: ①成果物本体 | G15: 必須
A16: 15 | B16: 4 | C16: =IFERROR(INDEX(自主点検項目!$B:$B,MATCH(B16,自主点検項目!$A:$A,0)),"") -> 滞留債権の分析 | D16: 売掛金明細・試算表の一致 | E16: データソース・抽出条件 | F16: ③共通添付 | G16: 必須
A17: 16 | B17: 4 | C17: =IFERROR(INDEX(自主点検項目!$B:$B,MATCH(B17,自主点検項目!$A:$A,0)),"") -> 滞留債権の分析 | D17: 回収遅延理由の承認証跡 | F17: ②根拠資料 | G17: 代替 | H17: 部門責任者等の承認(チェックリスト承認で代替可)
A18: 17 | B18: 4 | C18: =IFERROR(INDEX(自主点検項目!$B:$B,MATCH(B18,自主点検項目!$A:$A,0)),"") -> 滞留債権の分析 | D18: 外部証憑 | E18: 契約書・注文書・納品書 等 | F18: ②根拠資料 | G18: 条件付き | H18: 回収遅延理由が合理的でない債権がある場合
A19: 18 | B19: 5 | C19: =IFERROR(INDEX(自主点検項目!$B:$B,MATCH(B19,自主点検項目!$A:$A,0)),"") -> 異常取引の分析 | D19: 年間取引データ | E19: 取引先別・案件別ソート,マイナス理由記載 | F19: ①成果物本体 | G19: 必須
A20: 19 | B20: 5 | C20: =IFERROR(INDEX(自主点検項目!$B:$B,MATCH(B20,自主点検項目!$A:$A,0)),"") -> 異常取引の分析 | D20: 翌期4月分の二次提出データ | F20: ①成果物本体 | G20: 必須
A21: 20 | B21: 5 | C21: =IFERROR(INDEX(自主点検項目!$B:$B,MATCH(B21,自主点検項目!$A:$A,0)),"") -> 異常取引の分析 | D21: データソース・抽出条件 | E21: 全明細と試算表の一致 | F21: ③共通添付 | G21: 必須
A22: 21 | B22: 5 | C22: =IFERROR(INDEX(自主点検項目!$B:$B,MATCH(B22,自主点検項目!$A:$A,0)),"") -> 異常取引の分析 | D22: マイナス取引の根拠資料 | E22: ①計上妥当②取消妥当 | F22: ②根拠資料 | G22: 条件付き | H22: 2次レビューで確認が必要な取引
A23: 22 | B23: 6 | C23: =IFERROR(INDEX(自主点検項目!$B:$B,MATCH(B23,自主点検項目!$A:$A,0)),"") -> 売上の期末変動分析 | D23: 月次の売上・粗利推移データ | E23: グラフ・増減分析コメント | F23: ①成果物本体 | G23: 必須
A24: 23 | B24: 6 | C24: =IFERROR(INDEX(自主点検項目!$B:$B,MATCH(B24,自主点検項目!$A:$A,0)),"") -> 売上の期末変動分析 | D24: データソース・抽出条件 | E24: 試算表との一致 | F24: ③共通添付 | G24: 必須
A25: 24 | B25: 6 | C25: =IFERROR(INDEX(自主点検項目!$B:$B,MATCH(B25,自主点検項目!$A:$A,0)),"") -> 売上の期末変動分析 | D25: 増減要因の根拠証憑 | F25: ②根拠資料 | G25: 条件付き | H25: 四半期末月に上昇傾向・重要変動がある場合
A26: 25 | B26: 7 | C26: =IFERROR(INDEX(自主点検項目!$B:$B,MATCH(B26,自主点検項目!$A:$A,0)),"") -> 収益認識アンケート（証憑提出含む） | D26: 収益認識アンケート回答 | E26: SPファイル直接更新/メール返信 | F26: ①成果物本体 | G26: 必須
A27: 26 | B27: 7 | C27: =IFERROR(INDEX(自主点検項目!$B:$B,MATCH(B27,自主点検項目!$A:$A,0)),"") -> 収益認識アンケート（証憑提出含む） | D27: 契約書PDF | E27: 取引基本契約書等 | F27: ②根拠資料 | G27: 条件付き | H27: 年間売上金額が閾値以上の取引(半期提出済は再提出不要)
A28: 27 | B28: 7 | C28: =IFERROR(INDEX(自主点検項目!$B:$B,MATCH(B28,自主点検項目!$A:$A,0)),"") -> 収益認識アンケート（証憑提出含む） | D28: 当期の売上明細データ | E28: 試算表との一致を事前確認 | F28: ③共通添付 | G28: 必須
A29: 28 | B29: 8 | C29: =IFERROR(INDEX(自主点検項目!$B:$B,MATCH(B29,自主点検項目!$A:$A,0)),"") -> 売上のカットオフテスト | D29: 売上明細データ | E29: 検証結果コメント付 | F29: ①成果物本体 | G29: 必須
A30: 29 | B30: 8 | C30: =IFERROR(INDEX(自主点検項目!$B:$B,MATCH(B30,自主点検項目!$A:$A,0)),"") -> 売上のカットオフテスト | D30: データソース・抽出条件 | E30: 3月単月の試算表一致 | F30: ③共通添付 | G30: 必須
A31: 30 | B31: 8 | C31: =IFERROR(INDEX(自主点検項目!$B:$B,MATCH(B31,自主点検項目!$A:$A,0)),"") -> 売上のカットオフテスト | D31: 収益認識の根拠資料 | F31: ②根拠資料 | G31: 条件付き | H31: 一定金額以上の取引に限る
A32: 31 | B32: 9 | C32: =IFERROR(INDEX(自主点検項目!$B:$B,MATCH(B32,自主点検項目!$A:$A,0)),"") -> 長期請負工事案件の洗い出し | D32: 進行基準適用案件リスト | E32: 履行義務毎の判断根拠 | F32: ①成果物本体 | G32: 必須
A33: 32 | B33: 9 | C33: =IFERROR(INDEX(自主点検項目!$B:$B,MATCH(B33,自主点検項目!$A:$A,0)),"") -> 長期請負工事案件の洗い出し | D33: データソース・抽出条件 | E33: PKG進行基準売上との一致 | F33: ③共通添付 | G33: 必須
A34: 33 | B34: 9 | C34: =IFERROR(INDEX(自主点検項目!$B:$B,MATCH(B34,自主点検項目!$A:$A,0)),"") -> 長期請負工事案件の洗い出し | D34: 契約書 | E34: 請負高5億円超の案件 | F34: ②根拠資料 | G34: 条件付き | H34: 請負高が閾値超の案件(No.7で提出済を確認)
A35: 34 | B35: 10 | C35: =IFERROR(INDEX(自主点検項目!$B:$B,MATCH(B35,自主点検項目!$A:$A,0)),"") -> 実行予算の取得・確認 | D35: 進行基準適用案件毎の実行予算 月次推移 | E35: グラフ・増減コメント | F35: ①成果物本体 | G35: 必須
A36: 35 | B36: 10 | C36: =IFERROR(INDEX(自主点検項目!$B:$B,MATCH(B36,自主点検項目!$A:$A,0)),"") -> 実行予算の取得・確認 | D36: データソース・抽出条件 | E36: No.9リストとの整合 | F36: ③共通添付 | G36: 必須
A37: 36 | B37: 11 | C37: =IFERROR(INDEX(自主点検項目!$B:$B,MATCH(B37,自主点検項目!$A:$A,0)),"") -> 材料費の実際発生原価の確認 | D37: 原材料購買データと入庫データの月次比較表 | F37: ①成果物本体 | G37: 必須
A38: 37 | B38: 11 | C38: =IFERROR(INDEX(自主点検項目!$B:$B,MATCH(B38,自主点検項目!$A:$A,0)),"") -> 材料費の実際発生原価の確認 | D38: 工事案件原価明細と出庫データの紐づけ | E38: 案件毎シート | F38: ①成果物本体 | G38: 必須
A39: 38 | B39: 11 | C39: =IFERROR(INDEX(自主点検項目!$B:$B,MATCH(B39,自主点検項目!$A:$A,0)),"") -> 材料費の実際発生原価の確認 | D39: 差異取引の外部根拠証憑 | F39: ②根拠資料 | G39: 条件付き | H39: 入出庫と整合しない購買・原価明細がある場合
A40: 39 | B40: 12 | C40: =IFERROR(INDEX(自主点検項目!$B:$B,MATCH(B40,自主点検項目!$A:$A,0)),"") -> 進捗率の算定根拠の確認 | D40: 進行基準適用案件毎の進捗率 月次推移表 | E40: 要因コメント | F40: ①成果物本体 | G40: 必須
A41: 40 | B41: 12 | C41: =IFERROR(INDEX(自主点検項目!$B:$B,MATCH(B41,自主点検項目!$A:$A,0)),"") -> 進捗率の算定根拠の確認 | D41: 進捗率の算定根拠資料 | E41: 実行予算書・原価明細 | F41: ②根拠資料 | G41: 必須
A42: 41 | B42: 12 | C42: =IFERROR(INDEX(自主点検項目!$B:$B,MATCH(B42,自主点検項目!$A:$A,0)),"") -> 進捗率の算定根拠の確認 | D42: データソース・抽出条件 | E42: No.9整合 | F42: ③共通添付 | G42: 必須
A43: 42 | B43: 13 | C43: =IFERROR(INDEX(自主点検項目!$B:$B,MATCH(B43,自主点検項目!$A:$A,0)),"") -> 経費の実際発生原価の確認 | D43: 滞留未成工事支出金一覧 | E43: 滞留要因・初回原価発生日・振替予定日 | F43: ①成果物本体 | G43: 必須
A44: 43 | B44: 13 | C44: =IFERROR(INDEX(自主点検項目!$B:$B,MATCH(B44,自主点検項目!$A:$A,0)),"") -> 経費の実際発生原価の確認 | D44: データソース・抽出条件 | E44: 試算表との一致 | F44: ③共通添付 | G44: 必須
A45: 44 | B45: 13 | C45: =IFERROR(INDEX(自主点検項目!$B:$B,MATCH(B45,自主点検項目!$A:$A,0)),"") -> 経費の実際発生原価の確認 | D45: 滞留要因の根拠証憑 | F45: ②根拠資料 | G45: 条件付き | H45: 2次レビューで必要に応じ依頼
A46: 45 | B46: 14 | C46: =IFERROR(INDEX(自主点検項目!$B:$B,MATCH(B46,自主点検項目!$A:$A,0)),"") -> 原価振替取引の要因説明 | D46: 案件毎原価明細のマイナス取引と取消・振替理由 | F46: ①成果物本体 | G46: 必須
A47: 46 | B47: 14 | C47: =IFERROR(INDEX(自主点検項目!$B:$B,MATCH(B47,自主点検項目!$A:$A,0)),"") -> 原価振替取引の要因説明 | D47: データソース・抽出基準/手順 | E47: 発生原価合計との一致 | F47: ③共通添付 | G47: 必須
A48: 47 | B48: 14 | C48: =IFERROR(INDEX(自主点検項目!$B:$B,MATCH(B48,自主点検項目!$A:$A,0)),"") -> 原価振替取引の要因説明 | D48: 原価マイナス取引の根拠証憑 | E48: 承認証跡含む | F48: ②根拠資料 | G48: 条件付き | H48: 請負高が閾値以上の案件
A49: 48 | B49: 15 | C49: =IFERROR(INDEX(自主点検項目!$B:$B,MATCH(B49,自主点検項目!$A:$A,0)),"") -> 低粗利案件の分析 | D49: 案件毎の利益率 月次推移表 | E49: 全案件 | F49: ①成果物本体 | G49: 必須
A50: 49 | B50: 15 | C50: =IFERROR(INDEX(自主点検項目!$B:$B,MATCH(B50,自主点検項目!$A:$A,0)),"") -> 低粗利案件の分析 | D50: 原価振替有無の調査結果と根拠資料 | F50: ①成果物本体 | G50: 条件付き | H50: 請負高1億円以上＆利益率5%以下＆一定期間変動なしの案件
A51: 50 | B51: 15 | C51: =IFERROR(INDEX(自主点検項目!$B:$B,MATCH(B51,自主点検項目!$A:$A,0)),"") -> 低粗利案件の分析 | D51: データソース・抽出条件 | E51: No.14原価明細との整合 | F51: ③共通添付 | G51: 必須
A52: 51 | B52: 16 | C52: =IFERROR(INDEX(自主点検項目!$B:$B,MATCH(B52,自主点検項目!$A:$A,0)),"") -> 社内/会社間取引の価格設定の妥当性チェック | D52: 価格設定の妥当性確認資料 | F52: ①成果物本体 | G52: 条件付き | H52: 親会社が別途指定(個別ルール)
A53: 52 | B53: 17 | C53: =IFERROR(INDEX(自主点検項目!$B:$B,MATCH(B53,自主点検項目!$A:$A,0)),"") -> 費用振替取引の要因説明 | D53: 費用振替の承認者・理由の記録 | F53: ①成果物本体 | G53: 条件付き | H53: 親会社が別途指定(個別ルール)
A54: 53 | B54: 18 | C54: =IFERROR(INDEX(自主点検項目!$B:$B,MATCH(B54,自主点検項目!$A:$A,0)),"") -> 各費用月次推移分析 | D54: 販管費の月次推移データ | E54: グラフ・期末月増加の分析コメント | F54: ①成果物本体 | G54: 必須
A55: 54 | B55: 18 | C55: =IFERROR(INDEX(自主点検項目!$B:$B,MATCH(B55,自主点検項目!$A:$A,0)),"") -> 各費用月次推移分析 | D55: データソース・抽出条件 | E55: 試算表との一致 | F55: ③共通添付 | G55: 必須
A56: 55 | B56: 18 | C56: =IFERROR(INDEX(自主点検項目!$B:$B,MATCH(B56,自主点検項目!$A:$A,0)),"") -> 各費用月次推移分析 | D56: 著しい増加の根拠資料 | F56: ②根拠資料 | G56: 条件付き | H56: 期末月に著しい増加がある場合
A57: 56 | B57: 19 | C57: =IFERROR(INDEX(自主点検項目!$B:$B,MATCH(B57,自主点検項目!$A:$A,0)),"") -> 翌期取引の確認 | D57: 翌期4月計上仕訳データ一覧 | E57: 3月計上すべき費用の顛末 | F57: ①成果物本体 | G57: 必須
A58: 57 | B58: 19 | C58: =IFERROR(INDEX(自主点検項目!$B:$B,MATCH(B58,自主点検項目!$A:$A,0)),"") -> 翌期取引の確認 | D58: データソース・抽出条件 | E58: 試算表との一致 | F58: ③共通添付 | G58: 必須
A59: 58 | B59: 19 | C59: =IFERROR(INDEX(自主点検項目!$B:$B,MATCH(B59,自主点検項目!$A:$A,0)),"") -> 翌期取引の確認 | D59: 3月分として計上すべき費用の根拠資料 | F59: ②根拠資料 | G59: 条件付き | H59: 当期3月計上すべき費用が見つかった場合
A60: 59 | B60: 20 | C60: =IFERROR(INDEX(自主点検項目!$B:$B,MATCH(B60,自主点検項目!$A:$A,0)),"") -> 非経常的取引の識別と説明 | D60: 管理部門が各部署から情報収集したことが分かる資料 | E60: メール・アンケート | F60: ①成果物本体 | G60: 必須
A61: 60 | B61: 20 | C61: =IFERROR(INDEX(自主点検項目!$B:$B,MATCH(B61,自主点検項目!$A:$A,0)),"") -> 非経常的取引の識別と説明 | D61: 収集情報を基に会計処理を検討したことが分かる資料 | F61: ①成果物本体 | G61: 条件付き | H61: 非経常的な取引・事象がある場合
A62: 61 | B62: 21 | C62: =IFERROR(INDEX(自主点検項目!$B:$B,MATCH(B62,自主点検項目!$A:$A,0)),"") -> 見積計上費用：計上根拠 | D62: 当期3月の見積計上費用リスト | E62: 会計処理の顛末 | F62: ①成果物本体 | G62: 必須
A63: 62 | B63: 21 | C63: =IFERROR(INDEX(自主点検項目!$B:$B,MATCH(B63,自主点検項目!$A:$A,0)),"") -> 見積計上費用：計上根拠 | D63: 見積根拠資料 | E63: 契約書・正式見積書・検針データ等 | F63: ②根拠資料 | G63: 必須
A64: 63 | B64: 21 | C64: =IFERROR(INDEX(自主点検項目!$B:$B,MATCH(B64,自主点検項目!$A:$A,0)),"") -> 見積計上費用：計上根拠 | D64: データソース・網羅性の確認 | F64: ③共通添付 | G64: 必須
A65: 64 | B65: 22 | C65: =IFERROR(INDEX(自主点検項目!$B:$B,MATCH(B65,自主点検項目!$A:$A,0)),"") -> 固定資産除却損の計上確認 | D65: 総勘定元帳から抽出した当期の除却取引 | E65: コメント付 | F65: ①成果物本体 | G65: 必須
A66: 65 | B66: 22 | C66: =IFERROR(INDEX(自主点検項目!$B:$B,MATCH(B66,自主点検項目!$A:$A,0)),"") -> 固定資産除却損の計上確認 | D66: データソース／試算表との一致 | E66: 総勘定元帳 | F66: ③共通添付 | G66: 必須
A67: 66 | B67: 22 | C67: =IFERROR(INDEX(自主点検項目!$B:$B,MATCH(B67,自主点検項目!$A:$A,0)),"") -> 固定資産除却損の計上確認 | D67: 除却の根拠資料 | E67: 除却申請書・廃棄証明書 等 | F67: ②根拠資料 | G67: 必須
A68: 67 | B68: 23 | C68: =IFERROR(INDEX(自主点検項目!$B:$B,MATCH(B68,自主点検項目!$A:$A,0)),"") -> 固定資産の資産性確認 | D68: 固定資産台帳でフラグ付けした明細＋資産計上妥当性コメント | F68: ①成果物本体 | G68: 必須
A69: 68 | B69: 23 | C69: =IFERROR(INDEX(自主点検項目!$B:$B,MATCH(B69,自主点検項目!$A:$A,0)),"") -> 固定資産の資産性確認 | D69: データソース・抽出条件 | E69: 台帳簿価と試算表の一致 | F69: ③共通添付 | G69: 必須
A70: 69 | B70: 23 | C70: =IFERROR(INDEX(自主点検項目!$B:$B,MATCH(B70,自主点検項目!$A:$A,0)),"") -> 固定資産の資産性確認 | D70: 資産計上の根拠資料 | E70: 見積書・仕様書・請求書・稟議書 | F70: ②根拠資料 | G70: 必須
A71: 70 | B71: 24 | C71: =IFERROR(INDEX(自主点検項目!$B:$B,MATCH(B71,自主点検項目!$A:$A,0)),"") -> 資産除去債務の計上要否の判断を証憑に基づいて整理（証憑提出含む） | D71: 「資産除去債務に関するアンケート」回答済みエクセル | F71: ①成果物本体 | G71: 必須
A72: 71 | B72: 24 | C72: =IFERROR(INDEX(自主点検項目!$B:$B,MATCH(B72,自主点検項目!$A:$A,0)),"") -> 資産除去債務の計上要否の判断を証憑に基づいて整理（証憑提出含む） | D72: アンケートに記載の必要資料 | F72: ②根拠資料 | G72: 条件付き | H72: 該当固定資産を保有(質問Ⅰ・Ⅱに該当)する場合
A73: 72 | B73: 25 | C73: =IFERROR(INDEX(自主点検項目!$B:$B,MATCH(B73,自主点検項目!$A:$A,0)),"") -> 減損テスト | D73: 各CGUの減損判定資料 | F73: ①成果物本体 | G73: 必須
A74: 73 | B74: 25 | C74: =IFERROR(INDEX(自主点検項目!$B:$B,MATCH(B74,自主点検項目!$A:$A,0)),"") -> 減損テスト | D74: 割引前・割引後 将来CF算定資料 | F74: ②根拠資料 | G74: 条件付き | H74: 減損の兆候に抵触したCGUがある場合(IFRS含め検討)
A75: 74 | B75: 25 | C75: =IFERROR(INDEX(自主点検項目!$B:$B,MATCH(B75,自主点検項目!$A:$A,0)),"") -> 減損テスト | D75: 固定資産領域の内部統制・減損処理アンケート | E75: フォーム回答 | F75: ①成果物本体 | G75: 必須
A76: 75 | B76: 25 | C76: =IFERROR(INDEX(自主点検項目!$B:$B,MATCH(B76,自主点検項目!$A:$A,0)),"") -> 減損テスト | D76: データソース | E76: CGU営業損益と全社TBの一致 | F76: ③共通添付 | G76: 必須
A77: 76 | B77: 26 | C77: =IFERROR(INDEX(自主点検項目!$B:$B,MATCH(B77,自主点検項目!$A:$A,0)),"") -> 賞与引当金の計上確認 | D77: 計上根拠資料 | E77: 繰入額の計算根拠 | F77: ②根拠資料 | G77: 排他 | H77: 賞与引当金を計上している場合
A78: 77 | B78: 26 | C78: =IFERROR(INDEX(自主点検項目!$B:$B,MATCH(B78,自主点検項目!$A:$A,0)),"") -> 賞与引当金の計上確認 | D78: 取崩時の支払証跡＋当初計上額と支払額の比較分析 | F78: ①成果物本体 | G78: 条件付き | H78: 計上・取崩がある場合
A79: 78 | B79: 26 | C79: =IFERROR(INDEX(自主点検項目!$B:$B,MATCH(B79,自主点検項目!$A:$A,0)),"") -> 賞与引当金の計上確認 | D79: 計上不要とした理由コメント | F79: ①成果物本体 | G79: 排他 | H79: 賞与引当金を計上していない場合
A80: 79 | B80: 26 | C80: =IFERROR(INDEX(自主点検項目!$B:$B,MATCH(B80,自主点検項目!$A:$A,0)),"") -> 賞与引当金の計上確認 | D80: 月次推移表／繰入額・残高と試算表の一致 | E80: PL | F80: ③共通添付 | G80: 必須
A81: 80 | B81: 27 | C81: =IFERROR(INDEX(自主点検項目!$B:$B,MATCH(B81,自主点検項目!$A:$A,0)),"") -> 自主点検チェックリスト | D81: 自主点検チェックリスト | E81: No.1〜26の自己評価 | F81: ①成果物本体 | G81: 必須
A82: 81 | B82: 28 | C82: =IFERROR(INDEX(自主点検項目!$B:$B,MATCH(B82,自主点検項目!$A:$A,0)),"") -> 財務分析 | D82: 連結PKG上の増減分析 | F82: ①成果物本体 | G82: 必須
A83: 82 | B83: 28 | C83: =IFERROR(INDEX(自主点検項目!$B:$B,MATCH(B83,自主点検項目!$A:$A,0)),"") -> 財務分析 | D83: 個社別の財務分析用ファイル | F83: ①成果物本体 | G83: 条件付き | H83: 個社別財務分析の対象会社

Sheet レビュー指針
A1: レビュー項目No | B1: 自主点検項目No | C1: 自主点検項目名 | D1: カテゴリ | E1: レビュー区分 | F1: 構成単位区分 | G1: 種別 | H1: レビュー項目 | I1: メモ | J1: 紐づくCP数 | K1: 紐づく事例件数
A2: 1 | B2: 4 | C2: =IFERROR(INDEX(自主点検項目!$B:$B,MATCH(B2,自主点検項目!$A:$A,0)),"") -> 滞留債権の分析 | D2: 成果物 | E2: 1次レビュー | F2: 共通 | G2: レビュー項目 | H2: データソースと抽出条件（手順）の記録が成果物として提出されている | I2: 試算表との一致確認がなく、データソース・抽出手順も不明の資料は不備ありとする | J2: =COUNTIF(チェックポイント!$I:$I,A2) -> 2 | K2: =SUMIF(チェックポイント!$I:$I,A2,チェックポイント!$G:$G) -> 71
A3: 2 | B3: 4 | C3: =IFERROR(INDEX(自主点検項目!$B:$B,MATCH(B3,自主点検項目!$A:$A,0)),"") -> 滞留債権の分析 | D3: 成果物 | E3: 1次レビュー | F3: 共通 | G3: レビュー項目 | H3: 網羅性が確認できる情報が記載又は提出されている（試算表との一致が確認できる） | I3: 網羅性の確認 | J3: =COUNTIF(チェックポイント!$I:$I,A3) -> 1 | K3: =SUMIF(チェックポイント!$I:$I,A3,チェックポイント!$G:$G) -> 85
A4: 3 | B4: 4 | C4: =IFERROR(INDEX(自主点検項目!$B:$B,MATCH(B4,自主点検項目!$A:$A,0)),"") -> 滞留債権の分析 | D4: 成果物 | E4: 1次レビュー | F4: 共通 | G4: レビュー項目 | H4: 回収が遅延している債権全てにつき、回収遅延理由が記載されている | J4: =COUNTIF(チェックポイント!$I:$I,A4) -> 2 | K4: =SUMIF(チェックポイント!$I:$I,A4,チェックポイント!$G:$G) -> 15
A5: 4 | B5: 4 | C5: =IFERROR(INDEX(自主点検項目!$B:$B,MATCH(B5,自主点検項目!$A:$A,0)),"") -> 滞留債権の分析 | D5: 成果物 | E5: 1次レビュー | F5: 共通 | G5: レビュー項目 | H5: 回収遅延理由について、部門責任者等の適切な承認者の承認を得ている | I5: 承認証跡がなくても追加依頼は不要（チェックリストの承認を承認証跡として考えればok） | J5: =COUNTIF(チェックポイント!$I:$I,A5) -> 2 | K5: =SUMIF(チェックポイント!$I:$I,A5,チェックポイント!$G:$G) -> 3
A6: 5 | B6: 4 | C6: =IFERROR(INDEX(自主点検項目!$B:$B,MATCH(B6,自主点検項目!$A:$A,0)),"") -> 滞留債権の分析 | D6: コメントの妥当性 | E6: 2次レビュー | F6: 共通 | G6: レビュー項目 | H6: 回収遅延理由が合理的である | J6: =COUNTIF(チェックポイント!$I:$I,A6) -> 0 | K6: =SUMIF(チェックポイント!$I:$I,A6,チェックポイント!$G:$G) -> 0
A7: 6 | B7: 4 | C7: =IFERROR(INDEX(自主点検項目!$B:$B,MATCH(B7,自主点検項目!$A:$A,0)),"") -> 滞留債権の分析 | D7: 対応の十分性 | E7: 2次レビュー | F7: 共通 | G7: レビュー項目 | H7: 回収遅延理由が合理的でない場合、売上計上の妥当性に関するコメントが記載されている | J7: =COUNTIF(チェックポイント!$I:$I,A7) -> 0 | K7: =SUMIF(チェックポイント!$I:$I,A7,チェックポイント!$G:$G) -> 0
A8: 7 | B8: 4 | C8: =IFERROR(INDEX(自主点検項目!$B:$B,MATCH(B8,自主点検項目!$A:$A,0)),"") -> 滞留債権の分析 | D8: コメントの妥当性 | E8: 2次レビュー | F8: 共通 | G8: レビュー項目 | H8: 注文書などの外部証憑を確認したうえで、適切に売上計上の妥当性をコメントできている | I8: 対応する売上高に実態があるかどうかの確認 | J8: =COUNTIF(チェックポイント!$I:$I,A8) -> 0 | K8: =SUMIF(チェックポイント!$I:$I,A8,チェックポイント!$G:$G) -> 0
A9: 8 | B9: 5 | C9: =IFERROR(INDEX(自主点検項目!$B:$B,MATCH(B9,自主点検項目!$A:$A,0)),"") -> 異常取引の分析 | D9: 成果物 | E9: 1次レビュー | F9: 共通 | G9: レビュー項目 | H9: データソースと抽出条件（手順）の記録が成果物として提出されている | I9: 試算表との一致確認がなく、データソース・抽出手順も不明の資料は不備ありとする | J9: =COUNTIF(チェックポイント!$I:$I,A9) -> 1 | K9: =SUMIF(チェックポイント!$I:$I,A9,チェックポイント!$G:$G) -> 89
A10: 9 | B10: 5 | C10: =IFERROR(INDEX(自主点検項目!$B:$B,MATCH(B10,自主点検項目!$A:$A,0)),"") -> 異常取引の分析 | D10: 成果物 | E10: 1次レビュー | F10: 共通 | G10: レビュー項目 | H10: 25年4月~26年3月の全ての売上明細（マイナス含む）が提出されている（試算表との一致が確認できる） | I10: 網羅性の確認 | J10: =COUNTIF(チェックポイント!$I:$I,A10) -> 4 | K10: =SUMIF(チェックポイント!$I:$I,A10,チェックポイント!$G:$G) -> 159
A11: 10 | B11: 5 | C11: =IFERROR(INDEX(自主点検項目!$B:$B,MATCH(B11,自主点検項目!$A:$A,0)),"") -> 異常取引の分析 | D11: 成果物 | E11: 1次レビュー | F11: 共通 | G11: レビュー項目 | H11: マイナスの売上がある場合、売上計上の妥当性（収益認識基準を満たしているか）を検討したコメントが残されている | I11: No.5は根拠証憑が全件提出されていなくてもコメントがあればokとする。2次レビューにおいて、確認が必要なものだけ資料を依頼する | J11: =COUNTIF(チェックポイント!$I:$I,A11) -> 3 | K11: =SUMIF(チェックポイント!$I:$I,A11,チェックポイント!$G:$G) -> 14
A12: 11 | B12: 5 | C12: =IFERROR(INDEX(自主点検項目!$B:$B,MATCH(B12,自主点検項目!$A:$A,0)),"") -> 異常取引の分析 | D12: 収益認識基準の充足 | E12: 2次レビュー | F12: 共通 | G12: レビュー項目 | H12: マイナス売上の売上は収益認識基準を満たした売上計上である（例えば、リスクの高いマイナス取引については、根拠資料を確認したうえで①売上計上と②取消それぞれの観点で合理的なコメントが出来ているかの確認が必要） | J12: =COUNTIF(チェックポイント!$I:$I,A12) -> 2 | K12: =SUMIF(チェックポイント!$I:$I,A12,チェックポイント!$G:$G) -> 14
A13: 12 | B13: 5 | C13: =IFERROR(INDEX(自主点検項目!$B:$B,MATCH(B13,自主点検項目!$A:$A,0)),"") -> 異常取引の分析 | D13: 対応の適切性 | E13: 2次レビュー | F13: 共通 | G13: レビュー項目 | H13: 収益認識基準を満たさない売上計上の場合は、会計処理の顛末が記載されている | J13: =COUNTIF(チェックポイント!$I:$I,A13) -> 2 | K13: =SUMIF(チェックポイント!$I:$I,A13,チェックポイント!$G:$G) -> 7
A14: 13 | B14: 5 | C14: =IFERROR(INDEX(自主点検項目!$B:$B,MATCH(B14,自主点検項目!$A:$A,0)),"") -> 異常取引の分析 | D14: 閾値 （構成単位） | E14: 2次レビュー | F14: 構成単位 | G14: 選定方針 | H14: 当該項目は対象取引数が多いため、以下の閾値を設定し、レビュー対象を限定する 金額：2,000万円以上を対象。ただし、最低でも5件はレビューを実施 →当該閾値を設定しても件数が多い場合は自主点検Tまで連絡 | J14: =COUNTIF(チェックポイント!$I:$I,A14) -> 0 | K14: =SUMIF(チェックポイント!$I:$I,A14,チェックポイント!$G:$G) -> 0
A15: 14 | B15: 5 | C15: =IFERROR(INDEX(自主点検項目!$B:$B,MATCH(B15,自主点検項目!$A:$A,0)),"") -> 異常取引の分析 | D15: 閾値 （構成単位以外） | E15: 2次レビュー | F15: 構成単位以外 | G15: 選定方針 | H15: 当該項目は対象取引数が多いため、以下の閾値を設定し、レビュー対象を限定する 金額：2,000万円以上を対象。ただし、最低でも3件はレビューを実施 →当該閾値を設定しても件数が多い場合は自主点検Tまで連絡 | I15: 構成単位以外の最低件数は3件としている | J15: =COUNTIF(チェックポイント!$I:$I,A15) -> 0 | K15: =SUMIF(チェックポイント!$I:$I,A15,チェックポイント!$G:$G) -> 0
A16: 15 | B16: 5 | C16: =IFERROR(INDEX(自主点検項目!$B:$B,MATCH(B16,自主点検項目!$A:$A,0)),"") -> 異常取引の分析 | D16: 記入例 | E16: 2次レビュー | F16: 共通 | G16: 記入例 | H16: ①自主点検レビュー結果には、以下を記載 問題なしの場合→「特段異常なし。」 差し戻しの場合→「No.x、xxの取引について、リスクがあると判断（取引の詳細は成果物を参照）」 ②成果物には、取引ごとに以下の方針で記載（どれをレビュー対象としたのか） 問題なしの場合→「〇〇を確認し、売上計上は妥当である。また、取消理由についても妥当であることから、特段異常なし。」 差し戻しの場合→「取消理由に合理性がなく、〇〇を確認した結果、△△が不一致のため、売上計上にリスクがあり検討必要と判断」 ・〇〇は資料名 ・△△は数量、金額、計上日 | I16: ①はサマリのイメージ、②はどの取引をレビューしたのか、レビューの詳細を把握したい | J16: =COUNTIF(チェックポイント!$I:$I,A16) -> 0 | K16: =SUMIF(チェックポイント!$I:$I,A16,チェックポイント!$G:$G) -> 0
A17: 16 | B17: 6 | C17: =IFERROR(INDEX(自主点検項目!$B:$B,MATCH(B17,自主点検項目!$A:$A,0)),"") -> 売上の期末変動分析 | D17: 成果物 | E17: 1次レビュー | F17: 構成単位 | G17: レビュー項目 | H17: データソースと抽出条件（手順）の記録が成果物として提出されている | I17: 試算表との一致確認がなく、データソース・抽出手順も不明の資料は不備ありとする | J17: =COUNTIF(チェックポイント!$I:$I,A17) -> 2 | K17: =SUMIF(チェックポイント!$I:$I,A17,チェックポイント!$G:$G) -> 91
A18: 17 | B18: 6 | C18: =IFERROR(INDEX(自主点検項目!$B:$B,MATCH(B18,自主点検項目!$A:$A,0)),"") -> 売上の期末変動分析 | D18: 成果物 | E18: 1次レビュー | F18: 構成単位 | G18: レビュー項目 | H18: 網羅性が確認できる情報が記載又は提出されている（試算表との一致が確認できる） | I18: 網羅性の確認 | J18: =COUNTIF(チェックポイント!$I:$I,A18) -> 2 | K18: =SUMIF(チェックポイント!$I:$I,A18,チェックポイント!$G:$G) -> 88
A19: 18 | B19: 6 | C19: =IFERROR(INDEX(自主点検項目!$B:$B,MATCH(B19,自主点検項目!$A:$A,0)),"") -> 売上の期末変動分析 | D19: 成果物 | E19: 1次レビュー | F19: 構成単位 | G19: レビュー項目 | H19: 前年同期・前月比較ともに、10百万円の変動、かつ、20%以上の変動がある場合、増減コメントがされている | J19: =COUNTIF(チェックポイント!$I:$I,A19) -> 1 | K19: =SUMIF(チェックポイント!$I:$I,A19,チェックポイント!$G:$G) -> 9
A20: 19 | B20: 6 | C20: =IFERROR(INDEX(自主点検項目!$B:$B,MATCH(B20,自主点検項目!$A:$A,0)),"") -> 売上の期末変動分析 | D20: 成果物 | E20: 1次レビュー | F20: 構成単位 | G20: レビュー項目 | H20: 増減分析コメントにて、要因毎の影響金額を記載している（最低限、6割～7割程度） | J20: =COUNTIF(チェックポイント!$I:$I,A20) -> 2 | K20: =SUMIF(チェックポイント!$I:$I,A20,チェックポイント!$G:$G) -> 14
A21: 20 | B21: 6 | C21: =IFERROR(INDEX(自主点検項目!$B:$B,MATCH(B21,自主点検項目!$A:$A,0)),"") -> 売上の期末変動分析 | D21: 成果物 | E21: 1次レビュー | F21: 構成単位 | G21: レビュー項目 | H21: 特に四半期末月に上昇傾向があった場合に、根拠資料に基づいて売上計上の妥当性を検証している。また、検証した旨がコメントされている。 | J21: =COUNTIF(チェックポイント!$I:$I,A21) -> 3 | K21: =SUMIF(チェックポイント!$I:$I,A21,チェックポイント!$G:$G) -> 11
A22: 21 | B22: 6 | C22: =IFERROR(INDEX(自主点検項目!$B:$B,MATCH(B22,自主点検項目!$A:$A,0)),"") -> 売上の期末変動分析 | D22: 分析の妥当性 | E22: 2次レビュー | F22: 構成単位 | G22: レビュー項目 | H22: 増減分析コメントにて、増減内容の説明になっている | J22: =COUNTIF(チェックポイント!$I:$I,A22) -> 1 | K22: =SUMIF(チェックポイント!$I:$I,A22,チェックポイント!$G:$G) -> 2
A23: 22 | B23: 6 | C23: =IFERROR(INDEX(自主点検項目!$B:$B,MATCH(B23,自主点検項目!$A:$A,0)),"") -> 売上の期末変動分析 | D23: 分析の妥当性 | E23: 2次レビュー | F23: 構成単位 | G23: レビュー項目 | H23: 増減分析コメントにて、金額推移と整合した説明になっている | J23: =COUNTIF(チェックポイント!$I:$I,A23) -> 0 | K23: =SUMIF(チェックポイント!$I:$I,A23,チェックポイント!$G:$G) -> 0
A24: 23 | B24: 6 | C24: =IFERROR(INDEX(自主点検項目!$B:$B,MATCH(B24,自主点検項目!$A:$A,0)),"") -> 売上の期末変動分析 | D24: 成果物 | E24: 1次レビュー | F24: 構成単位以外 | G24: レビュー項目 | H24: データソースと抽出条件（手順）の記録が成果物として提出されている | I24: 試算表との一致確認がなく、データソース・抽出手順も不明の資料は不備ありとする | J24: =COUNTIF(チェックポイント!$I:$I,A24) -> 0 | K24: =SUMIF(チェックポイント!$I:$I,A24,チェックポイント!$G:$G) -> 0
A25: 24 | B25: 6 | C25: =IFERROR(INDEX(自主点検項目!$B:$B,MATCH(B25,自主点検項目!$A:$A,0)),"") -> 売上の期末変動分析 | D25: 成果物 | E25: 1次レビュー | F25: 構成単位以外 | G25: レビュー項目 | H25: 網羅性が確認できる情報が記載又は提出されている（試算表との一致が確認できる） | I25: 網羅性の確認 | J25: =COUNTIF(チェックポイント!$I:$I,A25) -> 0 | K25: =SUMIF(チェックポイント!$I:$I,A25,チェックポイント!$G:$G) -> 0
A26: 25 | B26: 6 | C26: =IFERROR(INDEX(自主点検項目!$B:$B,MATCH(B26,自主点検項目!$A:$A,0)),"") -> 売上の期末変動分析 | D26: 成果物 | E26: 1次レビュー | F26: 構成単位以外 | G26: レビュー項目 | H26: 前年同期・前月比較ともに、10百万円の変動、かつ、20%以上の変動がある場合、増減コメントがされている 特に四半期末月に上昇傾向があった場合に、増減分析コメントにて、要因を記載している | I26: 売上高・粗利に重要な変動があればコメントが記載されていることを確認する。10百万円の変動、かつ、20%以上の変動は1つの基準にはなるが、毎月の記載は不要とする。四半期末月において、10百万円の変動、かつ、20%以上の変動があった場合には増減コメントを記載する。 | J26: =COUNTIF(チェックポイント!$I:$I,A26) -> 0 | K26: =SUMIF(チェックポイント!$I:$I,A26,チェックポイント!$G:$G) -> 0
A27: 26 | B27: 6 | C27: =IFERROR(INDEX(自主点検項目!$B:$B,MATCH(B27,自主点検項目!$A:$A,0)),"") -> 売上の期末変動分析 | D27: 分析の妥当性 | E27: 2次レビュー | F27: 構成単位以外 | G27: レビュー項目 | H27: 増減分析コメントにて、増減内容の説明になっている | I27: 定量的な記載は必ずしも必要とはしない。定性的に増減内容の説明になっていれば（矛盾がなければ）okとする。 | J27: =COUNTIF(チェックポイント!$I:$I,A27) -> 0 | K27: =SUMIF(チェックポイント!$I:$I,A27,チェックポイント!$G:$G) -> 0
A28: 27 | B28: 8 | C28: =IFERROR(INDEX(自主点検項目!$B:$B,MATCH(B28,自主点検項目!$A:$A,0)),"") -> 売上のカットオフテスト | D28: 成果物 | E28: 1次レビュー | F28: 共通 | G28: レビュー項目 | H28: データソースと抽出条件（手順）の記録が成果物として提出されている | I28: 試算表との一致確認がなく、データソース・抽出手順も不明の資料は不備ありとする | J28: =COUNTIF(チェックポイント!$I:$I,A28) -> 2 | K28: =SUMIF(チェックポイント!$I:$I,A28,チェックポイント!$G:$G) -> 76
A29: 28 | B29: 8 | C29: =IFERROR(INDEX(自主点検項目!$B:$B,MATCH(B29,自主点検項目!$A:$A,0)),"") -> 売上のカットオフテスト | D29: 成果物 | E29: 1次レビュー | F29: 共通 | G29: レビュー項目 | H29: 26年3月単月の全ての売上明細が提出されている（試算表との一致が確認できる） | I29: 網羅性の確認 | J29: =COUNTIF(チェックポイント!$I:$I,A29) -> 5 | K29: =SUMIF(チェックポイント!$I:$I,A29,チェックポイント!$G:$G) -> 104
A30: 29 | B30: 8 | C30: =IFERROR(INDEX(自主点検項目!$B:$B,MATCH(B30,自主点検項目!$A:$A,0)),"") -> 売上のカットオフテスト | D30: 成果物 | E30: 1次レビュー | F30: 共通 | G30: レビュー項目 | H30: 全ての明細に対して売上計上の妥当性（収益認識基準を満たしているか）を検討したコメントが残されている | J30: =COUNTIF(チェックポイント!$I:$I,A30) -> 4 | K30: =SUMIF(チェックポイント!$I:$I,A30,チェックポイント!$G:$G) -> 36
A31: 30 | B31: 8 | C31: =IFERROR(INDEX(自主点検項目!$B:$B,MATCH(B31,自主点検項目!$A:$A,0)),"") -> 売上のカットオフテスト | D31: 根拠資料 | E31: 1次レビュー | F31: 共通 | G31: レビュー項目 | H31: 1,000万円以上の取引について、根拠資料が提出されている | J31: =COUNTIF(チェックポイント!$I:$I,A31) -> 3 | K31: =SUMIF(チェックポイント!$I:$I,A31,チェックポイント!$G:$G) -> 11
A32: 31 | B32: 8 | C32: =IFERROR(INDEX(自主点検項目!$B:$B,MATCH(B32,自主点検項目!$A:$A,0)),"") -> 売上のカットオフテスト | D32: 根拠資料の信頼性 | E32: 2次レビュー | F32: 共通 | G32: レビュー項目 | H32: 根拠資料は第三者により作成または承認されたものである | J32: =COUNTIF(チェックポイント!$I:$I,A32) -> 1 | K32: =SUMIF(チェックポイント!$I:$I,A32,チェックポイント!$G:$G) -> 1
A33: 32 | B33: 8 | C33: =IFERROR(INDEX(自主点検項目!$B:$B,MATCH(B33,自主点検項目!$A:$A,0)),"") -> 売上のカットオフテスト | D33: 収益認識基準の充足 | E33: 2次レビュー | F33: 共通 | G33: レビュー項目 | H33: 収益認識基準を満たした売上計上である（根拠資料により、製品・サービス、数量が確認できる） | J33: =COUNTIF(チェックポイント!$I:$I,A33) -> 1 | K33: =SUMIF(チェックポイント!$I:$I,A33,チェックポイント!$G:$G) -> 1
A34: 33 | B34: 8 | C34: =IFERROR(INDEX(自主点検項目!$B:$B,MATCH(B34,自主点検項目!$A:$A,0)),"") -> 売上のカットオフテスト | D34: 収益認識基準の充足 | E34: 2次レビュー | F34: 共通 | G34: レビュー項目 | H34: 収益認識基準を満たした売上計上である（根拠資料により、売上計上日の妥当性が確認できる） | I34: 分割売上、未検収売上がないかチェック | J34: =COUNTIF(チェックポイント!$I:$I,A34) -> 0 | K34: =SUMIF(チェックポイント!$I:$I,A34,チェックポイント!$G:$G) -> 0
A35: 34 | B35: 8 | C35: =IFERROR(INDEX(自主点検項目!$B:$B,MATCH(B35,自主点検項目!$A:$A,0)),"") -> 売上のカットオフテスト | D35: 対応の適切性 | E35: 2次レビュー | F35: 共通 | G35: レビュー項目 | H35: 収益認識基準を満たさない売上計上の場合は、売上計上の可否を検討し、会計処理の顛末が記載されている | J35: =COUNTIF(チェックポイント!$I:$I,A35) -> 0 | K35: =SUMIF(チェックポイント!$I:$I,A35,チェックポイント!$G:$G) -> 0
A36: 35 | B36: 8 | C36: =IFERROR(INDEX(自主点検項目!$B:$B,MATCH(B36,自主点検項目!$A:$A,0)),"") -> 売上のカットオフテスト | D36: 閾値 （構成単位） | E36: 2次レビュー | F36: 構成単位 | G36: 選定方針 | H36: 当該項目は対象取引数が多いため、以下の閾値を設定し、レビュー対象を限定する 金額：2,000万円以上を対象。ただし、最低でも5件はレビューを実施 →当該閾値を設定しても件数が多い場合は自主点検Tまで連絡 | J36: =COUNTIF(チェックポイント!$I:$I,A36) -> 0 | K36: =SUMIF(チェックポイント!$I:$I,A36,チェックポイント!$G:$G) -> 0
A37: 36 | B37: 8 | C37: =IFERROR(INDEX(自主点検項目!$B:$B,MATCH(B37,自主点検項目!$A:$A,0)),"") -> 売上のカットオフテスト | D37: 閾値 （構成単位以外） | E37: 2次レビュー | F37: 構成単位以外 | G37: 選定方針 | H37: 当該項目は対象取引数が多いため、以下の閾値を設定し、レビュー対象を限定する 金額：2,000万円以上を対象。ただし、最低でも3件はレビューを実施 →当該閾値を設定しても件数が多い場合は自主点検Tまで連絡 | I37: 最低件数は3件としている | J37: =COUNTIF(チェックポイント!$I:$I,A37) -> 0 | K37: =SUMIF(チェックポイント!$I:$I,A37,チェックポイント!$G:$G) -> 0
A38: 37 | B38: 8 | C38: =IFERROR(INDEX(自主点検項目!$B:$B,MATCH(B38,自主点検項目!$A:$A,0)),"") -> 売上のカットオフテスト | D38: 記入例 | E38: 2次レビュー | F38: 共通 | G38: 記入例 | H38: ①自主点検レビュー結果には、以下を記載 問題なしの場合→「特段異常なし。」 差し戻しの場合→「No.x、xx、xxxの取引について、リスクがあり検討必要と判断（取引の詳細は成果物を参照）」 ②成果物には、取引ごとに以下の方針で記載（どれをレビュー対象としたのか） 問題なしの場合→「〇〇と数量、金額、計上日が一致しており、特段異常なし。」 差し戻しの場合→「〇〇を確認した結果、△△が不一致のため、リスクがあり検討必要と判断」 ・〇〇は資料名 ・△△は数量、金額、計上日 | I38: ①はサマリのイメージ、②はどの取引をレビューしたのか、レビューの詳細を把握したい | J38: =COUNTIF(チェックポイント!$I:$I,A38) -> 0 | K38: =SUMIF(チェックポイント!$I:$I,A38,チェックポイント!$G:$G) -> 0
A39: 38 | B39: 9 | C39: =IFERROR(INDEX(自主点検項目!$B:$B,MATCH(B39,自主点検項目!$A:$A,0)),"") -> 長期請負工事案件の洗い出し | D39: 成果物 | E39: 1次レビュー | F39: 共通 | G39: レビュー項目 | H39: データソースと抽出条件（手順）の記録が成果物として提出されている | I39: 試算表との一致確認がなく、データソース・抽出手順も不明の資料は不備ありとする | J39: =COUNTIF(チェックポイント!$I:$I,A39) -> 2 | K39: =SUMIF(チェックポイント!$I:$I,A39,チェックポイント!$G:$G) -> 9
A40: 39 | B40: 9 | C40: =IFERROR(INDEX(自主点検項目!$B:$B,MATCH(B40,自主点検項目!$A:$A,0)),"") -> 長期請負工事案件の洗い出し | D40: 成果物 | E40: 1次レビュー | F40: 共通 | G40: レビュー項目 | H40: 網羅性が確認できる情報が記載又は提出されている（例：PKGの進行基準売上との一致） | I40: 網羅性の確認 | J40: =COUNTIF(チェックポイント!$I:$I,A40) -> 2 | K40: =SUMIF(チェックポイント!$I:$I,A40,チェックポイント!$G:$G) -> 4
A41: 40 | B41: 9 | C41: =IFERROR(INDEX(自主点検項目!$B:$B,MATCH(B41,自主点検項目!$A:$A,0)),"") -> 長期請負工事案件の洗い出し | D41: 成果物 | E41: 1次レビュー | F41: 共通 | G41: レビュー項目 | H41: 全ての取引について進行基準の適用可否に関する判断根拠が記載されている | J41: =COUNTIF(チェックポイント!$I:$I,A41) -> 1 | K41: =SUMIF(チェックポイント!$I:$I,A41,チェックポイント!$G:$G) -> 4
A42: 41 | B42: 9 | C42: =IFERROR(INDEX(自主点検項目!$B:$B,MATCH(B42,自主点検項目!$A:$A,0)),"") -> 長期請負工事案件の洗い出し | D42: コメントの妥当性 | E42: 2次レビュー | F42: 共通 | G42: レビュー項目 | H42: 判断根拠が会計基準の要求事項に沿う内容になっている | I42: 自主点検説明資料の判定条件①~③は要求事項の例示である。 それ以上に会計基準に当てはめて検討していればokとする | J42: =COUNTIF(チェックポイント!$I:$I,A42) -> 0 | K42: =SUMIF(チェックポイント!$I:$I,A42,チェックポイント!$G:$G) -> 0
A43: 42 | B43: 9 | C43: =IFERROR(INDEX(自主点検項目!$B:$B,MATCH(B43,自主点検項目!$A:$A,0)),"") -> 長期請負工事案件の洗い出し | D43: コメントの妥当性 | E43: 2次レビュー | F43: 共通 | G43: レビュー項目 | H43: 会社の判断根拠によれば、一定期間にわたって収益を認識することが妥当である | I43: 予算の信頼性はNo.10で確認し、進行基準の適切性を判断する | J43: =COUNTIF(チェックポイント!$I:$I,A43) -> 1 | K43: =SUMIF(チェックポイント!$I:$I,A43,チェックポイント!$G:$G) -> 1
A44: 43 | B44: 9 | C44: =IFERROR(INDEX(自主点検項目!$B:$B,MATCH(B44,自主点検項目!$A:$A,0)),"") -> 長期請負工事案件の洗い出し | D44: コメントの妥当性 | E44: 2次レビュー | F44: 共通 | G44: レビュー項目 | H44: 請負高が5億円を超える工事案件は、会社の判断根拠の適切性を確認する | I44: 請負額が5億円を超える案件はNo.7収益認識アンケートで契約書を提出してもらっているため、契約書を確認する | J44: =COUNTIF(チェックポイント!$I:$I,A44) -> 0 | K44: =SUMIF(チェックポイント!$I:$I,A44,チェックポイント!$G:$G) -> 0
A45: 44 | B45: 10 | C45: =IFERROR(INDEX(自主点検項目!$B:$B,MATCH(B45,自主点検項目!$A:$A,0)),"") -> 実行予算の取得・確認 | D45: 成果物 | E45: 1次レビュー | F45: 共通 | G45: レビュー項目 | H45: データソースと抽出条件（手順）の記録が成果物として提出されている | J45: =COUNTIF(チェックポイント!$I:$I,A45) -> 2 | K45: =SUMIF(チェックポイント!$I:$I,A45,チェックポイント!$G:$G) -> 9
A46: 45 | B46: 10 | C46: =IFERROR(INDEX(自主点検項目!$B:$B,MATCH(B46,自主点検項目!$A:$A,0)),"") -> 実行予算の取得・確認 | D46: 成果物 | E46: 1次レビュー | F46: 共通 | G46: レビュー項目 | H46: 網羅性が確認できる情報が記載又は提出されている（試算表との一致を確認できる） | I46: 網羅性の確認 No.9にてリスト化されており、整合していれば問題ない | J46: =COUNTIF(チェックポイント!$I:$I,A46) -> 2 | K46: =SUMIF(チェックポイント!$I:$I,A46,チェックポイント!$G:$G) -> 6
A47: 46 | B47: 10 | C47: =IFERROR(INDEX(自主点検項目!$B:$B,MATCH(B47,自主点検項目!$A:$A,0)),"") -> 実行予算の取得・確認 | D47: 成果物 | E47: 1次レビュー | F47: 共通 | G47: レビュー項目 | H47: 実行予算に著増減がある場合、コメントを記載している | J47: =COUNTIF(チェックポイント!$I:$I,A47) -> 1 | K47: =SUMIF(チェックポイント!$I:$I,A47,チェックポイント!$G:$G) -> 1
A48: 47 | B48: 10 | C48: =IFERROR(INDEX(自主点検項目!$B:$B,MATCH(B48,自主点検項目!$A:$A,0)),"") -> 実行予算の取得・確認 | D48: コメントの妥当性 | E48: 2次レビュー | F48: 共通 | G48: レビュー項目 | H48: 増減コメントが変動要因の説明になっている | J48: =COUNTIF(チェックポイント!$I:$I,A48) -> 0 | K48: =SUMIF(チェックポイント!$I:$I,A48,チェックポイント!$G:$G) -> 0
A49: 48 | B49: 10 | C49: =IFERROR(INDEX(自主点検項目!$B:$B,MATCH(B49,自主点検項目!$A:$A,0)),"") -> 実行予算の取得・確認 | D49: コメントの妥当性 | E49: 2次レビュー | F49: 共通 | G49: レビュー項目 | H49: 増減コメントにより、予算の信頼性が低いと判断される場合、進行基準の適用可否を検討できている | J49: =COUNTIF(チェックポイント!$I:$I,A49) -> 0 | K49: =SUMIF(チェックポイント!$I:$I,A49,チェックポイント!$G:$G) -> 0
A50: 49 | B50: 11 | C50: =IFERROR(INDEX(自主点検項目!$B:$B,MATCH(B50,自主点検項目!$A:$A,0)),"") -> 材料費の実際発生原価の確認 | D50: 成果物 | E50: 1次レビュー | F50: 共通 | G50: レビュー項目 | H50: データソースと抽出条件（手順）の記録が成果物として提出されている | I50: 試算表との一致確認がなく、データソース・抽出手順も不明の資料は不備ありとする | J50: =COUNTIF(チェックポイント!$I:$I,A50) -> 1 | K50: =SUMIF(チェックポイント!$I:$I,A50,チェックポイント!$G:$G) -> 6
A51: 50 | B51: 11 | C51: =IFERROR(INDEX(自主点検項目!$B:$B,MATCH(B51,自主点検項目!$A:$A,0)),"") -> 材料費の実際発生原価の確認 | D51: 成果物 | E51: 1次レビュー | F51: 共通 | G51: レビュー項目 | H51: 網羅性が確認できる情報が記載又は提出されている（試算表との一致を確認できる） | I51: 網羅性の確認 検討対象の工事がNo.9のリストと整合しているかどうか | J51: =COUNTIF(チェックポイント!$I:$I,A51) -> 1 | K51: =SUMIF(チェックポイント!$I:$I,A51,チェックポイント!$G:$G) -> 3
A52: 51 | B52: 11 | C52: =IFERROR(INDEX(自主点検項目!$B:$B,MATCH(B52,自主点検項目!$A:$A,0)),"") -> 材料費の実際発生原価の確認 | D52: 成果物 | E52: 1次レビュー | F52: 共通 | G52: レビュー項目 | H52: 購買データ、入出庫データ、原価明細を比較し整合性を確認できている | J52: =COUNTIF(チェックポイント!$I:$I,A52) -> 1 | K52: =SUMIF(チェックポイント!$I:$I,A52,チェックポイント!$G:$G) -> 3
A53: 52 | B53: 11 | C53: =IFERROR(INDEX(自主点検項目!$B:$B,MATCH(B53,自主点検項目!$A:$A,0)),"") -> 材料費の実際発生原価の確認 | D53: 成果物 | E53: 1次レビュー | F53: 共通 | G53: レビュー項目 | H53: 差異のある取引について、差異要因がコメントされている | J53: =COUNTIF(チェックポイント!$I:$I,A53) -> 0 | K53: =SUMIF(チェックポイント!$I:$I,A53,チェックポイント!$G:$G) -> 0
A54: 53 | B54: 11 | C54: =IFERROR(INDEX(自主点検項目!$B:$B,MATCH(B54,自主点検項目!$A:$A,0)),"") -> 材料費の実際発生原価の確認 | D54: コメントの妥当性 | E54: 2次レビュー | F54: 共通 | G54: レビュー項目 | H54: 差異要因のコメントが合理的である | I54: 完全一致していなくても差異要因に一定合理性があれば問題なしという判断はあり得る | J54: =COUNTIF(チェックポイント!$I:$I,A54) -> 0 | K54: =SUMIF(チェックポイント!$I:$I,A54,チェックポイント!$G:$G) -> 0
A55: 54 | B55: 11 | C55: =IFERROR(INDEX(自主点検項目!$B:$B,MATCH(B55,自主点検項目!$A:$A,0)),"") -> 材料費の実際発生原価の確認 | D55: コメントの妥当性 | E55: 2次レビュー | F55: 共通 | G55: レビュー項目 | H55: 差異要因のコメントが合理的である | I55: 必要に応じて根拠証憑を依頼して合理性を確認する | J55: =COUNTIF(チェックポイント!$I:$I,A55) -> 0 | K55: =SUMIF(チェックポイント!$I:$I,A55,チェックポイント!$G:$G) -> 0
A56: 55 | B56: 12 | C56: =IFERROR(INDEX(自主点検項目!$B:$B,MATCH(B56,自主点検項目!$A:$A,0)),"") -> 進捗率の算定根拠の確認 | D56: 成果物 | E56: 1次レビュー | F56: 共通 | G56: レビュー項目 | H56: データソースと抽出条件（手順）の記録が成果物として提出されている | J56: =COUNTIF(チェックポイント!$I:$I,A56) -> 1 | K56: =SUMIF(チェックポイント!$I:$I,A56,チェックポイント!$G:$G) -> 9
A57: 56 | B57: 12 | C57: =IFERROR(INDEX(自主点検項目!$B:$B,MATCH(B57,自主点検項目!$A:$A,0)),"") -> 進捗率の算定根拠の確認 | D57: 成果物 | E57: 1次レビュー | F57: 共通 | G57: レビュー項目 | H57: 網羅性が確認できる情報が記載又は提出されている（試算表との一致を確認できる） | I57: 網羅性の確認 No.9にてリスト化されており、整合していれば問題ない | J57: =COUNTIF(チェックポイント!$I:$I,A57) -> 1 | K57: =SUMIF(チェックポイント!$I:$I,A57,チェックポイント!$G:$G) -> 8
A58: 57 | B58: 12 | C58: =IFERROR(INDEX(自主点検項目!$B:$B,MATCH(B58,自主点検項目!$A:$A,0)),"") -> 進捗率の算定根拠の確認 | D58: 成果物 | E58: 1次レビュー | F58: 共通 | G58: レビュー項目 | H58: 案件ごとに進捗率を月次に並べて推移分析ができている | J58: =COUNTIF(チェックポイント!$I:$I,A58) -> 1 | K58: =SUMIF(チェックポイント!$I:$I,A58,チェックポイント!$G:$G) -> 1
A59: 58 | B59: 12 | C59: =IFERROR(INDEX(自主点検項目!$B:$B,MATCH(B59,自主点検項目!$A:$A,0)),"") -> 進捗率の算定根拠の確認 | D59: 成果物 | E59: 1次レビュー | F59: 共通 | G59: レビュー項目 | H59: 著しい進捗や進捗率のマイナス理由がコメントできている | J59: =COUNTIF(チェックポイント!$I:$I,A59) -> 0 | K59: =SUMIF(チェックポイント!$I:$I,A59,チェックポイント!$G:$G) -> 0
A60: 59 | B60: 12 | C60: =IFERROR(INDEX(自主点検項目!$B:$B,MATCH(B60,自主点検項目!$A:$A,0)),"") -> 進捗率の算定根拠の確認 | D60: 根拠資料 | E60: 1次レビュー | F60: 共通 | G60: レビュー項目 | H60: 進捗率の算定根拠資料が提出されている | J60: =COUNTIF(チェックポイント!$I:$I,A60) -> 0 | K60: =SUMIF(チェックポイント!$I:$I,A60,チェックポイント!$G:$G) -> 0
A61: 60 | B61: 12 | C61: =IFERROR(INDEX(自主点検項目!$B:$B,MATCH(B61,自主点検項目!$A:$A,0)),"") -> 進捗率の算定根拠の確認 | D61: コメントの妥当性 | E61: 2次レビュー | F61: 共通 | G61: レビュー項目 | H61: 著しい進捗や進捗率のマイナス理由が合理的である | J61: =COUNTIF(チェックポイント!$I:$I,A61) -> 0 | K61: =SUMIF(チェックポイント!$I:$I,A61,チェックポイント!$G:$G) -> 0
A62: 61 | B62: 12 | C62: =IFERROR(INDEX(自主点検項目!$B:$B,MATCH(B62,自主点検項目!$A:$A,0)),"") -> 進捗率の算定根拠の確認 | D62: 会計処理の妥当性 | E62: 2次レビュー | F62: 共通 | G62: レビュー項目 | H62: 進捗率が算定根拠資料に基づいて適切に算定されている | J62: =COUNTIF(チェックポイント!$I:$I,A62) -> 0 | K62: =SUMIF(チェックポイント!$I:$I,A62,チェックポイント!$G:$G) -> 0
A63: 62 | B63: 13 | C63: =IFERROR(INDEX(自主点検項目!$B:$B,MATCH(B63,自主点検項目!$A:$A,0)),"") -> 経費の実際発生原価の確認 | D63: 成果物 | E63: 1次レビュー | F63: 共通 | G63: レビュー項目 | H63: データソースと抽出条件（手順）の記録が成果物として提出されている | I63: 試算表との一致確認がなく、データソース・抽出手順も不明の資料は不備ありとする | J63: =COUNTIF(チェックポイント!$I:$I,A63) -> 1 | K63: =SUMIF(チェックポイント!$I:$I,A63,チェックポイント!$G:$G) -> 6
A64: 63 | B64: 13 | C64: =IFERROR(INDEX(自主点検項目!$B:$B,MATCH(B64,自主点検項目!$A:$A,0)),"") -> 経費の実際発生原価の確認 | D64: 成果物 | E64: 1次レビュー | F64: 共通 | G64: レビュー項目 | H64: 網羅性が確認できる情報が記載又は提出されている（試算表との一致を確認できる） | I64: 網羅性の確認 | J64: =COUNTIF(チェックポイント!$I:$I,A64) -> 1 | K64: =SUMIF(チェックポイント!$I:$I,A64,チェックポイント!$G:$G) -> 7
A65: 64 | B65: 13 | C65: =IFERROR(INDEX(自主点検項目!$B:$B,MATCH(B65,自主点検項目!$A:$A,0)),"") -> 経費の実際発生原価の確認 | D65: 成果物 | E65: 1次レビュー | F65: 共通 | G65: レビュー項目 | H65: 1年以上滞留している未成工事支出金を一覧化し、滞留要因、初回原価発生日、売上原価への振替予定日が記載されている | J65: =COUNTIF(チェックポイント!$I:$I,A65) -> 2 | K65: =SUMIF(チェックポイント!$I:$I,A65,チェックポイント!$G:$G) -> 2
A66: 65 | B66: 13 | C66: =IFERROR(INDEX(自主点検項目!$B:$B,MATCH(B66,自主点検項目!$A:$A,0)),"") -> 経費の実際発生原価の確認 | D66: コメントの妥当性 | E66: 2次レビュー | F66: 共通 | G66: レビュー項目 | H66: 滞留要因が合理的である | I66: 売上原価が繰延られていないか否かを検討する | J66: =COUNTIF(チェックポイント!$I:$I,A66) -> 0 | K66: =SUMIF(チェックポイント!$I:$I,A66,チェックポイント!$G:$G) -> 0
A67: 66 | B67: 13 | C67: =IFERROR(INDEX(自主点検項目!$B:$B,MATCH(B67,自主点検項目!$A:$A,0)),"") -> 経費の実際発生原価の確認 | D67: コメントの妥当性 | E67: 2次レビュー | F67: 共通 | G67: レビュー項目 | H67: 滞留要因が合理的である | I67: 必要に応じて根拠証憑を依頼して合理性を確認する | J67: =COUNTIF(チェックポイント!$I:$I,A67) -> 0 | K67: =SUMIF(チェックポイント!$I:$I,A67,チェックポイント!$G:$G) -> 0
A68: 67 | B68: 14 | C68: =IFERROR(INDEX(自主点検項目!$B:$B,MATCH(B68,自主点検項目!$A:$A,0)),"") -> 原価振替取引の要因説明 | D68: 成果物 | E68: 1次レビュー | F68: 共通 | G68: レビュー項目 | H68: データソースと抽出条件（手順）の記録が成果物として提出されている | I68: 原価明細自体の網羅性確認は難しいと思われるため、データソースだけでなく、抽出基準や手順の記録が必要 | J68: =COUNTIF(チェックポイント!$I:$I,A68) -> 1 | K68: =SUMIF(チェックポイント!$I:$I,A68,チェックポイント!$G:$G) -> 5
A69: 68 | B69: 14 | C69: =IFERROR(INDEX(自主点検項目!$B:$B,MATCH(B69,自主点検項目!$A:$A,0)),"") -> 原価振替取引の要因説明 | D69: 成果物 | E69: 1次レビュー | F69: 共通 | G69: レビュー項目 | H69: 原価明細と発生原価合計が案件ごとに一致している | I69: 原価明細が案件ごとに分かれていない（売上原価の総勘定元帳のイメージ）場合、合計額と試算表の一致を確かめる | J69: =COUNTIF(チェックポイント!$I:$I,A69) -> 1 | K69: =SUMIF(チェックポイント!$I:$I,A69,チェックポイント!$G:$G) -> 3
A70: 69 | B70: 14 | C70: =IFERROR(INDEX(自主点検項目!$B:$B,MATCH(B70,自主点検項目!$A:$A,0)),"") -> 原価振替取引の要因説明 | D70: 成果物 | E70: 1次レビュー | F70: 共通 | G70: レビュー項目 | H70: 全ての案件のマイナス処理について、取消理由がコメントされている | I70: ※No.14は一度原価計上した後に別の工番に振替えたものを検出する手続きであるため、マイナス取引に着目している。 対して、No.15は原価計上する際に、正しい工番ではなく別の工番に計上するリスクを識別して実施する手続きである。 | J70: =COUNTIF(チェックポイント!$I:$I,A70) -> 1 | K70: =SUMIF(チェックポイント!$I:$I,A70,チェックポイント!$G:$G) -> 1
A71: 70 | B71: 14 | C71: =IFERROR(INDEX(自主点検項目!$B:$B,MATCH(B71,自主点検項目!$A:$A,0)),"") -> 原価振替取引の要因説明 | D71: 成果物 | E71: 1次レビュー | F71: 共通 | G71: レビュー項目 | H71: 請負高1億円以上の案件全てについて、マイナス取引の根拠証憑が提出されている | I71: コメントは全案件、根拠証憑の提出対象は1億円基準 | J71: =COUNTIF(チェックポイント!$I:$I,A71) -> 1 | K71: =SUMIF(チェックポイント!$I:$I,A71,チェックポイント!$G:$G) -> 2
A72: 71 | B72: 14 | C72: =IFERROR(INDEX(自主点検項目!$B:$B,MATCH(B72,自主点検項目!$A:$A,0)),"") -> 原価振替取引の要因説明 | D72: コメントの妥当性 | E72: 2次レビュー | F72: 共通 | G72: レビュー項目 | H72: 取消理由や案件間の振替理由が合理的である | I72: 原価の付け替えではないことの確認 | J72: =COUNTIF(チェックポイント!$I:$I,A72) -> 0 | K72: =SUMIF(チェックポイント!$I:$I,A72,チェックポイント!$G:$G) -> 0
A73: 72 | B73: 15 | C73: =IFERROR(INDEX(自主点検項目!$B:$B,MATCH(B73,自主点検項目!$A:$A,0)),"") -> 低粗利案件の分析 | D73: 成果物 | E73: 1次レビュー | F73: 共通 | G73: レビュー項目 | H73: データソースと抽出条件（手順）の記録が成果物として提出されている | I73: 試算表との一致確認がなく、データソース・抽出手順も不明の資料は不備ありとする | J73: =COUNTIF(チェックポイント!$I:$I,A73) -> 1 | K73: =SUMIF(チェックポイント!$I:$I,A73,チェックポイント!$G:$G) -> 7
A74: 73 | B74: 15 | C74: =IFERROR(INDEX(自主点検項目!$B:$B,MATCH(B74,自主点検項目!$A:$A,0)),"") -> 低粗利案件の分析 | D74: 成果物 | E74: 1次レビュー | F74: 共通 | G74: レビュー項目 | H74: 網羅性が確認できる情報が記載又は提出されている | I74: 網羅性の確認 No.14の原価明細と整合していれば問題ない | J74: =COUNTIF(チェックポイント!$I:$I,A74) -> 1 | K74: =SUMIF(チェックポイント!$I:$I,A74,チェックポイント!$G:$G) -> 3
A75: 74 | B75: 15 | C75: =IFERROR(INDEX(自主点検項目!$B:$B,MATCH(B75,自主点検項目!$A:$A,0)),"") -> 低粗利案件の分析 | D75: 成果物 | E75: 1次レビュー | F75: 共通 | G75: レビュー項目 | H75: 案件明細を貼り付けるだけでなく、案件ごとに月次で金額が並べられ、推移分析ができる状態に整理されている | J75: =COUNTIF(チェックポイント!$I:$I,A75) -> 1 | K75: =SUMIF(チェックポイント!$I:$I,A75,チェックポイント!$G:$G) -> 1
A76: 75 | B76: 15 | C76: =IFERROR(INDEX(自主点検項目!$B:$B,MATCH(B76,自主点検項目!$A:$A,0)),"") -> 低粗利案件の分析 | D76: 成果物 | E76: 1次レビュー | F76: 共通 | G76: レビュー項目 | H76: 請負高1億円以上の案件だけではなくすべての案件について分析が実施されている | J76: =COUNTIF(チェックポイント!$I:$I,A76) -> 0 | K76: =SUMIF(チェックポイント!$I:$I,A76,チェックポイント!$G:$G) -> 0
A77: 76 | B77: 15 | C77: =IFERROR(INDEX(自主点検項目!$B:$B,MATCH(B77,自主点検項目!$A:$A,0)),"") -> 低粗利案件の分析 | D77: 成果物 | E77: 1次レビュー | F77: 共通 | G77: レビュー項目 | H77: 請負高1億円以上で、利益率5%以下、かつ、一定期間変動がない案件全てについて、原価振替の有無に関する調査結果が記載されている | J77: =COUNTIF(チェックポイント!$I:$I,A77) -> 0 | K77: =SUMIF(チェックポイント!$I:$I,A77,チェックポイント!$G:$G) -> 0
A78: 77 | B78: 15 | C78: =IFERROR(INDEX(自主点検項目!$B:$B,MATCH(B78,自主点検項目!$A:$A,0)),"") -> 低粗利案件の分析 | D78: 成果物 | E78: 1次レビュー | F78: 共通 | G78: レビュー項目 | H78: 請負高1億円以上で、利益率5%以下、かつ、一定期間変動がない案件全てについて、原価振替の有無に関する調査結果が提出されている | I78: ※No.14は一度原価計上した後に別の工番に振替えたものを検出する手続きである。 対して、No.15は原価計上する際に、正しい工番ではなく別の工番に計上するリスクを識別して実施する手続きである。 | J78: =COUNTIF(チェックポイント!$I:$I,A78) -> 0 | K78: =SUMIF(チェックポイント!$I:$I,A78,チェックポイント!$G:$G) -> 0
A79: 78 | B79: 15 | C79: =IFERROR(INDEX(自主点検項目!$B:$B,MATCH(B79,自主点検項目!$A:$A,0)),"") -> 低粗利案件の分析 | D79: コメントの妥当性 | E79: 2次レビュー | F79: 共通 | G79: レビュー項目 | H79: 請負高1億円以上で、利益率5%以下、かつ、一定期間変動がない案件全てについて、利益率悪化の要因のコメントや残工事予算と実績の突合などから、要因を説明できている | I79: 第三者（親会社や監査法人）に説明できるかという観点で確認する。どのような調査をしたか、具体的な調査内容と判断に関するコメントが記載されていると望ましい | J79: =COUNTIF(チェックポイント!$I:$I,A79) -> 1 | K79: =SUMIF(チェックポイント!$I:$I,A79,チェックポイント!$G:$G) -> 1
A80: 79 | B80: 18 | C80: =IFERROR(INDEX(自主点検項目!$B:$B,MATCH(B80,自主点検項目!$A:$A,0)),"") -> 各費用月次推移分析 | D80: 成果物 | E80: 1次レビュー | F80: 構成単位 | G80: レビュー項目 | H80: データソースと抽出条件（手順）の記録が成果物として提出されている | I80: 試算表との一致確認がなく、データソース・抽出手順も不明の資料は不備ありとする | J80: =COUNTIF(チェックポイント!$I:$I,A80) -> 1 | K80: =SUMIF(チェックポイント!$I:$I,A80,チェックポイント!$G:$G) -> 77
A81: 80 | B81: 18 | C81: =IFERROR(INDEX(自主点検項目!$B:$B,MATCH(B81,自主点検項目!$A:$A,0)),"") -> 各費用月次推移分析 | D81: 成果物 | E81: 1次レビュー | F81: 構成単位 | G81: レビュー項目 | H81: 網羅性が確認できる情報が記載又は提出されている | I81: 網羅性の確認 | J81: =COUNTIF(チェックポイント!$I:$I,A81) -> 3 | K81: =SUMIF(チェックポイント!$I:$I,A81,チェックポイント!$G:$G) -> 88
A82: 81 | B82: 18 | C82: =IFERROR(INDEX(自主点検項目!$B:$B,MATCH(B82,自主点検項目!$A:$A,0)),"") -> 各費用月次推移分析 | D82: 成果物 | E82: 1次レビュー | F82: 構成単位 | G82: レビュー項目 | H82: 25年4月～26年3月の科目毎の月次推移表及びグラフが作成されている | I82: グラフがなくても、コメントが適切に記載されている場合は差戻としない | J82: =COUNTIF(チェックポイント!$I:$I,A82) -> 1 | K82: =SUMIF(チェックポイント!$I:$I,A82,チェックポイント!$G:$G) -> 27
A83: 82 | B83: 18 | C83: =IFERROR(INDEX(自主点検項目!$B:$B,MATCH(B83,自主点検項目!$A:$A,0)),"") -> 各費用月次推移分析 | D83: 分析の妥当性 | E83: 2次レビュー | F83: 構成単位 | G83: レビュー項目 | H83: 変動額と要因分析のコメントに記載されている影響金額が概ね整合している | I83: 増減金額の2-3割程度しか説明できていない場合は不十分である可能性がある | J83: =COUNTIF(チェックポイント!$I:$I,A83) -> 2 | K83: =SUMIF(チェックポイント!$I:$I,A83,チェックポイント!$G:$G) -> 15
A84: 83 | B84: 18 | C84: =IFERROR(INDEX(自主点検項目!$B:$B,MATCH(B84,自主点検項目!$A:$A,0)),"") -> 各費用月次推移分析 | D84: 分析の妥当性 | E84: 2次レビュー | F84: 構成単位 | G84: レビュー項目 | H84: 変動の大きい科目について、要因の説明が十分にされている | I84: 要因説明の十分性は科目/金額による。第三者（親会社や監査法人）に説明できるかという観点で確認する | J84: =COUNTIF(チェックポイント!$I:$I,A84) -> 0 | K84: =SUMIF(チェックポイント!$I:$I,A84,チェックポイント!$G:$G) -> 0
A85: 84 | B85: 18 | C85: =IFERROR(INDEX(自主点検項目!$B:$B,MATCH(B85,自主点検項目!$A:$A,0)),"") -> 各費用月次推移分析 | D85: 根拠資料の適切性 | E85: 2次レビュー | F85: 構成単位 | G85: レビュー項目 | H85: 変動の説明をサポートする適切な根拠資料が提出されている | J85: =COUNTIF(チェックポイント!$I:$I,A85) -> 3 | K85: =SUMIF(チェックポイント!$I:$I,A85,チェックポイント!$G:$G) -> 31
A86: 85 | B86: 18 | C86: =IFERROR(INDEX(自主点検項目!$B:$B,MATCH(B86,自主点検項目!$A:$A,0)),"") -> 各費用月次推移分析 | D86: 成果物 | E86: 1次レビュー | F86: 構成単位以外 | G86: レビュー項目 | H86: データソースと抽出条件（手順）の記録が成果物として提出されている | I86: 試算表との一致確認がなく、データソース・抽出手順も不明の資料は不備ありとする | J86: =COUNTIF(チェックポイント!$I:$I,A86) -> 0 | K86: =SUMIF(チェックポイント!$I:$I,A86,チェックポイント!$G:$G) -> 0
A87: 86 | B87: 18 | C87: =IFERROR(INDEX(自主点検項目!$B:$B,MATCH(B87,自主点検項目!$A:$A,0)),"") -> 各費用月次推移分析 | D87: 成果物 | E87: 1次レビュー | F87: 構成単位以外 | G87: レビュー項目 | H87: 網羅性が確認できる情報が記載又は提出されている | I87: 網羅性の確認 | J87: =COUNTIF(チェックポイント!$I:$I,A87) -> 0 | K87: =SUMIF(チェックポイント!$I:$I,A87,チェックポイント!$G:$G) -> 0
A88: 87 | B88: 18 | C88: =IFERROR(INDEX(自主点検項目!$B:$B,MATCH(B88,自主点検項目!$A:$A,0)),"") -> 各費用月次推移分析 | D88: 成果物 | E88: 1次レビュー | F88: 構成単位以外 | G88: レビュー項目 | H88: 25年4月～26年3月の科目毎の月次推移表が作成されている | I88: グラフは必要としない | J88: =COUNTIF(チェックポイント!$I:$I,A88) -> 0 | K88: =SUMIF(チェックポイント!$I:$I,A88,チェックポイント!$G:$G) -> 0
A89: 88 | B89: 18 | C89: =IFERROR(INDEX(自主点検項目!$B:$B,MATCH(B89,自主点検項目!$A:$A,0)),"") -> 各費用月次推移分析 | D89: 分析の妥当性 | E89: 2次レビュー | F89: 構成単位以外 | G89: レビュー項目 | H89: 変動の大きい科目について、要因の説明がなされている | I89: 定量的な説明がなくても、定性的に説明がなされていれば（矛盾がなければ）okとする | J89: =COUNTIF(チェックポイント!$I:$I,A89) -> 0 | K89: =SUMIF(チェックポイント!$I:$I,A89,チェックポイント!$G:$G) -> 0
A90: 89 | B90: 19 | C90: =IFERROR(INDEX(自主点検項目!$B:$B,MATCH(B90,自主点検項目!$A:$A,0)),"") -> 翌期取引の確認 | D90: 成果物 | E90: 1次レビュー | F90: 共通 | G90: レビュー項目 | H90: データソースと抽出条件（手順）の記録が成果物として提出されている | I90: 試算表との一致確認がなく、データソース・抽出手順も不明の資料は不備ありとする | J90: =COUNTIF(チェックポイント!$I:$I,A90) -> 2 | K90: =SUMIF(チェックポイント!$I:$I,A90,チェックポイント!$G:$G) -> 44
A91: 90 | B91: 19 | C91: =IFERROR(INDEX(自主点検項目!$B:$B,MATCH(B91,自主点検項目!$A:$A,0)),"") -> 翌期取引の確認 | D91: 成果物 | E91: 1次レビュー | F91: 共通 | G91: レビュー項目 | H91: 網羅性が確認できる情報が記載又は提出されている | I91: 網羅性の確認 | J91: =COUNTIF(チェックポイント!$I:$I,A91) -> 3 | K91: =SUMIF(チェックポイント!$I:$I,A91,チェックポイント!$G:$G) -> 39
A92: 91 | B92: 19 | C92: =IFERROR(INDEX(自主点検項目!$B:$B,MATCH(B92,自主点検項目!$A:$A,0)),"") -> 翌期取引の確認 | D92: 成果物 | E92: 1次レビュー | F92: 共通 | G92: レビュー項目 | H92: 仕訳明細データの摘要欄等から、26年3月以前に費用計上すべき費用の有無を確認している | J92: =COUNTIF(チェックポイント!$I:$I,A92) -> 4 | K92: =SUMIF(チェックポイント!$I:$I,A92,チェックポイント!$G:$G) -> 37
A93: 92 | B93: 19 | C93: =IFERROR(INDEX(自主点検項目!$B:$B,MATCH(B93,自主点検項目!$A:$A,0)),"") -> 翌期取引の確認 | D93: 分析の妥当性 | E93: 2次レビュー | F93: 共通 | G93: レビュー項目 | H93: 26年3月以前に費用計上すべきリスクのある費用について会計処理の顛末が適切に記載されている | I93: 要因説明の十分性は科目/金額による。第三者（親会社や監査法人）に説明できるかという観点で確認する | J93: =COUNTIF(チェックポイント!$I:$I,A93) -> 4 | K93: =SUMIF(チェックポイント!$I:$I,A93,チェックポイント!$G:$G) -> 14
A94: 93 | B94: 19 | C94: =IFERROR(INDEX(自主点検項目!$B:$B,MATCH(B94,自主点検項目!$A:$A,0)),"") -> 翌期取引の確認 | D94: 分析の妥当性 | E94: 2次レビュー | F94: 共通 | G94: レビュー項目 | H94: 修正した場合、伝票番号等が記載され、第三者が確認できるようになっている | J94: =COUNTIF(チェックポイント!$I:$I,A94) -> 0 | K94: =SUMIF(チェックポイント!$I:$I,A94,チェックポイント!$G:$G) -> 0
A95: 94 | B95: 20 | C95: =IFERROR(INDEX(自主点検項目!$B:$B,MATCH(B95,自主点検項目!$A:$A,0)),"") -> 非経常的取引の識別と説明 | D95: 成果物 | E95: 1次レビュー | F95: 共通 | G95: レビュー項目 | H95: 管理部門により非経常的な取引について各部署から情報を収集している | J95: =COUNTIF(チェックポイント!$I:$I,A95) -> 2 | K95: =SUMIF(チェックポイント!$I:$I,A95,チェックポイント!$G:$G) -> 31
A96: 95 | B96: 20 | C96: =IFERROR(INDEX(自主点検項目!$B:$B,MATCH(B96,自主点検項目!$A:$A,0)),"") -> 非経常的取引の識別と説明 | D96: 成果物 | E96: 1次レビュー | F96: 共通 | G96: レビュー項目 | H96: 収集した情報を基に、管理部門が会計処理を検討している | J96: =COUNTIF(チェックポイント!$I:$I,A96) -> 1 | K96: =SUMIF(チェックポイント!$I:$I,A96,チェックポイント!$G:$G) -> 4
A97: 96 | B97: 20 | C97: =IFERROR(INDEX(自主点検項目!$B:$B,MATCH(B97,自主点検項目!$A:$A,0)),"") -> 非経常的取引の識別と説明 | D97: 会計処理の妥当性 | E97: 2次レビュー | F97: 共通 | G97: レビュー項目 | H97: 非経常的な取引がある場合、管理部門は収集情報に基づいて正しい会計処理を行っている | J97: =COUNTIF(チェックポイント!$I:$I,A97) -> 0 | K97: =SUMIF(チェックポイント!$I:$I,A97,チェックポイント!$G:$G) -> 0
A98: 97 | B98: 21 | C98: =IFERROR(INDEX(自主点検項目!$B:$B,MATCH(B98,自主点検項目!$A:$A,0)),"") -> 見積計上費用：計上根拠 | D98: 成果物 | E98: 1次レビュー | F98: 共通 | G98: レビュー項目 | H98: データソースと抽出条件（手順）の記録が成果物として提出されている | I98: 試算表との一致確認がなく、データソース・抽出手順も不明の資料は不備ありとする | J98: =COUNTIF(チェックポイント!$I:$I,A98) -> 3 | K98: =SUMIF(チェックポイント!$I:$I,A98,チェックポイント!$G:$G) -> 43
A99: 98 | B99: 21 | C99: =IFERROR(INDEX(自主点検項目!$B:$B,MATCH(B99,自主点検項目!$A:$A,0)),"") -> 見積計上費用：計上根拠 | D99: 成果物 | E99: 1次レビュー | F99: 共通 | G99: レビュー項目 | H99: 網羅性が確認できる情報が記載又は提出されている | I99: 試算表との一致による網羅性の確認はできないため、どのように見積計上費用の網羅性を確認したかが分かればokとする。 なお、通常の見積（引当金）以外で、確定でなく見積もりで未払費用等を計上しているものがあるかを確認できていれば問題ないこととする。 | J99: =COUNTIF(チェックポイント!$I:$I,A99) -> 3 | K99: =SUMIF(チェックポイント!$I:$I,A99,チェックポイント!$G:$G) -> 31
A100: 99 | B100: 21 | C100: =IFERROR(INDEX(自主点検項目!$B:$B,MATCH(B100,自主点検項目!$A:$A,0)),"") -> 見積計上費用：計上根拠 | D100: 会計処理の妥当性 | E100: 2次レビュー | F100: 共通 | G100: レビュー項目 | H100: 見積計上の根拠が十分に示されている | I100: 根拠の十分性は科目/金額による。第三者（親会社や監査法人）に説明できるかという観点で確認する | J100: =COUNTIF(チェックポイント!$I:$I,A100) -> 2 | K100: =SUMIF(チェックポイント!$I:$I,A100,チェックポイント!$G:$G) -> 25
...

Sheet チェックポイント
A1: No | B1: 自主点検項目No | C1: 自主点検項目名 | D1: 提出物No | E1: 提出物名 | F1: チェックポイント内容 | G1: 発生件数 | H1: 関連会社数 | I1: レビュー項目No | J1: カテゴリ | K1: レビュー区分 | L1: レビュー項目 | M1: 確認 | N1: 該当なし | O1: 非該当・未確認の理由 | P1: 備考
A2: 1 | B2: 4 | C2: =IFERROR(INDEX(自主点検項目!$B:$B,MATCH(B2,自主点検項目!$A:$A,0)),"") -> 滞留債権の分析 | D2: 15 | E2: =IFERROR(INDEX(提出物!$D:$D,MATCH(D2,提出物!$A:$A,0)),"") -> 売掛金明細・試算表の一致 | F2: 成果物の作成に用いたデータソースと抽出条件（手順）の記録（画面コピー等）が提出されているか。 | G2: =COUNTIF('チェックポイント-問合せ・差戻し事例対応表'!$B:$B,A2) -> 68 | H2: =SUMPRODUCT(('チェックポイント-問合せ・差戻し事例対応表'!$B$2:$B$5000=A2)*('チェックポイント-問合せ・差戻し事例対応表'!$I$2:$I$5000<>"")/(COUNTIFS('チェックポイント-問合せ・差戻し事例対応表'!$B$2:$B$5000,'チェックポイント-問合せ・差戻し事例対応表'!$B$2:$B$5000,'チェックポイント-問合せ・差戻し事例対応表'!$I$2:$I$5000,'チェックポイント-問合せ・差戻し事例対応表'!$I$2:$I$5000)+('チェックポイント-問合せ・差戻し事例対応表'!$I$2:$I$5000=""))) -> 62 | I2: 1 | J2: =IFERROR(INDEX(レビュー指針!$D:$D,MATCH(I2,レビュー指針!$A:$A,0)),"") -> 成果物 | K2: =IFERROR(INDEX(レビュー指針!$E:$E,MATCH(I2,レビュー指針!$A:$A,0)),"") -> 1次レビュー | L2: =IFERROR(INDEX(レビュー指針!$H:$H,MATCH(I2,レビュー指針!$A:$A,0)),"") -> データソースと抽出条件（手順）の記録が成果物として提出されている | P2: Stage2精査 / 複合問合せを分割（網羅性は別CPへ） / 自主点検QA由来 / 件数57 / 要文言整備
A3: 7 | B3: 4 | C3: =IFERROR(INDEX(自主点検項目!$B:$B,MATCH(B3,自主点検項目!$A:$A,0)),"") -> 滞留債権の分析 | D3: 共通 | E3: =IFERROR(INDEX(提出物!$D:$D,MATCH(D3,提出物!$A:$A,0)),"") | F3: 成果物の作成に用いたデータソースと抽出条件（手順）の記録（画面コピー等）が提出されているか。 | G3: =COUNTIF('チェックポイント-問合せ・差戻し事例対応表'!$B:$B,A3) -> 3 | H3: =SUMPRODUCT(('チェックポイント-問合せ・差戻し事例対応表'!$B$2:$B$5000=A3)*('チェックポイント-問合せ・差戻し事例対応表'!$I$2:$I$5000<>"")/(COUNTIFS('チェックポイント-問合せ・差戻し事例対応表'!$B$2:$B$5000,'チェックポイント-問合せ・差戻し事例対応表'!$B$2:$B$5000,'チェックポイント-問合せ・差戻し事例対応表'!$I$2:$I$5000,'チェックポイント-問合せ・差戻し事例対応表'!$I$2:$I$5000)+('チェックポイント-問合せ・差戻し事例対応表'!$I$2:$I$5000=""))) -> 3 | I3: 1 | J3: =IFERROR(INDEX(レビュー指針!$D:$D,MATCH(I3,レビュー指針!$A:$A,0)),"") -> 成果物 | K3: =IFERROR(INDEX(レビュー指針!$E:$E,MATCH(I3,レビュー指針!$A:$A,0)),"") -> 1次レビュー | L3: =IFERROR(INDEX(レビュー指針!$H:$H,MATCH(I3,レビュー指針!$A:$A,0)),"") -> データソースと抽出条件（手順）の記録が成果物として提出されている | P3: Stage2精査 / データソースチェック（英文） / 自主点検QA由来 / 件数3 / 要文言整備
A4: 8 | B4: 4 | C4: =IFERROR(INDEX(自主点検項目!$B:$B,MATCH(B4,自主点検項目!$A:$A,0)),"") -> 滞留債権の分析 | D4: 共通 | E4: =IFERROR(INDEX(提出物!$D:$D,MATCH(D4,提出物!$A:$A,0)),"") | F4: 期末時点で滞留している債権について、取引発生日・回収予定日・最新の回収予定日（回収遅延理由）が記載されているか。 | G4: =COUNTIF('チェックポイント-問合せ・差戻し事例対応表'!$B:$B,A4) -> 13 | H4: =SUMPRODUCT(('チェックポイント-問合せ・差戻し事例対応表'!$B$2:$B$5000=A4)*('チェックポイント-問合せ・差戻し事例対応表'!$I$2:$I$5000<>"")/(COUNTIFS('チェックポイント-問合せ・差戻し事例対応表'!$B$2:$B$5000,'チェックポイント-問合せ・差戻し事例対応表'!$B$2:$B$5000,'チェックポイント-問合せ・差戻し事例対応表'!$I$2:$I$5000,'チェックポイント-問合せ・差戻し事例対応表'!$I$2:$I$5000)+('チェックポイント-問合せ・差戻し事例対応表'!$I$2:$I$5000=""))) -> 11 | I4: 3 | J4: =IFERROR(INDEX(レビュー指針!$D:$D,MATCH(I4,レビュー指針!$A:$A,0)),"") -> 成果物 | K4: =IFERROR(INDEX(レビュー指針!$E:$E,MATCH(I4,レビュー指針!$A:$A,0)),"") -> 1次レビュー | L4: =IFERROR(INDEX(レビュー指針!$H:$H,MATCH(I4,レビュー指針!$A:$A,0)),"") -> 回収が遅延している債権全てにつき、回収遅延理由が記載されている | P4: Stage2精査 / 回収遅延理由 / 自主点検QA由来 / 件数2 / 要文言整備
A5: 9 | B5: 4 | C5: =IFERROR(INDEX(自主点検項目!$B:$B,MATCH(B5,自主点検項目!$A:$A,0)),"") -> 滞留債権の分析 | D5: 共通 | E5: =IFERROR(INDEX(提出物!$D:$D,MATCH(D5,提出物!$A:$A,0)),"") | F5: 回収遅延理由について部門責任者等の適切な承認を得ていることを示す資料が提出されているか。 | G5: =COUNTIF('チェックポイント-問合せ・差戻し事例対応表'!$B:$B,A5) -> 2 | H5: =SUMPRODUCT(('チェックポイント-問合せ・差戻し事例対応表'!$B$2:$B$5000=A5)*('チェックポイント-問合せ・差戻し事例対応表'!$I$2:$I$5000<>"")/(COUNTIFS('チェックポイント-問合せ・差戻し事例対応表'!$B$2:$B$5000,'チェックポイント-問合せ・差戻し事例対応表'!$B$2:$B$5000,'チェックポイント-問合せ・差戻し事例対応表'!$I$2:$I$5000,'チェックポイント-問合せ・差戻し事例対応表'!$I$2:$I$5000)+('チェックポイント-問合せ・差戻し事例対応表'!$I$2:$I$5000=""))) -> 2 | I5: 4 | J5: =IFERROR(INDEX(レビュー指針!$D:$D,MATCH(I5,レビュー指針!$A:$A,0)),"") -> 成果物 | K5: =IFERROR(INDEX(レビュー指針!$E:$E,MATCH(I5,レビュー指針!$A:$A,0)),"") -> 1次レビュー | L5: =IFERROR(INDEX(レビュー指針!$H:$H,MATCH(I5,レビュー指針!$A:$A,0)),"") -> 回収遅延理由について、部門責任者等の適切な承認者の承認を得ている | P5: Stage2精査 / 承認 / 自主点検QA由来 / 件数2 / 要文言整備
A6: 11 | B6: 5 | C6: =IFERROR(INDEX(自主点検項目!$B:$B,MATCH(B6,自主点検項目!$A:$A,0)),"") -> 異常取引の分析 | D6: 20 | E6: =IFERROR(INDEX(提出物!$D:$D,MATCH(D6,提出物!$A:$A,0)),"") -> データソース・抽出条件 | F6: 成果物の作成に用いたデータソースと抽出条件（手順）の記録（画面コピー等）が提出されているか。 | G6: =COUNTIF('チェックポイント-問合せ・差戻し事例対応表'!$B:$B,A6) -> 89 | H6: =SUMPRODUCT(('チェックポイント-問合せ・差戻し事例対応表'!$B$2:$B$5000=A6)*('チェックポイント-問合せ・差戻し事例対応表'!$I$2:$I$5000<>"")/(COUNTIFS('チェックポイント-問合せ・差戻し事例対応表'!$B$2:$B$5000,'チェックポイント-問合せ・差戻し事例対応表'!$B$2:$B$5000,'チェックポイント-問合せ・差戻し事例対応表'!$I$2:$I$5000,'チェックポイント-問合せ・差戻し事例対応表'!$I$2:$I$5000)+('チェックポイント-問合せ・差戻し事例対応表'!$I$2:$I$5000=""))) -> 80 | I6: 8 | J6: =IFERROR(INDEX(レビュー指針!$D:$D,MATCH(I6,レビュー指針!$A:$A,0)),"") -> 成果物 | K6: =IFERROR(INDEX(レビュー指針!$E:$E,MATCH(I6,レビュー指針!$A:$A,0)),"") -> 1次レビュー | L6: =IFERROR(INDEX(レビュー指針!$H:$H,MATCH(I6,レビュー指針!$A:$A,0)),"") -> データソースと抽出条件（手順）の記録が成果物として提出されている | P6: Stage2精査 / 複合問合せを分割（網羅性は別CPへ） / 自主点検QA由来 / 件数68 / 要文言整備
A7: 22 | B7: 5 | C7: =IFERROR(INDEX(自主点検項目!$B:$B,MATCH(B7,自主点検項目!$A:$A,0)),"") -> 異常取引の分析 | D7: 20 | E7: =IFERROR(INDEX(提出物!$D:$D,MATCH(D7,提出物!$A:$A,0)),"") -> データソース・抽出条件 | F7: 全ての売上明細を提出のうえ、マイナス売上について売上計上の妥当性（収益認識基準の充足）のコメントが記載されているか。 | G7: =COUNTIF('チェックポイント-問合せ・差戻し事例対応表'!$B:$B,A7) -> 2 | H7: =SUMPRODUCT(('チェックポイント-問合せ・差戻し事例対応表'!$B$2:$B$5000=A7)*('チェックポイント-問合せ・差戻し事例対応表'!$I$2:$I$5000<>"")/(COUNTIFS('チェックポイント-問合せ・差戻し事例対応表'!$B$2:$B$5000,'チェックポイント-問合せ・差戻し事例対応表'!$B$2:$B$5000,'チェックポイント-問合せ・差戻し事例対応表'!$I$2:$I$5000,'チェックポイント-問合せ・差戻し事例対応表'!$I$2:$I$5000)+('チェックポイント-問合せ・差戻し事例対応表'!$I$2:$I$5000=""))) -> 2 | I7: 10 | J7: =IFERROR(INDEX(レビュー指針!$D:$D,MATCH(I7,レビュー指針!$A:$A,0)),"") -> 成果物 | K7: =IFERROR(INDEX(レビュー指針!$E:$E,MATCH(I7,レビュー指針!$A:$A,0)),"") -> 1次レビュー | L7: =IFERROR(INDEX(レビュー指針!$H:$H,MATCH(I7,レビュー指針!$A:$A,0)),"") -> マイナスの売上がある場合、売上計上の妥当性（収益認識基準を満たしているか）を検討したコメントが残されている | P7: Stage2精査 / マイナス妥当性 / 自主点検QA由来 / 件数2 / 要文言整備
A8: 25 | B8: 5 | C8: =IFERROR(INDEX(自主点検項目!$B:$B,MATCH(B8,自主点検項目!$A:$A,0)),"") -> 異常取引の分析 | D8: 21 | E8: =IFERROR(INDEX(提出物!$D:$D,MATCH(D8,提出物!$A:$A,0)),"") -> マイナス取引の根拠資料 | F8: マイナス売上について売上計上の妥当性（収益認識基準の充足）を検討したコメントが提出されているか（翌期4月分含む）。 | G8: =COUNTIF('チェックポイント-問合せ・差戻し事例対応表'!$B:$B,A8) -> 6 | H8: =SUMPRODUCT(('チェックポイント-問合せ・差戻し事例対応表'!$B$2:$B$5000=A8)*('チェックポイント-問合せ・差戻し事例対応表'!$I$2:$I$5000<>"")/(COUNTIFS('チェックポイント-問合せ・差戻し事例対応表'!$B$2:$B$5000,'チェックポイント-問合せ・差戻し事例対応表'!$B$2:$B$5000,'チェックポイント-問合せ・差戻し事例対応表'!$I$2:$I$5000,'チェックポイント-問合せ・差戻し事例対応表'!$I$2:$I$5000)+('チェックポイント-問合せ・差戻し事例対応表'!$I$2:$I$5000=""))) -> 6 | I8: 10 | J8: =IFERROR(INDEX(レビュー指針!$D:$D,MATCH(I8,レビュー指針!$A:$A,0)),"") -> 成果物 | K8: =IFERROR(INDEX(レビュー指針!$E:$E,MATCH(I8,レビュー指針!$A:$A,0)),"") -> 1次レビュー | L8: =IFERROR(INDEX(レビュー指針!$H:$H,MATCH(I8,レビュー指針!$A:$A,0)),"") -> マイナスの売上がある場合、売上計上の妥当性（収益認識基準を満たしているか）を検討したコメントが残されている | P8: Stage2精査 / マイナス妥当性 / 自主点検QA由来 / 件数6 / 要文言整備
A9: 26 | B9: 5 | C9: =IFERROR(INDEX(自主点検項目!$B:$B,MATCH(B9,自主点検項目!$A:$A,0)),"") -> 異常取引の分析 | D9: 共通 | E9: =IFERROR(INDEX(提出物!$D:$D,MATCH(D9,提出物!$A:$A,0)),"") | F9: 25年4月〜26年3月の全売上明細（マイナス含む）が提出され、試算表と一致することが確認できるか。 | G9: =COUNTIF('チェックポイント-問合せ・差戻し事例対応表'!$B:$B,A9) -> 12 | H9: =SUMPRODUCT(('チェックポイント-問合せ・差戻し事例対応表'!$B$2:$B$5000=A9)*('チェックポイント-問合せ・差戻し事例対応表'!$I$2:$I$5000<>"")/(COUNTIFS('チェックポイント-問合せ・差戻し事例対応表'!$B$2:$B$5000,'チェックポイント-問合せ・差戻し事例対応表'!$B$2:$B$5000,'チェックポイント-問合せ・差戻し事例対応表'!$I$2:$I$5000,'チェックポイント-問合せ・差戻し事例対応表'!$I$2:$I$5000)+('チェックポイント-問合せ・差戻し事例対応表'!$I$2:$I$5000=""))) -> 11 | I9: 9 | J9: =IFERROR(INDEX(レビュー指針!$D:$D,MATCH(I9,レビュー指針!$A:$A,0)),"") -> 成果物 | K9: =IFERROR(INDEX(レビュー指針!$E:$E,MATCH(I9,レビュー指針!$A:$A,0)),"") -> 1次レビュー | L9: =IFERROR(INDEX(レビュー指針!$H:$H,MATCH(I9,レビュー指針!$A:$A,0)),"") -> 25年4月~26年3月の全ての売上明細（マイナス含む）が提出されている（試算表との一致が確認できる） | P9: Stage2精査 / 網羅性 / 自主点検QA由来 / 件数2 / 要文言整備
A10: 27 | B10: 5 | C10: =IFERROR(INDEX(自主点検項目!$B:$B,MATCH(B10,自主点検項目!$A:$A,0)),"") -> 異常取引の分析 | D10: 共通 | E10: =IFERROR(INDEX(提出物!$D:$D,MATCH(D10,提出物!$A:$A,0)),"") | F10: マイナス売上について売上計上の妥当性（収益認識基準の充足）を検討したコメント・根拠が提出されているか。 | G10: =COUNTIF('チェックポイント-問合せ・差戻し事例対応表'!$B:$B,A10) -> 6 | H10: =SUMPRODUCT(('チェックポイント-問合せ・差戻し事例対応表'!$B$2:$B$5000=A10)*('チェックポイント-問合せ・差戻し事例対応表'!$I$2:$I$5000<>"")/(COUNTIFS('チェックポイント-問合せ・差戻し事例対応表'!$B$2:$B$5000,'チェックポイント-問合せ・差戻し事例対応表'!$B$2:$B$5000,'チェックポイント-問合せ・差戻し事例対応表'!$I$2:$I$5000,'チェックポイント-問合せ・差戻し事例対応表'!$I$2:$I$5000)+('チェックポイント-問合せ・差戻し事例対応表'!$I$2:$I$5000=""))) -> 6 | I10: 10 | J10: =IFERROR(INDEX(レビュー指針!$D:$D,MATCH(I10,レビュー指針!$A:$A,0)),"") -> 成果物 | K10: =IFERROR(INDEX(レビュー指針!$E:$E,MATCH(I10,レビュー指針!$A:$A,0)),"") -> 1次レビュー | L10: =IFERROR(INDEX(レビュー指針!$H:$H,MATCH(I10,レビュー指針!$A:$A,0)),"") -> マイナスの売上がある場合、売上計上の妥当性（収益認識基準を満たしているか）を検討したコメントが残されている | P10: Stage2精査 / マイナス妥当性 / 自主点検QA由来 / 件数2 / 要文言整備
A11: 31 | B11: 6 | C11: =IFERROR(INDEX(自主点検項目!$B:$B,MATCH(B11,自主点検項目!$A:$A,0)),"") -> 売上の期末変動分析 | D11: 22 | E11: =IFERROR(INDEX(提出物!$D:$D,MATCH(D11,提出物!$A:$A,0)),"") -> 月次の売上・粗利推移データ | F11: 前年同期・前月比較で10百万円かつ20%以上の変動がある場合、増減理由のコメントが記載されているか。 | G11: =COUNTIF('チェックポイント-問合せ・差戻し事例対応表'!$B:$B,A11) -> 9 | H11: =SUMPRODUCT(('チェックポイント-問合せ・差戻し事例対応表'!$B$2:$B$5000=A11)*('チェックポイント-問合せ・差戻し事例対応表'!$I$2:$I$5000<>"")/(COUNTIFS('チェックポイント-問合せ・差戻し事例対応表'!$B$2:$B$5000,'チェックポイント-問合せ・差戻し事例対応表'!$B$2:$B$5000,'チェックポイント-問合せ・差戻し事例対応表'!$I$2:$I$5000,'チェックポイント-問合せ・差戻し事例対応表'!$I$2:$I$5000)+('チェックポイント-問合せ・差戻し事例対応表'!$I$2:$I$5000=""))) -> 7 | I11: 18 | J11: =IFERROR(INDEX(レビュー指針!$D:$D,MATCH(I11,レビュー指針!$A:$A,0)),"") -> 成果物 | K11: =IFERROR(INDEX(レビュー指針!$E:$E,MATCH(I11,レビュー指針!$A:$A,0)),"") -> 1次レビュー | L11: =IFERROR(INDEX(レビュー指針!$H:$H,MATCH(I11,レビュー指針!$A:$A,0)),"") -> 前年同期・前月比較ともに、10百万円の変動、かつ、20%以上の変動がある場合、増減コメントがされている | P11: Stage2精査 / 増減コメント / 自主点検QA由来 / 件数4 / 要文言整備
A12: 34 | B12: 6 | C12: =IFERROR(INDEX(自主点検項目!$B:$B,MATCH(B12,自主点検項目!$A:$A,0)),"") -> 売上の期末変動分析 | D12: 22 | E12: =IFERROR(INDEX(提出物!$D:$D,MATCH(D12,提出物!$A:$A,0)),"") -> 月次の売上・粗利推移データ | F12: 増減分析コメントに、要因ごとの影響金額が記載されているか。 | G12: =COUNTIF('チェックポイント-問合せ・差戻し事例対応表'!$B:$B,A12) -> 12 | H12: =SUMPRODUCT(('チェックポイント-問合せ・差戻し事例対応表'!$B$2:$B$5000=A12)*('チェックポイント-問合せ・差戻し事例対応表'!$I$2:$I$5000<>"")/(COUNTIFS('チェックポイント-問合せ・差戻し事例対応表'!$B$2:$B$5000,'チェックポイント-問合せ・差戻し事例対応表'!$B$2:$B$5000,'チェックポイント-問合せ・差戻し事例対応表'!$I$2:$I$5000,'チェックポイント-問合せ・差戻し事例対応表'!$I$2:$I$5000)+('チェックポイント-問合せ・差戻し事例対応表'!$I$2:$I$5000=""))) -> 11 | I12: 19 | J12: =IFERROR(INDEX(レビュー指針!$D:$D,MATCH(I12,レビュー指針!$A:$A,0)),"") -> 成果物 | K12: =IFERROR(INDEX(レビュー指針!$E:$E,MATCH(I12,レビュー指針!$A:$A,0)),"") -> 1次レビュー | L12: =IFERROR(INDEX(レビュー指針!$H:$H,MATCH(I12,レビュー指針!$A:$A,0)),"") -> 増減分析コメントにて、要因毎の影響金額を記載している（最低限、6割～7割程度） | P12: Stage2精査 / 要因別影響金額 / 自主点検QA由来 / 件数2 / 要文言整備
A13: 35 | B13: 6 | C13: =IFERROR(INDEX(自主点検項目!$B:$B,MATCH(B13,自主点検項目!$A:$A,0)),"") -> 売上の期末変動分析 | D13: 23 | E13: =IFERROR(INDEX(提出物!$D:$D,MATCH(D13,提出物!$A:$A,0)),"") -> データソース・抽出条件 | F13: 成果物の作成に用いたデータソースと抽出条件（手順）の記録（画面コピー等）が提出されているか。 | G13: =COUNTIF('チェックポイント-問合せ・差戻し事例対応表'!$B:$B,A13) -> 86 | H13: =SUMPRODUCT(('チェックポイント-問合せ・差戻し事例対応表'!$B$2:$B$5000=A13)*('チェックポイント-問合せ・差戻し事例対応表'!$I$2:$I$5000<>"")/(COUNTIFS('チェックポイント-問合せ・差戻し事例対応表'!$B$2:$B$5000,'チェックポイント-問合せ・差戻し事例対応表'!$B$2:$B$5000,'チェックポイント-問合せ・差戻し事例対応表'!$I$2:$I$5000,'チェックポイント-問合せ・差戻し事例対応表'!$I$2:$I$5000)+('チェックポイント-問合せ・差戻し事例対応表'!$I$2:$I$5000=""))) -> 83 | I13: 16 | J13: =IFERROR(INDEX(レビュー指針!$D:$D,MATCH(I13,レビュー指針!$A:$A,0)),"") -> 成果物 | K13: =IFERROR(INDEX(レビュー指針!$E:$E,MATCH(I13,レビュー指針!$A:$A,0)),"") -> 1次レビュー | L13: =IFERROR(INDEX(レビュー指針!$H:$H,MATCH(I13,レビュー指針!$A:$A,0)),"") -> データソースと抽出条件（手順）の記録が成果物として提出されている | P13: Stage2精査 / 複合問合せを分割（網羅性は別CPへ） / 自主点検QA由来 / 件数82 / 要文言整備
A14: 38 | B14: 6 | C14: =IFERROR(INDEX(自主点検項目!$B:$B,MATCH(B14,自主点検項目!$A:$A,0)),"") -> 売上の期末変動分析 | D14: 23 | E14: =IFERROR(INDEX(提出物!$D:$D,MATCH(D14,提出物!$A:$A,0)),"") -> データソース・抽出条件 | F14: 進行基準・完成基準の差異や大口請負案件について、増減内容の合理的な説明がされているか。 | G14: =COUNTIF('チェックポイント-問合せ・差戻し事例対応表'!$B:$B,A14) -> 2 | H14: =SUMPRODUCT(('チェックポイント-問合せ・差戻し事例対応表'!$B$2:$B$5000=A14)*('チェックポイント-問合せ・差戻し事例対応表'!$I$2:$I$5000<>"")/(COUNTIFS('チェックポイント-問合せ・差戻し事例対応表'!$B$2:$B$5000,'チェックポイント-問合せ・差戻し事例対応表'!$B$2:$B$5000,'チェックポイント-問合せ・差戻し事例対応表'!$I$2:$I$5000,'チェックポイント-問合せ・差戻し事例対応表'!$I$2:$I$5000)+('チェックポイント-問合せ・差戻し事例対応表'!$I$2:$I$5000=""))) -> 2 | I14: 21 | J14: =IFERROR(INDEX(レビュー指針!$D:$D,MATCH(I14,レビュー指針!$A:$A,0)),"") -> 分析の妥当性 | K14: =IFERROR(INDEX(レビュー指針!$E:$E,MATCH(I14,レビュー指針!$A:$A,0)),"") -> 2次レビュー | L14: =IFERROR(INDEX(レビュー指針!$H:$H,MATCH(I14,レビュー指針!$A:$A,0)),"") -> 増減分析コメントにて、増減内容の説明になっている | P14: Stage2精査 / 分析の妥当性 / 自主点検QA由来 / 件数2 / 要文言整備
A15: 39 | B15: 6 | C15: =IFERROR(INDEX(自主点検項目!$B:$B,MATCH(B15,自主点検項目!$A:$A,0)),"") -> 売上の期末変動分析 | D15: 共通 | E15: =IFERROR(INDEX(提出物!$D:$D,MATCH(D15,提出物!$A:$A,0)),"") | F15: 成果物の作成に用いたデータソースと抽出条件（手順）の記録（画面コピー等）が提出されているか。 | G15: =COUNTIF('チェックポイント-問合せ・差戻し事例対応表'!$B:$B,A15) -> 5 | H15: =SUMPRODUCT(('チェックポイント-問合せ・差戻し事例対応表'!$B$2:$B$5000=A15)*('チェックポイント-問合せ・差戻し事例対応表'!$I$2:$I$5000<>"")/(COUNTIFS('チェックポイント-問合せ・差戻し事例対応表'!$B$2:$B$5000,'チェックポイント-問合せ・差戻し事例対応表'!$B$2:$B$5000,'チェックポイント-問合せ・差戻し事例対応表'!$I$2:$I$5000,'チェックポイント-問合せ・差戻し事例対応表'!$I$2:$I$5000)+('チェックポイント-問合せ・差戻し事例対応表'!$I$2:$I$5000=""))) -> 5 | I15: 16 | J15: =IFERROR(INDEX(レビュー指針!$D:$D,MATCH(I15,レビュー指針!$A:$A,0)),"") -> 成果物 | K15: =IFERROR(INDEX(レビュー指針!$E:$E,MATCH(I15,レビュー指針!$A:$A,0)),"") -> 1次レビュー | L15: =IFERROR(INDEX(レビュー指針!$H:$H,MATCH(I15,レビュー指針!$A:$A,0)),"") -> データソースと抽出条件（手順）の記録が成果物として提出されている | P15: Stage2精査 / データソースチェック（英文問合せ）へ整形 / 自主点検QA由来 / 件数5 / 要文言整備
A16: 40 | B16: 6 | C16: =IFERROR(INDEX(自主点検項目!$B:$B,MATCH(B16,自主点検項目!$A:$A,0)),"") -> 売上の期末変動分析 | D16: 共通 | E16: =IFERROR(INDEX(提出物!$D:$D,MATCH(D16,提出物!$A:$A,0)),"") | F16: 粗利益（売上総利益）が損益計算書と一致しているか（数値の整合）。 | G16: =COUNTIF('チェックポイント-問合せ・差戻し事例対応表'!$B:$B,A16) -> 2 | H16: =SUMPRODUCT(('チェックポイント-問合せ・差戻し事例対応表'!$B$2:$B$5000=A16)*('チェックポイント-問合せ・差戻し事例対応表'!$I$2:$I$5000<>"")/(COUNTIFS('チェックポイント-問合せ・差戻し事例対応表'!$B$2:$B$5000,'チェックポイント-問合せ・差戻し事例対応表'!$B$2:$B$5000,'チェックポイント-問合せ・差戻し事例対応表'!$I$2:$I$5000,'チェックポイント-問合せ・差戻し事例対応表'!$I$2:$I$5000)+('チェックポイント-問合せ・差戻し事例対応表'!$I$2:$I$5000=""))) -> 1 | I16: 17 | J16: =IFERROR(INDEX(レビュー指針!$D:$D,MATCH(I16,レビュー指針!$A:$A,0)),"") -> 成果物 | K16: =IFERROR(INDEX(レビュー指針!$E:$E,MATCH(I16,レビュー指針!$A:$A,0)),"") -> 1次レビュー | L16: =IFERROR(INDEX(レビュー指針!$H:$H,MATCH(I16,レビュー指針!$A:$A,0)),"") -> 網羅性が確認できる情報が記載又は提出されている（試算表との一致が確認できる） | P16: Stage2精査 / 網羅性・整合 / 自主点検QA由来 / 件数2 / 要文言整備
A17: 41 | B17: 8 | C17: =IFERROR(INDEX(自主点検項目!$B:$B,MATCH(B17,自主点検項目!$A:$A,0)),"") -> 売上のカットオフテスト | D17: 28 | E17: =IFERROR(INDEX(提出物!$D:$D,MATCH(D17,提出物!$A:$A,0)),"") -> 売上明細データ | F17: 成果物の作成に用いたデータソースと抽出条件（手順）の記録（画面コピー等）が提出されているか。 | G17: =COUNTIF('チェックポイント-問合せ・差戻し事例対応表'!$B:$B,A17) -> 9 | H17: =SUMPRODUCT(('チェックポイント-問合せ・差戻し事例対応表'!$B$2:$B$5000=A17)*('チェックポイント-問合せ・差戻し事例対応表'!$I$2:$I$5000<>"")/(COUNTIFS('チェックポイント-問合せ・差戻し事例対応表'!$B$2:$B$5000,'チェックポイント-問合せ・差戻し事例対応表'!$B$2:$B$5000,'チェックポイント-問合せ・差戻し事例対応表'!$I$2:$I$5000,'チェックポイント-問合せ・差戻し事例対応表'!$I$2:$I$5000)+('チェックポイント-問合せ・差戻し事例対応表'!$I$2:$I$5000=""))) -> 8 | I17: 27 | J17: =IFERROR(INDEX(レビュー指針!$D:$D,MATCH(I17,レビュー指針!$A:$A,0)),"") -> 成果物 | K17: =IFERROR(INDEX(レビュー指針!$E:$E,MATCH(I17,レビュー指針!$A:$A,0)),"") -> 1次レビュー | L17: =IFERROR(INDEX(レビュー指針!$H:$H,MATCH(I17,レビュー指針!$A:$A,0)),"") -> データソースと抽出条件（手順）の記録が成果物として提出されている | P17: Stage2精査 / 複合問合せを分割（網羅性は別CPへ） / 自主点検QA由来 / 件数9 / 要文言整備
A18: 42 | B18: 8 | C18: =IFERROR(INDEX(自主点検項目!$B:$B,MATCH(B18,自主点検項目!$A:$A,0)),"") -> 売上のカットオフテスト | D18: 28 | E18: =IFERROR(INDEX(提出物!$D:$D,MATCH(D18,提出物!$A:$A,0)),"") -> 売上明細データ | F18: 全ての明細について売上計上の妥当性（収益認識基準の充足）を検討したコメントが提出されているか。 | G18: =COUNTIF('チェックポイント-問合せ・差戻し事例対応表'!$B:$B,A18) -> 15 | H18: =SUMPRODUCT(('チェックポイント-問合せ・差戻し事例対応表'!$B$2:$B$5000=A18)*('チェックポイント-問合せ・差戻し事例対応表'!$I$2:$I$5000<>"")/(COUNTIFS('チェックポイント-問合せ・差戻し事例対応表'!$B$2:$B$5000,'チェックポイント-問合せ・差戻し事例対応表'!$B$2:$B$5000,'チェックポイント-問合せ・差戻し事例対応表'!$I$2:$I$5000,'チェックポイント-問合せ・差戻し事例対応表'!$I$2:$I$5000)+('チェックポイント-問合せ・差戻し事例対応表'!$I$2:$I$5000=""))) -> 15 | I18: 29 | J18: =IFERROR(INDEX(レビュー指針!$D:$D,MATCH(I18,レビュー指針!$A:$A,0)),"") -> 成果物 | K18: =IFERROR(INDEX(レビュー指針!$E:$E,MATCH(I18,レビュー指針!$A:$A,0)),"") -> 1次レビュー | L18: =IFERROR(INDEX(レビュー指針!$H:$H,MATCH(I18,レビュー指針!$A:$A,0)),"") -> 全ての明細に対して売上計上の妥当性（収益認識基準を満たしているか）を検討したコメントが残されている | P18: Stage2精査 / 妥当性コメント / 自主点検QA由来 / 件数3 / 要文言整備
A19: 45 | B19: 8 | C19: =IFERROR(INDEX(自主点検項目!$B:$B,MATCH(B19,自主点検項目!$A:$A,0)),"") -> 売上のカットオフテスト | D19: 28 | E19: =IFERROR(INDEX(提出物!$D:$D,MATCH(D19,提出物!$A:$A,0)),"") -> 売上明細データ | F19: 提出された売上明細の合計が試算表・根拠資料と一致することが確認できるか。 | G19: =COUNTIF('チェックポイント-問合せ・差戻し事例対応表'!$B:$B,A19) -> 21 | H19: =SUMPRODUCT(('チェックポイント-問合せ・差戻し事例対応表'!$B$2:$B$5000=A19)*('チェックポイント-問合せ・差戻し事例対応表'!$I$2:$I$5000<>"")/(COUNTIFS('チェックポイント-問合せ・差戻し事例対応表'!$B$2:$B$5000,'チェックポイント-問合せ・差戻し事例対応表'!$B$2:$B$5000,'チェックポイント-問合せ・差戻し事例対応表'!$I$2:$I$5000,'チェックポイント-問合せ・差戻し事例対応表'!$I$2:$I$5000)+('チェックポイント-問合せ・差戻し事例対応表'!$I$2:$I$5000=""))) -> 18 | I19: 28 | J19: =IFERROR(INDEX(レビュー指針!$D:$D,MATCH(I19,レビュー指針!$A:$A,0)),"") -> 成果物 | K19: =IFERROR(INDEX(レビュー指針!$E:$E,MATCH(I19,レビュー指針!$A:$A,0)),"") -> 1次レビュー | L19: =IFERROR(INDEX(レビュー指針!$H:$H,MATCH(I19,レビュー指針!$A:$A,0)),"") -> 26年3月単月の全ての売上明細が提出されている（試算表との一致が確認できる） | P19: Stage2精査 / 網羅性・一致 / 自主点検QA由来 / 件数2 / 要文言整備
A20: 46 | B20: 8 | C20: =IFERROR(INDEX(自主点検項目!$B:$B,MATCH(B20,自主点検項目!$A:$A,0)),"") -> 売上のカットオフテスト | D20: 29 | E20: =IFERROR(INDEX(提出物!$D:$D,MATCH(D20,提出物!$A:$A,0)),"") -> データソース・抽出条件 | F20: 成果物の作成に用いたデータソースと抽出条件（手順）の記録（画面コピー等）が提出されているか。 | G20: =COUNTIF('チェックポイント-問合せ・差戻し事例対応表'!$B:$B,A20) -> 67 | H20: =SUMPRODUCT(('チェックポイント-問合せ・差戻し事例対応表'!$B$2:$B$5000=A20)*('チェックポイント-問合せ・差戻し事例対応表'!$I$2:$I$5000<>"")/(COUNTIFS('チェックポイント-問合せ・差戻し事例対応表'!$B$2:$B$5000,'チェックポイント-問合せ・差戻し事例対応表'!$B$2:$B$5000,'チェックポイント-問合せ・差戻し事例対応表'!$I$2:$I$5000,'チェックポイント-問合せ・差戻し事例対応表'!$I$2:$I$5000)+('チェックポイント-問合せ・差戻し事例対応表'!$I$2:$I$5000=""))) -> 63 | I20: 27 | J20: =IFERROR(INDEX(レビュー指針!$D:$D,MATCH(I20,レビュー指針!$A:$A,0)),"") -> 成果物 | K20: =IFERROR(INDEX(レビュー指針!$E:$E,MATCH(I20,レビュー指針!$A:$A,0)),"") -> 1次レビュー | L20: =IFERROR(INDEX(レビュー指針!$H:$H,MATCH(I20,レビュー指針!$A:$A,0)),"") -> データソースと抽出条件（手順）の記録が成果物として提出されている | P20: Stage2精査 / 複合問合せを分割（網羅性は別CPへ） / 自主点検QA由来 / 件数49 / 要文言整備
A21: 48 | B21: 8 | C21: =IFERROR(INDEX(自主点検項目!$B:$B,MATCH(B21,自主点検項目!$A:$A,0)),"") -> 売上のカットオフテスト | D21: 30 | E21: =IFERROR(INDEX(提出物!$D:$D,MATCH(D21,提出物!$A:$A,0)),"") -> 収益認識の根拠資料 | F21: 網羅性が確認できる情報（試算表との一致）が提出されているか。 | G21: =COUNTIF('チェックポイント-問合せ・差戻し事例対応表'!$B:$B,A21) -> 3 | H21: =SUMPRODUCT(('チェックポイント-問合せ・差戻し事例対応表'!$B$2:$B$5000=A21)*('チェックポイント-問合せ・差戻し事例対応表'!$I$2:$I$5000<>"")/(COUNTIFS('チェックポイント-問合せ・差戻し事例対応表'!$B$2:$B$5000,'チェックポイント-問合せ・差戻し事例対応表'!$B$2:$B$5000,'チェックポイント-問合せ・差戻し事例対応表'!$I$2:$I$5000,'チェックポイント-問合せ・差戻し事例対応表'!$I$2:$I$5000)+('チェックポイント-問合せ・差戻し事例対応表'!$I$2:$I$5000=""))) -> 3 | I21: 28 | J21: =IFERROR(INDEX(レビュー指針!$D:$D,MATCH(I21,レビュー指針!$A:$A,0)),"") -> 成果物 | K21: =IFERROR(INDEX(レビュー指針!$E:$E,MATCH(I21,レビュー指針!$A:$A,0)),"") -> 1次レビュー | L21: =IFERROR(INDEX(レビュー指針!$H:$H,MATCH(I21,レビュー指針!$A:$A,0)),"") -> 26年3月単月の全ての売上明細が提出されている（試算表との一致が確認できる） | P21: Stage2精査 / 網羅性 / 自主点検QA由来 / 件数2 / 要文言整備
A22: 49 | B22: 8 | C22: =IFERROR(INDEX(自主点検項目!$B:$B,MATCH(B22,自主点検項目!$A:$A,0)),"") -> 売上のカットオフテスト | D22: 30 | E22: =IFERROR(INDEX(提出物!$D:$D,MATCH(D22,提出物!$A:$A,0)),"") -> 収益認識の根拠資料 | F22: 全ての明細について売上計上の妥当性（収益認識基準の充足）を検討したコメントが提出されているか。 | G22: =COUNTIF('チェックポイント-問合せ・差戻し事例対応表'!$B:$B,A22) -> 2 | H22: =SUMPRODUCT(('チェックポイント-問合せ・差戻し事例対応表'!$B$2:$B$5000=A22)*('チェックポイント-問合せ・差戻し事例対応表'!$I$2:$I$5000<>"")/(COUNTIFS('チェックポイント-問合せ・差戻し事例対応表'!$B$2:$B$5000,'チェックポイント-問合せ・差戻し事例対応表'!$B$2:$B$5000,'チェックポイント-問合せ・差戻し事例対応表'!$I$2:$I$5000,'チェックポイント-問合せ・差戻し事例対応表'!$I$2:$I$5000)+('チェックポイント-問合せ・差戻し事例対応表'!$I$2:$I$5000=""))) -> 2 | I22: 29 | J22: =IFERROR(INDEX(レビュー指針!$D:$D,MATCH(I22,レビュー指針!$A:$A,0)),"") -> 成果物 | K22: =IFERROR(INDEX(レビュー指針!$E:$E,MATCH(I22,レビュー指針!$A:$A,0)),"") -> 1次レビュー | L22: =IFERROR(INDEX(レビュー指針!$H:$H,MATCH(I22,レビュー指針!$A:$A,0)),"") -> 全ての明細に対して売上計上の妥当性（収益認識基準を満たしているか）を検討したコメントが残されている | P22: Stage2精査 / 妥当性コメント / 自主点検QA由来 / 件数2 / 要文言整備
A23: 50 | B23: 8 | C23: =IFERROR(INDEX(自主点検項目!$B:$B,MATCH(B23,自主点検項目!$A:$A,0)),"") -> 売上のカットオフテスト | D23: 共通 | E23: =IFERROR(INDEX(提出物!$D:$D,MATCH(D23,提出物!$A:$A,0)),"") | F23: 全ての明細について売上計上の妥当性（収益認識基準の充足）を検討したコメントが提出されているか。 | G23: =COUNTIF('チェックポイント-問合せ・差戻し事例対応表'!$B:$B,A23) -> 15 | H23: =SUMPRODUCT(('チェックポイント-問合せ・差戻し事例対応表'!$B$2:$B$5000=A23)*('チェックポイント-問合せ・差戻し事例対応表'!$I$2:$I$5000<>"")/(COUNTIFS('チェックポイント-問合せ・差戻し事例対応表'!$B$2:$B$5000,'チェックポイント-問合せ・差戻し事例対応表'!$B$2:$B$5000,'チェックポイント-問合せ・差戻し事例対応表'!$I$2:$I$5000,'チェックポイント-問合せ・差戻し事例対応表'!$I$2:$I$5000)+('チェックポイント-問合せ・差戻し事例対応表'!$I$2:$I$5000=""))) -> 14 | I23: 29 | J23: =IFERROR(INDEX(レビュー指針!$D:$D,MATCH(I23,レビュー指針!$A:$A,0)),"") -> 成果物 | K23: =IFERROR(INDEX(レビュー指針!$E:$E,MATCH(I23,レビュー指針!$A:$A,0)),"") -> 1次レビュー | L23: =IFERROR(INDEX(レビュー指針!$H:$H,MATCH(I23,レビュー指針!$A:$A,0)),"") -> 全ての明細に対して売上計上の妥当性（収益認識基準を満たしているか）を検討したコメントが残されている | P23: Stage2精査 / 妥当性コメントチェック / 自主点検QA由来 / 件数5 / 要文言整備
A24: 52 | B24: 8 | C24: =IFERROR(INDEX(自主点検項目!$B:$B,MATCH(B24,自主点検項目!$A:$A,0)),"") -> 売上のカットオフテスト | D24: 共通 | E24: =IFERROR(INDEX(提出物!$D:$D,MATCH(D24,提出物!$A:$A,0)),"") | F24: 全ての明細について売上計上の妥当性（収益認識基準の充足）を検討したコメントが提出されているか。 | G24: =COUNTIF('チェックポイント-問合せ・差戻し事例対応表'!$B:$B,A24) -> 4 | H24: =SUMPRODUCT(('チェックポイント-問合せ・差戻し事例対応表'!$B$2:$B$5000=A24)*('チェックポイント-問合せ・差戻し事例対応表'!$I$2:$I$5000<>"")/(COUNTIFS('チェックポイント-問合せ・差戻し事例対応表'!$B$2:$B$5000,'チェックポイント-問合せ・差戻し事例対応表'!$B$2:$B$5000,'チェックポイント-問合せ・差戻し事例対応表'!$I$2:$I$5000,'チェックポイント-問合せ・差戻し事例対応表'!$I$2:$I$5000)+('チェックポイント-問合せ・差戻し事例対応表'!$I$2:$I$5000=""))) -> 4 | I24: 29 | J24: =IFERROR(INDEX(レビュー指針!$D:$D,MATCH(I24,レビュー指針!$A:$A,0)),"") -> 成果物 | K24: =IFERROR(INDEX(レビュー指針!$E:$E,MATCH(I24,レビュー指針!$A:$A,0)),"") -> 1次レビュー | L24: =IFERROR(INDEX(レビュー指針!$H:$H,MATCH(I24,レビュー指針!$A:$A,0)),"") -> 全ての明細に対して売上計上の妥当性（収益認識基準を満たしているか）を検討したコメントが残されている | P24: Stage2精査 / 妥当性コメント / 自主点検QA由来 / 件数2 / 要文言整備
A25: 53 | B25: 8 | C25: =IFERROR(INDEX(自主点検項目!$B:$B,MATCH(B25,自主点検項目!$A:$A,0)),"") -> 売上のカットオフテスト | D25: 共通 | E25: =IFERROR(INDEX(提出物!$D:$D,MATCH(D25,提出物!$A:$A,0)),"") | F25: 一定金額以上の取引について、数量・単価・計上日が確認できる根拠資料（注文書・請求書等）が提出されているか。 | G25: =COUNTIF('チェックポイント-問合せ・差戻し事例対応表'!$B:$B,A25) -> 5 | H25: =SUMPRODUCT(('チェックポイント-問合せ・差戻し事例対応表'!$B$2:$B$5000=A25)*('チェックポイント-問合せ・差戻し事例対応表'!$I$2:$I$5000<>"")/(COUNTIFS('チェックポイント-問合せ・差戻し事例対応表'!$B$2:$B$5000,'チェックポイント-問合せ・差戻し事例対応表'!$B$2:$B$5000,'チェックポイント-問合せ・差戻し事例対応表'!$I$2:$I$5000,'チェックポイント-問合せ・差戻し事例対応表'!$I$2:$I$5000)+('チェックポイント-問合せ・差戻し事例対応表'!$I$2:$I$5000=""))) -> 2 | I25: 30 | J25: =IFERROR(INDEX(レビュー指針!$D:$D,MATCH(I25,レビュー指針!$A:$A,0)),"") -> 根拠資料 | K25: =IFERROR(INDEX(レビュー指針!$E:$E,MATCH(I25,レビュー指針!$A:$A,0)),"") -> 1次レビュー | L25: =IFERROR(INDEX(レビュー指針!$H:$H,MATCH(I25,レビュー指針!$A:$A,0)),"") -> 1,000万円以上の取引について、根拠資料が提出されている | P25: Stage2精査 / 根拠資料 / 自主点検QA由来 / 件数2 / 要文言整備
A26: 56 | B26: 9 | C26: =IFERROR(INDEX(自主点検項目!$B:$B,MATCH(B26,自主点検項目!$A:$A,0)),"") -> 長期請負工事案件の洗い出し | D26: 32 | E26: =IFERROR(INDEX(提出物!$D:$D,MATCH(D26,提出物!$A:$A,0)),"") -> データソース・抽出条件 | F26: 成果物の作成に用いたデータソースと抽出条件（手順）の記録（画面コピー等）が提出されているか。 | G26: =COUNTIF('チェックポイント-問合せ・差戻し事例対応表'!$B:$B,A26) -> 6 | H26: =SUMPRODUCT(('チェックポイント-問合せ・差戻し事例対応表'!$B$2:$B$5000=A26)*('チェックポイント-問合せ・差戻し事例対応表'!$I$2:$I$5000<>"")/(COUNTIFS('チェックポイント-問合せ・差戻し事例対応表'!$B$2:$B$5000,'チェックポイント-問合せ・差戻し事例対応表'!$B$2:$B$5000,'チェックポイント-問合せ・差戻し事例対応表'!$I$2:$I$5000,'チェックポイント-問合せ・差戻し事例対応表'!$I$2:$I$5000)+('チェックポイント-問合せ・差戻し事例対応表'!$I$2:$I$5000=""))) -> 6 | I26: 38 | J26: =IFERROR(INDEX(レビュー指針!$D:$D,MATCH(I26,レビュー指針!$A:$A,0)),"") -> 成果物 | K26: =IFERROR(INDEX(レビュー指針!$E:$E,MATCH(I26,レビュー指針!$A:$A,0)),"") -> 1次レビュー | L26: =IFERROR(INDEX(レビュー指針!$H:$H,MATCH(I26,レビュー指針!$A:$A,0)),"") -> データソースと抽出条件（手順）の記録が成果物として提出されている | P26: Stage2精査 / データソース / 自主点検QA由来 / 件数4 / 要文言整備
A27: 57 | B27: 9 | C27: =IFERROR(INDEX(自主点検項目!$B:$B,MATCH(B27,自主点検項目!$A:$A,0)),"") -> 長期請負工事案件の洗い出し | D27: 共通 | E27: =IFERROR(INDEX(提出物!$D:$D,MATCH(D27,提出物!$A:$A,0)),"") | F27: 成果物の作成に用いたデータソースと抽出条件（手順）の記録（画面コピー等）が提出されているか。 | G27: =COUNTIF('チェックポイント-問合せ・差戻し事例対応表'!$B:$B,A27) -> 3 | H27: =SUMPRODUCT(('チェックポイント-問合せ・差戻し事例対応表'!$B$2:$B$5000=A27)*('チェックポイント-問合せ・差戻し事例対応表'!$I$2:$I$5000<>"")/(COUNTIFS('チェックポイント-問合せ・差戻し事例対応表'!$B$2:$B$5000,'チェックポイント-問合せ・差戻し事例対応表'!$B$2:$B$5000,'チェックポイント-問合せ・差戻し事例対応表'!$I$2:$I$5000,'チェックポイント-問合せ・差戻し事例対応表'!$I$2:$I$5000)+('チェックポイント-問合せ・差戻し事例対応表'!$I$2:$I$5000=""))) -> 3 | I27: 38 | J27: =IFERROR(INDEX(レビュー指針!$D:$D,MATCH(I27,レビュー指針!$A:$A,0)),"") -> 成果物 | K27: =IFERROR(INDEX(レビュー指針!$E:$E,MATCH(I27,レビュー指針!$A:$A,0)),"") -> 1次レビュー | L27: =IFERROR(INDEX(レビュー指針!$H:$H,MATCH(I27,レビュー指針!$A:$A,0)),"") -> データソースと抽出条件（手順）の記録が成果物として提出されている | P27: Stage2精査 / データソース / 自主点検QA由来 / 件数3 / 要文言整備
A28: 58 | B28: 9 | C28: =IFERROR(INDEX(自主点検項目!$B:$B,MATCH(B28,自主点検項目!$A:$A,0)),"") -> 長期請負工事案件の洗い出し | D28: 共通 | E28: =IFERROR(INDEX(提出物!$D:$D,MATCH(D28,提出物!$A:$A,0)),"") | F28: 網羅性が確認できる情報（2026年3月試算表・PKGの進行基準売上との一致）が提出されているか。 | G28: =COUNTIF('チェックポイント-問合せ・差戻し事例対応表'!$B:$B,A28) -> 3 | H28: =SUMPRODUCT(('チェックポイント-問合せ・差戻し事例対応表'!$B$2:$B$5000=A28)*('チェックポイント-問合せ・差戻し事例対応表'!$I$2:$I$5000<>"")/(COUNTIFS('チェックポイント-問合せ・差戻し事例対応表'!$B$2:$B$5000,'チェックポイント-問合せ・差戻し事例対応表'!$B$2:$B$5000,'チェックポイント-問合せ・差戻し事例対応表'!$I$2:$I$5000,'チェックポイント-問合せ・差戻し事例対応表'!$I$2:$I$5000)+('チェックポイント-問合せ・差戻し事例対応表'!$I$2:$I$5000=""))) -> 3 | I28: 39 | J28: =IFERROR(INDEX(レビュー指針!$D:$D,MATCH(I28,レビュー指針!$A:$A,0)),"") -> 成果物 | K28: =IFERROR(INDEX(レビュー指針!$E:$E,MATCH(I28,レビュー指針!$A:$A,0)),"") -> 1次レビュー | L28: =IFERROR(INDEX(レビュー指針!$H:$H,MATCH(I28,レビュー指針!$A:$A,0)),"") -> 網羅性が確認できる情報が記載又は提出されている（例：PKGの進行基準売上との一致） | P28: Stage2精査 / 網羅性 / 自主点検QA由来 / 件数2 / 要文言整備
A29: 59 | B29: 9 | C29: =IFERROR(INDEX(自主点検項目!$B:$B,MATCH(B29,自主点検項目!$A:$A,0)),"") -> 長期請負工事案件の洗い出し | D29: 共通 | E29: =IFERROR(INDEX(提出物!$D:$D,MATCH(D29,提出物!$A:$A,0)),"") | F29: 全ての取引について進行基準の適用可否に関する判断根拠が記載されているか。 | G29: =COUNTIF('チェックポイント-問合せ・差戻し事例対応表'!$B:$B,A29) -> 4 | H29: =SUMPRODUCT(('チェックポイント-問合せ・差戻し事例対応表'!$B$2:$B$5000=A29)*('チェックポイント-問合せ・差戻し事例対応表'!$I$2:$I$5000<>"")/(COUNTIFS('チェックポイント-問合せ・差戻し事例対応表'!$B$2:$B$5000,'チェックポイント-問合せ・差戻し事例対応表'!$B$2:$B$5000,'チェックポイント-問合せ・差戻し事例対応表'!$I$2:$I$5000,'チェックポイント-問合せ・差戻し事例対応表'!$I$2:$I$5000)+('チェックポイント-問合せ・差戻し事例対応表'!$I$2:$I$5000=""))) -> 4 | I29: 40 | J29: =IFERROR(INDEX(レビュー指針!$D:$D,MATCH(I29,レビュー指針!$A:$A,0)),"") -> 成果物 | K29: =IFERROR(INDEX(レビュー指針!$E:$E,MATCH(I29,レビュー指針!$A:$A,0)),"") -> 1次レビュー | L29: =IFERROR(INDEX(レビュー指針!$H:$H,MATCH(I29,レビュー指針!$A:$A,0)),"") -> 全ての取引について進行基準の適用可否に関する判断根拠が記載されている | P29: Stage2精査 / 判断根拠 / 自主点検QA由来 / 件数2 / 要文言整備
A30: 60 | B30: 10 | C30: =IFERROR(INDEX(自主点検項目!$B:$B,MATCH(B30,自主点検項目!$A:$A,0)),"") -> 実行予算の取得・確認 | D30: 35 | E30: =IFERROR(INDEX(提出物!$D:$D,MATCH(D30,提出物!$A:$A,0)),"") -> データソース・抽出条件 | F30: 成果物の作成に用いたデータソースと抽出条件（手順）の記録（画面コピー等）が提出されているか。 | G30: =COUNTIF('チェックポイント-問合せ・差戻し事例対応表'!$B:$B,A30) -> 8 | H30: =SUMPRODUCT(('チェックポイント-問合せ・差戻し事例対応表'!$B$2:$B$5000=A30)*('チェックポイント-問合せ・差戻し事例対応表'!$I$2:$I$5000<>"")/(COUNTIFS('チェックポイント-問合せ・差戻し事例対応表'!$B$2:$B$5000,'チェックポイント-問合せ・差戻し事例対応表'!$B$2:$B$5000,'チェックポイント-問合せ・差戻し事例対応表'!$I$2:$I$5000,'チェックポイント-問合せ・差戻し事例対応表'!$I$2:$I$5000)+('チェックポイント-問合せ・差戻し事例対応表'!$I$2:$I$5000=""))) -> 8 | I30: 44 | J30: =IFERROR(INDEX(レビュー指針!$D:$D,MATCH(I30,レビュー指針!$A:$A,0)),"") -> 成果物 | K30: =IFERROR(INDEX(レビュー指針!$E:$E,MATCH(I30,レビュー指針!$A:$A,0)),"") -> 1次レビュー | L30: =IFERROR(INDEX(レビュー指針!$H:$H,MATCH(I30,レビュー指針!$A:$A,0)),"") -> データソースと抽出条件（手順）の記録が成果物として提出されている | P30: Stage2精査 / 複合問合せを分割（網羅性は別CPへ） / 自主点検QA由来 / 件数5 / 要文言整備
A31: 62 | B31: 11 | C31: =IFERROR(INDEX(自主点検項目!$B:$B,MATCH(B31,自主点検項目!$A:$A,0)),"") -> 材料費の実際発生原価の確認 | D31: 共通 | E31: =IFERROR(INDEX(提出物!$D:$D,MATCH(D31,提出物!$A:$A,0)),"") | F31: 成果物の作成に用いたデータソースと抽出条件（手順）の記録（画面コピー等）が提出されているか。 | G31: =COUNTIF('チェックポイント-問合せ・差戻し事例対応表'!$B:$B,A31) -> 6 | H31: =SUMPRODUCT(('チェックポイント-問合せ・差戻し事例対応表'!$B$2:$B$5000=A31)*('チェックポイント-問合せ・差戻し事例対応表'!$I$2:$I$5000<>"")/(COUNTIFS('チェックポイント-問合せ・差戻し事例対応表'!$B$2:$B$5000,'チェックポイント-問合せ・差戻し事例対応表'!$B$2:$B$5000,'チェックポイント-問合せ・差戻し事例対応表'!$I$2:$I$5000,'チェックポイント-問合せ・差戻し事例対応表'!$I$2:$I$5000)+('チェックポイント-問合せ・差戻し事例対応表'!$I$2:$I$5000=""))) -> 6 | I31: 49 | J31: =IFERROR(INDEX(レビュー指針!$D:$D,MATCH(I31,レビュー指針!$A:$A,0)),"") -> 成果物 | K31: =IFERROR(INDEX(レビュー指針!$E:$E,MATCH(I31,レビュー指針!$A:$A,0)),"") -> 1次レビュー | L31: =IFERROR(INDEX(レビュー指針!$H:$H,MATCH(I31,レビュー指針!$A:$A,0)),"") -> データソースと抽出条件（手順）の記録が成果物として提出されている | P31: Stage2精査 / データソース / 自主点検QA由来 / 件数5 / 要文言整備
A32: 63 | B32: 11 | C32: =IFERROR(INDEX(自主点検項目!$B:$B,MATCH(B32,自主点検項目!$A:$A,0)),"") -> 材料費の実際発生原価の確認 | D32: 共通 | E32: =IFERROR(INDEX(提出物!$D:$D,MATCH(D32,提出物!$A:$A,0)),"") | F32: 購買データ・入出庫データ・原価明細を比較し整合性が確認できているか。 | G32: =COUNTIF('チェックポイント-問合せ・差戻し事例対応表'!$B:$B,A32) -> 3 | H32: =SUMPRODUCT(('チェックポイント-問合せ・差戻し事例対応表'!$B$2:$B$5000=A32)*('チェックポイント-問合せ・差戻し事例対応表'!$I$2:$I$5000<>"")/(COUNTIFS('チェックポイント-問合せ・差戻し事例対応表'!$B$2:$B$5000,'チェックポイント-問合せ・差戻し事例対応表'!$B$2:$B$5000,'チェックポイント-問合せ・差戻し事例対応表'!$I$2:$I$5000,'チェックポイント-問合せ・差戻し事例対応表'!$I$2:$I$5000)+('チェックポイント-問合せ・差戻し事例対応表'!$I$2:$I$5000=""))) -> 2 | I32: 51 | J32: =IFERROR(INDEX(レビュー指針!$D:$D,MATCH(I32,レビュー指針!$A:$A,0)),"") -> 成果物 | K32: =IFERROR(INDEX(レビュー指針!$E:$E,MATCH(I32,レビュー指針!$A:$A,0)),"") -> 1次レビュー | L32: =IFERROR(INDEX(レビュー指針!$H:$H,MATCH(I32,レビュー指針!$A:$A,0)),"") -> 購買データ、入出庫データ、原価明細を比較し整合性を確認できている | P32: Stage2精査 / 整合性 / 自主点検QA由来 / 件数2 / 要文言整備
A33: 64 | B33: 11 | C33: =IFERROR(INDEX(自主点検項目!$B:$B,MATCH(B33,自主点検項目!$A:$A,0)),"") -> 材料費の実際発生原価の確認 | D33: 共通 | E33: =IFERROR(INDEX(提出物!$D:$D,MATCH(D33,提出物!$A:$A,0)),"") | F33: 網羅性が確認できる情報（試算表との一致）が提出されているか。 | G33: =COUNTIF('チェックポイント-問合せ・差戻し事例対応表'!$B:$B,A33) -> 3 | H33: =SUMPRODUCT(('チェックポイント-問合せ・差戻し事例対応表'!$B$2:$B$5000=A33)*('チェックポイント-問合せ・差戻し事例対応表'!$I$2:$I$5000<>"")/(COUNTIFS('チェックポイント-問合せ・差戻し事例対応表'!$B$2:$B$5000,'チェックポイント-問合せ・差戻し事例対応表'!$B$2:$B$5000,'チェックポイント-問合せ・差戻し事例対応表'!$I$2:$I$5000,'チェックポイント-問合せ・差戻し事例対応表'!$I$2:$I$5000)+('チェックポイント-問合せ・差戻し事例対応表'!$I$2:$I$5000=""))) -> 3 | I33: 50 | J33: =IFERROR(INDEX(レビュー指針!$D:$D,MATCH(I33,レビュー指針!$A:$A,0)),"") -> 成果物 | K33: =IFERROR(INDEX(レビュー指針!$E:$E,MATCH(I33,レビュー指針!$A:$A,0)),"") -> 1次レビュー | L33: =IFERROR(INDEX(レビュー指針!$H:$H,MATCH(I33,レビュー指針!$A:$A,0)),"") -> 網羅性が確認できる情報が記載又は提出されている（試算表との一致を確認できる） | P33: Stage2精査 / 網羅性 / 自主点検QA由来 / 件数2 / 要文言整備
A34: 65 | B34: 12 | C34: =IFERROR(INDEX(自主点検項目!$B:$B,MATCH(B34,自主点検項目!$A:$A,0)),"") -> 進捗率の算定根拠の確認 | D34: 41 | E34: =IFERROR(INDEX(提出物!$D:$D,MATCH(D34,提出物!$A:$A,0)),"") -> データソース・抽出条件 | F34: 成果物の作成に用いたデータソースと抽出条件（手順）の記録（画面コピー等）が提出されているか。 | G34: =COUNTIF('チェックポイント-問合せ・差戻し事例対応表'!$B:$B,A34) -> 9 | H34: =SUMPRODUCT(('チェックポイント-問合せ・差戻し事例対応表'!$B$2:$B$5000=A34)*('チェックポイント-問合せ・差戻し事例対応表'!$I$2:$I$5000<>"")/(COUNTIFS('チェックポイント-問合せ・差戻し事例対応表'!$B$2:$B$5000,'チェックポイント-問合せ・差戻し事例対応表'!$B$2:$B$5000,'チェックポイント-問合せ・差戻し事例対応表'!$I$2:$I$5000,'チェックポイント-問合せ・差戻し事例対応表'!$I$2:$I$5000)+('チェックポイント-問合せ・差戻し事例対応表'!$I$2:$I$5000=""))) -> 9 | I34: 55 | J34: =IFERROR(INDEX(レビュー指針!$D:$D,MATCH(I34,レビュー指針!$A:$A,0)),"") -> 成果物 | K34: =IFERROR(INDEX(レビュー指針!$E:$E,MATCH(I34,レビュー指針!$A:$A,0)),"") -> 1次レビュー | L34: =IFERROR(INDEX(レビュー指針!$H:$H,MATCH(I34,レビュー指針!$A:$A,0)),"") -> データソースと抽出条件（手順）の記録が成果物として提出されている | P34: Stage2精査 / 複合問合せを分割（網羅性は別CPへ） / 自主点検QA由来 / 件数8 / 要文言整備
A35: 66 | B35: 13 | C35: =IFERROR(INDEX(自主点検項目!$B:$B,MATCH(B35,自主点検項目!$A:$A,0)),"") -> 経費の実際発生原価の確認 | D35: 43 | E35: =IFERROR(INDEX(提出物!$D:$D,MATCH(D35,提出物!$A:$A,0)),"") -> データソース・抽出条件 | F35: 成果物の作成に用いたデータソースと抽出条件（手順）の記録（画面コピー等）が提出されているか。 | G35: =COUNTIF('チェックポイント-問合せ・差戻し事例対応表'!$B:$B,A35) -> 6 | H35: =SUMPRODUCT(('チェックポイント-問合せ・差戻し事例対応表'!$B$2:$B$5000=A35)*('チェックポイント-問合せ・差戻し事例対応表'!$I$2:$I$5000<>"")/(COUNTIFS('チェックポイント-問合せ・差戻し事例対応表'!$B$2:$B$5000,'チェックポイント-問合せ・差戻し事例対応表'!$B$2:$B$5000,'チェックポイント-問合せ・差戻し事例対応表'!$I$2:$I$5000,'チェックポイント-問合せ・差戻し事例対応表'!$I$2:$I$5000)+('チェックポイント-問合せ・差戻し事例対応表'!$I$2:$I$5000=""))) -> 6 | I35: 62 | J35: =IFERROR(INDEX(レビュー指針!$D:$D,MATCH(I35,レビュー指針!$A:$A,0)),"") -> 成果物 | K35: =IFERROR(INDEX(レビュー指針!$E:$E,MATCH(I35,レビュー指針!$A:$A,0)),"") -> 1次レビュー | L35: =IFERROR(INDEX(レビュー指針!$H:$H,MATCH(I35,レビュー指針!$A:$A,0)),"") -> データソースと抽出条件（手順）の記録が成果物として提出されている | P35: Stage2精査 / 複合問合せを分割（網羅性は別CPへ） / 自主点検QA由来 / 件数6 / 要文言整備
A36: 67 | B36: 14 | C36: =IFERROR(INDEX(自主点検項目!$B:$B,MATCH(B36,自主点検項目!$A:$A,0)),"") -> 原価振替取引の要因説明 | D36: 46 | E36: =IFERROR(INDEX(提出物!$D:$D,MATCH(D36,提出物!$A:$A,0)),"") -> データソース・抽出基準/手順 | F36: 成果物の作成に用いたデータソースと抽出条件（手順）の記録（画面コピー等）が提出されているか。 | G36: =COUNTIF('チェックポイント-問合せ・差戻し事例対応表'!$B:$B,A36) -> 5 | H36: =SUMPRODUCT(('チェックポイント-問合せ・差戻し事例対応表'!$B$2:$B$5000=A36)*('チェックポイント-問合せ・差戻し事例対応表'!$I$2:$I$5000<>"")/(COUNTIFS('チェックポイント-問合せ・差戻し事例対応表'!$B$2:$B$5000,'チェックポイント-問合せ・差戻し事例対応表'!$B$2:$B$5000,'チェックポイント-問合せ・差戻し事例対応表'!$I$2:$I$5000,'チェックポイント-問合せ・差戻し事例対応表'!$I$2:$I$5000)+('チェックポイント-問合せ・差戻し事例対応表'!$I$2:$I$5000=""))) -> 5 | I36: 67 | J36: =IFERROR(INDEX(レビュー指針!$D:$D,MATCH(I36,レビュー指針!$A:$A,0)),"") -> 成果物 | K36: =IFERROR(INDEX(レビュー指針!$E:$E,MATCH(I36,レビュー指針!$A:$A,0)),"") -> 1次レビュー | L36: =IFERROR(INDEX(レビュー指針!$H:$H,MATCH(I36,レビュー指針!$A:$A,0)),"") -> データソースと抽出条件（手順）の記録が成果物として提出されている | P36: Stage2精査 / データソース / 自主点検QA由来 / 件数5 / 要文言整備
A37: 68 | B37: 15 | C37: =IFERROR(INDEX(自主点検項目!$B:$B,MATCH(B37,自主点検項目!$A:$A,0)),"") -> 低粗利案件の分析 | D37: 50 | E37: =IFERROR(INDEX(提出物!$D:$D,MATCH(D37,提出物!$A:$A,0)),"") -> データソース・抽出条件 | F37: 成果物の作成に用いたデータソースと抽出条件（手順）の記録（画面コピー等）が提出されているか。 | G37: =COUNTIF('チェックポイント-問合せ・差戻し事例対応表'!$B:$B,A37) -> 7 | H37: =SUMPRODUCT(('チェックポイント-問合せ・差戻し事例対応表'!$B$2:$B$5000=A37)*('チェックポイント-問合せ・差戻し事例対応表'!$I$2:$I$5000<>"")/(COUNTIFS('チェックポイント-問合せ・差戻し事例対応表'!$B$2:$B$5000,'チェックポイント-問合せ・差戻し事例対応表'!$B$2:$B$5000,'チェックポイント-問合せ・差戻し事例対応表'!$I$2:$I$5000,'チェックポイント-問合せ・差戻し事例対応表'!$I$2:$I$5000)+('チェックポイント-問合せ・差戻し事例対応表'!$I$2:$I$5000=""))) -> 7 | I37: 72 | J37: =IFERROR(INDEX(レビュー指針!$D:$D,MATCH(I37,レビュー指針!$A:$A,0)),"") -> 成果物 | K37: =IFERROR(INDEX(レビュー指針!$E:$E,MATCH(I37,レビュー指針!$A:$A,0)),"") -> 1次レビュー | L37: =IFERROR(INDEX(レビュー指針!$H:$H,MATCH(I37,レビュー指針!$A:$A,0)),"") -> データソースと抽出条件（手順）の記録が成果物として提出されている | P37: Stage2精査 / 複合問合せを分割（網羅性は別CPへ） / 自主点検QA由来 / 件数3 / 要文言整備
A38: 70 | B38: 18 | C38: =IFERROR(INDEX(自主点検項目!$B:$B,MATCH(B38,自主点検項目!$A:$A,0)),"") -> 各費用月次推移分析 | D38: 53 | E38: =IFERROR(INDEX(提出物!$D:$D,MATCH(D38,提出物!$A:$A,0)),"") -> 販管費の月次推移データ | F38: 販管費科目の月次推移表・グラフが作成され、絶対額・変化率の両面で必要箇所にコメントがあるか。 | G38: =COUNTIF('チェックポイント-問合せ・差戻し事例対応表'!$B:$B,A38) -> 27 | H38: =SUMPRODUCT(('チェックポイント-問合せ・差戻し事例対応表'!$B$2:$B$5000=A38)*('チェックポイント-問合せ・差戻し事例対応表'!$I$2:$I$5000<>"")/(COUNTIFS('チェックポイント-問合せ・差戻し事例対応表'!$B$2:$B$5000,'チェックポイント-問合せ・差戻し事例対応表'!$B$2:$B$5000,'チェックポイント-問合せ・差戻し事例対応表'!$I$2:$I$5000,'チェックポイント-問合せ・差戻し事例対応表'!$I$2:$I$5000)+('チェックポイント-問合せ・差戻し事例対応表'!$I$2:$I$5000=""))) -> 27 | I38: 81 | J38: =IFERROR(INDEX(レビュー指針!$D:$D,MATCH(I38,レビュー指針!$A:$A,0)),"") -> 成果物 | K38: =IFERROR(INDEX(レビュー指針!$E:$E,MATCH(I38,レビュー指針!$A:$A,0)),"") -> 1次レビュー | L38: =IFERROR(INDEX(レビュー指針!$H:$H,MATCH(I38,レビュー指針!$A:$A,0)),"") -> 25年4月～26年3月の科目毎の月次推移表及びグラフが作成されている | P38: Stage2精査 / 推移表作成チェック / 自主点検QA由来 / 件数11 / 要文言整備
A39: 77 | B39: 18 | C39: =IFERROR(INDEX(自主点検項目!$B:$B,MATCH(B39,自主点検項目!$A:$A,0)),"") -> 各費用月次推移分析 | D39: 54 | E39: =IFERROR(INDEX(提出物!$D:$D,MATCH(D39,提出物!$A:$A,0)),"") -> データソース・抽出条件 | F39: 成果物の作成に用いたデータソースと抽出条件（手順）の記録（画面コピー等）が提出されているか。 | G39: =COUNTIF('チェックポイント-問合せ・差戻し事例対応表'!$B:$B,A39) -> 77 | H39: =SUMPRODUCT(('チェックポイント-問合せ・差戻し事例対応表'!$B$2:$B$5000=A39)*('チェックポイント-問合せ・差戻し事例対応表'!$I$2:$I$5000<>"")/(COUNTIFS('チェックポイント-問合せ・差戻し事例対応表'!$B$2:$B$5000,'チェックポイント-問合せ・差戻し事例対応表'!$B$2:$B$5000,'チェックポイント-問合せ・差戻し事例対応表'!$I$2:$I$5000,'チェックポイント-問合せ・差戻し事例対応表'!$I$2:$I$5000)+('チェックポイント-問合せ・差戻し事例対応表'!$I$2:$I$5000=""))) -> 73 | I39: 79 | J39: =IFERROR(INDEX(レビュー指針!$D:$D,MATCH(I39,レビュー指針!$A:$A,0)),"") -> 成果物 | K39: =IFERROR(INDEX(レビュー指針!$E:$E,MATCH(I39,レビュー指針!$A:$A,0)),"") -> 1次レビュー | L39: =IFERROR(INDEX(レビュー指針!$H:$H,MATCH(I39,レビュー指針!$A:$A,0)),"") -> データソースと抽出条件（手順）の記録が成果物として提出されている | P39: Stage2精査 / 複合問合せを分割（網羅性は別CPへ） / 自主点検QA由来 / 件数65 / 要文言整備
A40: 83 | B40: 18 | C40: =IFERROR(INDEX(自主点検項目!$B:$B,MATCH(B40,自主点検項目!$A:$A,0)),"") -> 各費用月次推移分析 | D40: 55 | E40: =IFERROR(INDEX(提出物!$D:$D,MATCH(D40,提出物!$A:$A,0)),"") -> 著しい増加の根拠資料 | F40: 網羅性が確認できる情報が記載又は提出されている | G40: =COUNTIF('チェックポイント-問合せ・差戻し事例対応表'!$B:$B,A40) -> 8 | H40: =SUMPRODUCT(('チェックポイント-問合せ・差戻し事例対応表'!$B$2:$B$5000=A40)*('チェックポイント-問合せ・差戻し事例対応表'!$I$2:$I$5000<>"")/(COUNTIFS('チェックポイント-問合せ・差戻し事例対応表'!$B$2:$B$5000,'チェックポイント-問合せ・差戻し事例対応表'!$B$2:$B$5000,'チェックポイント-問合せ・差戻し事例対応表'!$I$2:$I$5000,'チェックポイント-問合せ・差戻し事例対応表'!$I$2:$I$5000)+('チェックポイント-問合せ・差戻し事例対応表'!$I$2:$I$5000=""))) -> 8 | I40: 80 | J40: =IFERROR(INDEX(レビュー指針!$D:$D,MATCH(I40,レビュー指針!$A:$A,0)),"") -> 成果物 | K40: =IFERROR(INDEX(レビュー指針!$E:$E,MATCH(I40,レビュー指針!$A:$A,0)),"") -> 1次レビュー | L40: =IFERROR(INDEX(レビュー指針!$H:$H,MATCH(I40,レビュー指針!$A:$A,0)),"") -> 網羅性が確認できる情報が記載又は提出されている | P40: Stage2精査(裾野・要確認) / 自主点検QA由来 / 件数2 / 要文言整備
A41: 87 | B41: 18 | C41: =IFERROR(INDEX(自主点検項目!$B:$B,MATCH(B41,自主点検項目!$A:$A,0)),"") -> 各費用月次推移分析 | D41: 共通 | E41: =IFERROR(INDEX(提出物!$D:$D,MATCH(D41,提出物!$A:$A,0)),"") | F41: 網羅性が確認できる情報が記載又は提出されている | G41: =COUNTIF('チェックポイント-問合せ・差戻し事例対応表'!$B:$B,A41) -> 6 | H41: =SUMPRODUCT(('チェックポイント-問合せ・差戻し事例対応表'!$B$2:$B$5000=A41)*('チェックポイント-問合せ・差戻し事例対応表'!$I$2:$I$5000<>"")/(COUNTIFS('チェックポイント-問合せ・差戻し事例対応表'!$B$2:$B$5000,'チェックポイント-問合せ・差戻し事例対応表'!$B$2:$B$5000,'チェックポイント-問合せ・差戻し事例対応表'!$I$2:$I$5000,'チェックポイント-問合せ・差戻し事例対応表'!$I$2:$I$5000)+('チェックポイント-問合せ・差戻し事例対応表'!$I$2:$I$5000=""))) -> 6 | I41: 80 | J41: =IFERROR(INDEX(レビュー指針!$D:$D,MATCH(I41,レビュー指針!$A:$A,0)),"") -> 成果物 | K41: =IFERROR(INDEX(レビュー指針!$E:$E,MATCH(I41,レビュー指針!$A:$A,0)),"") -> 1次レビュー | L41: =IFERROR(INDEX(レビュー指針!$H:$H,MATCH(I41,レビュー指針!$A:$A,0)),"") -> 網羅性が確認できる情報が記載又は提出されている | P41: Stage2精査(裾野・要確認) / 自主点検QA由来 / 件数4 / 要文言整備
A42: 89 | B42: 19 | C42: =IFERROR(INDEX(自主点検項目!$B:$B,MATCH(B42,自主点検項目!$A:$A,0)),"") -> 翌期取引の確認 | D42: 56 | E42: =IFERROR(INDEX(提出物!$D:$D,MATCH(D42,提出物!$A:$A,0)),"") -> 翌期4月計上仕訳データ一覧 | F42: 仕訳明細データの摘要欄等から、26年3月以前に費用計上すべき費用の有無を確認している | G42: =COUNTIF('チェックポイント-問合せ・差戻し事例対応表'!$B:$B,A42) -> 2 | H42: =SUMPRODUCT(('チェックポイント-問合せ・差戻し事例対応表'!$B$2:$B$5000=A42)*('チェックポイント-問合せ・差戻し事例対応表'!$I$2:$I$5000<>"")/(COUNTIFS('チェックポイント-問合せ・差戻し事例対応表'!$B$2:$B$5000,'チェックポイント-問合せ・差戻し事例対応表'!$B$2:$B$5000,'チェックポイント-問合せ・差戻し事例対応表'!$I$2:$I$5000,'チェックポイント-問合せ・差戻し事例対応表'!$I$2:$I$5000)+('チェックポイント-問合せ・差戻し事例対応表'!$I$2:$I$5000=""))) -> 2 | I42: 91 | J42: =IFERROR(INDEX(レビュー指針!$D:$D,MATCH(I42,レビュー指針!$A:$A,0)),"") -> 成果物 | K42: =IFERROR(INDEX(レビュー指針!$E:$E,MATCH(I42,レビュー指針!$A:$A,0)),"") -> 1次レビュー | L42: =IFERROR(INDEX(レビュー指針!$H:$H,MATCH(I42,レビュー指針!$A:$A,0)),"") -> 仕訳明細データの摘要欄等から、26年3月以前に費用計上すべき費用の有無を確認している | P42: Stage2精査(裾野・要確認) / 自主点検QA由来 / 件数2 / 要文言整備
A43: 90 | B43: 19 | C43: =IFERROR(INDEX(自主点検項目!$B:$B,MATCH(B43,自主点検項目!$A:$A,0)),"") -> 翌期取引の確認 | D43: 57 | E43: =IFERROR(INDEX(提出物!$D:$D,MATCH(D43,提出物!$A:$A,0)),"") -> データソース・抽出条件 | F43: 成果物の作成に用いたデータソースと抽出条件（手順）の記録（画面コピー等）が提出されているか。 | G43: =COUNTIF('チェックポイント-問合せ・差戻し事例対応表'!$B:$B,A43) -> 41 | H43: =SUMPRODUCT(('チェックポイント-問合せ・差戻し事例対応表'!$B$2:$B$5000=A43)*('チェックポイント-問合せ・差戻し事例対応表'!$I$2:$I$5000<>"")/(COUNTIFS('チェックポイント-問合せ・差戻し事例対応表'!$B$2:$B$5000,'チェックポイント-問合せ・差戻し事例対応表'!$B$2:$B$5000,'チェックポイント-問合せ・差戻し事例対応表'!$I$2:$I$5000,'チェックポイント-問合せ・差戻し事例対応表'!$I$2:$I$5000)+('チェックポイント-問合せ・差戻し事例対応表'!$I$2:$I$5000=""))) -> 39 | I43: 89 | J43: =IFERROR(INDEX(レビュー指針!$D:$D,MATCH(I43,レビュー指針!$A:$A,0)),"") -> 成果物 | K43: =IFERROR(INDEX(レビュー指針!$E:$E,MATCH(I43,レビュー指針!$A:$A,0)),"") -> 1次レビュー | L43: =IFERROR(INDEX(レビュー指針!$H:$H,MATCH(I43,レビュー指針!$A:$A,0)),"") -> データソースと抽出条件（手順）の記録が成果物として提出されている | P43: Stage2精査 / 複合問合せを分割（網羅性は別CPへ） / 自主点検QA由来 / 件数24 / 要文言整備
A44: 91 | B44: 19 | C44: =IFERROR(INDEX(自主点検項目!$B:$B,MATCH(B44,自主点検項目!$A:$A,0)),"") -> 翌期取引の確認 | D44: 57 | E44: =IFERROR(INDEX(提出物!$D:$D,MATCH(D44,提出物!$A:$A,0)),"") -> データソース・抽出条件 | F44: 費用計上に関する成果物の指摘事項（仕訳・計上時期等）が適切に修正・説明されているか。 | G44: =COUNTIF('チェックポイント-問合せ・差戻し事例対応表'!$B:$B,A44) -> 8 | H44: =SUMPRODUCT(('チェックポイント-問合せ・差戻し事例対応表'!$B$2:$B$5000=A44)*('チェックポイント-問合せ・差戻し事例対応表'!$I$2:$I$5000<>"")/(COUNTIFS('チェックポイント-問合せ・差戻し事例対応表'!$B$2:$B$5000,'チェックポイント-問合せ・差戻し事例対応表'!$B$2:$B$5000,'チェックポイント-問合せ・差戻し事例対応表'!$I$2:$I$5000,'チェックポイント-問合せ・差戻し事例対応表'!$I$2:$I$5000)+('チェックポイント-問合せ・差戻し事例対応表'!$I$2:$I$5000=""))) -> 8 | I44: 92 | J44: =IFERROR(INDEX(レビュー指針!$D:$D,MATCH(I44,レビュー指針!$A:$A,0)),"") -> 分析の妥当性 | K44: =IFERROR(INDEX(レビュー指針!$E:$E,MATCH(I44,レビュー指針!$A:$A,0)),"") -> 2次レビュー | L44: =IFERROR(INDEX(レビュー指針!$H:$H,MATCH(I44,レビュー指針!$A:$A,0)),"") -> 26年3月以前に費用計上すべきリスクのある費用について会計処理の顛末が適切に記載されている | P44: Stage2精査 / 2次指摘の整形 / 自主点検QA由来 / 件数8 / 要文言整備
A45: 97 | B45: 19 | C45: =IFERROR(INDEX(自主点検項目!$B:$B,MATCH(B45,自主点検項目!$A:$A,0)),"") -> 翌期取引の確認 | D45: 58 | E45: =IFERROR(INDEX(提出物!$D:$D,MATCH(D45,提出物!$A:$A,0)),"") -> 3月分として計上すべき費用の根拠資料 | F45: 網羅性が確認できる情報が記載又は提出されている | G45: =COUNTIF('チェックポイント-問合せ・差戻し事例対応表'!$B:$B,A45) -> 5 | H45: =SUMPRODUCT(('チェックポイント-問合せ・差戻し事例対応表'!$B$2:$B$5000=A45)*('チェックポイント-問合せ・差戻し事例対応表'!$I$2:$I$5000<>"")/(COUNTIFS('チェックポイント-問合せ・差戻し事例対応表'!$B$2:$B$5000,'チェックポイント-問合せ・差戻し事例対応表'!$B$2:$B$5000,'チェックポイント-問合せ・差戻し事例対応表'!$I$2:$I$5000,'チェックポイント-問合せ・差戻し事例対応表'!$I$2:$I$5000)+('チェックポイント-問合せ・差戻し事例対応表'!$I$2:$I$5000=""))) -> 5 | I45: 90 | J45: =IFERROR(INDEX(レビュー指針!$D:$D,MATCH(I45,レビュー指針!$A:$A,0)),"") -> 成果物 | K45: =IFERROR(INDEX(レビュー指針!$E:$E,MATCH(I45,レビュー指針!$A:$A,0)),"") -> 1次レビュー | L45: =IFERROR(INDEX(レビュー指針!$H:$H,MATCH(I45,レビュー指針!$A:$A,0)),"") -> 網羅性が確認できる情報が記載又は提出されている | P45: Stage2精査(裾野・要確認) / 自主点検QA由来 / 件数3 / 要文言整備
A46: 98 | B46: 19 | C46: =IFERROR(INDEX(自主点検項目!$B:$B,MATCH(B46,自主点検項目!$A:$A,0)),"") -> 翌期取引の確認 | D46: 58 | E46: =IFERROR(INDEX(提出物!$D:$D,MATCH(D46,提出物!$A:$A,0)),"") -> 3月分として計上すべき費用の根拠資料 | F46: 仕訳明細データの摘要欄等から、26年3月以前に費用計上すべき費用の有無を確認している | G46: =COUNTIF('チェックポイント-問合せ・差戻し事例対応表'!$B:$B,A46) -> 13 | H46: =SUMPRODUCT(('チェックポイント-問合せ・差戻し事例対応表'!$B$2:$B$5000=A46)*('チェックポイント-問合せ・差戻し事例対応表'!$I$2:$I$5000<>"")/(COUNTIFS('チェックポイント-問合せ・差戻し事例対応表'!$B$2:$B$5000,'チェックポイント-問合せ・差戻し事例対応表'!$B$2:$B$5000,'チェックポイント-問合せ・差戻し事例対応表'!$I$2:$I$5000,'チェックポイント-問合せ・差戻し事例対応表'!$I$2:$I$5000)+('チェックポイント-問合せ・差戻し事例対応表'!$I$2:$I$5000=""))) -> 12 | I46: 91 | J46: =IFERROR(INDEX(レビュー指針!$D:$D,MATCH(I46,レビュー指針!$A:$A,0)),"") -> 成果物 | K46: =IFERROR(INDEX(レビュー指針!$E:$E,MATCH(I46,レビュー指針!$A:$A,0)),"") -> 1次レビュー | L46: =IFERROR(INDEX(レビュー指針!$H:$H,MATCH(I46,レビュー指針!$A:$A,0)),"") -> 仕訳明細データの摘要欄等から、26年3月以前に費用計上すべき費用の有無を確認している | P46: Stage2精査(裾野・要確認) / 自主点検QA由来 / 件数3 / 要文言整備
A47: 101 | B47: 19 | C47: =IFERROR(INDEX(自主点検項目!$B:$B,MATCH(B47,自主点検項目!$A:$A,0)),"") -> 翌期取引の確認 | D47: 共通 | E47: =IFERROR(INDEX(提出物!$D:$D,MATCH(D47,提出物!$A:$A,0)),"") | F47: 仕訳明細データ等から2026年3月以前に費用計上すべき費用の有無が確認されているか（成果物が説明資料の様式どおりか）。 | G47: =COUNTIF('チェックポイント-問合せ・差戻し事例対応表'!$B:$B,A47) -> 19 | H47: =SUMPRODUCT(('チェックポイント-問合せ・差戻し事例対応表'!$B$2:$B$5000=A47)*('チェックポイント-問合せ・差戻し事例対応表'!$I$2:$I$5000<>"")/(COUNTIFS('チェックポイント-問合せ・差戻し事例対応表'!$B$2:$B$5000,'チェックポイント-問合せ・差戻し事例対応表'!$B$2:$B$5000,'チェックポイント-問合せ・差戻し事例対応表'!$I$2:$I$5000,'チェックポイント-問合せ・差戻し事例対応表'!$I$2:$I$5000)+('チェックポイント-問合せ・差戻し事例対応表'!$I$2:$I$5000=""))) -> 13 | I47: 91 | J47: =IFERROR(INDEX(レビュー指針!$D:$D,MATCH(I47,レビュー指針!$A:$A,0)),"") -> 成果物 | K47: =IFERROR(INDEX(レビュー指針!$E:$E,MATCH(I47,レビュー指針!$A:$A,0)),"") -> 1次レビュー | L47: =IFERROR(INDEX(レビュー指針!$H:$H,MATCH(I47,レビュー指針!$A:$A,0)),"") -> 仕訳明細データの摘要欄等から、26年3月以前に費用計上すべき費用の有無を確認している | P47: Stage2精査 / 費用計上時期チェック / 自主点検QA由来 / 件数10 / 要文言整備
A48: 102 | B48: 19 | C48: =IFERROR(INDEX(自主点検項目!$B:$B,MATCH(B48,自主点検項目!$A:$A,0)),"") -> 翌期取引の確認 | D48: 共通 | E48: =IFERROR(INDEX(提出物!$D:$D,MATCH(D48,提出物!$A:$A,0)),"") | F48: データソースと抽出条件（手順）の記録が成果物として提出されている | G48: =COUNTIF('チェックポイント-問合せ・差戻し事例対応表'!$B:$B,A48) -> 3 | H48: =SUMPRODUCT(('チェックポイント-問合せ・差戻し事例対応表'!$B$2:$B$5000=A48)*('チェックポイント-問合せ・差戻し事例対応表'!$I$2:$I$5000<>"")/(COUNTIFS('チェックポイント-問合せ・差戻し事例対応表'!$B$2:$B$5000,'チェックポイント-問合せ・差戻し事例対応表'!$B$2:$B$5000,'チェックポイント-問合せ・差戻し事例対応表'!$I$2:$I$5000,'チェックポイント-問合せ・差戻し事例対応表'!$I$2:$I$5000)+('チェックポイント-問合せ・差戻し事例対応表'!$I$2:$I$5000=""))) -> 3 | I48: 89 | J48: =IFERROR(INDEX(レビュー指針!$D:$D,MATCH(I48,レビュー指針!$A:$A,0)),"") -> 成果物 | K48: =IFERROR(INDEX(レビュー指針!$E:$E,MATCH(I48,レビュー指針!$A:$A,0)),"") -> 1次レビュー | L48: =IFERROR(INDEX(レビュー指針!$H:$H,MATCH(I48,レビュー指針!$A:$A,0)),"") -> データソースと抽出条件（手順）の記録が成果物として提出されている | P48: Stage2精査(裾野・要確認) / 自主点検QA由来 / 件数3 / 要文言整備
A49: 103 | B49: 19 | C49: =IFERROR(INDEX(自主点検項目!$B:$B,MATCH(B49,自主点検項目!$A:$A,0)),"") -> 翌期取引の確認 | D49: 共通 | E49: =IFERROR(INDEX(提出物!$D:$D,MATCH(D49,提出物!$A:$A,0)),"") | F49: 網羅性が確認できる情報が記載又は提出されている | G49: =COUNTIF('チェックポイント-問合せ・差戻し事例対応表'!$B:$B,A49) -> 4 | H49: =SUMPRODUCT(('チェックポイント-問合せ・差戻し事例対応表'!$B$2:$B$5000=A49)*('チェックポイント-問合せ・差戻し事例対応表'!$I$2:$I$5000<>"")/(COUNTIFS('チェックポイント-問合せ・差戻し事例対応表'!$B$2:$B$5000,'チェックポイント-問合せ・差戻し事例対応表'!$B$2:$B$5000,'チェックポイント-問合せ・差戻し事例対応表'!$I$2:$I$5000,'チェックポイント-問合せ・差戻し事例対応表'!$I$2:$I$5000)+('チェックポイント-問合せ・差戻し事例対応表'!$I$2:$I$5000=""))) -> 3 | I49: 90 | J49: =IFERROR(INDEX(レビュー指針!$D:$D,MATCH(I49,レビュー指針!$A:$A,0)),"") -> 成果物 | K49: =IFERROR(INDEX(レビュー指針!$E:$E,MATCH(I49,レビュー指針!$A:$A,0)),"") -> 1次レビュー | L49: =IFERROR(INDEX(レビュー指針!$H:$H,MATCH(I49,レビュー指針!$A:$A,0)),"") -> 網羅性が確認できる情報が記載又は提出されている | P49: Stage2精査(裾野・要確認) / 自主点検QA由来 / 件数2 / 要文言整備
A50: 107 | B50: 20 | C50: =IFERROR(INDEX(自主点検項目!$B:$B,MATCH(B50,自主点検項目!$A:$A,0)),"") -> 非経常的取引の識別と説明 | D50: 59 | E50: =IFERROR(INDEX(提出物!$D:$D,MATCH(D50,提出物!$A:$A,0)),"") -> 管理部門が各部署から情報収集したことが分かる資料 | F50: 「該当なし」回答の場合、管理部門が各部署から情報収集したことが分かる証憑（メール・アンケート等）が提出されているか。 | G50: =COUNTIF('チェックポイント-問合せ・差戻し事例対応表'!$B:$B,A50) -> 29 | H50: =SUMPRODUCT(('チェックポイント-問合せ・差戻し事例対応表'!$B$2:$B$5000=A50)*('チェックポイント-問合せ・差戻し事例対応表'!$I$2:$I$5000<>"")/(COUNTIFS('チェックポイント-問合せ・差戻し事例対応表'!$B$2:$B$5000,'チェックポイント-問合せ・差戻し事例対応表'!$B$2:$B$5000,'チェックポイント-問合せ・差戻し事例対応表'!$I$2:$I$5000,'チェックポイント-問合せ・差戻し事例対応表'!$I$2:$I$5000)+('チェックポイント-問合せ・差戻し事例対応表'!$I$2:$I$5000=""))) -> 29 | I50: 94 | J50: =IFERROR(INDEX(レビュー指針!$D:$D,MATCH(I50,レビュー指針!$A:$A,0)),"") -> 成果物 | K50: =IFERROR(INDEX(レビュー指針!$E:$E,MATCH(I50,レビュー指針!$A:$A,0)),"") -> 1次レビュー | L50: =IFERROR(INDEX(レビュー指針!$H:$H,MATCH(I50,レビュー指針!$A:$A,0)),"") -> 管理部門により非経常的な取引について各部署から情報を収集している | P50: Stage2精査 / 情報収集の証憑 / 自主点検QA由来 / 件数9 / 要文言整備
A51: 113 | B51: 20 | C51: =IFERROR(INDEX(自主点検項目!$B:$B,MATCH(B51,自主点検項目!$A:$A,0)),"") -> 非経常的取引の識別と説明 | D51: 60 | E51: =IFERROR(INDEX(提出物!$D:$D,MATCH(D51,提出物!$A:$A,0)),"") -> 収集情報を基に会計処理を検討したことが分かる資料 | F51: 収集した情報を基に、管理部門が会計処理を検討している | G51: =COUNTIF('チェックポイント-問合せ・差戻し事例対応表'!$B:$B,A51) -> 4 | H51: =SUMPRODUCT(('チェックポイント-問合せ・差戻し事例対応表'!$B$2:$B$5000=A51)*('チェックポイント-問合せ・差戻し事例対応表'!$I$2:$I$5000<>"")/(COUNTIFS('チェックポイント-問合せ・差戻し事例対応表'!$B$2:$B$5000,'チェックポイント-問合せ・差戻し事例対応表'!$B$2:$B$5000,'チェックポイント-問合せ・差戻し事例対応表'!$I$2:$I$5000,'チェックポイント-問合せ・差戻し事例対応表'!$I$2:$I$5000)+('チェックポイント-問合せ・差戻し事例対応表'!$I$2:$I$5000=""))) -> 4 | I51: 95 | J51: =IFERROR(INDEX(レビュー指針!$D:$D,MATCH(I51,レビュー指針!$A:$A,0)),"") -> 成果物 | K51: =IFERROR(INDEX(レビュー指針!$E:$E,MATCH(I51,レビュー指針!$A:$A,0)),"") -> 1次レビュー | L51: =IFERROR(INDEX(レビュー指針!$H:$H,MATCH(I51,レビュー指針!$A:$A,0)),"") -> 収集した情報を基に、管理部門が会計処理を検討している | P51: Stage2精査(裾野・要確認) / 自主点検QA由来 / 件数2 / 要文言整備
A52: 115 | B52: 20 | C52: =IFERROR(INDEX(自主点検項目!$B:$B,MATCH(B52,自主点検項目!$A:$A,0)),"") -> 非経常的取引の識別と説明 | D52: 共通 | E52: =IFERROR(INDEX(提出物!$D:$D,MATCH(D52,提出物!$A:$A,0)),"") | F52: 管理部門により非経常的な取引について各部署から情報を収集している | G52: =COUNTIF('チェックポイント-問合せ・差戻し事例対応表'!$B:$B,A52) -> 2 | H52: =SUMPRODUCT(('チェックポイント-問合せ・差戻し事例対応表'!$B$2:$B$5000=A52)*('チェックポイント-問合せ・差戻し事例対応表'!$I$2:$I$5000<>"")/(COUNTIFS('チェックポイント-問合せ・差戻し事例対応表'!$B$2:$B$5000,'チェックポイント-問合せ・差戻し事例対応表'!$B$2:$B$5000,'チェックポイント-問合せ・差戻し事例対応表'!$I$2:$I$5000,'チェックポイント-問合せ・差戻し事例対応表'!$I$2:$I$5000)+('チェックポイント-問合せ・差戻し事例対応表'!$I$2:$I$5000=""))) -> 2 | I52: 94 | J52: =IFERROR(INDEX(レビュー指針!$D:$D,MATCH(I52,レビュー指針!$A:$A,0)),"") -> 成果物 | K52: =IFERROR(INDEX(レビュー指針!$E:$E,MATCH(I52,レビュー指針!$A:$A,0)),"") -> 1次レビュー | L52: =IFERROR(INDEX(レビュー指針!$H:$H,MATCH(I52,レビュー指針!$A:$A,0)),"") -> 管理部門により非経常的な取引について各部署から情報を収集している | P52: Stage2精査(裾野・要確認) / 自主点検QA由来 / 件数2 / 要文言整備
A53: 116 | B53: 21 | C53: =IFERROR(INDEX(自主点検項目!$B:$B,MATCH(B53,自主点検項目!$A:$A,0)),"") -> 見積計上費用：計上根拠 | D53: 61 | E53: =IFERROR(INDEX(提出物!$D:$D,MATCH(D53,提出物!$A:$A,0)),"") -> 当期3月の見積計上費用リスト | F53: 網羅性が確認できる情報が記載又は提出されている | G53: =COUNTIF('チェックポイント-問合せ・差戻し事例対応表'!$B:$B,A53) -> 9 | H53: =SUMPRODUCT(('チェックポイント-問合せ・差戻し事例対応表'!$B$2:$B$5000=A53)*('チェックポイント-問合せ・差戻し事例対応表'!$I$2:$I$5000<>"")/(COUNTIFS('チェックポイント-問合せ・差戻し事例対応表'!$B$2:$B$5000,'チェックポイント-問合せ・差戻し事例対応表'!$B$2:$B$5000,'チェックポイント-問合せ・差戻し事例対応表'!$I$2:$I$5000,'チェックポイント-問合せ・差戻し事例対応表'!$I$2:$I$5000)+('チェックポイント-問合せ・差戻し事例対応表'!$I$2:$I$5000=""))) -> 9 | I53: 98 | J53: =IFERROR(INDEX(レビュー指針!$D:$D,MATCH(I53,レビュー指針!$A:$A,0)),"") -> 成果物 | K53: =IFERROR(INDEX(レビュー指針!$E:$E,MATCH(I53,レビュー指針!$A:$A,0)),"") -> 1次レビュー | L53: =IFERROR(INDEX(レビュー指針!$H:$H,MATCH(I53,レビュー指針!$A:$A,0)),"") -> 網羅性が確認できる情報が記載又は提出されている | P53: Stage2精査(裾野・要確認) / 自主点検QA由来 / 件数3 / 要文言整備
A54: 120 | B54: 21 | C54: =IFERROR(INDEX(自主点検項目!$B:$B,MATCH(B54,自主点検項目!$A:$A,0)),"") -> 見積計上費用：計上根拠 | D54: 61 | E54: =IFERROR(INDEX(提出物!$D:$D,MATCH(D54,提出物!$A:$A,0)),"") -> 当期3月の見積計上費用リスト | F54: 見積計上の根拠が十分に示されている | G54: =COUNTIF('チェックポイント-問合せ・差戻し事例対応表'!$B:$B,A54) -> 19 | H54: =SUMPRODUCT(('チェックポイント-問合せ・差戻し事例対応表'!$B$2:$B$5000=A54)*('チェックポイント-問合せ・差戻し事例対応表'!$I$2:$I$5000<>"")/(COUNTIFS('チェックポイント-問合せ・差戻し事例対応表'!$B$2:$B$5000,'チェックポイント-問合せ・差戻し事例対応表'!$B$2:$B$5000,'チェックポイント-問合せ・差戻し事例対応表'!$I$2:$I$5000,'チェックポイント-問合せ・差戻し事例対応表'!$I$2:$I$5000)+('チェックポイント-問合せ・差戻し事例対応表'!$I$2:$I$5000=""))) -> 16 | I54: 99 | J54: =IFERROR(INDEX(レビュー指針!$D:$D,MATCH(I54,レビュー指針!$A:$A,0)),"") -> 会計処理の妥当性 | K54: =IFERROR(INDEX(レビュー指針!$E:$E,MATCH(I54,レビュー指針!$A:$A,0)),"") -> 2次レビュー | L54: =IFERROR(INDEX(レビュー指針!$H:$H,MATCH(I54,レビュー指針!$A:$A,0)),"") -> 見積計上の根拠が十分に示されている | P54: Stage2精査(裾野・要確認) / 自主点検QA由来 / 件数2 / 要文言整備
A55: 121 | B55: 21 | C55: =IFERROR(INDEX(自主点検項目!$B:$B,MATCH(B55,自主点検項目!$A:$A,0)),"") -> 見積計上費用：計上根拠 | D55: 63 | E55: =IFERROR(INDEX(提出物!$D:$D,MATCH(D55,提出物!$A:$A,0)),"") -> データソース・網羅性の確認 | F55: 該当データが無い場合、その確認方法（データソースと抽出条件の記録）が提出されているか。 | G55: =COUNTIF('チェックポイント-問合せ・差戻し事例対応表'!$B:$B,A55) -> 39 | H55: =SUMPRODUCT(('チェックポイント-問合せ・差戻し事例対応表'!$B$2:$B$5000=A55)*('チェックポイント-問合せ・差戻し事例対応表'!$I$2:$I$5000<>"")/(COUNTIFS('チェックポイント-問合せ・差戻し事例対応表'!$B$2:$B$5000,'チェックポイント-問合せ・差戻し事例対応表'!$B$2:$B$5000,'チェックポイント-問合せ・差戻し事例対応表'!$I$2:$I$5000,'チェックポイント-問合せ・差戻し事例対応表'!$I$2:$I$5000)+('チェックポイント-問合せ・差戻し事例対応表'!$I$2:$I$5000=""))) -> 38 | I55: 97 | J55: =IFERROR(INDEX(レビュー指針!$D:$D,MATCH(I55,レビュー指針!$A:$A,0)),"") -> 成果物 | K55: =IFERROR(INDEX(レビュー指針!$E:$E,MATCH(I55,レビュー指針!$A:$A,0)),"") -> 1次レビュー | L55: =IFERROR(INDEX(レビュー指針!$H:$H,MATCH(I55,レビュー指針!$A:$A,0)),"") -> データソースと抽出条件（手順）の記録が成果物として提出されている | P55: Stage2精査 / データソースチェックへ整形 / 自主点検QA由来 / 件数11 / 要文言整備
A56: 123 | B56: 21 | C56: =IFERROR(INDEX(自主点検項目!$B:$B,MATCH(B56,自主点検項目!$A:$A,0)),"") -> 見積計上費用：計上根拠 | D56: 63 | E56: =IFERROR(INDEX(提出物!$D:$D,MATCH(D56,提出物!$A:$A,0)),"") -> データソース・網羅性の確認 | F56: 該当が無いことの確認方法（網羅性が確認できる情報）が提出されているか。 | G56: =COUNTIF('チェックポイント-問合せ・差戻し事例対応表'!$B:$B,A56) -> 11 | H56: =SUMPRODUCT(('チェックポイント-問合せ・差戻し事例対応表'!$B$2:$B$5000=A56)*('チェックポイント-問合せ・差戻し事例対応表'!$I$2:$I$5000<>"")/(COUNTIFS('チェックポイント-問合せ・差戻し事例対応表'!$B$2:$B$5000,'チェックポイント-問合せ・差戻し事例対応表'!$B$2:$B$5000,'チェックポイント-問合せ・差戻し事例対応表'!$I$2:$I$5000,'チェックポイント-問合せ・差戻し事例対応表'!$I$2:$I$5000)+('チェックポイント-問合せ・差戻し事例対応表'!$I$2:$I$5000=""))) -> 11 | I56: 98 | J56: =IFERROR(INDEX(レビュー指針!$D:$D,MATCH(I56,レビュー指針!$A:$A,0)),"") -> 成果物 | K56: =IFERROR(INDEX(レビュー指針!$E:$E,MATCH(I56,レビュー指針!$A:$A,0)),"") -> 1次レビュー | L56: =IFERROR(INDEX(レビュー指針!$H:$H,MATCH(I56,レビュー指針!$A:$A,0)),"") -> 網羅性が確認できる情報が記載又は提出されている | P56: Stage2精査 / 網羅性チェックへ整形 / 自主点検QA由来 / 件数8 / 要文言整備
A57: 127 | B57: 21 | C57: =IFERROR(INDEX(自主点検項目!$B:$B,MATCH(B57,自主点検項目!$A:$A,0)),"") -> 見積計上費用：計上根拠 | D57: 共通 | E57: =IFERROR(INDEX(提出物!$D:$D,MATCH(D57,提出物!$A:$A,0)),"") | F57: 網羅性が確認できる情報が記載又は提出されている | G57: =COUNTIF('チェックポイント-問合せ・差戻し事例対応表'!$B:$B,A57) -> 11 | H57: =SUMPRODUCT(('チェックポイント-問合せ・差戻し事例対応表'!$B$2:$B$5000=A57)*('チェックポイント-問合せ・差戻し事例対応表'!$I$2:$I$5000<>"")/(COUNTIFS('チェックポイント-問合せ・差戻し事例対応表'!$B$2:$B$5000,'チェックポイント-問合せ・差戻し事例対応表'!$B$2:$B$5000,'チェックポイント-問合せ・差戻し事例対応表'!$I$2:$I$5000,'チェックポイント-問合せ・差戻し事例対応表'!$I$2:$I$5000)+('チェックポイント-問合せ・差戻し事例対応表'!$I$2:$I$5000=""))) -> 11 | I57: 98 | J57: =IFERROR(INDEX(レビュー指針!$D:$D,MATCH(I57,レビュー指針!$A:$A,0)),"") -> 成果物 | K57: =IFERROR(INDEX(レビュー指針!$E:$E,MATCH(I57,レビュー指針!$A:$A,0)),"") -> 1次レビュー | L57: =IFERROR(INDEX(レビュー指針!$H:$H,MATCH(I57,レビュー指針!$A:$A,0)),"") -> 網羅性が確認できる情報が記載又は提出されている | P57: Stage2精査(裾野・要確認) / 自主点検QA由来 / 件数4 / 要文言整備
A58: 130 | B58: 22 | C58: =IFERROR(INDEX(自主点検項目!$B:$B,MATCH(B58,自主点検項目!$A:$A,0)),"") -> 固定資産除却損の計上確認 | D58: 64 | E58: =IFERROR(INDEX(提出物!$D:$D,MATCH(D58,提出物!$A:$A,0)),"") -> 総勘定元帳から抽出した当期の除却取引 | F58: 除却取引全てについて根拠資料(仕訳伝票だけでなく、例えば、除却申請書や職務権限決裁報告書)が提出されている | G58: =COUNTIF('チェックポイント-問合せ・差戻し事例対応表'!$B:$B,A58) -> 4 | H58: =SUMPRODUCT(('チェックポイント-問合せ・差戻し事例対応表'!$B$2:$B$5000=A58)*('チェックポイント-問合せ・差戻し事例対応表'!$I$2:$I$5000<>"")/(COUNTIFS('チェックポイント-問合せ・差戻し事例対応表'!$B$2:$B$5000,'チェックポイント-問合せ・差戻し事例対応表'!$B$2:$B$5000,'チェックポイント-問合せ・差戻し事例対応表'!$I$2:$I$5000,'チェックポイント-問合せ・差戻し事例対応表'!$I$2:$I$5000)+('チェックポイント-問合せ・差戻し事例対応表'!$I$2:$I$5000=""))) -> 3 | I58: 102 | J58: =IFERROR(INDEX(レビュー指針!$D:$D,MATCH(I58,レビュー指針!$A:$A,0)),"") -> 成果物 | K58: =IFERROR(INDEX(レビュー指針!$E:$E,MATCH(I58,レビュー指針!$A:$A,0)),"") -> 1次レビュー | L58: =IFERROR(INDEX(レビュー指針!$H:$H,MATCH(I58,レビュー指針!$A:$A,0)),"") -> 除却取引全てについて根拠資料(仕訳伝票だけでなく、例えば、除却申請書や職務権限決裁報告書)が提出されている | P58: Stage2精査(裾野・要確認) / 自主点検QA由来 / 件数2 / 要文言整備
A59: 132 | B59: 22 | C59: =IFERROR(INDEX(自主点検項目!$B:$B,MATCH(B59,自主点検項目!$A:$A,0)),"") -> 固定資産除却損の計上確認 | D59: 64 | E59: =IFERROR(INDEX(提出物!$D:$D,MATCH(D59,提出物!$A:$A,0)),"") -> 総勘定元帳から抽出した当期の除却取引 | F59: 網羅性が確認できる情報が記載又は提出されている | G59: =COUNTIF('チェックポイント-問合せ・差戻し事例対応表'!$B:$B,A59) -> 2 | H59: =SUMPRODUCT(('チェックポイント-問合せ・差戻し事例対応表'!$B$2:$B$5000=A59)*('チェックポイント-問合せ・差戻し事例対応表'!$I$2:$I$5000<>"")/(COUNTIFS('チェックポイント-問合せ・差戻し事例対応表'!$B$2:$B$5000,'チェックポイント-問合せ・差戻し事例対応表'!$B$2:$B$5000,'チェックポイント-問合せ・差戻し事例対応表'!$I$2:$I$5000,'チェックポイント-問合せ・差戻し事例対応表'!$I$2:$I$5000)+('チェックポイント-問合せ・差戻し事例対応表'!$I$2:$I$5000=""))) -> 2 | I59: 101 | J59: =IFERROR(INDEX(レビュー指針!$D:$D,MATCH(I59,レビュー指針!$A:$A,0)),"") -> 成果物 | K59: =IFERROR(INDEX(レビュー指針!$E:$E,MATCH(I59,レビュー指針!$A:$A,0)),"") -> 1次レビュー | L59: =IFERROR(INDEX(レビュー指針!$H:$H,MATCH(I59,レビュー指針!$A:$A,0)),"") -> 網羅性が確認できる情報が記載又は提出されている | P59: Stage2精査(裾野・要確認) / 自主点検QA由来 / 件数2 / 要文言整備
A60: 133 | B60: 22 | C60: =IFERROR(INDEX(自主点検項目!$B:$B,MATCH(B60,自主点検項目!$A:$A,0)),"") -> 固定資産除却損の計上確認 | D60: 65 | E60: =IFERROR(INDEX(提出物!$D:$D,MATCH(D60,提出物!$A:$A,0)),"") -> データソース／試算表との一致 | F60: 網羅性（全件の記載）及び試算表との一致が確認できる資料が提出されているか。 | G60: =COUNTIF('チェックポイント-問合せ・差戻し事例対応表'!$B:$B,A60) -> 25 | H60: =SUMPRODUCT(('チェックポイント-問合せ・差戻し事例対応表'!$B$2:$B$5000=A60)*('チェックポイント-問合せ・差戻し事例対応表'!$I$2:$I$5000<>"")/(COUNTIFS('チェックポイント-問合せ・差戻し事例対応表'!$B$2:$B$5000,'チェックポイント-問合せ・差戻し事例対応表'!$B$2:$B$5000,'チェックポイント-問合せ・差戻し事例対応表'!$I$2:$I$5000,'チェックポイント-問合せ・差戻し事例対応表'!$I$2:$I$5000)+('チェックポイント-問合せ・差戻し事例対応表'!$I$2:$I$5000=""))) -> 23 | I60: 101 | J60: =IFERROR(INDEX(レビュー指針!$D:$D,MATCH(I60,レビュー指針!$A:$A,0)),"") -> 成果物 | K60: =IFERROR(INDEX(レビュー指針!$E:$E,MATCH(I60,レビュー指針!$A:$A,0)),"") -> 1次レビュー | L60: =IFERROR(INDEX(レビュー指針!$H:$H,MATCH(I60,レビュー指針!$A:$A,0)),"") -> 網羅性が確認できる情報が記載又は提出されている | P60: Stage2精査 / 網羅性チェックへ整形 / 自主点検QA由来 / 件数15 / 要文言整備
A61: 136 | B61: 22 | C61: =IFERROR(INDEX(自主点検項目!$B:$B,MATCH(B61,自主点検項目!$A:$A,0)),"") -> 固定資産除却損の計上確認 | D61: 65 | E61: =IFERROR(INDEX(提出物!$D:$D,MATCH(D61,提出物!$A:$A,0)),"") -> データソース／試算表との一致 | F61: データソースと抽出条件（手順）の記録が成果物として提出されている | G61: =COUNTIF('チェックポイント-問合せ・差戻し事例対応表'!$B:$B,A61) -> 6 | H61: =SUMPRODUCT(('チェックポイント-問合せ・差戻し事例対応表'!$B$2:$B$5000=A61)*('チェックポイント-問合せ・差戻し事例対応表'!$I$2:$I$5000<>"")/(COUNTIFS('チェックポイント-問合せ・差戻し事例対応表'!$B$2:$B$5000,'チェックポイント-問合せ・差戻し事例対応表'!$B$2:$B$5000,'チェックポイント-問合せ・差戻し事例対応表'!$I$2:$I$5000,'チェックポイント-問合せ・差戻し事例対応表'!$I$2:$I$5000)+('チェックポイント-問合せ・差戻し事例対応表'!$I$2:$I$5000=""))) -> 6 | I61: 100 | J61: =IFERROR(INDEX(レビュー指針!$D:$D,MATCH(I61,レビュー指針!$A:$A,0)),"") -> 成果物 | K61: =IFERROR(INDEX(レビュー指針!$E:$E,MATCH(I61,レビュー指針!$A:$A,0)),"") -> 1次レビュー | L61: =IFERROR(INDEX(レビュー指針!$H:$H,MATCH(I61,レビュー指針!$A:$A,0)),"") -> データソースと抽出条件（手順）の記録が成果物として提出されている | P61: Stage2精査(裾野・要確認) / 自主点検QA由来 / 件数2 / 要文言整備
A62: 139 | B62: 22 | C62: =IFERROR(INDEX(自主点検項目!$B:$B,MATCH(B62,自主点検項目!$A:$A,0)),"") -> 固定資産除却損の計上確認 | D62: 66 | E62: =IFERROR(INDEX(提出物!$D:$D,MATCH(D62,提出物!$A:$A,0)),"") -> 除却の根拠資料 | F62: 除却取引全てについて根拠資料(仕訳伝票だけでなく、例えば、除却申請書や職務権限決裁報告書)が提出されている | G62: =COUNTIF('チェックポイント-問合せ・差戻し事例対応表'!$B:$B,A62) -> 18 | H62: =SUMPRODUCT(('チェックポイント-問合せ・差戻し事例対応表'!$B$2:$B$5000=A62)*('チェックポイント-問合せ・差戻し事例対応表'!$I$2:$I$5000<>"")/(COUNTIFS('チェックポイント-問合せ・差戻し事例対応表'!$B$2:$B$5000,'チェックポイント-問合せ・差戻し事例対応表'!$B$2:$B$5000,'チェックポイント-問合せ・差戻し事例対応表'!$I$2:$I$5000,'チェックポイント-問合せ・差戻し事例対応表'!$I$2:$I$5000)+('チェックポイント-問合せ・差戻し事例対応表'!$I$2:$I$5000=""))) -> 16 | I62: 102 | J62: =IFERROR(INDEX(レビュー指針!$D:$D,MATCH(I62,レビュー指針!$A:$A,0)),"") -> 成果物 | K62: =IFERROR(INDEX(レビュー指針!$E:$E,MATCH(I62,レビュー指針!$A:$A,0)),"") -> 1次レビュー | L62: =IFERROR(INDEX(レビュー指針!$H:$H,MATCH(I62,レビュー指針!$A:$A,0)),"") -> 除却取引全てについて根拠資料(仕訳伝票だけでなく、例えば、除却申請書や職務権限決裁報告書)が提出されている | P62: Stage2精査(裾野・要確認) / 自主点検QA由来 / 件数4 / 要文言整備
A63: 140 | B63: 22 | C63: =IFERROR(INDEX(自主点検項目!$B:$B,MATCH(B63,自主点検項目!$A:$A,0)),"") -> 固定資産除却損の計上確認 | D63: 66 | E63: =IFERROR(INDEX(提出物!$D:$D,MATCH(D63,提出物!$A:$A,0)),"") -> 除却の根拠資料 | F63: 網羅性が確認できる情報が記載又は提出されている | G63: =COUNTIF('チェックポイント-問合せ・差戻し事例対応表'!$B:$B,A63) -> 6 | H63: =SUMPRODUCT(('チェックポイント-問合せ・差戻し事例対応表'!$B$2:$B$5000=A63)*('チェックポイント-問合せ・差戻し事例対応表'!$I$2:$I$5000<>"")/(COUNTIFS('チェックポイント-問合せ・差戻し事例対応表'!$B$2:$B$5000,'チェックポイント-問合せ・差戻し事例対応表'!$B$2:$B$5000,'チェックポイント-問合せ・差戻し事例対応表'!$I$2:$I$5000,'チェックポイント-問合せ・差戻し事例対応表'!$I$2:$I$5000)+('チェックポイント-問合せ・差戻し事例対応表'!$I$2:$I$5000=""))) -> 6 | I63: 101 | J63: =IFERROR(INDEX(レビュー指針!$D:$D,MATCH(I63,レビュー指針!$A:$A,0)),"") -> 成果物 | K63: =IFERROR(INDEX(レビュー指針!$E:$E,MATCH(I63,レビュー指針!$A:$A,0)),"") -> 1次レビュー | L63: =IFERROR(INDEX(レビュー指針!$H:$H,MATCH(I63,レビュー指針!$A:$A,0)),"") -> 網羅性が確認できる情報が記載又は提出されている | P63: Stage2精査(裾野・要確認) / 自主点検QA由来 / 件数4 / 要文言整備
A64: 145 | B64: 22 | C64: =IFERROR(INDEX(自主点検項目!$B:$B,MATCH(B64,自主点検項目!$A:$A,0)),"") -> 固定資産除却損の計上確認 | D64: 共通 | E64: =IFERROR(INDEX(提出物!$D:$D,MATCH(D64,提出物!$A:$A,0)),"") | F64: 網羅性が確認できる情報（試算表の全件・総額との一致）が提出されているか。 | G64: =COUNTIF('チェックポイント-問合せ・差戻し事例対応表'!$B:$B,A64) -> 15 | H64: =SUMPRODUCT(('チェックポイント-問合せ・差戻し事例対応表'!$B$2:$B$5000=A64)*('チェックポイント-問合せ・差戻し事例対応表'!$I$2:$I$5000<>"")/(COUNTIFS('チェックポイント-問合せ・差戻し事例対応表'!$B$2:$B$5000,'チェックポイント-問合せ・差戻し事例対応表'!$B$2:$B$5000,'チェックポイント-問合せ・差戻し事例対応表'!$I$2:$I$5000,'チェックポイント-問合せ・差戻し事例対応表'!$I$2:$I$5000)+('チェックポイント-問合せ・差戻し事例対応表'!$I$2:$I$5000=""))) -> 15 | I64: 101 | J64: =IFERROR(INDEX(レビュー指針!$D:$D,MATCH(I64,レビュー指針!$A:$A,0)),"") -> 成果物 | K64: =IFERROR(INDEX(レビュー指針!$E:$E,MATCH(I64,レビュー指針!$A:$A,0)),"") -> 1次レビュー | L64: =IFERROR(INDEX(レビュー指針!$H:$H,MATCH(I64,レビュー指針!$A:$A,0)),"") -> 網羅性が確認できる情報が記載又は提出されている | P64: Stage2精査 / 網羅性チェック（英文問合せ） / 自主点検QA由来 / 件数6 / 要文言整備
A65: 148 | B65: 22 | C65: =IFERROR(INDEX(自主点検項目!$B:$B,MATCH(B65,自主点検項目!$A:$A,0)),"") -> 固定資産除却損の計上確認 | D65: 共通 | E65: =IFERROR(INDEX(提出物!$D:$D,MATCH(D65,提出物!$A:$A,0)),"") | F65: データソースと抽出条件（手順）の記録が成果物として提出されている | G65: =COUNTIF('チェックポイント-問合せ・差戻し事例対応表'!$B:$B,A65) -> 3 | H65: =SUMPRODUCT(('チェックポイント-問合せ・差戻し事例対応表'!$B$2:$B$5000=A65)*('チェックポイント-問合せ・差戻し事例対応表'!$I$2:$I$5000<>"")/(COUNTIFS('チェックポイント-問合せ・差戻し事例対応表'!$B$2:$B$5000,'チェックポイント-問合せ・差戻し事例対応表'!$B$2:$B$5000,'チェックポイント-問合せ・差戻し事例対応表'!$I$2:$I$5000,'チェックポイント-問合せ・差戻し事例対応表'!$I$2:$I$5000)+('チェックポイント-問合せ・差戻し事例対応表'!$I$2:$I$5000=""))) -> 3 | I65: 100 | J65: =IFERROR(INDEX(レビュー指針!$D:$D,MATCH(I65,レビュー指針!$A:$A,0)),"") -> 成果物 | K65: =IFERROR(INDEX(レビュー指針!$E:$E,MATCH(I65,レビュー指針!$A:$A,0)),"") -> 1次レビュー | L65: =IFERROR(INDEX(レビュー指針!$H:$H,MATCH(I65,レビュー指針!$A:$A,0)),"") -> データソースと抽出条件（手順）の記録が成果物として提出されている | P65: Stage2精査(裾野・要確認) / 自主点検QA由来 / 件数3 / 要文言整備
A66: 150 | B66: 23 | C66: =IFERROR(INDEX(自主点検項目!$B:$B,MATCH(B66,自主点検項目!$A:$A,0)),"") -> 固定資産の資産性確認 | D66: 67 | E66: =IFERROR(INDEX(提出物!$D:$D,MATCH(D66,提出物!$A:$A,0)),"") -> 固定資産台帳でフラグ付けした明細＋資産計上妥当性コメント | F66: 網羅性が確認できる情報が記載又は提出されている | G66: =COUNTIF('チェックポイント-問合せ・差戻し事例対応表'!$B:$B,A66) -> 11 | H66: =SUMPRODUCT(('チェックポイント-問合せ・差戻し事例対応表'!$B$2:$B$5000=A66)*('チェックポイント-問合せ・差戻し事例対応表'!$I$2:$I$5000<>"")/(COUNTIFS('チェックポイント-問合せ・差戻し事例対応表'!$B$2:$B$5000,'チェックポイント-問合せ・差戻し事例対応表'!$B$2:$B$5000,'チェックポイント-問合せ・差戻し事例対応表'!$I$2:$I$5000,'チェックポイント-問合せ・差戻し事例対応表'!$I$2:$I$5000)+('チェックポイント-問合せ・差戻し事例対応表'!$I$2:$I$5000=""))) -> 11 | I66: 105 | J66: =IFERROR(INDEX(レビュー指針!$D:$D,MATCH(I66,レビュー指針!$A:$A,0)),"") -> 成果物 | K66: =IFERROR(INDEX(レビュー指針!$E:$E,MATCH(I66,レビュー指針!$A:$A,0)),"") -> 1次レビュー | L66: =IFERROR(INDEX(レビュー指針!$H:$H,MATCH(I66,レビュー指針!$A:$A,0)),"") -> 網羅性が確認できる情報が記載又は提出されている | P66: Stage2精査(裾野・要確認) / 自主点検QA由来 / 件数4 / 要文言整備
A67: 151 | B67: 23 | C67: =IFERROR(INDEX(自主点検項目!$B:$B,MATCH(B67,自主点検項目!$A:$A,0)),"") -> 固定資産の資産性確認 | D67: 67 | E67: =IFERROR(INDEX(提出物!$D:$D,MATCH(D67,提出物!$A:$A,0)),"") -> 固定資産台帳でフラグ付けした明細＋資産計上妥当性コメント | F67: 修繕費や研究費等の費用計上すべき内容が固定資産計上されている可能性がある明細にフラグが付けられており、資産計上の妥当性に関するコメントが記載されている | G67: =COUNTIF('チェックポイント-問合せ・差戻し事例対応表'!$B:$B,A67) -> 20 | H67: =SUMPRODUCT(('チェックポイント-問合せ・差戻し事例対応表'!$B$2:$B$5000=A67)*('チェックポイント-問合せ・差戻し事例対応表'!$I$2:$I$5000<>"")/(COUNTIFS('チェックポイント-問合せ・差戻し事例対応表'!$B$2:$B$5000,'チェックポイント-問合せ・差戻し事例対応表'!$B$2:$B$5000,'チェックポイント-問合せ・差戻し事例対応表'!$I$2:$I$5000,'チェックポイント-問合せ・差戻し事例対応表'!$I$2:$I$5000)+('チェックポイント-問合せ・差戻し事例対応表'!$I$2:$I$5000=""))) -> 16 | I67: 106 | J67: =IFERROR(INDEX(レビュー指針!$D:$D,MATCH(I67,レビュー指針!$A:$A,0)),"") -> 成果物 | K67: =IFERROR(INDEX(レビュー指針!$E:$E,MATCH(I67,レビュー指針!$A:$A,0)),"") -> 1次レビュー | L67: =IFERROR(INDEX(レビュー指針!$H:$H,MATCH(I67,レビュー指針!$A:$A,0)),"") -> 修繕費や研究費等の費用計上すべき内容が固定資産計上されている可能性がある明細にフラグが付けられており、資産計上の妥当性に関するコメントが記載されている | P67: Stage2精査(裾野・要確認) / 自主点検QA由来 / 件数3 / 要文言整備
A68: 156 | B68: 23 | C68: =IFERROR(INDEX(自主点検項目!$B:$B,MATCH(B68,自主点検項目!$A:$A,0)),"") -> 固定資産の資産性確認 | D68: 68 | E68: =IFERROR(INDEX(提出物!$D:$D,MATCH(D68,提出物!$A:$A,0)),"") -> データソース・抽出条件 | F68: 成果物の作成に用いたデータソースと抽出条件（手順）の記録（画面コピー等）が提出されているか。 | G68: =COUNTIF('チェックポイント-問合せ・差戻し事例対応表'!$B:$B,A68) -> 26 | H68: =SUMPRODUCT(('チェックポイント-問合せ・差戻し事例対応表'!$B$2:$B$5000=A68)*('チェックポイント-問合せ・差戻し事例対応表'!$I$2:$I$5000<>"")/(COUNTIFS('チェックポイント-問合せ・差戻し事例対応表'!$B$2:$B$5000,'チェックポイント-問合せ・差戻し事例対応表'!$B$2:$B$5000,'チェックポイント-問合せ・差戻し事例対応表'!$I$2:$I$5000,'チェックポイント-問合せ・差戻し事例対応表'!$I$2:$I$5000)+('チェックポイント-問合せ・差戻し事例対応表'!$I$2:$I$5000=""))) -> 26 | I68: 104 | J68: =IFERROR(INDEX(レビュー指針!$D:$D,MATCH(I68,レビュー指針!$A:$A,0)),"") -> 成果物 | K68: =IFERROR(INDEX(レビュー指針!$E:$E,MATCH(I68,レビュー指針!$A:$A,0)),"") -> 1次レビュー | L68: =IFERROR(INDEX(レビュー指針!$H:$H,MATCH(I68,レビュー指針!$A:$A,0)),"") -> データソースと抽出条件（手順）の記録が成果物として提出されている | P68: Stage2精査 / 複合問合せを分割（網羅性は別CPへ） / 自主点検QA由来 / 件数15 / 要文言整備
A69: 159 | B69: 23 | C69: =IFERROR(INDEX(自主点検項目!$B:$B,MATCH(B69,自主点検項目!$A:$A,0)),"") -> 固定資産の資産性確認 | D69: 69 | E69: =IFERROR(INDEX(提出物!$D:$D,MATCH(D69,提出物!$A:$A,0)),"") -> 資産計上の根拠資料 | F69: 網羅性が確認できる情報が記載又は提出されている | G69: =COUNTIF('チェックポイント-問合せ・差戻し事例対応表'!$B:$B,A69) -> 4 | H69: =SUMPRODUCT(('チェックポイント-問合せ・差戻し事例対応表'!$B$2:$B$5000=A69)*('チェックポイント-問合せ・差戻し事例対応表'!$I$2:$I$5000<>"")/(COUNTIFS('チェックポイント-問合せ・差戻し事例対応表'!$B$2:$B$5000,'チェックポイント-問合せ・差戻し事例対応表'!$B$2:$B$5000,'チェックポイント-問合せ・差戻し事例対応表'!$I$2:$I$5000,'チェックポイント-問合せ・差戻し事例対応表'!$I$2:$I$5000)+('チェックポイント-問合せ・差戻し事例対応表'!$I$2:$I$5000=""))) -> 4 | I69: 105 | J69: =IFERROR(INDEX(レビュー指針!$D:$D,MATCH(I69,レビュー指針!$A:$A,0)),"") -> 成果物 | K69: =IFERROR(INDEX(レビュー指針!$E:$E,MATCH(I69,レビュー指針!$A:$A,0)),"") -> 1次レビュー | L69: =IFERROR(INDEX(レビュー指針!$H:$H,MATCH(I69,レビュー指針!$A:$A,0)),"") -> 網羅性が確認できる情報が記載又は提出されている | P69: Stage2精査(裾野・要確認) / 自主点検QA由来 / 件数4 / 要文言整備
A70: 160 | B70: 23 | C70: =IFERROR(INDEX(自主点検項目!$B:$B,MATCH(B70,自主点検項目!$A:$A,0)),"") -> 固定資産の資産性確認 | D70: 69 | E70: =IFERROR(INDEX(提出物!$D:$D,MATCH(D70,提出物!$A:$A,0)),"") -> 資産計上の根拠資料 | F70: 修繕費や研究費等の費用計上すべき内容が固定資産計上されている可能性がある明細にフラグが付けられており、資産計上の妥当性に関するコメントが記載されている | G70: =COUNTIF('チェックポイント-問合せ・差戻し事例対応表'!$B:$B,A70) -> 17 | H70: =SUMPRODUCT(('チェックポイント-問合せ・差戻し事例対応表'!$B$2:$B$5000=A70)*('チェックポイント-問合せ・差戻し事例対応表'!$I$2:$I$5000<>"")/(COUNTIFS('チェックポイント-問合せ・差戻し事例対応表'!$B$2:$B$5000,'チェックポイント-問合せ・差戻し事例対応表'!$B$2:$B$5000,'チェックポイント-問合せ・差戻し事例対応表'!$I$2:$I$5000,'チェックポイント-問合せ・差戻し事例対応表'!$I$2:$I$5000)+('チェックポイント-問合せ・差戻し事例対応表'!$I$2:$I$5000=""))) -> 16 | I70: 106 | J70: =IFERROR(INDEX(レビュー指針!$D:$D,MATCH(I70,レビュー指針!$A:$A,0)),"") -> 成果物 | K70: =IFERROR(INDEX(レビュー指針!$E:$E,MATCH(I70,レビュー指針!$A:$A,0)),"") -> 1次レビュー | L70: =IFERROR(INDEX(レビュー指針!$H:$H,MATCH(I70,レビュー指針!$A:$A,0)),"") -> 修繕費や研究費等の費用計上すべき内容が固定資産計上されている可能性がある明細にフラグが付けられており、資産計上の妥当性に関するコメントが記載されている | P70: Stage2精査(裾野・要確認) / 自主点検QA由来 / 件数2 / 要文言整備
A71: 161 | B71: 25 | C71: =IFERROR(INDEX(自主点検項目!$B:$B,MATCH(B71,自主点検項目!$A:$A,0)),"") -> 減損テスト | D71: 72 | E71: =IFERROR(INDEX(提出物!$D:$D,MATCH(D71,提出物!$A:$A,0)),"") -> 各CGUの減損判定資料 | F71: 減損判定資料が当期末（2026年3月末）基準で作成・検討されているか（古い基準日のままでないか）。 | G71: =COUNTIF('チェックポイント-問合せ・差戻し事例対応表'!$B:$B,A71) -> 21 | H71: =SUMPRODUCT(('チェックポイント-問合せ・差戻し事例対応表'!$B$2:$B$5000=A71)*('チェックポイント-問合せ・差戻し事例対応表'!$I$2:$I$5000<>"")/(COUNTIFS('チェックポイント-問合せ・差戻し事例対応表'!$B$2:$B$5000,'チェックポイント-問合せ・差戻し事例対応表'!$B$2:$B$5000,'チェックポイント-問合せ・差戻し事例対応表'!$I$2:$I$5000,'チェックポイント-問合せ・差戻し事例対応表'!$I$2:$I$5000)+('チェックポイント-問合せ・差戻し事例対応表'!$I$2:$I$5000=""))) -> 15 | I71: 112 | J71: =IFERROR(INDEX(レビュー指針!$D:$D,MATCH(I71,レビュー指針!$A:$A,0)),"") -> 会計処理の妥当性 | K71: =IFERROR(INDEX(レビュー指針!$E:$E,MATCH(I71,レビュー指針!$A:$A,0)),"") -> 2次レビュー | L71: =IFERROR(INDEX(レビュー指針!$H:$H,MATCH(I71,レビュー指針!$A:$A,0)),"") -> 減損検討結果の判断に合理性はあるか | P71: Stage2精査 / 基準日の妥当性 / 自主点検QA由来 / 件数15 / 要文言整備
A72: 162 | B72: 25 | C72: =IFERROR(INDEX(自主点検項目!$B:$B,MATCH(B72,自主点検項目!$A:$A,0)),"") -> 減損テスト | D72: 72 | E72: =IFERROR(INDEX(提出物!$D:$D,MATCH(D72,提出物!$A:$A,0)),"") -> 各CGUの減損判定資料 | F72: 減損の兆候に抵触するCGUについて、どのような考えでグルーピングを行っているのかについて記述されているか | G72: =COUNTIF('チェックポイント-問合せ・差戻し事例対応表'!$B:$B,A72) -> 4 | H72: =SUMPRODUCT(('チェックポイント-問合せ・差戻し事例対応表'!$B$2:$B$5000=A72)*('チェックポイント-問合せ・差戻し事例対応表'!$I$2:$I$5000<>"")/(COUNTIFS('チェックポイント-問合せ・差戻し事例対応表'!$B$2:$B$5000,'チェックポイント-問合せ・差戻し事例対応表'!$B$2:$B$5000,'チェックポイント-問合せ・差戻し事例対応表'!$I$2:$I$5000,'チェックポイント-問合せ・差戻し事例対応表'!$I$2:$I$5000)+('チェックポイント-問合せ・差戻し事例対応表'!$I$2:$I$5000=""))) -> 4 | I72: 111 | J72: =IFERROR(INDEX(レビュー指針!$D:$D,MATCH(I72,レビュー指針!$A:$A,0)),"") -> 成果物 | K72: =IFERROR(INDEX(レビュー指針!$E:$E,MATCH(I72,レビュー指針!$A:$A,0)),"") -> 1次レビュー | L72: =IFERROR(INDEX(レビュー指針!$H:$H,MATCH(I72,レビュー指針!$A:$A,0)),"") -> 減損の兆候に抵触するCGUについて、どのような考えでグルーピングを行っているのかについて記述されているか | P72: Stage2精査(裾野・要確認) / 自主点検QA由来 / 件数3 / 要文言整備
A73: 166 | B73: 25 | C73: =IFERROR(INDEX(自主点検項目!$B:$B,MATCH(B73,自主点検項目!$A:$A,0)),"") -> 減損テスト | D73: 75 | E73: =IFERROR(INDEX(提出物!$D:$D,MATCH(D73,提出物!$A:$A,0)),"") -> データソース | F73: 成果物の作成に用いたデータソースと抽出条件（手順）の記録（画面コピー等）が提出されているか。 | G73: =COUNTIF('チェックポイント-問合せ・差戻し事例対応表'!$B:$B,A73) -> 30 | H73: =SUMPRODUCT(('チェックポイント-問合せ・差戻し事例対応表'!$B$2:$B$5000=A73)*('チェックポイント-問合せ・差戻し事例対応表'!$I$2:$I$5000<>"")/(COUNTIFS('チェックポイント-問合せ・差戻し事例対応表'!$B$2:$B$5000,'チェックポイント-問合せ・差戻し事例対応表'!$B$2:$B$5000,'チェックポイント-問合せ・差戻し事例対応表'!$I$2:$I$5000,'チェックポイント-問合せ・差戻し事例対応表'!$I$2:$I$5000)+('チェックポイント-問合せ・差戻し事例対応表'!$I$2:$I$5000=""))) -> 29 | I73: 108 | J73: =IFERROR(INDEX(レビュー指針!$D:$D,MATCH(I73,レビュー指針!$A:$A,0)),"") -> 成果物 | K73: =IFERROR(INDEX(レビュー指針!$E:$E,MATCH(I73,レビュー指針!$A:$A,0)),"") -> 1次レビュー | L73: =IFERROR(INDEX(レビュー指針!$H:$H,MATCH(I73,レビュー指針!$A:$A,0)),"") -> データソースと抽出条件（手順）の記録が成果物として提出されている | P73: Stage2精査 / 複合問合せを分割（網羅性は別CPへ） / 自主点検QA由来 / 件数20 / 要文言整備
A74: 173 | B74: 25 | C74: =IFERROR(INDEX(自主点検項目!$B:$B,MATCH(B74,自主点検項目!$A:$A,0)),"") -> 減損テスト | D74: 75 | E74: =IFERROR(INDEX(提出物!$D:$D,MATCH(D74,提出物!$A:$A,0)),"") -> データソース | F74: 減損検討結果の判断に合理性はあるか | G74: =COUNTIF('チェックポイント-問合せ・差戻し事例対応表'!$B:$B,A74) -> 2 | H74: =SUMPRODUCT(('チェックポイント-問合せ・差戻し事例対応表'!$B$2:$B$5000=A74)*('チェックポイント-問合せ・差戻し事例対応表'!$I$2:$I$5000<>"")/(COUNTIFS('チェックポイント-問合せ・差戻し事例対応表'!$B$2:$B$5000,'チェックポイント-問合せ・差戻し事例対応表'!$B$2:$B$5000,'チェックポイント-問合せ・差戻し事例対応表'!$I$2:$I$5000,'チェックポイント-問合せ・差戻し事例対応表'!$I$2:$I$5000)+('チェックポイント-問合せ・差戻し事例対応表'!$I$2:$I$5000=""))) -> 2 | I74: 112 | J74: =IFERROR(INDEX(レビュー指針!$D:$D,MATCH(I74,レビュー指針!$A:$A,0)),"") -> 会計処理の妥当性 | K74: =IFERROR(INDEX(レビュー指針!$E:$E,MATCH(I74,レビュー指針!$A:$A,0)),"") -> 2次レビュー | L74: =IFERROR(INDEX(レビュー指針!$H:$H,MATCH(I74,レビュー指針!$A:$A,0)),"") -> 減損検討結果の判断に合理性はあるか | P74: Stage2精査(裾野・要確認) / 自主点検QA由来 / 件数2 / 要文言整備
A75: 174 | B75: 25 | C75: =IFERROR(INDEX(自主点検項目!$B:$B,MATCH(B75,自主点検項目!$A:$A,0)),"") -> 減損テスト | D75: 共通 | E75: =IFERROR(INDEX(提出物!$D:$D,MATCH(D75,提出物!$A:$A,0)),"") | F75: 資産のグルーピングに関する判断が（記載例のままでなく）具体的に記述されているか。 | G75: =COUNTIF('チェックポイント-問合せ・差戻し事例対応表'!$B:$B,A75) -> 19 | H75: =SUMPRODUCT(('チェックポイント-問合せ・差戻し事例対応表'!$B$2:$B$5000=A75)*('チェックポイント-問合せ・差戻し事例対応表'!$I$2:$I$5000<>"")/(COUNTIFS('チェックポイント-問合せ・差戻し事例対応表'!$B$2:$B$5000,'チェックポイント-問合せ・差戻し事例対応表'!$B$2:$B$5000,'チェックポイント-問合せ・差戻し事例対応表'!$I$2:$I$5000,'チェックポイント-問合せ・差戻し事例対応表'!$I$2:$I$5000)+('チェックポイント-問合せ・差戻し事例対応表'!$I$2:$I$5000=""))) -> 19 | I75: 111 | J75: =IFERROR(INDEX(レビュー指針!$D:$D,MATCH(I75,レビュー指針!$A:$A,0)),"") -> 成果物 | K75: =IFERROR(INDEX(レビュー指針!$E:$E,MATCH(I75,レビュー指針!$A:$A,0)),"") -> 1次レビュー | L75: =IFERROR(INDEX(レビュー指針!$H:$H,MATCH(I75,レビュー指針!$A:$A,0)),"") -> 減損の兆候に抵触するCGUについて、どのような考えでグルーピングを行っているのかについて記述されているか | P75: Stage2精査 / グルーピング記述 / 自主点検QA由来 / 件数9 / 要文言整備
A76: 176 | B76: 25 | C76: =IFERROR(INDEX(自主点検項目!$B:$B,MATCH(B76,自主点検項目!$A:$A,0)),"") -> 減損テスト | D76: 共通 | E76: =IFERROR(INDEX(提出物!$D:$D,MATCH(D76,提出物!$A:$A,0)),"") | F76: 減損検討結果の判断に合理性はあるか | G76: =COUNTIF('チェックポイント-問合せ・差戻し事例対応表'!$B:$B,A76) -> 3 | H76: =SUMPRODUCT(('チェックポイント-問合せ・差戻し事例対応表'!$B$2:$B$5000=A76)*('チェックポイント-問合せ・差戻し事例対応表'!$I$2:$I$5000<>"")/(COUNTIFS('チェックポイント-問合せ・差戻し事例対応表'!$B$2:$B$5000,'チェックポイント-問合せ・差戻し事例対応表'!$B$2:$B$5000,'チェックポイント-問合せ・差戻し事例対応表'!$I$2:$I$5000,'チェックポイント-問合せ・差戻し事例対応表'!$I$2:$I$5000)+('チェックポイント-問合せ・差戻し事例対応表'!$I$2:$I$5000=""))) -> 2 | I76: 112 | J76: =IFERROR(INDEX(レビュー指針!$D:$D,MATCH(I76,レビュー指針!$A:$A,0)),"") -> 会計処理の妥当性 | K76: =IFERROR(INDEX(レビュー指針!$E:$E,MATCH(I76,レビュー指針!$A:$A,0)),"") -> 2次レビュー | L76: =IFERROR(INDEX(レビュー指針!$H:$H,MATCH(I76,レビュー指針!$A:$A,0)),"") -> 減損検討結果の判断に合理性はあるか | P76: Stage2精査(裾野・要確認) / 自主点検QA由来 / 件数3 / 要文言整備
A77: 177 | B77: 25 | C77: =IFERROR(INDEX(自主点検項目!$B:$B,MATCH(B77,自主点検項目!$A:$A,0)),"") -> 減損テスト | D77: 共通 | E77: =IFERROR(INDEX(提出物!$D:$D,MATCH(D77,提出物!$A:$A,0)),"") | F77: 網羅性が確認できる情報が記載又は提出されている | G77: =COUNTIF('チェックポイント-問合せ・差戻し事例対応表'!$B:$B,A77) -> 5 | H77: =SUMPRODUCT(('チェックポイント-問合せ・差戻し事例対応表'!$B$2:$B$5000=A77)*('チェックポイント-問合せ・差戻し事例対応表'!$I$2:$I$5000<>"")/(COUNTIFS('チェックポイント-問合せ・差戻し事例対応表'!$B$2:$B$5000,'チェックポイント-問合せ・差戻し事例対応表'!$B$2:$B$5000,'チェックポイント-問合せ・差戻し事例対応表'!$I$2:$I$5000,'チェックポイント-問合せ・差戻し事例対応表'!$I$2:$I$5000)+('チェックポイント-問合せ・差戻し事例対応表'!$I$2:$I$5000=""))) -> 5 | I77: 109 | J77: =IFERROR(INDEX(レビュー指針!$D:$D,MATCH(I77,レビュー指針!$A:$A,0)),"") -> 成果物 | K77: =IFERROR(INDEX(レビュー指針!$E:$E,MATCH(I77,レビュー指針!$A:$A,0)),"") -> 1次レビュー | L77: =IFERROR(INDEX(レビュー指針!$H:$H,MATCH(I77,レビュー指針!$A:$A,0)),"") -> 網羅性が確認できる情報が記載又は提出されている | P77: Stage2精査(裾野・要確認) / 自主点検QA由来 / 件数3 / 要文言整備
A78: 180 | B78: 26 | C78: =IFERROR(INDEX(自主点検項目!$B:$B,MATCH(B78,自主点検項目!$A:$A,0)),"") -> 賞与引当金の計上確認 | D78: 76 | E78: =IFERROR(INDEX(提出物!$D:$D,MATCH(D78,提出物!$A:$A,0)),"") -> 計上根拠資料 | F78: 賞与引当金繰入額（PL）、賞与引当金（BS）が試算表と一致することが確認できる | G78: =COUNTIF('チェックポイント-問合せ・差戻し事例対応表'!$B:$B,A78) -> 7 | H78: =SUMPRODUCT(('チェックポイント-問合せ・差戻し事例対応表'!$B$2:$B$5000=A78)*('チェックポイント-問合せ・差戻し事例対応表'!$I$2:$I$5000<>"")/(COUNTIFS('チェックポイント-問合せ・差戻し事例対応表'!$B$2:$B$5000,'チェックポイント-問合せ・差戻し事例対応表'!$B$2:$B$5000,'チェックポイント-問合せ・差戻し事例対応表'!$I$2:$I$5000,'チェックポイント-問合せ・差戻し事例対応表'!$I$2:$I$5000)+('チェックポイント-問合せ・差戻し事例対応表'!$I$2:$I$5000=""))) -> 6 | I78: 115 | J78: =IFERROR(INDEX(レビュー指針!$D:$D,MATCH(I78,レビュー指針!$A:$A,0)),"") -> 成果物 | K78: =IFERROR(INDEX(レビュー指針!$E:$E,MATCH(I78,レビュー指針!$A:$A,0)),"") -> 1次レビュー | L78: =IFERROR(INDEX(レビュー指針!$H:$H,MATCH(I78,レビュー指針!$A:$A,0)),"") -> 賞与引当金繰入額（PL）、賞与引当金（BS）が試算表と一致することが確認できる | P78: Stage2精査(裾野・要確認) / 自主点検QA由来 / 件数2 / 要文言整備
A79: 181 | B79: 26 | C79: =IFERROR(INDEX(自主点検項目!$B:$B,MATCH(B79,自主点検項目!$A:$A,0)),"") -> 賞与引当金の計上確認 | D79: 77 | E79: =IFERROR(INDEX(提出物!$D:$D,MATCH(D79,提出物!$A:$A,0)),"") -> 取崩時の支払証跡＋当初計上額と支払額の比較分析 | F79: 賞与引当金繰入額（PL）、賞与引当金（BS）が試算表と一致することが確認できる | G79: =COUNTIF('チェックポイント-問合せ・差戻し事例対応表'!$B:$B,A79) -> 3 | H79: =SUMPRODUCT(('チェックポイント-問合せ・差戻し事例対応表'!$B$2:$B$5000=A79)*('チェックポイント-問合せ・差戻し事例対応表'!$I$2:$I$5000<>"")/(COUNTIFS('チェックポイント-問合せ・差戻し事例対応表'!$B$2:$B$5000,'チェックポイント-問合せ・差戻し事例対応表'!$B$2:$B$5000,'チェックポイント-問合せ・差戻し事例対応表'!$I$2:$I$5000,'チェックポイント-問合せ・差戻し事例対応表'!$I$2:$I$5000)+('チェックポイント-問合せ・差戻し事例対応表'!$I$2:$I$5000=""))) -> 3 | I79: 115 | J79: =IFERROR(INDEX(レビュー指針!$D:$D,MATCH(I79,レビュー指針!$A:$A,0)),"") -> 成果物 | K79: =IFERROR(INDEX(レビュー指針!$E:$E,MATCH(I79,レビュー指針!$A:$A,0)),"") -> 1次レビュー | L79: =IFERROR(INDEX(レビュー指針!$H:$H,MATCH(I79,レビュー指針!$A:$A,0)),"") -> 賞与引当金繰入額（PL）、賞与引当金（BS）が試算表と一致することが確認できる | P79: Stage2精査(裾野・要確認) / 自主点検QA由来 / 件数2 / 要文言整備
A80: 182 | B80: 26 | C80: =IFERROR(INDEX(自主点検項目!$B:$B,MATCH(B80,自主点検項目!$A:$A,0)),"") -> 賞与引当金の計上確認 | D80: 77 | E80: =IFERROR(INDEX(提出物!$D:$D,MATCH(D80,提出物!$A:$A,0)),"") -> 取崩時の支払証跡＋当初計上額と支払額の比較分析 | F80: 賞与引当金が計上されている場合、見積金額の根拠資料が提出されている | G80: =COUNTIF('チェックポイント-問合せ・差戻し事例対応表'!$B:$B,A80) -> 2 | H80: =SUMPRODUCT(('チェックポイント-問合せ・差戻し事例対応表'!$B$2:$B$5000=A80)*('チェックポイント-問合せ・差戻し事例対応表'!$I$2:$I$5000<>"")/(COUNTIFS('チェックポイント-問合せ・差戻し事例対応表'!$B$2:$B$5000,'チェックポイント-問合せ・差戻し事例対応表'!$B$2:$B$5000,'チェックポイント-問合せ・差戻し事例対応表'!$I$2:$I$5000,'チェックポイント-問合せ・差戻し事例対応表'!$I$2:$I$5000)+('チェックポイント-問合せ・差戻し事例対応表'!$I$2:$I$5000=""))) -> 2 | I80: 117 | J80: =IFERROR(INDEX(レビュー指針!$D:$D,MATCH(I80,レビュー指針!$A:$A,0)),"") -> 根拠資料 | K80: =IFERROR(INDEX(レビュー指針!$E:$E,MATCH(I80,レビュー指針!$A:$A,0)),"") -> 1次レビュー | L80: =IFERROR(INDEX(レビュー指針!$H:$H,MATCH(I80,レビュー指針!$A:$A,0)),"") -> 賞与引当金が計上されている場合、見積金額の根拠資料が提出されている | P80: Stage2精査(裾野・要確認) / 自主点検QA由来 / 件数2 / 要文言整備
A81: 183 | B81: 26 | C81: =IFERROR(INDEX(自主点検項目!$B:$B,MATCH(B81,自主点検項目!$A:$A,0)),"") -> 賞与引当金の計上確認 | D81: 79 | E81: =IFERROR(INDEX(提出物!$D:$D,MATCH(D81,提出物!$A:$A,0)),"") -> 月次推移表／繰入額・残高と試算表の一致 | F81: 賞与引当金繰入額（PL）・賞与引当金残高（BS）が試算表と一致し、算定資料の金額と成果物の金額が整合しているか。 | G81: =COUNTIF('チェックポイント-問合せ・差戻し事例対応表'!$B:$B,A81) -> 45 | H81: =SUMPRODUCT(('チェックポイント-問合せ・差戻し事例対応表'!$B$2:$B$5000=A81)*('チェックポイント-問合せ・差戻し事例対応表'!$I$2:$I$5000<>"")/(COUNTIFS('チェックポイント-問合せ・差戻し事例対応表'!$B$2:$B$5000,'チェックポイント-問合せ・差戻し事例対応表'!$B$2:$B$5000,'チェックポイント-問合せ・差戻し事例対応表'!$I$2:$I$5000,'チェックポイント-問合せ・差戻し事例対応表'!$I$2:$I$5000)+('チェックポイント-問合せ・差戻し事例対応表'!$I$2:$I$5000=""))) -> 43 | I81: 115 | J81: =IFERROR(INDEX(レビュー指針!$D:$D,MATCH(I81,レビュー指針!$A:$A,0)),"") -> 成果物 | K81: =IFERROR(INDEX(レビュー指針!$E:$E,MATCH(I81,レビュー指針!$A:$A,0)),"") -> 1次レビュー | L81: =IFERROR(INDEX(レビュー指針!$H:$H,MATCH(I81,レビュー指針!$A:$A,0)),"") -> 賞与引当金繰入額（PL）、賞与引当金（BS）が試算表と一致することが確認できる | P81: Stage2精査 / 網羅性・整合チェックへ整形 / 自主点検QA由来 / 件数29 / 要文言整備
A82: 184 | B82: 26 | C82: =IFERROR(INDEX(自主点検項目!$B:$B,MATCH(B82,自主点検項目!$A:$A,0)),"") -> 賞与引当金の計上確認 | D82: 79 | E82: =IFERROR(INDEX(提出物!$D:$D,MATCH(D82,提出物!$A:$A,0)),"") -> 月次推移表／繰入額・残高と試算表の一致 | F82: 賞与引当金繰入額・残高の月次推移表の作成に用いたデータソースと抽出条件（手順）の記録が提出されているか。 | G82: =COUNTIF('チェックポイント-問合せ・差戻し事例対応表'!$B:$B,A82) -> 35 | H82: =SUMPRODUCT(('チェックポイント-問合せ・差戻し事例対応表'!$B$2:$B$5000=A82)*('チェックポイント-問合せ・差戻し事例対応表'!$I$2:$I$5000<>"")/(COUNTIFS('チェックポイント-問合せ・差戻し事例対応表'!$B$2:$B$5000,'チェックポイント-問合せ・差戻し事例対応表'!$B$2:$B$5000,'チェックポイント-問合せ・差戻し事例対応表'!$I$2:$I$5000,'チェックポイント-問合せ・差戻し事例対応表'!$I$2:$I$5000)+('チェックポイント-問合せ・差戻し事例対応表'!$I$2:$I$5000=""))) -> 33 | I82: 114 | J82: =IFERROR(INDEX(レビュー指針!$D:$D,MATCH(I82,レビュー指針!$A:$A,0)),"") -> 成果物 | K82: =IFERROR(INDEX(レビュー指針!$E:$E,MATCH(I82,レビュー指針!$A:$A,0)),"") -> 1次レビュー | L82: =IFERROR(INDEX(レビュー指針!$H:$H,MATCH(I82,レビュー指針!$A:$A,0)),"") -> データソースと抽出条件（手順）の記録が成果物として提出されている | P82: Stage2精査 / データソースチェックへ整形 / 自主点検QA由来 / 件数29 / 要文言整備
A83: 188 | B83: 26 | C83: =IFERROR(INDEX(自主点検項目!$B:$B,MATCH(B83,自主点検項目!$A:$A,0)),"") -> 賞与引当金の計上確認 | D83: 共通 | E83: =IFERROR(INDEX(提出物!$D:$D,MATCH(D83,提出物!$A:$A,0)),"") | F83: 賞与引当金の見積金額の根拠資料（繰入額の計算資料）が提出されているか。 | G83: =COUNTIF('チェックポイント-問合せ・差戻し事例対応表'!$B:$B,A83) -> 9 | H83: =SUMPRODUCT(('チェックポイント-問合せ・差戻し事例対応表'!$B$2:$B$5000=A83)*('チェックポイント-問合せ・差戻し事例対応表'!$I$2:$I$5000<>"")/(COUNTIFS('チェックポイント-問合せ・差戻し事例対応表'!$B$2:$B$5000,'チェックポイント-問合せ・差戻し事例対応表'!$B$2:$B$5000,'チェックポイント-問合せ・差戻し事例対応表'!$I$2:$I$5000,'チェックポイント-問合せ・差戻し事例対応表'!$I$2:$I$5000)+('チェックポイント-問合せ・差戻し事例対応表'!$I$2:$I$5000=""))) -> 9 | I83: 117 | J83: =IFERROR(INDEX(レビュー指針!$D:$D,MATCH(I83,レビュー指針!$A:$A,0)),"") -> 根拠資料 | K83: =IFERROR(INDEX(レビュー指針!$E:$E,MATCH(I83,レビュー指針!$A:$A,0)),"") -> 1次レビュー | L83: =IFERROR(INDEX(レビュー指針!$H:$H,MATCH(I83,レビュー指針!$A:$A,0)),"") -> 賞与引当金が計上されている場合、見積金額の根拠資料が提出されている | P83: Stage2精査 / 根拠資料チェック / 自主点検QA由来 / 件数7 / 要文言整備
A84: 189 | B84: 26 | C84: =IFERROR(INDEX(自主点検項目!$B:$B,MATCH(B84,自主点検項目!$A:$A,0)),"") -> 賞与引当金の計上確認 | D84: 共通 | E84: =IFERROR(INDEX(提出物!$D:$D,MATCH(D84,提出物!$A:$A,0)),"") | F84: データソースと抽出条件（手順）の記録が成果物として提出されている | G84: =COUNTIF('チェックポイント-問合せ・差戻し事例対応表'!$B:$B,A84) -> 7 | H84: =SUMPRODUCT(('チェックポイント-問合せ・差戻し事例対応表'!$B$2:$B$5000=A84)*('チェックポイント-問合せ・差戻し事例対応表'!$I$2:$I$5000<>"")/(COUNTIFS('チェックポイント-問合せ・差戻し事例対応表'!$B$2:$B$5000,'チェックポイント-問合せ・差戻し事例対応表'!$B$2:$B$5000,'チェックポイント-問合せ・差戻し事例対応表'!$I$2:$I$5000,'チェックポイント-問合せ・差戻し事例対応表'!$I$2:$I$5000)+('チェックポイント-問合せ・差戻し事例対応表'!$I$2:$I$5000=""))) -> 6 | I84: 114 | J84: =IFERROR(INDEX(レビュー指針!$D:$D,MATCH(I84,レビュー指針!$A:$A,0)),"") -> 成果物 | K84: =IFERROR(INDEX(レビュー指針!$E:$E,MATCH(I84,レビュー指針!$A:$A,0)),"") -> 1次レビュー | L84: =IFERROR(INDEX(レビュー指針!$H:$H,MATCH(I84,レビュー指針!$A:$A,0)),"") -> データソースと抽出条件（手順）の記録が成果物として提出されている | P84: Stage2精査(裾野・要確認) / 自主点検QA由来 / 件数4 / 要文言整備
A85: 190 | B85: 26 | C85: =IFERROR(INDEX(自主点検項目!$B:$B,MATCH(B85,自主点検項目!$A:$A,0)),"") -> 賞与引当金の計上確認 | D85: 共通 | E85: =IFERROR(INDEX(提出物!$D:$D,MATCH(D85,提出物!$A:$A,0)),"") | F85: 賞与引当金繰入額（PL）、賞与引当金（BS）が試算表と一致することが確認できる | G85: =COUNTIF('チェックポイント-問合せ・差戻し事例対応表'!$B:$B,A85) -> 8 | H85: =SUMPRODUCT(('チェックポイント-問合せ・差戻し事例対応表'!$B$2:$B$5000=A85)*('チェックポイント-問合せ・差戻し事例対応表'!$I$2:$I$5000<>"")/(COUNTIFS('チェックポイント-問合せ・差戻し事例対応表'!$B$2:$B$5000,'チェックポイント-問合せ・差戻し事例対応表'!$B$2:$B$5000,'チェックポイント-問合せ・差戻し事例対応表'!$I$2:$I$5000,'チェックポイント-問合せ・差戻し事例対応表'!$I$2:$I$5000)+('チェックポイント-問合せ・差戻し事例対応表'!$I$2:$I$5000=""))) -> 8 | I85: 115 | J85: =IFERROR(INDEX(レビュー指針!$D:$D,MATCH(I85,レビュー指針!$A:$A,0)),"") -> 成果物 | K85: =IFERROR(INDEX(レビュー指針!$E:$E,MATCH(I85,レビュー指針!$A:$A,0)),"") -> 1次レビュー | L85: =IFERROR(INDEX(レビュー指針!$H:$H,MATCH(I85,レビュー指針!$A:$A,0)),"") -> 賞与引当金繰入額（PL）、賞与引当金（BS）が試算表と一致することが確認できる | P85: Stage2精査(裾野・要確認) / 自主点検QA由来 / 件数4 / 要文言整備
A86: 191 | B86: 26 | C86: =IFERROR(INDEX(自主点検項目!$B:$B,MATCH(B86,自主点検項目!$A:$A,0)),"") -> 賞与引当金の計上確認 | D86: 共通 | E86: =IFERROR(INDEX(提出物!$D:$D,MATCH(D86,提出物!$A:$A,0)),"") | F86: 賞与引当金が計上されていない場合、理由が記載されている | G86: =COUNTIF('チェックポイント-問合せ・差戻し事例対応表'!$B:$B,A86) -> 5 | H86: =SUMPRODUCT(('チェックポイント-問合せ・差戻し事例対応表'!$B$2:$B$5000=A86)*('チェックポイント-問合せ・差戻し事例対応表'!$I$2:$I$5000<>"")/(COUNTIFS('チェックポイント-問合せ・差戻し事例対応表'!$B$2:$B$5000,'チェックポイント-問合せ・差戻し事例対応表'!$B$2:$B$5000,'チェックポイント-問合せ・差戻し事例対応表'!$I$2:$I$5000,'チェックポイント-問合せ・差戻し事例対応表'!$I$2:$I$5000)+('チェックポイント-問合せ・差戻し事例対応表'!$I$2:$I$5000=""))) -> 5 | I86: 118 | J86: =IFERROR(INDEX(レビュー指針!$D:$D,MATCH(I86,レビュー指針!$A:$A,0)),"") -> 根拠資料 | K86: =IFERROR(INDEX(レビュー指針!$E:$E,MATCH(I86,レビュー指針!$A:$A,0)),"") -> 1次レビュー | L86: =IFERROR(INDEX(レビュー指針!$H:$H,MATCH(I86,レビュー指針!$A:$A,0)),"") -> 賞与引当金が計上されていない場合、理由が記載されている | P86: Stage2精査(裾野・要確認) / 自主点検QA由来 / 件数3 / 要文言整備
A87: 196 | B87: 28 | C87: =IFERROR(INDEX(自主点検項目!$B:$B,MATCH(B87,自主点検項目!$A:$A,0)),"") -> 財務分析 | D87: 共通 | E87: =IFERROR(INDEX(提出物!$D:$D,MATCH(D87,提出物!$A:$A,0)),"") | F87: No.28が対象外でも、連結PKGで大きな増減が検出された科目について増減理由が確認できるか。 | G87: =COUNTIF('チェックポイント-問合せ・差戻し事例対応表'!$B:$B,A87) -> 9 | H87: =SUMPRODUCT(('チェックポイント-問合せ・差戻し事例対応表'!$B$2:$B$5000=A87)*('チェックポイント-問合せ・差戻し事例対応表'!$I$2:$I$5000<>"")/(COUNTIFS('チェックポイント-問合せ・差戻し事例対応表'!$B$2:$B$5000,'チェックポイント-問合せ・差戻し事例対応表'!$B$2:$B$5000,'チェックポイント-問合せ・差戻し事例対応表'!$I$2:$I$5000,'チェックポイント-問合せ・差戻し事例対応表'!$I$2:$I$5000)+('チェックポイント-問合せ・差戻し事例対応表'!$I$2:$I$5000=""))) -> 9 | J87: =IFERROR(INDEX(レビュー指針!$D:$D,MATCH(I87,レビュー指針!$A:$A,0)),"") | K87: =IFERROR(INDEX(レビュー指針!$E:$E,MATCH(I87,レビュー指針!$A:$A,0)),"") | L87: =IFERROR(INDEX(レビュー指針!$H:$H,MATCH(I87,レビュー指針!$A:$A,0)),"") | P87: Stage2精査 / 項28は指針なし / 自主点検QA由来 / 件数9 / 要文言整備
A88: 197 | C88: =IFERROR(INDEX(自主点検項目!$B:$B,MATCH(B88,自主点検項目!$A:$A,0)),"") | D88: 共通 | E88: =IFERROR(INDEX(提出物!$D:$D,MATCH(D88,提出物!$A:$A,0)),"") | F88: 「12_工事案件の進捗率分析_嶋田工業」ではプロジェクト別に実際発生原価、進捗率が算定されています。一方「進行基準適用判断_嶋田工業」では工事番号別に工事実行予算、未成工事支出金、実施出来高が算定されています。どのプロジェクトがどの工事番号 | G88: =COUNTIF('チェックポイント-問合せ・差戻し事例対応表'!$B:$B,A88) -> 2 | H88: =SUMPRODUCT(('チェックポイント-問合せ・差戻し事例対応表'!$B$2:$B$5000=A88)*('チェックポイント-問合せ・差戻し事例対応表'!$I$2:$I$5000<>"")/(COUNTIFS('チェックポイント-問合せ・差戻し事例対応表'!$B$2:$B$5000,'チェックポイント-問合せ・差戻し事例対応表'!$B$2:$B$5000,'チェックポイント-問合せ・差戻し事例対応表'!$I$2:$I$5000,'チェックポイント-問合せ・差戻し事例対応表'!$I$2:$I$5000)+('チェックポイント-問合せ・差戻し事例対応表'!$I$2:$I$5000=""))) -> 2 | J88: =IFERROR(INDEX(レビュー指針!$D:$D,MATCH(I88,レビュー指針!$A:$A,0)),"") | K88: =IFERROR(INDEX(レビュー指針!$E:$E,MATCH(I88,レビュー指針!$A:$A,0)),"") | L88: =IFERROR(INDEX(レビュー指針!$H:$H,MATCH(I88,レビュー指針!$A:$A,0)),"") | P88: 監査QA由来 / 件数2 / 要文言整備
A89: 198 | B89: 4 | C89: =IFERROR(INDEX(自主点検項目!$B:$B,MATCH(B89,自主点検項目!$A:$A,0)),"") -> 滞留債権の分析 | D89: 15 | E89: =IFERROR(INDEX(提出物!$D:$D,MATCH(D89,提出物!$A:$A,0)),"") -> 売掛金明細・試算表の一致 | F89: （項目4 提出物15 その他個別事例・恒常的なCP化は要個別判断） | G89: =COUNTIF('チェックポイント-問合せ・差戻し事例対応表'!$B:$B,A89) -> 16 | H89: =SUMPRODUCT(('チェックポイント-問合せ・差戻し事例対応表'!$B$2:$B$5000=A89)*('チェックポイント-問合せ・差戻し事例対応表'!$I$2:$I$5000<>"")/(COUNTIFS('チェックポイント-問合せ・差戻し事例対応表'!$B$2:$B$5000,'チェックポイント-問合せ・差戻し事例対応表'!$B$2:$B$5000,'チェックポイント-問合せ・差戻し事例対応表'!$I$2:$I$5000,'チェックポイント-問合せ・差戻し事例対応表'!$I$2:$I$5000)+('チェックポイント-問合せ・差戻し事例対応表'!$I$2:$I$5000=""))) -> 13 | J89: =IFERROR(INDEX(レビュー指針!$D:$D,MATCH(I89,レビュー指針!$A:$A,0)),"") | K89: =IFERROR(INDEX(レビュー指針!$E:$E,MATCH(I89,レビュー指針!$A:$A,0)),"") | L89: =IFERROR(INDEX(レビュー指針!$H:$H,MATCH(I89,レビュー指針!$A:$A,0)),"") | P89: Stage2精査(裾野) / 一過性事例の残置バケツ
A90: 199 | B90: 4 | C90: =IFERROR(INDEX(自主点検項目!$B:$B,MATCH(B90,自主点検項目!$A:$A,0)),"") -> 滞留債権の分析 | D90: 17 | E90: =IFERROR(INDEX(提出物!$D:$D,MATCH(D90,提出物!$A:$A,0)),"") -> 外部証憑 | F90: （項目4 提出物17 その他個別事例・恒常的なCP化は要個別判断） | G90: =COUNTIF('チェックポイント-問合せ・差戻し事例対応表'!$B:$B,A90) -> 2 | H90: =SUMPRODUCT(('チェックポイント-問合せ・差戻し事例対応表'!$B$2:$B$5000=A90)*('チェックポイント-問合せ・差戻し事例対応表'!$I$2:$I$5000<>"")/(COUNTIFS('チェックポイント-問合せ・差戻し事例対応表'!$B$2:$B$5000,'チェックポイント-問合せ・差戻し事例対応表'!$B$2:$B$5000,'チェックポイント-問合せ・差戻し事例対応表'!$I$2:$I$5000,'チェックポイント-問合せ・差戻し事例対応表'!$I$2:$I$5000)+('チェックポイント-問合せ・差戻し事例対応表'!$I$2:$I$5000=""))) -> 2 | J90: =IFERROR(INDEX(レビュー指針!$D:$D,MATCH(I90,レビュー指針!$A:$A,0)),"") | K90: =IFERROR(INDEX(レビュー指針!$E:$E,MATCH(I90,レビュー指針!$A:$A,0)),"") | L90: =IFERROR(INDEX(レビュー指針!$H:$H,MATCH(I90,レビュー指針!$A:$A,0)),"") | P90: Stage2精査(裾野) / 一過性事例の残置バケツ
A91: 200 | B91: 4 | C91: =IFERROR(INDEX(自主点検項目!$B:$B,MATCH(B91,自主点検項目!$A:$A,0)),"") -> 滞留債権の分析 | D91: 共通 | E91: =IFERROR(INDEX(提出物!$D:$D,MATCH(D91,提出物!$A:$A,0)),"") | F91: （項目4 共通 その他個別事例・恒常的なCP化は要個別判断） | G91: =COUNTIF('チェックポイント-問合せ・差戻し事例対応表'!$B:$B,A91) -> 22 | H91: =SUMPRODUCT(('チェックポイント-問合せ・差戻し事例対応表'!$B$2:$B$5000=A91)*('チェックポイント-問合せ・差戻し事例対応表'!$I$2:$I$5000<>"")/(COUNTIFS('チェックポイント-問合せ・差戻し事例対応表'!$B$2:$B$5000,'チェックポイント-問合せ・差戻し事例対応表'!$B$2:$B$5000,'チェックポイント-問合せ・差戻し事例対応表'!$I$2:$I$5000,'チェックポイント-問合せ・差戻し事例対応表'!$I$2:$I$5000)+('チェックポイント-問合せ・差戻し事例対応表'!$I$2:$I$5000=""))) -> 19 | J91: =IFERROR(INDEX(レビュー指針!$D:$D,MATCH(I91,レビュー指針!$A:$A,0)),"") | K91: =IFERROR(INDEX(レビュー指針!$E:$E,MATCH(I91,レビュー指針!$A:$A,0)),"") | L91: =IFERROR(INDEX(レビュー指針!$H:$H,MATCH(I91,レビュー指針!$A:$A,0)),"") | P91: Stage2精査(裾野) / 一過性事例の残置バケツ
A92: 202 | B92: 5 | C92: =IFERROR(INDEX(自主点検項目!$B:$B,MATCH(B92,自主点検項目!$A:$A,0)),"") -> 異常取引の分析 | D92: 20 | E92: =IFERROR(INDEX(提出物!$D:$D,MATCH(D92,提出物!$A:$A,0)),"") -> データソース・抽出条件 | F92: （項目5 提出物20 その他個別事例・恒常的なCP化は要個別判断） | G92: =COUNTIF('チェックポイント-問合せ・差戻し事例対応表'!$B:$B,A92) -> 10 | H92: =SUMPRODUCT(('チェックポイント-問合せ・差戻し事例対応表'!$B$2:$B$5000=A92)*('チェックポイント-問合せ・差戻し事例対応表'!$I$2:$I$5000<>"")/(COUNTIFS('チェックポイント-問合せ・差戻し事例対応表'!$B$2:$B$5000,'チェックポイント-問合せ・差戻し事例対応表'!$B$2:$B$5000,'チェックポイント-問合せ・差戻し事例対応表'!$I$2:$I$5000,'チェックポイント-問合せ・差戻し事例対応表'!$I$2:$I$5000)+('チェックポイント-問合せ・差戻し事例対応表'!$I$2:$I$5000=""))) -> 10 | J92: =IFERROR(INDEX(レビュー指針!$D:$D,MATCH(I92,レビュー指針!$A:$A,0)),"") | K92: =IFERROR(INDEX(レビュー指針!$E:$E,MATCH(I92,レビュー指針!$A:$A,0)),"") | L92: =IFERROR(INDEX(レビュー指針!$H:$H,MATCH(I92,レビュー指針!$A:$A,0)),"") | P92: Stage2精査(裾野) / 一過性事例の残置バケツ
A93: 203 | B93: 5 | C93: =IFERROR(INDEX(自主点検項目!$B:$B,MATCH(B93,自主点検項目!$A:$A,0)),"") -> 異常取引の分析 | D93: 21 | E93: =IFERROR(INDEX(提出物!$D:$D,MATCH(D93,提出物!$A:$A,0)),"") -> マイナス取引の根拠資料 | F93: （項目5 提出物21 その他個別事例・恒常的なCP化は要個別判断） | G93: =COUNTIF('チェックポイント-問合せ・差戻し事例対応表'!$B:$B,A93) -> 3 | H93: =SUMPRODUCT(('チェックポイント-問合せ・差戻し事例対応表'!$B$2:$B$5000=A93)*('チェックポイント-問合せ・差戻し事例対応表'!$I$2:$I$5000<>"")/(COUNTIFS('チェックポイント-問合せ・差戻し事例対応表'!$B$2:$B$5000,'チェックポイント-問合せ・差戻し事例対応表'!$B$2:$B$5000,'チェックポイント-問合せ・差戻し事例対応表'!$I$2:$I$5000,'チェックポイント-問合せ・差戻し事例対応表'!$I$2:$I$5000)+('チェックポイント-問合せ・差戻し事例対応表'!$I$2:$I$5000=""))) -> 3 | J93: =IFERROR(INDEX(レビュー指針!$D:$D,MATCH(I93,レビュー指針!$A:$A,0)),"") | K93: =IFERROR(INDEX(レビュー指針!$E:$E,MATCH(I93,レビュー指針!$A:$A,0)),"") | L93: =IFERROR(INDEX(レビュー指針!$H:$H,MATCH(I93,レビュー指針!$A:$A,0)),"") | P93: Stage2精査(裾野) / 一過性事例の残置バケツ
A94: 204 | B94: 5 | C94: =IFERROR(INDEX(自主点検項目!$B:$B,MATCH(B94,自主点検項目!$A:$A,0)),"") -> 異常取引の分析 | D94: 共通 | E94: =IFERROR(INDEX(提出物!$D:$D,MATCH(D94,提出物!$A:$A,0)),"") | F94: （項目5 共通 その他個別事例・恒常的なCP化は要個別判断） | G94: =COUNTIF('チェックポイント-問合せ・差戻し事例対応表'!$B:$B,A94) -> 23 | H94: =SUMPRODUCT(('チェックポイント-問合せ・差戻し事例対応表'!$B$2:$B$5000=A94)*('チェックポイント-問合せ・差戻し事例対応表'!$I$2:$I$5000<>"")/(COUNTIFS('チェックポイント-問合せ・差戻し事例対応表'!$B$2:$B$5000,'チェックポイント-問合せ・差戻し事例対応表'!$B$2:$B$5000,'チェックポイント-問合せ・差戻し事例対応表'!$I$2:$I$5000,'チェックポイント-問合せ・差戻し事例対応表'!$I$2:$I$5000)+('チェックポイント-問合せ・差戻し事例対応表'!$I$2:$I$5000=""))) -> 22 | J94: =IFERROR(INDEX(レビュー指針!$D:$D,MATCH(I94,レビュー指針!$A:$A,0)),"") | K94: =IFERROR(INDEX(レビュー指針!$E:$E,MATCH(I94,レビュー指針!$A:$A,0)),"") | L94: =IFERROR(INDEX(レビュー指針!$H:$H,MATCH(I94,レビュー指針!$A:$A,0)),"") | P94: Stage2精査(裾野) / 一過性事例の残置バケツ
A95: 205 | B95: 6 | C95: =IFERROR(INDEX(自主点検項目!$B:$B,MATCH(B95,自主点検項目!$A:$A,0)),"") -> 売上の期末変動分析 | D95: 22 | E95: =IFERROR(INDEX(提出物!$D:$D,MATCH(D95,提出物!$A:$A,0)),"") -> 月次の売上・粗利推移データ | F95: （項目6 提出物22 その他個別事例・恒常的なCP化は要個別判断） | G95: =COUNTIF('チェックポイント-問合せ・差戻し事例対応表'!$B:$B,A95) -> 19 | H95: =SUMPRODUCT(('チェックポイント-問合せ・差戻し事例対応表'!$B$2:$B$5000=A95)*('チェックポイント-問合せ・差戻し事例対応表'!$I$2:$I$5000<>"")/(COUNTIFS('チェックポイント-問合せ・差戻し事例対応表'!$B$2:$B$5000,'チェックポイント-問合せ・差戻し事例対応表'!$B$2:$B$5000,'チェックポイント-問合せ・差戻し事例対応表'!$I$2:$I$5000,'チェックポイント-問合せ・差戻し事例対応表'!$I$2:$I$5000)+('チェックポイント-問合せ・差戻し事例対応表'!$I$2:$I$5000=""))) -> 17 | J95: =IFERROR(INDEX(レビュー指針!$D:$D,MATCH(I95,レビュー指針!$A:$A,0)),"") | K95: =IFERROR(INDEX(レビュー指針!$E:$E,MATCH(I95,レビュー指針!$A:$A,0)),"") | L95: =IFERROR(INDEX(レビュー指針!$H:$H,MATCH(I95,レビュー指針!$A:$A,0)),"") | P95: Stage2精査(裾野) / 一過性事例の残置バケツ
A96: 206 | B96: 6 | C96: =IFERROR(INDEX(自主点検項目!$B:$B,MATCH(B96,自主点検項目!$A:$A,0)),"") -> 売上の期末変動分析 | D96: 23 | E96: =IFERROR(INDEX(提出物!$D:$D,MATCH(D96,提出物!$A:$A,0)),"") -> データソース・抽出条件 | F96: （項目6 提出物23 その他個別事例・恒常的なCP化は要個別判断） | G96: =COUNTIF('チェックポイント-問合せ・差戻し事例対応表'!$B:$B,A96) -> 9 | H96: =SUMPRODUCT(('チェックポイント-問合せ・差戻し事例対応表'!$B$2:$B$5000=A96)*('チェックポイント-問合せ・差戻し事例対応表'!$I$2:$I$5000<>"")/(COUNTIFS('チェックポイント-問合せ・差戻し事例対応表'!$B$2:$B$5000,'チェックポイント-問合せ・差戻し事例対応表'!$B$2:$B$5000,'チェックポイント-問合せ・差戻し事例対応表'!$I$2:$I$5000,'チェックポイント-問合せ・差戻し事例対応表'!$I$2:$I$5000)+('チェックポイント-問合せ・差戻し事例対応表'!$I$2:$I$5000=""))) -> 9 | J96: =IFERROR(INDEX(レビュー指針!$D:$D,MATCH(I96,レビュー指針!$A:$A,0)),"") | K96: =IFERROR(INDEX(レビュー指針!$E:$E,MATCH(I96,レビュー指針!$A:$A,0)),"") | L96: =IFERROR(INDEX(レビュー指針!$H:$H,MATCH(I96,レビュー指針!$A:$A,0)),"") | P96: Stage2精査(裾野) / 一過性事例の残置バケツ
A97: 207 | B97: 6 | C97: =IFERROR(INDEX(自主点検項目!$B:$B,MATCH(B97,自主点検項目!$A:$A,0)),"") -> 売上の期末変動分析 | D97: 共通 | E97: =IFERROR(INDEX(提出物!$D:$D,MATCH(D97,提出物!$A:$A,0)),"") | F97: （項目6 共通 その他個別事例・恒常的なCP化は要個別判断） | G97: =COUNTIF('チェックポイント-問合せ・差戻し事例対応表'!$B:$B,A97) -> 6 | H97: =SUMPRODUCT(('チェックポイント-問合せ・差戻し事例対応表'!$B$2:$B$5000=A97)*('チェックポイント-問合せ・差戻し事例対応表'!$I$2:$I$5000<>"")/(COUNTIFS('チェックポイント-問合せ・差戻し事例対応表'!$B$2:$B$5000,'チェックポイント-問合せ・差戻し事例対応表'!$B$2:$B$5000,'チェックポイント-問合せ・差戻し事例対応表'!$I$2:$I$5000,'チェックポイント-問合せ・差戻し事例対応表'!$I$2:$I$5000)+('チェックポイント-問合せ・差戻し事例対応表'!$I$2:$I$5000=""))) -> 6 | J97: =IFERROR(INDEX(レビュー指針!$D:$D,MATCH(I97,レビュー指針!$A:$A,0)),"") | K97: =IFERROR(INDEX(レビュー指針!$E:$E,MATCH(I97,レビュー指針!$A:$A,0)),"") | L97: =IFERROR(INDEX(レビュー指針!$H:$H,MATCH(I97,レビュー指針!$A:$A,0)),"") | P97: Stage2精査(裾野) / 一過性事例の残置バケツ
A98: 208 | B98: 8 | C98: =IFERROR(INDEX(自主点検項目!$B:$B,MATCH(B98,自主点検項目!$A:$A,0)),"") -> 売上のカットオフテスト | D98: 28 | E98: =IFERROR(INDEX(提出物!$D:$D,MATCH(D98,提出物!$A:$A,0)),"") -> 売上明細データ | F98: （項目8 提出物28 その他個別事例・恒常的なCP化は要個別判断） | G98: =COUNTIF('チェックポイント-問合せ・差戻し事例対応表'!$B:$B,A98) -> 3 | H98: =SUMPRODUCT(('チェックポイント-問合せ・差戻し事例対応表'!$B$2:$B$5000=A98)*('チェックポイント-問合せ・差戻し事例対応表'!$I$2:$I$5000<>"")/(COUNTIFS('チェックポイント-問合せ・差戻し事例対応表'!$B$2:$B$5000,'チェックポイント-問合せ・差戻し事例対応表'!$B$2:$B$5000,'チェックポイント-問合せ・差戻し事例対応表'!$I$2:$I$5000,'チェックポイント-問合せ・差戻し事例対応表'!$I$2:$I$5000)+('チェックポイント-問合せ・差戻し事例対応表'!$I$2:$I$5000=""))) -> 3 | J98: =IFERROR(INDEX(レビュー指針!$D:$D,MATCH(I98,レビュー指針!$A:$A,0)),"") | K98: =IFERROR(INDEX(レビュー指針!$E:$E,MATCH(I98,レビュー指針!$A:$A,0)),"") | L98: =IFERROR(INDEX(レビュー指針!$H:$H,MATCH(I98,レビュー指針!$A:$A,0)),"") | P98: Stage2精査(裾野) / 一過性事例の残置バケツ
A99: 209 | B99: 8 | C99: =IFERROR(INDEX(自主点検項目!$B:$B,MATCH(B99,自主点検項目!$A:$A,0)),"") -> 売上のカットオフテスト | D99: 29 | E99: =IFERROR(INDEX(提出物!$D:$D,MATCH(D99,提出物!$A:$A,0)),"") -> データソース・抽出条件 | F99: （項目8 提出物29 その他個別事例・恒常的なCP化は要個別判断） | G99: =COUNTIF('チェックポイント-問合せ・差戻し事例対応表'!$B:$B,A99) -> 2 | H99: =SUMPRODUCT(('チェックポイント-問合せ・差戻し事例対応表'!$B$2:$B$5000=A99)*('チェックポイント-問合せ・差戻し事例対応表'!$I$2:$I$5000<>"")/(COUNTIFS('チェックポイント-問合せ・差戻し事例対応表'!$B$2:$B$5000,'チェックポイント-問合せ・差戻し事例対応表'!$B$2:$B$5000,'チェックポイント-問合せ・差戻し事例対応表'!$I$2:$I$5000,'チェックポイント-問合せ・差戻し事例対応表'!$I$2:$I$5000)+('チェックポイント-問合せ・差戻し事例対応表'!$I$2:$I$5000=""))) -> 2 | J99: =IFERROR(INDEX(レビュー指針!$D:$D,MATCH(I99,レビュー指針!$A:$A,0)),"") | K99: =IFERROR(INDEX(レビュー指針!$E:$E,MATCH(I99,レビュー指針!$A:$A,0)),"") | L99: =IFERROR(INDEX(レビュー指針!$H:$H,MATCH(I99,レビュー指針!$A:$A,0)),"") | P99: Stage2精査(裾野) / 一過性事例の残置バケツ
A100: 210 | B100: 8 | C100: =IFERROR(INDEX(自主点検項目!$B:$B,MATCH(B100,自主点検項目!$A:$A,0)),"") -> 売上のカットオフテスト | D100: 30 | E100: =IFERROR(INDEX(提出物!$D:$D,MATCH(D100,提出物!$A:$A,0)),"") -> 収益認識の根拠資料 | F100: （項目8 提出物30 その他個別事例・恒常的なCP化は要個別判断） | G100: =COUNTIF('チェックポイント-問合せ・差戻し事例対応表'!$B:$B,A100) -> 6 | H100: =SUMPRODUCT(('チェックポイント-問合せ・差戻し事例対応表'!$B$2:$B$5000=A100)*('チェックポイント-問合せ・差戻し事例対応表'!$I$2:$I$5000<>"")/(COUNTIFS('チェックポイント-問合せ・差戻し事例対応表'!$B$2:$B$5000,'チェックポイント-問合せ・差戻し事例対応表'!$B$2:$B$5000,'チェックポイント-問合せ・差戻し事例対応表'!$I$2:$I$5000,'チェックポイント-問合せ・差戻し事例対応表'!$I$2:$I$5000)+('チェックポイント-問合せ・差戻し事例対応表'!$I$2:$I$5000=""))) -> 6 | J100: =IFERROR(INDEX(レビュー指針!$D:$D,MATCH(I100,レビュー指針!$A:$A,0)),"") | K100: =IFERROR(INDEX(レビュー指針!$E:$E,MATCH(I100,レビュー指針!$A:$A,0)),"") | L100: =IFERROR(INDEX(レビュー指針!$H:$H,MATCH(I100,レビュー指針!$A:$A,0)),"") | P100: Stage2精査(裾野) / 一過性事例の残置バケツ
...

Sheet 問合せ・差戻し事例
A1: No | B1: ソース | C1: 元No | D1: 会社管理番号 | E1: 会社名 | F1: ユニット | G1: 自主点検項目No | H1: 問合せ事項 | I1: CP化判定
A2: 1 | B2: 自主点検QA | C2: 23-1 | D2: 230103 | E2: =IFERROR(INDEX(会社マスタ!$B:$B,MATCH(D2,会社マスタ!$A:$A,0)),"") -> 竹中運輸(株) | F2: =IFERROR(INDEX(会社マスタ!$C:$C,MATCH(D2,会社マスタ!$A:$A,0)),"") -> エア・ウォーター東日本(株) | G2: 26 | H2: ・賞与引当金を計上する際に、繰入金額の計算資料の送付をお願いします | I2: 未判定
A3: 2 | B3: 自主点検QA | C3: 23-2 | D3: 230700 | E3: =IFERROR(INDEX(会社マスタ!$B:$B,MATCH(D3,会社マスタ!$A:$A,0)),"") -> 亀山液酸(株) | F3: =IFERROR(INDEX(会社マスタ!$C:$C,MATCH(D3,会社マスタ!$A:$A,0)),"") -> エア・ウォーター東日本(株) | G3: 26 | H3: ・賞与引当金を計上する際に、繰入金額の計算資料の送付をお願いします | I3: 未判定
A4: 3 | B4: 自主点検QA | C4: 23-3 | D4: 230900 | E4: =IFERROR(INDEX(会社マスタ!$B:$B,MATCH(D4,会社マスタ!$A:$A,0)),"") -> 静岡液酸(株) | F4: =IFERROR(INDEX(会社マスタ!$C:$C,MATCH(D4,会社マスタ!$A:$A,0)),"") -> エア・ウォーター東日本(株) | G4: 26 | H4: ・賞与引当金を計上する際に、繰入金額の計算資料の送付をお願いします | I4: 未判定
A5: 4 | B5: 自主点検QA | C5: 23-4 | D5: 231000 | E5: =IFERROR(INDEX(会社マスタ!$B:$B,MATCH(D5,会社マスタ!$A:$A,0)),"") -> 東海液酸(株) | F5: =IFERROR(INDEX(会社マスタ!$C:$C,MATCH(D5,会社マスタ!$A:$A,0)),"") -> エア・ウォーター東日本(株) | G5: 26 | H5: ・賞与引当金を計上する際に、繰入金額の計算資料の送付をお願いします | I5: 未判定
A6: 5 | B6: 自主点検QA | C6: 23-5 | D6: 231400 | E6: =IFERROR(INDEX(会社マスタ!$B:$B,MATCH(D6,会社マスタ!$A:$A,0)),"") -> (株)元気 | F6: =IFERROR(INDEX(会社マスタ!$C:$C,MATCH(D6,会社マスタ!$A:$A,0)),"") -> エア・ウォーター東日本(株) | G6: 26 | H6: ・網羅性が確認できる資料（試算表との一致確認）の送付をお願いします ・賞与引当金を計上する際に、繰入金額の計算資料の送付をお願いします | I6: 未判定
A7: 6 | B7: 自主点検QA | C7: 23-6 | D7: 230900 | E7: =IFERROR(INDEX(会社マスタ!$B:$B,MATCH(D7,会社マスタ!$A:$A,0)),"") -> 静岡液酸(株) | F7: =IFERROR(INDEX(会社マスタ!$C:$C,MATCH(D7,会社マスタ!$A:$A,0)),"") -> エア・ウォーター東日本(株) | G7: 8 | H7: ・1,000万円以上の売上の根拠として契約書を提出いただいておりますが単価のみの記載のため請求額の根拠資料となる数量が分かる資料の送付をお願いします | I7: 未判定
A8: 7 | B8: 自主点検QA | C8: 23-7 | D8: 231000 | E8: =IFERROR(INDEX(会社マスタ!$B:$B,MATCH(D8,会社マスタ!$A:$A,0)),"") -> 東海液酸(株) | F8: =IFERROR(INDEX(会社マスタ!$C:$C,MATCH(D8,会社マスタ!$A:$A,0)),"") -> エア・ウォーター東日本(株) | G8: 8 | H8: ・網羅性が確認できる資料（試算表との一致確認）の送付をお願いします ・1,000万円以上の売上が計上されているため、該当取引について収益認識の根拠となる資料の送付をお願いします | I8: 未判定
A9: 8 | B9: 自主点検QA | C9: 23-8 | D9: 230101 | E9: =IFERROR(INDEX(会社マスタ!$B:$B,MATCH(D9,会社マスタ!$A:$A,0)),"") -> (株)環境技術センター | F9: =IFERROR(INDEX(会社マスタ!$C:$C,MATCH(D9,会社マスタ!$A:$A,0)),"") -> エア・ウォーター東日本(株) | G9: 5 | H9: ・データソース及び抽出条件が分かる資料（抽出する際の条件を記載した画面スクショなど）の提出をお願い出来ますでしょうか。 ・マイナスの売上計上の妥当性を確認するため、全てのエントリーに対してマイナス売上理由のコメント及び、各マイナスの売上計上に対してそこまで至った経緯・取り消しの妥当性を裏付けるの証跡の提出をお願い出来ますでしょうか。 | I9: 未判定
A10: 9 | B10: 自主点検QA | C10: 23-9 | D10: 230103 | E10: =IFERROR(INDEX(会社マスタ!$B:$B,MATCH(D10,会社マスタ!$A:$A,0)),"") -> 竹中運輸(株) | F10: =IFERROR(INDEX(会社マスタ!$C:$C,MATCH(D10,会社マスタ!$A:$A,0)),"") -> エア・ウォーター東日本(株) | G10: 5 | H10: ・データソース及び抽出条件が分かる資料（抽出する際の条件を記載した画面スクショなど）の提出をお願い出来ますでしょうか。 | I10: 未判定
A11: 10 | B11: 自主点検QA | C11: 23-10 | D11: 230700 | E11: =IFERROR(INDEX(会社マスタ!$B:$B,MATCH(D11,会社マスタ!$A:$A,0)),"") -> 亀山液酸(株) | F11: =IFERROR(INDEX(会社マスタ!$C:$C,MATCH(D11,会社マスタ!$A:$A,0)),"") -> エア・ウォーター東日本(株) | G11: 5 | H11: ・網羅性及び売上伝票/明細と試算表の整合性を確認するため、25年4月~26年3月の全ての売上明細（マイナス含む）の提出をお願い出来ますでしょうか ・マイナスの売上計上の妥当性を確認するため、全てのエントリーに対してマイナス売上理由のコメント及び、各マイナスの売上計上に対してそこまで至った経緯・取り消しの妥当性を裏付けるの証跡の提出をお願い出来ますでしょうか。 | I11: 未判定
A12: 11 | B12: 自主点検QA | C12: 23-11 | D12: 230900 | E12: =IFERROR(INDEX(会社マスタ!$B:$B,MATCH(D12,会社マスタ!$A:$A,0)),"") -> 静岡液酸(株) | F12: =IFERROR(INDEX(会社マスタ!$C:$C,MATCH(D12,会社マスタ!$A:$A,0)),"") -> エア・ウォーター東日本(株) | G12: 5 | H12: ・網羅性及び売上伝票/明細と試算表の整合性を確認するため、25年4月~26年3月の全ての売上明細（マイナス含む）の提出をお願い出来ますでしょうか ・マイナスの売上計上の妥当性を確認するため、全てのエントリーに対してマイナス売上理由のコメント及び、各マイナスの売上計上に対してそこまで至った経緯・取り消しの妥当性を裏付けるの証跡の提出をお願い出来ますでしょうか。 | I12: 未判定
A13: 12 | B13: 自主点検QA | C13: 23-12 | D13: 231000 | E13: =IFERROR(INDEX(会社マスタ!$B:$B,MATCH(D13,会社マスタ!$A:$A,0)),"") -> 東海液酸(株) | F13: =IFERROR(INDEX(会社マスタ!$C:$C,MATCH(D13,会社マスタ!$A:$A,0)),"") -> エア・ウォーター東日本(株) | G13: 5 | H13: ・網羅性及び売上伝票/明細と試算表の整合性を確認するため、25年4月~26年3月の全ての売上明細（マイナス含む）の提出をお願い出来ますでしょうか ・マイナスの売上計上の妥当性を確認するため、全てのエントリーに対してマイナス売上理由のコメント及び、各マイナスの売上計上に対してそこまで至った経緯・取り消しの妥当性を裏付けるの証跡の提出をお願い出来ますでしょうか。 | I13: 未判定
... A86: 85 | B86: 自主点検QA | C86: 23-85 | D86: 230103 | E86: =IFERROR(INDEX(会社マスタ!$B:$B,MATCH(D86,会社マスタ!$A:$A,0)),"") -> 竹中運輸(株) | F86: =IFERROR(INDEX(会社マスタ!$C:$C,MATCH(D86,会社マスタ!$A:$A,0)),"") -> エア・ウォーター東日本(株) | G86: 8 | H86: ・データソース及び抽出条件が分かる資料（画面コピーなど）の提出してください ・網羅性が確認できる資料（試算表との一致確認）の提出してください | I86: 未判定
A87: 86 | B87: 自主点検QA | C87: 23-86 | D87: 230300 | E87: =IFERROR(INDEX(会社マスタ!$B:$B,MATCH(D87,会社マスタ!$A:$A,0)),"") -> エア・ウォーター東日本メディエス(株) | F87: =IFERROR(INDEX(会社マスタ!$C:$C,MATCH(D87,会社マスタ!$A:$A,0)),"") -> エア・ウォーター東日本(株) | G87: 5 | I87: 未判定
A88: 87 | B88: 自主点検QA | C88: 23-87 | D88: 230200 | E88: =IFERROR(INDEX(会社マスタ!$B:$B,MATCH(D88,会社マスタ!$A:$A,0)),"") -> エア・ウォーター・スマイル(株) | F88: =IFERROR(INDEX(会社マスタ!$C:$C,MATCH(D88,会社マスタ!$A:$A,0)),"") -> エア・ウォーター東日本(株) | G88: 8 | H88: ・データソース及び抽出条件が分かる資料（画面コピーなど）の提出してください ・網羅性が確認できる資料（試算表との一致確認）の提出してください ・全ての明細に対し、売上計上の妥当性（収益認識基準を満たしているか）を検討したことがわかるよう、コメントを記載してください ・10百万円以上の取引について、根拠資料（数量、単価、計上日の3点が確認できる根拠を具備しているもの）の提出してください | I88: 未判定
A89: 88 | B89: 自主点検QA | C89: 23-88 | D89: 230102 | E89: =IFERROR(INDEX(会社マスタ!$B:$B,MATCH(D89,会社マスタ!$A:$A,0)),"") -> (株)関茂助商店 | F89: =IFERROR(INDEX(会社マスタ!$C:$C,MATCH(D89,会社マスタ!$A:$A,0)),"") -> エア・ウォーター東日本(株) | G89: 5 | H89: ・データソース及び抽出条件が分かる資料（画面コピーなど）の送付をお願いします | I89: 未判定
A90: 89 | B90: 自主点検QA | C90: 23-89 | D90: 230600 | E90: =IFERROR(INDEX(会社マスタ!$B:$B,MATCH(D90,会社マスタ!$A:$A,0)),"") -> (株)大森器械店 | F90: =IFERROR(INDEX(会社マスタ!$C:$C,MATCH(D90,会社マスタ!$A:$A,0)),"") -> エア・ウォーター東日本(株) | G90: 8 | H90: ・10百万円以上の2件については、収益計上の妥当性の検証を終えました。ただ、全ての売上について、売上計上の妥当性（収益認識基準を満たしているか）を検討したコメントを付すことが求められていますのでお願いいたします。 | I90: 未判定
A91: 90 | B91: 自主点検QA | C91: 23-90 | D91: 230000 | E91: =IFERROR(INDEX(会社マスタ!$B:$B,MATCH(D91,会社マスタ!$A:$A,0)),"") -> エア・ウォーター東日本(株) | F91: =IFERROR(INDEX(会社マスタ!$C:$C,MATCH(D91,会社マスタ!$A:$A,0)),"") -> エア・ウォーター東日本(株) | G91: 19 | H91: 貴社親会社が作成した自主点検の説明資料によると、確認方法（作業イメージ）は以下の通りです。 １．2026年4月に費用計上された仕訳の明細データを出⼒し、明細データの合計と試算表の⾦額が一致することを確かめる。 ２．仕訳明細データの摘要欄等から、2026年3月に計上すべき費用の有無を確認する。 ３．2026年4月に受領した請求書から、2026年3月分として計上すべき取引がないかを確かめる。 ４．2026年3月分として計上すべき費用について、根拠資料を整理し、会計処理の顛末を記載する。 作業いただいた元帳は締め途中のものと存じますが、元帳と試算表が一致するように出力をお願いいたします。 難しいようでしたら、今時点の元帳と試算表を同時に出力いただき、一致を確認の上で検討をお願いできればと思います。 また、3月とコメントいただいておりますが、本来は3月で計上すべき費用だったのか、それとも4月計上でOKなのかを判断した理由（確認方法）も併記いただきたく存じます。 なお、上記4月の取引全てではなく、何らかの基準で一部を抽出したうえで確認する場合は、その抽出基準も明記願います。 | I91: 未判定
A92: 91 | B92: 自主点検QA | C92: 23-91 | D92: 230600 | E92: =IFERROR(INDEX(会社マスタ!$B:$B,MATCH(D92,会社マスタ!$A:$A,0)),"") -> (株)大森器械店 | F92: =IFERROR(INDEX(会社マスタ!$C:$C,MATCH(D92,会社マスタ!$A:$A,0)),"") -> エア・ウォーター東日本(株) | G92: 26 | H92: 当リストのNo66について資料のご提出ありがとうございます。 追加のご依頼となり恐縮ですが以下のご対応をお願いできますでしょうか。 ・賞与引当金の計算根拠：2026年6月の支払い見込みをもとに計上しているかと存じますが、当該支払い見込みはどのように算定しているのでしょうか（例えば、直近の実績等を鑑みて算定など）。 ・取り崩し時の支払証跡（2025年6月支払、2025年12月支払）として、三菱UFJ銀行の出金明細をご提出いただきましたが、「26_賞与引当金の計上根拠資料、支払額比較_成果物イメージ」に記載いただいた数値と差異があるかと存じます。お手数をおかけしますが当該差異が分かる資料を合わせてご提出いただけますでしょうか。 | I92: 未判定
A93: 92 | B93: 自主点検QA | C93: 23-92 | D93: 230200 | E93: =IFERROR(INDEX(会社マスタ!$B:$B,MATCH(D93,会社マスタ!$A:$A,0)),"") -> エア・ウォーター・スマイル(株) | F93: =IFERROR(INDEX(会社マスタ!$C:$C,MATCH(D93,会社マスタ!$A:$A,0)),"") -> エア・ウォーター東日本(株) | G93: 26 | H93: ・データソース及び抽出条件が分かる資料（画面コピーなど）の提出してください | I93: 未判定
A94: 93 | B94: 自主点検QA | C94: 23-93 | D94: 230300 | E94: =IFERROR(INDEX(会社マスタ!$B:$B,MATCH(D94,会社マスタ!$A:$A,0)),"") -> エア・ウォーター東日本メディエス(株) | F94: =IFERROR(INDEX(会社マスタ!$C:$C,MATCH(D94,会社マスタ!$A:$A,0)),"") -> エア・ウォーター東日本(株) | G94: 4 | H94: ・データソース及び抽出条件が分かる資料（画面コピーなど）の提出してください | I94: 未判定
A95: 94 | B95: 自主点検QA | C95: 23-94 | D95: 230400 | E95: =IFERROR(INDEX(会社マスタ!$B:$B,MATCH(D95,会社マスタ!$A:$A,0)),"") -> エア・ウォーター・ミライ(株) | F95: =IFERROR(INDEX(会社マスタ!$C:$C,MATCH(D95,会社マスタ!$A:$A,0)),"") -> エア・ウォーター東日本(株) | G95: 5 | H95: ・データソース及び抽出条件が分かる資料（画面コピーなど）の送付をお願いします ・網羅性及び売上伝票/明細との整合性を確認するため、25年4月~26年3月の全ての売上明細（マイナス含む）の提出してください ・試算表の提出してください | I95: 未判定
A96: 95 | B96: 自主点検QA | C96: 23-95 | D96: 230101 | E96: =IFERROR(INDEX(会社マスタ!$B:$B,MATCH(D96,会社マスタ!$A:$A,0)),"") -> (株)環境技術センター | F96: =IFERROR(INDEX(会社マスタ!$C:$C,MATCH(D96,会社マスタ!$A:$A,0)),"") -> エア・ウォーター東日本(株) | G96: 19 | H96: ・データソース及び抽出条件が分かる資料（画面コピーなど）の提出してください ・網羅性が確認できる資料（試算表との一致確認）の提出してください | I96: 未判定
A97: 96 | B97: 自主点検QA | C97: 23-96 | D97: 230301 | E97: =IFERROR(INDEX(会社マスタ!$B:$B,MATCH(D97,会社マスタ!$A:$A,0)),"") | F97: =IFERROR(INDEX(会社マスタ!$C:$C,MATCH(D97,会社マスタ!$A:$A,0)),"") | G97: 8 | H97: ・データソース及び抽出条件が分かる資料（画面コピーなど）の提出してください ・網羅性が確認できる資料（試算表との一致確認）の提出してください ・全ての明細に対し、売上計上の妥当性（収益認識基準を満たしているか）を検討したことがわかるよう、コメントを記載してください ・10百万円以上の取引について、根拠資料（数量、単価、計上日の3点が確認できる根拠を具備しているもの）の提出してください | I97: 未判定
A98: 97 | B98: 自主点検QA | C98: 23-97 | D98: 230102 | E98: =IFERROR(INDEX(会社マスタ!$B:$B,MATCH(D98,会社マスタ!$A:$A,0)),"") -> (株)関茂助商店 | F98: =IFERROR(INDEX(会社マスタ!$C:$C,MATCH(D98,会社マスタ!$A:$A,0)),"") -> エア・ウォーター東日本(株) | G98: 26 | H98: ・データソース及び抽出条件が分かる資料（画面コピーなど）の提出してください ・網羅性が確認できる資料（試算表との一致確認）の送付をお願いします | I98: 未判定
A99: 98 | B99: 自主点検QA | C99: 23-98 | D99: 230300 | E99: =IFERROR(INDEX(会社マスタ!$B:$B,MATCH(D99,会社マスタ!$A:$A,0)),"") -> エア・ウォーター東日本メディエス(株) | F99: =IFERROR(INDEX(会社マスタ!$C:$C,MATCH(D99,会社マスタ!$A:$A,0)),"") -> エア・ウォーター東日本(株) | G99: 26 | H99: ・データソース及び抽出条件が分かる資料（画面コピーなど）の提出してください | I99: 未判定
... A582: 581 | B582: 自主点検QA | C582: 【使-210 | D582: 100204 | E582: =IFERROR(INDEX(会社マスタ!$B:$B,MATCH(D582,会社マスタ!$A:$A,0)),"") -> (株)デンタルフィット | F582: =IFERROR(INDEX(会社マスタ!$C:$C,MATCH(D582,会社マスタ!$A:$A,0)),"") -> デンタルケアユニット | G582: 4 | H582: No79ご修正・提出ありがとうございます。 別のユニットのフォルダに格納されおりますため、移動の程お願いします。 ↓格納されている場所 https://airwatero365.sharepoint.com/sites/Guest_AW2026316/Shared%20Documents/Forms/AllItems.aspx?id=%2Fsites%2FGuest%5FAW2026316%2FShared%20Documents%2F01%5F%E5%80%8B%E7%A4%BE%E5%88%A5%E3%83%95%E3%82%A9%E3%83%AB%E3%83%80%EF%BC%88%E3%82%B5%E3%83%9D%E3%83%BC%E3%83%88%EF%BC%89%2F07%5F%E5%9C%A8%E5%AE%85%E3%83%98%E3%83%AB%E3%82%B9%E3%82%B1%E3%82%A2%E3%83%A6%E3%83%8B%E3%83%83%E3%83%88%2F070201%5F%E6%B5%99%E6%B1%9F%E5%B7%9D%E6%9C%AC%E5%8D%AB%E7%94%9F%E6%9D%90%E6%96%99%E6%9C%89%E9%99%90%E5%85%AC%E5%8F%B8%2F10%5Fself%2Dinspection%2F04%5F%E6%BB%9E%E7%95%99%E5%82%B5%E6%A8%A9%28Review%20of%20Overdue%20Receivables%29%2F01%5F%E4%BC%9A%E7%A4%BE%E6%8F%90%E5%87%BA%E8%B3%87%E6%96%99%28Company%2DSubmitted%20Materials%29%2F01%5F%E6%88%90%E6%9E%9C%E7%89%A9%28Deliverables%29%2F02%5F%E4%B8%80%E6%AC%A1%E3%83%AC%E3%83%93%E3%83%A5%E3%83%BC%28First%20review%29&viewid=ee2603a6%2D4932%2D4a94%2D9d46%2D0553af612636&csf=1&ovuser=36da45f1%2Ddd2c%2D4d1f%2Daf13%2D5abe46b99921%2Ckohei%2Eshimada%40tohmatsu%2Eco%2Ejp&OR=Teams%2DHL&CT=1778551640482&clickparams=eyJBcHBOYW1lIjoiVGVhbXMtRGVza3RvcCIsIkFwcFZlcnNpb24iOiI0OS8yNjAyMjcwNDIxNSIsIkhhc0ZlZGVyYXRlZFVzZXIiOmZhbHNlfQ%3D%3D&CID=d2c112a2%2Da0be%2D5000%2D95ba%2Db5f2b5432ef7&cidOR=SPO&FolderCTID=0x0120000227B1927A958D47BED941039F8DA0E8 | I582: 未判定
A583: 582 | B583: 自主点検QA | C583: 【使-211 | E583: =IFERROR(INDEX(会社マスタ!$B:$B,MATCH(D583,会社マスタ!$A:$A,0)),"") | F583: =IFERROR(INDEX(会社マスタ!$C:$C,MATCH(D583,会社マスタ!$A:$A,0)),"") | I583: 未判定
A584: 583 | B584: 自主点検QA | C584: 【使-212 | D584: 100220 | E584: =IFERROR(INDEX(会社マスタ!$B:$B,MATCH(D584,会社マスタ!$A:$A,0)),"") -> (株)グローバルナイン | F584: =IFERROR(INDEX(会社マスタ!$C:$C,MATCH(D584,会社マスタ!$A:$A,0)),"") -> デンタルケアユニット | G584: 18 | H584: ・3月のカード手数料の増加要因として、「3月カード手数料1,816千円」とございます。こちら、3月のみ他の月度と比較して金額が大きく生じている理由をご記載いただけませんでしょうか。また、当該カード手数料の請求書もあわせてご提出いただけますでしょうか。 ・ページ下部の「From 試算表」での販管費金額が、ご提供いただいております試算表の金額と大きく乖離しております（明細合計が正しいように見受けられます）。恐れ入りますが、試算表との合計金額での一致を確かめるため、金額の更新をお願いいたします。 | I584: 未判定
A585: 584 | B585: 自主点検QA | C585: 【使-213 | D585: 100213 | E585: =IFERROR(INDEX(会社マスタ!$B:$B,MATCH(D585,会社マスタ!$A:$A,0)),"") -> (株)TDS | F585: =IFERROR(INDEX(会社マスタ!$C:$C,MATCH(D585,会社マスタ!$A:$A,0)),"") -> デンタルケアユニット | G585: 5 | H585: フォローアップ ・No.131のQA事項の③④に関してその後状況いかがでしょうか。お忙しい中とは存じますが対応可能になり次第対応いただきますようお願いいたします。 | I585: 未判定
A586: 585 | B586: 自主点検QA | C586: 08-1 | D586: 80400 | E586: =IFERROR(INDEX(会社マスタ!$B:$B,MATCH(D586,会社マスタ!$A:$A,0)),"") | F586: =IFERROR(INDEX(会社マスタ!$C:$C,MATCH(D586,会社マスタ!$A:$A,0)),"") | G586: 26 | H586: ・網羅性が確認できる資料（試算表との一致確認）の送付をお願いします | I586: 未判定
A587: 586 | B587: 自主点検QA | C587: 08-2 | D587: 80700 | E587: =IFERROR(INDEX(会社マスタ!$B:$B,MATCH(D587,会社マスタ!$A:$A,0)),"") | F587: =IFERROR(INDEX(会社マスタ!$C:$C,MATCH(D587,会社マスタ!$A:$A,0)),"") | G587: 26 | H587: ・賞与引当⾦繰入額および賞与引当⾦残高の月次推移表を作成する際に使用するデータソースと抽出条件が分かる資料（画面コピーなど）の送付をお願いします ・網羅性が確認できる資料（試算表との一致確認）の送付をお願いします | I587: 未判定
A588: 587 | B588: 自主点検QA | C588: 08-3 | D588: 100100 | E588: =IFERROR(INDEX(会社マスタ!$B:$B,MATCH(D588,会社マスタ!$A:$A,0)),"") -> デンケン・ハイデンタル(株) | F588: =IFERROR(INDEX(会社マスタ!$C:$C,MATCH(D588,会社マスタ!$A:$A,0)),"") -> デンタルケアユニット | G588: 26 | H588: ・賞与引当⾦繰入額および賞与引当⾦残高の月次推移表を作成する際に使用するデータソースと抽出条件が分かる資料（画面コピーなど）の送付をお願いします ・網羅性が確認できる資料（試算表との一致確認）の送付をお願いします ・賞与引当金を計上する際に、繰入金額の計算資料の送付をお願いします | I588: 未判定
A589: 588 | B589: 自主点検QA | C589: 08-4 | D589: 220400 | E589: =IFERROR(INDEX(会社マスタ!$B:$B,MATCH(D589,会社マスタ!$A:$A,0)),"") -> (株)札幌デンタル・ラボラトリー | F589: =IFERROR(INDEX(会社マスタ!$C:$C,MATCH(D589,会社マスタ!$A:$A,0)),"") -> デンタルケアユニット | G589: 26 | H589: ・賞与引当⾦繰入額および賞与引当⾦残高の月次推移表を作成する際に使用するデータソースと抽出条件が分かる資料（画面コピーなど）の送付をお願いします ・網羅性が確認できる資料（試算表との一致確認）の送付をお願いします ・賞与引当金を計上する際に、繰入金額の計算資料の送付をお願いします | I589: 未判定
A590: 589 | B590: 自主点検QA | C590: 08-5 | D590: 080100 | E590: =IFERROR(INDEX(会社マスタ!$B:$B,MATCH(D590,会社マスタ!$A:$A,0)),"") -> エア・ウォーター・メディカル(株) | F590: =IFERROR(INDEX(会社マスタ!$C:$C,MATCH(D590,会社マスタ!$A:$A,0)),"") -> メディカルプロダクツユニット | G590: 5 | H590: ・データソース及び抽出条件が分かる資料（抽出する際の条件を記載した画面スクショなど）の提出をお願い出来ますでしょうか。 ・網羅性及び売上伝票/明細との整合性を確認するため、25年4月~26年3月の全ての売上明細（マイナス含む）及び試算表の提出をお願い出来ますでしょうか。 ・マイナスの売上計上の妥当性を確認するため、全てのエントリーに対してマイナス売上理由のコメント及び、マイナスの売上計上に至った経緯・取り消しの妥当性を裏付けるの証跡の提出をお願い出来ますでしょうか。 | I590: 未判定
A591: 590 | B591: 自主点検QA | C591: 08-6 | D591: 080200 | E591: =IFERROR(INDEX(会社マスタ!$B:$B,MATCH(D591,会社マスタ!$A:$A,0)),"") -> エア・ウォーター・メディエイチ(株) | F591: =IFERROR(INDEX(会社マスタ!$C:$C,MATCH(D591,会社マスタ!$A:$A,0)),"") -> メディカルプロダクツユニット | G591: 5 | H591: ・網羅性及び売上伝票/明細との整合性を確認するため、25年4月~26年3月の全ての売上明細（マイナス含む）及び試算表の提出をお願い出来ますでしょうか。 | I591: 未判定
A592: 591 | B592: 自主点検QA | C592: 08-7 | D592: 080400 | E592: =IFERROR(INDEX(会社マスタ!$B:$B,MATCH(D592,会社マスタ!$A:$A,0)),"") -> エムシーサービス(株) | F592: =IFERROR(INDEX(会社マスタ!$C:$C,MATCH(D592,会社マスタ!$A:$A,0)),"") -> メディカルプロダクツユニット | G592: 5 | H592: ・データソース及び抽出条件が分かる資料（抽出する際の条件を記載した画面スクショなど）の提出をお願い出来ますでしょうか。 ・網羅性及び売上伝票/明細との整合性を確認するため、試算表の提出をお願い出来ますでしょうか。 | I592: 未判定
A593: 592 | B593: 自主点検QA | C593: 08-8 | D593: 080500 | E593: =IFERROR(INDEX(会社マスタ!$B:$B,MATCH(D593,会社マスタ!$A:$A,0)),"") -> エア・ウォーター・バイオデザイン(株) | F593: =IFERROR(INDEX(会社マスタ!$C:$C,MATCH(D593,会社マスタ!$A:$A,0)),"") -> メディカルプロダクツユニット | G593: 5 | H593: ・データソース及び抽出条件が分かる資料（抽出する際の条件を記載した画面スクショなど）の提出をお願い出来ますでしょうか。 ・網羅性及び売上伝票/明細との整合性を確認するため、試算表の提出をお願い出来ますでしょうか。 | I593: 未判定
A594: 593 | B594: 自主点検QA | C594: 08-9 | D594: 080700 | E594: =IFERROR(INDEX(会社マスタ!$B:$B,MATCH(D594,会社マスタ!$A:$A,0)),"") -> 湖北爱沃特医疗气体有限公司 | F594: =IFERROR(INDEX(会社マスタ!$C:$C,MATCH(D594,会社マスタ!$A:$A,0)),"") -> メディカルプロダクツユニット | G594: 5 | H594: ・データソース及び抽出条件が分かる資料（抽出する際の条件を記載した画面スクショなど）の提出をお願い出来ますでしょうか。 ・網羅性及び売上伝票/明細との整合性を確認するため、25年4月~26年3月の全ての売上明細（マイナス含む）及び試算表の提出をお願い出来ますでしょうか。 | I594: 未判定
A595: 594 | B595: 自主点検QA | C595: 08-10 | D595: 080800 | E595: =IFERROR(INDEX(会社マスタ!$B:$B,MATCH(D595,会社マスタ!$A:$A,0)),"") -> エア・ウォーター・アエラスバイオ（株） | F595: =IFERROR(INDEX(会社マスタ!$C:$C,MATCH(D595,会社マスタ!$A:$A,0)),"") -> メディカルプロダクツユニット | G595: 5 | H595: ・マイナスの売上計上の妥当性を確認するため、マイナスの売上計上に至った経緯・取り消しの妥当性を裏付けるの証跡の提出をお願い出来ますでしょうか。 | I595: 未判定
... A1010: 1009 | B1010: 自主点検QA | C1010: 02-146 | D1010: 20600 | E1010: =IFERROR(INDEX(会社マスタ!$B:$B,MATCH(D1010,会社マスタ!$A:$A,0)),"") | F1010: =IFERROR(INDEX(会社マスタ!$C:$C,MATCH(D1010,会社マスタ!$A:$A,0)),"") | G1010: 26 | H1010: ・貸借対照表25年5月末～2月末の各月末の賞与引当金残高がわかる資料のご提出をお願いいたします。 ・提出頂いた根拠資料①試算表では、賞与引当金繰入を損益計算書で確認できませんでした。各月次で賞与引当金繰入額がわかる試算表等の提出をお願いいたします。 ・根拠資料②を拝見していると、賞与引当金の計算については、賞与及び賞与に見合う社会保険料を含めて賞与引当金に計上されている理解で齟齬ございませんか？ ・令和7年7月31日の3,407,453円の賞与引当金取崩、令和7年12年30日の3,416,123円の賞与引当金取り崩しがわかる資料（根拠資料…会計伝票）のご提出をお願いいたします。 ・01_成果物→02_一次レビューが貴社成果物提出のご認識でしょうか？00_成果物フォーマットのひな型に合わせる形でご提出をお願いいたします。 ・出向者賞与予定計上一般3名に対して25年4月～9月の月次の賞与引当金繰入額を587,000円、25年10月～26年3月の賞与引当金繰入額を568,000円に設定された背景をご教示ください。また、4月～9月に比べて、10月～3月の月次の繰入額が少ない理由をご教示ください（例：対象者は同じであるが、支給月数で冬季賞与の方が多く配分しているため、かつベースアップは無いため等） ・プロパー社員賞与予定計上一般8名に対して25年4月～9月の月次の賞与引当金繰入額を3,594,000円、25年10月～26年3月の賞与引当金繰入額を3,117,000円に設定された背景をご教示ください。また、4月～9月に比べて、10月～3月の月次の繰入額が少ない理由をご教示ください（例：対象者は同じであるが、支給月数で冬季賞与の方が多く配分しているため、かつベースアップは無いため等） ・※引当金計上額と支払額の乖離要因：予定人員を採用できなかったため（引当を多く積んだ）と回答頂いておりますが、予定人員を確保できなかった点を深堀してご説明をお願いいたします。（例：求人を出したが適切な人材を確保できなかった。当初想定していない方の退職があり、人員を補充出来なかった等） | I1010: 未判定
A1011: 1010 | B1011: 自主点検QA | C1011: 02-152 | E1011: =IFERROR(INDEX(会社マスタ!$B:$B,MATCH(D1011,会社マスタ!$A:$A,0)),"") | F1011: =IFERROR(INDEX(会社マスタ!$C:$C,MATCH(D1011,会社マスタ!$A:$A,0)),"") | H1011: denta | I1011: 未判定
A1012: 1011 | B1012: 自主点検QA | C1012: 04-1 | D1012: 40100 | E1012: =IFERROR(INDEX(会社マスタ!$B:$B,MATCH(D1012,会社マスタ!$A:$A,0)),"") | F1012: =IFERROR(INDEX(会社マスタ!$C:$C,MATCH(D1012,会社マスタ!$A:$A,0)),"") | G1012: 26 | H1012: ・賞与引当⾦繰入額および賞与引当⾦残高の月次推移表を作成する際に使用するデータソースと抽出条件が分かる資料（画面コピーなど）の送付をお願いします | I1012: 未判定
A1013: 1012 | B1013: 自主点検QA | C1013: 04-2 | D1013: 40300 | E1013: =IFERROR(INDEX(会社マスタ!$B:$B,MATCH(D1013,会社マスタ!$A:$A,0)),"") | F1013: =IFERROR(INDEX(会社マスタ!$C:$C,MATCH(D1013,会社マスタ!$A:$A,0)),"") | G1013: 26 | H1013: ・網羅性が確認できる資料（試算表との一致確認）の送付をお願いします | I1013: 未判定
A1014: 1013 | B1014: 自主点検QA | C1014: 04-3 | D1014: 040800 | E1014: =IFERROR(INDEX(会社マスタ!$B:$B,MATCH(D1014,会社マスタ!$A:$A,0)),"") -> Taylor-Wharton Malaysia Sdn. Bhd. | F1014: =IFERROR(INDEX(会社マスタ!$C:$C,MATCH(D1014,会社マスタ!$A:$A,0)),"") -> グローバルエンジニアリングユニット | G1014: 26 | H1014: ・賞与引当⾦繰入額および賞与引当⾦残高の月次推移表を作成する際に使用するデータソースと抽出条件が分かる資料（画面コピーなど）の送付をお願いします | I1014: 未判定
A1015: 1014 | B1015: 自主点検QA | C1015: 04-4 | D1015: 040100 | E1015: =IFERROR(INDEX(会社マスタ!$B:$B,MATCH(D1015,会社マスタ!$A:$A,0)),"") -> エア・ウォーター・エンジニアリング(株) | F1015: =IFERROR(INDEX(会社マスタ!$C:$C,MATCH(D1015,会社マスタ!$A:$A,0)),"") -> グローバルエンジニアリングユニット | G1015: 5 | H1015: ・データソース及び抽出条件が分かる資料（抽出する際の条件を記載した画面スクショなど）の提出をお願い出来ますでしょうか。 ・網羅性及び売上伝票/明細との整合性を確認するため、試算表の提出をお願い出来ますでしょうか。 | I1015: 未判定
A1016: 1015 | B1016: 自主点検QA | C1016: 04-5 | D1016: 040600 | E1016: =IFERROR(INDEX(会社マスタ!$B:$B,MATCH(D1016,会社マスタ!$A:$A,0)),"") -> Power Partners Private Limited | F1016: =IFERROR(INDEX(会社マスタ!$C:$C,MATCH(D1016,会社マスタ!$A:$A,0)),"") -> グローバルエンジニアリングユニット | G1016: 5 | H1016: ・データソース及び抽出条件が分かる資料（抽出する際の条件を記載した画面スクショなど）の提出をお願い出来ますでしょうか。 ・網羅性及び売上伝票/明細との整合性を確認するため、25年4月~26年3月の全ての売上明細（マイナス含む）及び試算表の提出をお願い出来ますでしょうか。 ・マイナスの売上計上の妥当性を確認するため、全てのエントリーに対してマイナス売上理由のコメント及び、マイナスの売上計上に至った経緯・取り消しの妥当性を裏付けるの証跡の提出をお願い出来ますでしょうか。 | I1016: 未判定
A1017: 1016 | B1017: 自主点検QA | C1017: 04-6 | D1017: 040100 | E1017: =IFERROR(INDEX(会社マスタ!$B:$B,MATCH(D1017,会社マスタ!$A:$A,0)),"") -> エア・ウォーター・エンジニアリング(株) | F1017: =IFERROR(INDEX(会社マスタ!$C:$C,MATCH(D1017,会社マスタ!$A:$A,0)),"") -> グローバルエンジニアリングユニット | G1017: 6 | H1017: ・データソース及び抽出条件が分かる資料（画面コピーなど）の送付をお願いします ・網羅性が確認できる資料（試算表との一致確認）の送付をお願いします ・増減コメントにて、要因毎の影響金額の記載をお願いします（最低限、目安として増減金額の6~7割程度の要因説明をお願いします。細かい要因/案件の積み上げである場合は主にどのような要因/案件かをご記載ください。） | I1017: 未判定
A1018: 1017 | B1018: 自主点検QA | C1018: 04-7 | D1018: 040200 | E1018: =IFERROR(INDEX(会社マスタ!$B:$B,MATCH(D1018,会社マスタ!$A:$A,0)),"") -> AIR WATER INDIA PRIVATE LIMITED | F1018: =IFERROR(INDEX(会社マスタ!$C:$C,MATCH(D1018,会社マスタ!$A:$A,0)),"") -> グローバルエンジニアリングユニット | G1018: 6 | H1018: ・Please send us documentation that shows the data sources and extraction criteria, such as screen captures. ・Please send us documentation that allows us to confirm completeness, such as evidence of agreement with the trial balance. ・In the variance comments, please include the impact amount for each factor, covering at least approximately 60–70% of the total variance amount. | I1018: 未判定
A1019: 1018 | B1019: 自主点検QA | C1019: 04-8 | D1019: 040300 | E1019: =IFERROR(INDEX(会社マスタ!$B:$B,MATCH(D1019,会社マスタ!$A:$A,0)),"") -> AIR WATER VIETNAM CO., LTD. | F1019: =IFERROR(INDEX(会社マスタ!$C:$C,MATCH(D1019,会社マスタ!$A:$A,0)),"") -> グローバルエンジニアリングユニット | G1019: 6 | H1019: ・データソース及び抽出条件が分かる資料（画面コピーなど）の送付をお願いします ・網羅性が確認できる資料（試算表との一致確認）の送付をお願いします | I1019: 未判定
A1020: 1019 | B1020: 自主点検QA | C1020: 04-9 | D1020: 040402 | E1020: =IFERROR(INDEX(会社マスタ!$B:$B,MATCH(D1020,会社マスタ!$A:$A,0)),"") -> American Gas Products, Inc. | F1020: =IFERROR(INDEX(会社マスタ!$C:$C,MATCH(D1020,会社マスタ!$A:$A,0)),"") -> グローバルエンジニアリングユニット | G1020: 6 | H1020: ・Please send us documentation that shows the data sources and extraction criteria, such as screen captures. ・Please send us documentation that allows us to confirm completeness, such as evidence of agreement with the trial balance. | I1020: 未判定
A1021: 1020 | B1021: 自主点検QA | C1021: 04-10 | D1021: 040403 | E1021: =IFERROR(INDEX(会社マスタ!$B:$B,MATCH(D1021,会社マスタ!$A:$A,0)),"") -> Noble Gas Solutions, LLC | F1021: =IFERROR(INDEX(会社マスタ!$C:$C,MATCH(D1021,会社マスタ!$A:$A,0)),"") -> グローバルエンジニアリングユニット | G1021: 6 | H1021: ・Please send us documentation that shows the data sources and extraction criteria, such as screen captures. ・Please send us documentation that allows us to confirm completeness, such as evidence of agreement with the trial balance. | I1021: 未判定
A1022: 1021 | B1022: 自主点検QA | C1022: 04-11 | D1022: 040405 | E1022: =IFERROR(INDEX(会社マスタ!$B:$B,MATCH(D1022,会社マスタ!$A:$A,0)),"") -> Phoenix Welding Supply LLC | F1022: =IFERROR(INDEX(会社マスタ!$C:$C,MATCH(D1022,会社マスタ!$A:$A,0)),"") -> グローバルエンジニアリングユニット | G1022: 6 | H1022: ・Please send us documentation that shows the data sources and extraction criteria, such as screen captures. ・Please send us documentation that allows us to confirm completeness, such as evidence of agreement with the trial balance. | I1022: 未判定
A1023: 1022 | B1023: 自主点検QA | C1023: 04-12 | D1023: 040600 | E1023: =IFERROR(INDEX(会社マスタ!$B:$B,MATCH(D1023,会社マスタ!$A:$A,0)),"") -> Power Partners Private Limited | F1023: =IFERROR(INDEX(会社マスタ!$C:$C,MATCH(D1023,会社マスタ!$A:$A,0)),"") -> グローバルエンジニアリングユニット | G1023: 6 | H1023: ・Please send us documentation that shows the data sources and extraction criteria, such as screen captures. ・Please send us documentation that allows us to confirm completeness, such as evidence of agreement with the trial balance. | I1023: 未判定
... A1193: 1192 | B1193: 自主点検QA | C1193: 04-182 | D1193: 040403 | E1193: =IFERROR(INDEX(会社マスタ!$B:$B,MATCH(D1193,会社マスタ!$A:$A,0)),"") -> Noble Gas Solutions, LLC | F1193: =IFERROR(INDEX(会社マスタ!$C:$C,MATCH(D1193,会社マスタ!$A:$A,0)),"") -> グローバルエンジニアリングユニット | G1193: 26 | H1193: Please use the provided FORMAT FILE to prepare the deliverables. The format file is saved in the folder named "00_成果物フォーマット(Deliverables Format)". Please also refer to Page.63 on "Self-Inspection Instruction" file to prepare the deliverables | I1193: 未判定
A1194: 1193 | B1194: 自主点検QA | C1194: 04-183 | D1194: ー | E1194: =IFERROR(INDEX(会社マスタ!$B:$B,MATCH(D1194,会社マスタ!$A:$A,0)),"") | F1194: =IFERROR(INDEX(会社マスタ!$C:$C,MATCH(D1194,会社マスタ!$A:$A,0)),"") | G1194: ー | H1194: ー | I1194: 未判定
A1195: 1194 | B1195: 自主点検QA | C1195: 04-184 | D1195: 40701 | E1195: =IFERROR(INDEX(会社マスタ!$B:$B,MATCH(D1195,会社マスタ!$A:$A,0)),"") | F1195: =IFERROR(INDEX(会社マスタ!$C:$C,MATCH(D1195,会社マスタ!$A:$A,0)),"") | G1195: 18 | H1195: ・単体決算としては12月決算かとは思いますが、本分析においては2025年4月-2026年3月での月次推移分析を実施いただけますと幸いです。 | I1195: 未判定
A1196: 1195 | B1196: 自主点検QA | C1196: 04-185 | D1196: 040600 | E1196: =IFERROR(INDEX(会社マスタ!$B:$B,MATCH(D1196,会社マスタ!$A:$A,0)),"") -> Power Partners Private Limited | F1196: =IFERROR(INDEX(会社マスタ!$C:$C,MATCH(D1196,会社マスタ!$A:$A,0)),"") -> グローバルエンジニアリングユニット | G1196: 25 | H1196: 2026年3月期末時点の減損判定資料について、親会社経理室で実施したものをご提出ください。 | I1196: 未判定
A1197: 1196 | B1197: 自主点検QA | C1197: 04-186 | D1197: 40402 | E1197: =IFERROR(INDEX(会社マスタ!$B:$B,MATCH(D1197,会社マスタ!$A:$A,0)),"") | F1197: =IFERROR(INDEX(会社マスタ!$C:$C,MATCH(D1197,会社マスタ!$A:$A,0)),"") | G1197: 18 | H1197: ・一般管理費(Total general expense)の数値のデータソースについて「Total general expenses are calculated by subtracting personnel expenses (salary, bonus, other employee benefits) from SG&A.」と伺いましたが、根拠資料中で見つけられずおそれいりますが具体的な箇所(〇〇シートの△△列●●行目等)をご教示いただいてもよろしいでしょうか。 | I1197: 未判定
A1198: 1197 | B1198: 自主点検QA | C1198: 04-187 | D1198: 040405 | E1198: =IFERROR(INDEX(会社マスタ!$B:$B,MATCH(D1198,会社マスタ!$A:$A,0)),"") -> Phoenix Welding Supply LLC | F1198: =IFERROR(INDEX(会社マスタ!$C:$C,MATCH(D1198,会社マスタ!$A:$A,0)),"") -> グローバルエンジニアリングユニット | G1198: 21 | H1198: ファイル「PO Rec'd Not Invoiced Accural 3-31-26」にACCOUNT Title：PO RECEIVED ー NOT INVOICEDとの記載があり、請求書は受領してないが注文書に基づき見積費用を計上したと推察されます。当該見積費用の計上根拠資料である注文書をご提出ください。 | I1198: 未判定
A1199: 1198 | B1199: 自主点検QA | C1199: 04-188 | D1199: 040402 | E1199: =IFERROR(INDEX(会社マスタ!$B:$B,MATCH(D1199,会社マスタ!$A:$A,0)),"") -> American Gas Products, Inc. | F1199: =IFERROR(INDEX(会社マスタ!$C:$C,MATCH(D1199,会社マスタ!$A:$A,0)),"") -> グローバルエンジニアリングユニット | G1199: 25 | H1199: No.153のQでTBを提出頂きましたが、ファイル「25_Impairment Assessment - AGP」にTBと整合確認する証跡がございません。 FY25の営業損益 736,551ドル FY26の営業損益 △24,648,009ドル FY26の帳簿価額 126,354,241ドル がTBとの照合を記載お願いいたします。 | I1199: 未判定
A1200: 1199 | B1200: 自主点検QA | C1200: 04-189 | D1200: 40701 | E1200: =IFERROR(INDEX(会社マスタ!$B:$B,MATCH(D1200,会社マスタ!$A:$A,0)),"") | F1200: =IFERROR(INDEX(会社マスタ!$C:$C,MATCH(D1200,会社マスタ!$A:$A,0)),"") | G1200: 6 | H1200: ・単体決算としては12月決算かとは思いますが、本分析においては2025年4月-2026年3月での月次推移分析を実施いただけますと幸いです。 | I1200: 未判定
A1201: 1200 | B1201: 自主点検QA | C1201: 04-190 | D1201: 40600 | E1201: =IFERROR(INDEX(会社マスタ!$B:$B,MATCH(D1201,会社マスタ!$A:$A,0)),"") | F1201: =IFERROR(INDEX(会社マスタ!$C:$C,MATCH(D1201,会社マスタ!$A:$A,0)),"") | G1201: 9 | H1201: 3つのファイル（ACT,PP,PPIN）があり、工事進行基準を適用して良いかどうかをチェックしています。これらのファイルにある工事は、どのように抽出されたのでしょうか？試算表との一致を確かめたいと考えています。 There are three files (ACT, PP, PPIN) for checking whether the percentage of completion method can be applied. How were the construction projects in the three files extracted? We would like to make sure that the total amount of the extracted details of the construction and trial balance agree with each other. | I1201: 未判定
A1202: 1201 | B1202: 自主点検QA | C1202: 04-191 | D1202: 40600 | E1202: =IFERROR(INDEX(会社マスタ!$B:$B,MATCH(D1202,会社マスタ!$A:$A,0)),"") | F1202: =IFERROR(INDEX(会社マスタ!$C:$C,MATCH(D1202,会社マスタ!$A:$A,0)),"") | G1202: 12 | H1202: No.9で抽出された工事の件数とNo12で検討されている工事の件数が不一致なのはなぜでしょうか？例えばNo.9の「ACT」ファイルの中の「ACT-Project」sheetでは、13案件検討されていますが、No12の「ACT」ファイルでは、4案件しか検討されていないです。PPも同様に不一致が生じています。 Why is the discrepancy between the number of projects identified in No. 9 and the number of projects under consideration in No. 12? For example, in the "ACT-Project" sheet in the "ACT" file of No. 9, 13 construction projects were considered, but in "ACT" file of No. 12, only 4 construction projects were considered. PP is also inconsistent. | I1202: 未判定
A1203: 1202 | B1203: 自主点検QA | C1203: 04-192 | D1203: 40600 | E1203: =IFERROR(INDEX(会社マスタ!$B:$B,MATCH(D1203,会社マスタ!$A:$A,0)),"") | F1203: =IFERROR(INDEX(会社マスタ!$C:$C,MATCH(D1203,会社マスタ!$A:$A,0)),"") | G1203: 14 | H1203: 「ACT_Project actual costs_FY2025」ファイルの中には「PDG (3-4)」シート、「Infineon Malaysia DLP」シート、「PDG Genset DLP (1-2)」シート、「PDG UGT DLP (1-2)」シートがあり、案件ごとに原価計上されているのに対して、「ACT WIP - Mar'26」ファイルの「Accumulated cost incurred from Apr'25 to Feb'26」、「Cost incurred for the month」では「－」となっており、原価計上されていないように見えます。その理由はなぜでしょうか？ In the "ACT _Project actual costs_FY 2025" file, there are "PDG (3-4) " sheet, "Infineon Malaysia DLP" sheet, "PDG Genset DLP (1 -2)" sheet, and "PDG UGT DLP (1 -2)" sheet, and each construction project have accounting record, but in the "ACT WIP-Mar '26" file, "Accumulated cost incurred from Apr'25 to Feb'26" and "Cost incurred for the month," "-" is shown, and it appears that the construction project do not have accounting record. Why is that? | I1203: 未判定
A1204: 1203 | B1204: 自主点検QA | C1204: 04-193 | D1204: 40600 | E1204: =IFERROR(INDEX(会社マスタ!$B:$B,MATCH(D1204,会社マスタ!$A:$A,0)),"") | F1204: =IFERROR(INDEX(会社マスタ!$C:$C,MATCH(D1204,会社マスタ!$A:$A,0)),"") | G1204: 11 | H1204: "2026年3月期の「WIP - Summary of Project as of 31 MARCH 2026」資料に記載されている各工事案件ごとの機械等の明細(2025年4月～2026年3月)について、試算表と照合可能な形でご提出いただきますようお願いいたします。具体的には、「WIP」資料に集計されている「Accumulated cost incurred from Apr'25 to Feb'26」及び「Cost incurred for the month Mar'26」について、各工事案件の仕入データをご提出いただきますようお願いいたします。 *** Please provide the machineries purchases breakdown, e.g. machinery and its associated costs, cost of other materials required for installing the machinery etc., for each Job/Project that was presented in ""WIP - Summary of Project as of 31 March 2026"" from Apr'25 ~ Mar'26, that would agreed to Trial Balances. In other words, the machinery and other materials purchase data of each project that are compiled for ""Accumulated cost incurred from Apr'25 to Feb'26"" and ""Cost incurred for the month Mar'26"" in 「WIP - Summary of Project as of 31 March 2026」 file." | I1204: 未判定
A1205: 1204 | B1205: 自主点検QA | C1205: 04-194 | D1205: 40600 | E1205: =IFERROR(INDEX(会社マスタ!$B:$B,MATCH(D1205,会社マスタ!$A:$A,0)),"") | F1205: =IFERROR(INDEX(会社マスタ!$C:$C,MATCH(D1205,会社マスタ!$A:$A,0)),"") | G1205: 10 | H1205: 四半期毎に親会社にご報告されているPKG、もしくはそれと突合する「WIP - Summary of Project」資料を提出いただいますようお願いいたします。例： ① Reporting PKG or WIP - Summary of Project as of 30 June 2025 ② Reporting PKG or WIP - Summary of Project as of 30 September 2025 ③ Reporting PKG or WIP - Summary of Project as of 31 December 2025 *** Please provide the quarterly reporting PKG or"WIP - Summary of Project" that was agreed to the quarterly reporting PKG submitted for each quarter. For example:- ① Reporting PKG or WIP - Summary of Project as of 30 June 2025 ② Reporting PKG or WIP - Summary of Project as of 30 September 2025 ③ Reporting PKG or WIP - Summary of Project as of 31 December 2025 | I1205: 未判定
A1206: 1205 | B1206: 自主点検QA | C1206: 04-195 | D1206: 040403 | E1206: =IFERROR(INDEX(会社マスタ!$B:$B,MATCH(D1206,会社マスタ!$A:$A,0)),"") -> Noble Gas Solutions, LLC | F1206: =IFERROR(INDEX(会社マスタ!$C:$C,MATCH(D1206,会社マスタ!$A:$A,0)),"") -> グローバルエンジニアリングユニット | G1206: 8 | H1206: ①Please provide a screenshot that shows the data extraction criteria for sales details provided? ②Please add overall comments about the appropriateness of revenue booked for March 2026? We understand it is impossible to comment for each transactions, so please explain the recognition timing for "Order Revenue" and "Cylinder Rent and Lease Revenue" would be useful. | I1206: 未判定
... A1249: 1248 | B1249: 自主点検QA | C1249: 04-238 | D1249: 040701 | E1249: =IFERROR(INDEX(会社マスタ!$B:$B,MATCH(D1249,会社マスタ!$A:$A,0)),"") -> M1 Engineering Limited | F1249: =IFERROR(INDEX(会社マスタ!$C:$C,MATCH(D1249,会社マスタ!$A:$A,0)),"") -> グローバルエンジニアリングユニット | G1249: 21 | H1249: 「21_Document the basis for recording estimated expenses」ファイルを見積費用のリストとして提出頂いておりますが、当該見積費用の項目はどのようにして抽出されたのでしょうか（見積計上項目を計上する勘定科目である××の内訳を記載している、費用勘定の仕訳の摘要欄で「見積」「予定」が入った仕訳を抽出した、等）。 抽出頂いたもの以外に見積費用がないことを確認するため、抽出方法をご教示ください。 デロイト追記) ・根拠資料として以下を提出いただけますでしょうか。ご多用の中とは存じますが、どうぞよろしくおねがいいたします。 - 2026年4月期仕訳明細データ - 試算表 自主点検説明資料に記載の通り、上記2つにて請求書の有無とその合計額が試算表の中で一致することを確認する必要があるというのが趣旨になります。(K列238行目付近にスクショ添付) | I1249: 未判定
A1250: 1249 | B1250: 自主点検QA | C1250: 04-243 | E1250: =IFERROR(INDEX(会社マスタ!$B:$B,MATCH(D1250,会社マスタ!$A:$A,0)),"") | F1250: =IFERROR(INDEX(会社マスタ!$C:$C,MATCH(D1250,会社マスタ!$A:$A,0)),"") | H1250: 追加質問は下段へ記載。削除はグレーアウト。途中での行削除や追加はしないこと | I1250: 未判定
A1251: 1250 | B1251: 自主点検QA | C1251: 05-1 | D1251: 050100 | E1251: =IFERROR(INDEX(会社マスタ!$B:$B,MATCH(D1251,会社マスタ!$A:$A,0)),"") -> Pacific Petro Import And Export Trading JSC | F1251: =IFERROR(INDEX(会社マスタ!$C:$C,MATCH(D1251,会社マスタ!$A:$A,0)),"") -> エネルギーソリューションユニット | G1251: 6 | H1251: ・データソース及び抽出条件が分かる資料（画面コピーなど）の送付をお願いします ・網羅性が確認できる資料（試算表との一致確認）の送付をお願いします ・増減コメントにて、要因毎の影響金額の記載をお願いします（2, 3月）（最低限、目安として増減金額の6~7割程度の要因説明をお願いします。細かい要因/案件の積み上げである場合は主にどのような要因/案件かをご記載ください。） | I1251: 未判定
A1252: 1251 | B1252: 自主点検QA | C1252: 05-2 | D1252: 050100 | E1252: =IFERROR(INDEX(会社マスタ!$B:$B,MATCH(D1252,会社マスタ!$A:$A,0)),"") -> Pacific Petro Import And Export Trading JSC | F1252: =IFERROR(INDEX(会社マスタ!$C:$C,MATCH(D1252,会社マスタ!$A:$A,0)),"") -> エネルギーソリューションユニット | G1252: 5 | H1252: ・データソース及び抽出条件が分かる資料（抽出する際の条件を記載した画面スクショなど）の提出をお願い出来ますでしょうか。 ・網羅性及び売上伝票/明細との整合性を確認するため、試算表の提出をお願い出来ますでしょうか。 | I1252: 未判定
A1253: 1252 | B1253: 自主点検QA | C1253: 05-3 | D1253: 50100 | E1253: =IFERROR(INDEX(会社マスタ!$B:$B,MATCH(D1253,会社マスタ!$A:$A,0)),"") | F1253: =IFERROR(INDEX(会社マスタ!$C:$C,MATCH(D1253,会社マスタ!$A:$A,0)),"") | G1253: 18 | H1253: ・各月のデータソース及び抽出条件(手順)が分かる資料(画面コピーなど)の送付をお願いいたします | I1253: 未判定
A1254: 1253 | B1254: 自主点検QA | C1254: 05-4 | D1254: 050100 | E1254: =IFERROR(INDEX(会社マスタ!$B:$B,MATCH(D1254,会社マスタ!$A:$A,0)),"") -> Pacific Petro Import And Export Trading JSC | F1254: =IFERROR(INDEX(会社マスタ!$C:$C,MATCH(D1254,会社マスタ!$A:$A,0)),"") -> エネルギーソリューションユニット | G1254: 4 | H1254: ・データソース及び抽出条件が分かる資料（画面コピーなど）の送付をお願いします ・網羅性が確認できる資料（試算表との一致確認）の送付をお願いします | I1254: 未判定
A1255: 1254 | B1255: 自主点検QA | C1255: 05-5 | D1255: 050100 | E1255: =IFERROR(INDEX(会社マスタ!$B:$B,MATCH(D1255,会社マスタ!$A:$A,0)),"") -> Pacific Petro Import And Export Trading JSC | F1255: =IFERROR(INDEX(会社マスタ!$C:$C,MATCH(D1255,会社マスタ!$A:$A,0)),"") -> エネルギーソリューションユニット | G1255: 8 | H1255: ・データソース及び抽出条件が分かる資料（画面コピーなど）のご提出をお願いします。 ・網羅性が確認できる資料（試算表との一致確認）のご提出をお願いします。 おそらくですが売上明細データに関して、2025年度と2026年度のそれぞれの全社PL等で、売上金額の一致を確認できると思いますので、それぞれの年度の全社PL（及びそれ以外に抽出条件等があればそちらも）をご提出ください。 | I1255: 未判定
A1256: 1255 | B1256: 自主点検QA | C1256: 05-6 | D1256: 050100 | E1256: =IFERROR(INDEX(会社マスタ!$B:$B,MATCH(D1256,会社マスタ!$A:$A,0)),"") -> Pacific Petro Import And Export Trading JSC | F1256: =IFERROR(INDEX(会社マスタ!$C:$C,MATCH(D1256,会社マスタ!$A:$A,0)),"") -> エネルギーソリューションユニット | G1256: 5 | H1256: ・売上のマイナス処理をしている取引について、当該取り消し処理の根拠資料を格納頂けますでしょうか。 | I1256: 未判定
A1257: 1256 | B1257: 自主点検QA | C1257: 05-7 | D1257: 050100 | E1257: =IFERROR(INDEX(会社マスタ!$B:$B,MATCH(D1257,会社マスタ!$A:$A,0)),"") -> Pacific Petro Import And Export Trading JSC | F1257: =IFERROR(INDEX(会社マスタ!$C:$C,MATCH(D1257,会社マスタ!$A:$A,0)),"") -> エネルギーソリューションユニット | G1257: 25 | H1257: ・データソースと抽出条件（手順）の記録が成果物として提出されていない …260506：自主点検：FY2025 パシフィックペトロ減損テスト WS_(5年計画)の中の54行目減価償却費、59行目設備投資、61行目運転資本の増減についてデータソースをご提出頂ければ幸いです。 セルD13の割引率・成長率ついても記載の背景をご記載頂ければ幸いです。 減損検討結果の判断に合理性はあるか …提出頂いた事業計画の営業利益について算式を御確認下さい。営業利益は総利益-販管費で算定されている認識です。02_根拠資料の260506：PP社：減損自主点検：PL予測エクセルのPLSheetの34行目を基に補正計算を行って算出されている認識ですが、こちらの確からしさを御確認下さい。 | I1257: 未判定
A1258: 1257 | B1258: 自主点検QA | C1258: 05-8 | D1258: 050100 | E1258: =IFERROR(INDEX(会社マスタ!$B:$B,MATCH(D1258,会社マスタ!$A:$A,0)),"") -> Pacific Petro Import And Export Trading JSC | F1258: =IFERROR(INDEX(会社マスタ!$C:$C,MATCH(D1258,会社マスタ!$A:$A,0)),"") -> エネルギーソリューションユニット | G1258: 21 | H1258: 「決算書」があり、「毎月、経理部から各部署に新規の契約書/請求書等の管理書類を4日までに提出するように指導しており、関連書類は全て経理部に集約され、見積もり計上等の会計処理について精査していると共に、現地会計法人にも相談・監査の上で、見積計上が必要なものがないことを確認している。」 の記載を頂いております。 ・「見積もり計上等の会計処理について精査している」とのことであり、精査の対象となった仕訳について具体的に再検証をしたく思います。お手数ですが、自主点検説明資料に基づき抽出及び資料の格納をお願いできますでしょうか？ | I1258: 未判定
A1259: 1258 | B1259: 自主点検QA | C1259: 05-9 | D1259: 050100 | E1259: =IFERROR(INDEX(会社マスタ!$B:$B,MATCH(D1259,会社マスタ!$A:$A,0)),"") -> Pacific Petro Import And Export Trading JSC | F1259: =IFERROR(INDEX(会社マスタ!$C:$C,MATCH(D1259,会社マスタ!$A:$A,0)),"") -> エネルギーソリューションユニット | G1259: 23 | H1259: ・№23自主点検一次レビューフォルダに成果物の格納がございませんでした。改めてご確認をお願いいたします（根拠資料は確認できました）。 ・台帳についてはデータソース及び抽出条件が分かる資料（どのように抽出したかが分かる画面コピーなど）の送付をお願いします ・網羅性が確認できる資料（試算表等）の送付をお願いします（部分ではなく一式） ・その上で、各資産に対して修繕費、研究費への該当の有無を網羅的に検討し、その証跡を残していただけますでしょうか（資産名称など抽出基準を明確にし、抽出した資産に対して、資産計上の妥当性ご検討ください）。 ・詳細は自主点検説明資料№23成果物イメージをご参照下さい。 | I1259: 未判定
A1260: 1259 | B1260: 自主点検QA | C1260: 07-1 | D1260: 070200 | E1260: =IFERROR(INDEX(会社マスタ!$B:$B,MATCH(D1260,会社マスタ!$A:$A,0)),"") -> 川本産業(株) | F1260: =IFERROR(INDEX(会社マスタ!$C:$C,MATCH(D1260,会社マスタ!$A:$A,0)),"") -> 在宅ヘルスケアユニット | G1260: 26 | H1260: ・賞与引当⾦繰入額および賞与引当⾦残高の月次推移表を作成する際に使用するデータソースと抽出条件が分かる資料（画面コピーなど）の送付をお願いします ・成果物フォーマットを使用し、2026年3月期年間の賞与引当⾦繰入額および賞与引当⾦残高の月次推移表の作成をお願いします。 ・網羅性が確認できる資料（試算表との一致確認）の送付をお願いします | I1260: 未判定
A1261: 1260 | B1261: 自主点検QA | C1261: 07-2 | D1261: 070200 | E1261: =IFERROR(INDEX(会社マスタ!$B:$B,MATCH(D1261,会社マスタ!$A:$A,0)),"") -> 川本産業(株) | F1261: =IFERROR(INDEX(会社マスタ!$C:$C,MATCH(D1261,会社マスタ!$A:$A,0)),"") -> 在宅ヘルスケアユニット | G1261: 6 | H1261: ・データソース及び抽出条件が分かる資料（画面コピーなど）の送付をお願いします ・網羅性が確認できる資料（試算表との一致確認）の送付をお願いします | I1261: 未判定
A1262: 1261 | B1262: 自主点検QA | C1262: 07-3 | D1262: 070100 | E1262: =IFERROR(INDEX(会社マスタ!$B:$B,MATCH(D1262,会社マスタ!$A:$A,0)),"") -> エア・ウォーター・リアライズ(株) | F1262: =IFERROR(INDEX(会社マスタ!$C:$C,MATCH(D1262,会社マスタ!$A:$A,0)),"") -> 在宅ヘルスケアユニット | G1262: 5 | H1262: ・データソース及び抽出条件が分かる資料（抽出する際の条件を記載した画面スクショなど）の提出をお願い出来ますでしょうか。 ・マイナスの売上計上の妥当性を確認するため、全てのマイナス計上のエントリーに対して理由/ 検証コメント及び、会計処理の顛末の説明を記載いただけますでしょうか。 | I1262: 未判定
... A1659: 1658 | B1659: 自主点検QA | C1659: 17-110 | D1659: 170108 | E1659: =IFERROR(INDEX(会社マスタ!$B:$B,MATCH(D1659,会社マスタ!$A:$A,0)),"") -> 宏廣新技股份有限公司 | F1659: =IFERROR(INDEX(会社マスタ!$C:$C,MATCH(D1659,会社マスタ!$A:$A,0)),"") -> グローバル戦略推進本部 | G1659: 23 | H1659: ・①台帳についてはデータソース及び抽出条件が分かる資料（どのように抽出したかが分かる画面コピーなど）の送付をお願いします ・②網羅性が確認できる資料（試算表等）の送付をお願いします（部分ではなく一式） ・③その上で、各資産に対して修繕費、研究費への該当の有無を網羅的に検討し、その証跡を残していただけますでしょうか（資産名称など抽出基準を明確にし、抽出した資産に対して、資産計上の妥当性ご検討ください）。 ・④詳細は自主点検説明資料№23成果物イメージをご参照下さい。 5/28追記：上記の質問へのご対応を更に狭める形で以下にコメント致しました。特段ご対応いただく内容に変更はございません。 F列自主点検No.を23に修正致しました。失礼致しました。 また、上記①、②は自主点検No.3でご提出されている資料及び、自主点検関連資料フォルダ内の資料のから、台帳と試算表の一致を確認できましたので、ご対応不要です。 一方、③、④については台帳（財産目録）で少なくとも、以下に対しては、コメントをお願いします。 ・「裝潢工程」は修繕費ではないか？ ・「實驗設備」は研究費ではないか？ ・「軟體設備」は資産計上できる性質のものか？ | I1659: 未判定
A1660: 1659 | B1660: 自主点検QA | C1660: 17-111 | D1660: 170104 | E1660: =IFERROR(INDEX(会社マスタ!$B:$B,MATCH(D1660,会社マスタ!$A:$A,0)),"") -> Inoueki (Thailand) Co., Ltd. | F1660: =IFERROR(INDEX(会社マスタ!$C:$C,MATCH(D1660,会社マスタ!$A:$A,0)),"") -> グローバル戦略推進本部 | G1660: 4,6,19 | H1660: No.69、No.70、No.92、No.93のご確認状況はいかがでしょうか。 お忙しいところ恐縮ですが、5月26日㈫までにお願いできますでしょうか。 難しい場合は、いつ頃提出可能か、ご教示頂けますでしょうか。 どうぞ宜しくお願い致します。 | I1660: 未判定
A1661: 1660 | B1661: 自主点検QA | C1661: 17-112 | D1661: 170108 | E1661: =IFERROR(INDEX(会社マスタ!$B:$B,MATCH(D1661,会社マスタ!$A:$A,0)),"") -> 宏廣新技股份有限公司 | F1661: =IFERROR(INDEX(会社マスタ!$C:$C,MATCH(D1661,会社マスタ!$A:$A,0)),"") -> グローバル戦略推進本部 | G1661: 6 | H1661: 06_売上・粗利月次推移分析_成果物イメージ.xlsx>No.6シートに関しまして、H列以降は記載例でしょうか？No.6シートに関しましては、記載例は削除し、貴社の自主点検結果のみ記載をお願いします。 | I1661: 未判定
A1662: 1661 | B1662: 自主点検QA | C1662: 17-113 | D1662: 170108 | E1662: =IFERROR(INDEX(会社マスタ!$B:$B,MATCH(D1662,会社マスタ!$A:$A,0)),"") -> 宏廣新技股份有限公司 | F1662: =IFERROR(INDEX(会社マスタ!$C:$C,MATCH(D1662,会社マスタ!$A:$A,0)),"") -> グローバル戦略推進本部 | G1662: 6 | H1662: 06_売上・粗利月次推移分析_成果物イメージ.xlsx>No.6シート＞A列〜の表において、「売上前月比」「売上前年同月比」および「粗利前月比」「粗利前年同月比」」の記載をお願いします。 | I1662: 未判定
A1663: 1662 | B1663: 自主点検QA | C1663: 17-114 | D1663: 170108 | E1663: =IFERROR(INDEX(会社マスタ!$B:$B,MATCH(D1663,会社マスタ!$A:$A,0)),"") -> 宏廣新技股份有限公司 | F1663: =IFERROR(INDEX(会社マスタ!$C:$C,MATCH(D1663,会社マスタ!$A:$A,0)),"") -> グローバル戦略推進本部 | G1663: 6 | H1663: 06_売上・粗利月次推移分析_成果物イメージ.xlsx>No.6シート＞A列〜の表において、現在、”The gross margin deteriorated because sales of in-house products were below expectations.”や”The revenue increased in the second half of the year due to the launch of new products”等、下記観点と異なった抽象的な記載となっているため、下記分析上のポイントを満たす記載をお願いいたします。 <分析上のポイント> •増減コメントには要因毎の影響⾦額を記載する •増減コメントは月次推移だけでなく、前期との比較の観点でも記載する（同じトレンドであればその旨を記載） •前年同期・前月比較ともに、10百万円の変動、かつ、20%以上の変動があれば増減コメントを記載する | I1663: 未判定
A1664: 1663 | B1664: 自主点検QA | C1664: 17-115 | D1664: 170103 | E1664: =IFERROR(INDEX(会社マスタ!$B:$B,MATCH(D1664,会社マスタ!$A:$A,0)),"") -> Inoueki Singapore Pte. Ltd. | F1664: =IFERROR(INDEX(会社マスタ!$C:$C,MATCH(D1664,会社マスタ!$A:$A,0)),"") -> グローバル戦略推進本部 | G1664: 21 | H1664: 21 見積計上費用の計上根拠整理_ISPのA10セルについて、記載が「USD＝SGD Rate use as of year end (31 Dec 2025)」となっていますが、数値が121.95（1SGD≒121.95円）であることから、USDはJPYの誤記との理解で相違ないでしょうか。 | I1664: 未判定
A1665: 1664 | B1665: 自主点検QA | C1665: 17-116 | D1665: 170103 | E1665: =IFERROR(INDEX(会社マスタ!$B:$B,MATCH(D1665,会社マスタ!$A:$A,0)),"") -> Inoueki Singapore Pte. Ltd. | F1665: =IFERROR(INDEX(会社マスタ!$C:$C,MATCH(D1665,会社マスタ!$A:$A,0)),"") -> グローバル戦略推進本部 | G1665: 23 | H1665: 固定資産台帳を格納頂きましたが、建物(Building)勘定が含まれていないようでして、そちらもご提示頂けますでしょうか。 | I1665: 未判定
A1666: 1665 | B1666: 自主点検QA | C1666: 17-117 | D1666: 170101 | E1666: =IFERROR(INDEX(会社マスタ!$B:$B,MATCH(D1666,会社マスタ!$A:$A,0)),"") -> Inoueki (Malaysia) Sdn. Bhd. | F1666: =IFERROR(INDEX(会社マスタ!$C:$C,MATCH(D1666,会社マスタ!$A:$A,0)),"") -> グローバル戦略推進本部 | G1666: 25 | H1666: 資産のグルーピングに関するご判断の記載が確認出来なかったため、記載頂けますでしょうか（単一事業であり全社が最小の資金生成単位であるなど）。 | I1666: 未判定
A1667: 1666 | B1667: 自主点検QA | C1667: 17-118 | D1667: 170102 | E1667: =IFERROR(INDEX(会社マスタ!$B:$B,MATCH(D1667,会社マスタ!$A:$A,0)),"") -> Inoueki Philippines, Inc. | F1667: =IFERROR(INDEX(会社マスタ!$C:$C,MATCH(D1667,会社マスタ!$A:$A,0)),"") -> グローバル戦略推進本部 | G1667: 25 | H1667: 資産のグルーピングに関するご判断の記載が確認出来なかったため、記載頂けますでしょうか（単一事業であり全社が最小の資金生成単位であるなど）。 | I1667: 未判定
A1668: 1667 | B1668: 自主点検QA | C1668: 17-119 | D1668: 170103 | E1668: =IFERROR(INDEX(会社マスタ!$B:$B,MATCH(D1668,会社マスタ!$A:$A,0)),"") -> Inoueki Singapore Pte. Ltd. | F1668: =IFERROR(INDEX(会社マスタ!$C:$C,MATCH(D1668,会社マスタ!$A:$A,0)),"") -> グローバル戦略推進本部 | G1668: 25 | H1668: 資産のグルーピングに関するご判断の記載が確認出来なかったため、記載頂けますでしょうか（単一事業であり全社が最小の資金生成単位であるなど）。 | I1668: 未判定
A1669: 1668 | B1669: 自主点検QA | C1669: 17-120 | D1669: 170102 | E1669: =IFERROR(INDEX(会社マスタ!$B:$B,MATCH(D1669,会社マスタ!$A:$A,0)),"") -> Inoueki Philippines, Inc. | F1669: =IFERROR(INDEX(会社マスタ!$C:$C,MATCH(D1669,会社マスタ!$A:$A,0)),"") -> グローバル戦略推進本部 | G1669: 4 | H1669: ■BS/TB売掛金67,652,315とAging Report66,368,135に差異1,284,179が生じている原因をご教示ください ■Aging Report上、TermsとDue Dateが一致していない高額案件がありますが、以下の正確な支払条件をご教示ください。 ①Fuji Electric（2601-022/8456） Invoice Date01/09/26、Terms30 days、Due Date04/30/26 5,321,700円 ②Nexperia（2603-014/8573） Invoice Date03/05/26、Terms30 days、Due Date07/31/26 4,278,371円 ③Nexperia（2603-015/8574） Invoice Date03/05/26、Terms30 days、Due Date07/31/26 876,556円 ④Nexperia（2603-016/8575） Invoice Date03/05/26、Terms30 days、Due Date07/31/26 2,089,245円 | I1669: 未判定
A1670: 1669 | B1670: 自主点検QA | C1670: 17-121 | D1670: 170102 | E1670: =IFERROR(INDEX(会社マスタ!$B:$B,MATCH(D1670,会社マスタ!$A:$A,0)),"") -> Inoueki Philippines, Inc. | F1670: =IFERROR(INDEX(会社マスタ!$C:$C,MATCH(D1670,会社マスタ!$A:$A,0)),"") -> グローバル戦略推進本部 | G1670: 6 | H1670: ・ご提出いただいた売上・粗利月次推移分析の売上および粗利と試算表の数値が一致しておらず、差異が生じている理由または、整合しているデータの箇所をご指摘ください | I1670: 未判定
A1671: 1670 | B1671: 自主点検QA | C1671: 17-122 | D1671: 170104 | E1671: =IFERROR(INDEX(会社マスタ!$B:$B,MATCH(D1671,会社マスタ!$A:$A,0)),"") -> Inoueki (Thailand) Co., Ltd. | F1671: =IFERROR(INDEX(会社マスタ!$C:$C,MATCH(D1671,会社マスタ!$A:$A,0)),"") -> グローバル戦略推進本部 | G1671: 19 | H1671: １．No.34、No.91でもご依頼させて頂いておりますが、 ●「19当期に費用計上すべき請求書の有無_成果物」ファイルに、No.19記載例に沿った内容（仕訳伝票No.、発生日、勘定科目、摘要、金額、3月に計上すべき費用か、会計処理の顛末/ 備考、修正した場合は伝票Noを記載）のすべての記載をお願い致します。2026年4月のTBは、Excelでお願い致します。 ●更新頂いたコメント「Inoueki Thailandにおける2026年3月、４月のJournal Voucher（原本：タイ語）について、Trial Balance（試算表）との突合を実施し、数値の一致を確認しております。 また、当該JVの内容を精査した結果、仕訳明細データの摘要欄等から、2026年3月に計上すべき費用がないことを確認済。」のみでは、自己点検として不十分ですし、監査人や我々第三者も検証が難しいです。 ●添付頂いた2026年4月のタイ語の仕訳伝票では、2026年4月の試算表に計上されている費用との一致が、網羅的に確認できません。 2.上記１の内容は、2026年4月単月の試算表と残高一致の確認ができるよう、資料のご準備をお願い致します。 なお、自主点検説明資料では、以下の確認項目がありますので、再度、ご確認ください。 1. 2026年4月に費用計上された仕訳の明細データを出⼒し、明細データの合計と試算表の⾦額が一致することを確かめる 2.仕訳明細データの摘要欄等から、2026年3月に計上すべき費用の有無を確認する 3. 2026年4月に受領した請求書から、2026年3月分として計上すべき取引がないかを確かめる 4. 2026年3月分として計上すべき費用について、根拠資料を整理し、会計処理の顛末を記載する | I1671: 未判定
A1672: 1671 | B1672: 自主点検QA | C1672: 17-123 | D1672: 170103 | E1672: =IFERROR(INDEX(会社マスタ!$B:$B,MATCH(D1672,会社マスタ!$A:$A,0)),"") -> Inoueki Singapore Pte. Ltd. | F1672: =IFERROR(INDEX(会社マスタ!$C:$C,MATCH(D1672,会社マスタ!$A:$A,0)),"") -> グローバル戦略推進本部 | G1672: 25 | H1672: ワークシート2-2で、前期・当期ともに営業赤字ですが翌期予算が営業利益予想のため減損の兆候なしとされています。 翌期予算資料を追加でご提示頂きたいのと、2期連続営業赤字にも関わらず翌期は大きな営業利益計画とされている根拠をご教示頂けますでしょうか。 | I1672: 未判定
... A1914: 1913 | B1914: 自主点検QA | C1914: 21-3 | D1914: 210104 | E1914: =IFERROR(INDEX(会社マスタ!$B:$B,MATCH(D1914,会社マスタ!$A:$A,0)),"") -> 嶋田工業(株) | F1914: =IFERROR(INDEX(会社マスタ!$C:$C,MATCH(D1914,会社マスタ!$A:$A,0)),"") -> 連結管理室 | G1914: 6 | H1914: 「06_売上・粗利月次推移分析_嶋田工業」上2025/4～2026/3までの売上の合計が約4,500百万円となっています。 一方「試算表2603_嶋田工業.pdf」上純売上高が4,712,446,337円と差異がございます。 そのため、「06_売上・粗利月次推移分析_嶋田工業」のデータソース及び抽出条件が分かる資料（画面コピーなど）をご提供ください。 (別途受領している「嶋田工業_売上明細データ」及び「05_売上マイナスデータ･売上の取消仕訳_嶋田工業」と「試算表2603_嶋田工業.pdf」とを照合すると一致は確認できます。） | I1914: 未判定
A1915: 1914 | B1915: 自主点検QA | C1915: 21-4 | D1915: 210104 | E1915: =IFERROR(INDEX(会社マスタ!$B:$B,MATCH(D1915,会社マスタ!$A:$A,0)),"") -> 嶋田工業(株) | F1915: =IFERROR(INDEX(会社マスタ!$C:$C,MATCH(D1915,会社マスタ!$A:$A,0)),"") -> 連結管理室 | G1915: 9 13 | H1915: 「進行基準適用判断_嶋田工業」上未成工事支出金の合計が814,200,755円となっています。(「滞留チェック_嶋田工業」も未成工事支出金の合計が814,200,755円となっています。 一方「試算表2603_嶋田工業.pdf」上未成工事支出金が814,208,134円と差異がございます。 そのため、当該差異について判明する資料をご提供ください。 | I1915: 未判定
A1916: 1915 | B1916: 自主点検QA | C1916: 21-5 | D1916: 210104 | E1916: =IFERROR(INDEX(会社マスタ!$B:$B,MATCH(D1916,会社マスタ!$A:$A,0)),"") -> 嶋田工業(株) | F1916: =IFERROR(INDEX(会社マスタ!$C:$C,MATCH(D1916,会社マスタ!$A:$A,0)),"") -> 連結管理室 | G1916: 11 | H1916: 「11_工事案件の購買・原材料入出庫データ分析_嶋田工業」の購買金額と、工事案件の原価明細で整合していることを確認できる資料をご提供ください。 | I1916: 未判定
...

Sheet チェックポイント-問合せ・差戻し事例対応表
A1: No | B1: チェックポイントNo | C1: 提出物No | D1: 提出物名 | E1: チェックポイント内容 | F1: 事例No | G1: ユニット | H1: 会社名 | I1: 会社管理番号 | J1: 自主点検項目No | K1: 問合せ事項
A2: 1 | B2: 1 | C2: =IFERROR(INDEX(チェックポイント!$D:$D,MATCH(B2,チェックポイント!$A:$A,0)),"") -> 15 | D2: =IFERROR(INDEX(チェックポイント!$E:$E,MATCH(B2,チェックポイント!$A:$A,0)),"") -> 売掛金明細・試算表の一致 | E2: =IFERROR(INDEX(チェックポイント!$F:$F,MATCH(B2,チェックポイント!$A:$A,0)),"") -> 成果物の作成に用いたデータソースと抽出条件（手順）の記録（画面コピー等）が提出されているか。 | F2: 26 | G2: =IFERROR(INDEX(問合せ・差戻し事例!$F:$F,MATCH(F2,問合せ・差戻し事例!$A:$A,0)),"") -> エア・ウォーター東日本(株) | H2: =IFERROR(INDEX(問合せ・差戻し事例!$E:$E,MATCH(F2,問合せ・差戻し事例!$A:$A,0)),"") -> 亀山液酸(株) | I2: =IFERROR(INDEX(問合せ・差戻し事例!$D:$D,MATCH(F2,問合せ・差戻し事例!$A:$A,0)),"") -> 230700 | J2: =IFERROR(INDEX(問合せ・差戻し事例!$G:$G,MATCH(F2,問合せ・差戻し事例!$A:$A,0)),"") -> 4 | K2: =IFERROR(INDEX(問合せ・差戻し事例!$H:$H,MATCH(F2,問合せ・差戻し事例!$A:$A,0)),"") -> ・データソース及び抽出条件が分かる資料（画面コピーなど）の送付をお願いします ・網羅性が確認できる資料（試算表との一致確認）の送付をお願いします
A3: 2 | B3: 1 | C3: =IFERROR(INDEX(チェックポイント!$D:$D,MATCH(B3,チェックポイント!$A:$A,0)),"") -> 15 | D3: =IFERROR(INDEX(チェックポイント!$E:$E,MATCH(B3,チェックポイント!$A:$A,0)),"") -> 売掛金明細・試算表の一致 | E3: =IFERROR(INDEX(チェックポイント!$F:$F,MATCH(B3,チェックポイント!$A:$A,0)),"") -> 成果物の作成に用いたデータソースと抽出条件（手順）の記録（画面コピー等）が提出されているか。 | F3: 28 | G3: =IFERROR(INDEX(問合せ・差戻し事例!$F:$F,MATCH(F3,問合せ・差戻し事例!$A:$A,0)),"") -> エア・ウォーター東日本(株) | H3: =IFERROR(INDEX(問合せ・差戻し事例!$E:$E,MATCH(F3,問合せ・差戻し事例!$A:$A,0)),"") -> (株)元気 | I3: =IFERROR(INDEX(問合せ・差戻し事例!$D:$D,MATCH(F3,問合せ・差戻し事例!$A:$A,0)),"") -> 231400 | J3: =IFERROR(INDEX(問合せ・差戻し事例!$G:$G,MATCH(F3,問合せ・差戻し事例!$A:$A,0)),"") -> 4 | K3: =IFERROR(INDEX(問合せ・差戻し事例!$H:$H,MATCH(F3,問合せ・差戻し事例!$A:$A,0)),"") -> ・データソース及び抽出条件が分かる資料（画面コピーなど）の送付をお願いします ・網羅性が確認できる資料（試算表との一致確認）の送付をお願いします
A4: 3 | B4: 1 | C4: =IFERROR(INDEX(チェックポイント!$D:$D,MATCH(B4,チェックポイント!$A:$A,0)),"") -> 15 | D4: =IFERROR(INDEX(チェックポイント!$E:$E,MATCH(B4,チェックポイント!$A:$A,0)),"") -> 売掛金明細・試算表の一致 | E4: =IFERROR(INDEX(チェックポイント!$F:$F,MATCH(B4,チェックポイント!$A:$A,0)),"") -> 成果物の作成に用いたデータソースと抽出条件（手順）の記録（画面コピー等）が提出されているか。 | F4: 52 | G4: =IFERROR(INDEX(問合せ・差戻し事例!$F:$F,MATCH(F4,問合せ・差戻し事例!$A:$A,0)),"") -> エア・ウォーター東日本(株) | H4: =IFERROR(INDEX(問合せ・差戻し事例!$E:$E,MATCH(F4,問合せ・差戻し事例!$A:$A,0)),"") -> エア・ウォーター東日本(株) | I4: =IFERROR(INDEX(問合せ・差戻し事例!$D:$D,MATCH(F4,問合せ・差戻し事例!$A:$A,0)),"") -> 230000 | J4: =IFERROR(INDEX(問合せ・差戻し事例!$G:$G,MATCH(F4,問合せ・差戻し事例!$A:$A,0)),"") -> 4 | K4: =IFERROR(INDEX(問合せ・差戻し事例!$H:$H,MATCH(F4,問合せ・差戻し事例!$A:$A,0)),"") -> ・データソース及び抽出条件が分かる資料（画面コピーなど）の送付をお願いします ・網羅性が確認できる資料（試算表との一致確認）の送付をお願いします ・成果物例に沿った形で送付お願いいたします
A5: 4 | B5: 1 | C5: =IFERROR(INDEX(チェックポイント!$D:$D,MATCH(B5,チェックポイント!$A:$A,0)),"") -> 15 | D5: =IFERROR(INDEX(チェックポイント!$E:$E,MATCH(B5,チェックポイント!$A:$A,0)),"") -> 売掛金明細・試算表の一致 | E5: =IFERROR(INDEX(チェックポイント!$F:$F,MATCH(B5,チェックポイント!$A:$A,0)),"") -> 成果物の作成に用いたデータソースと抽出条件（手順）の記録（画面コピー等）が提出されているか。 | F5: 61 | G5: =IFERROR(INDEX(問合せ・差戻し事例!$F:$F,MATCH(F5,問合せ・差戻し事例!$A:$A,0)),"") -> エア・ウォーター東日本(株) | H5: =IFERROR(INDEX(問合せ・差戻し事例!$E:$E,MATCH(F5,問合せ・差戻し事例!$A:$A,0)),"") -> (株)大森器械店 | I5: =IFERROR(INDEX(問合せ・差戻し事例!$D:$D,MATCH(F5,問合せ・差戻し事例!$A:$A,0)),"") -> 230600 | J5: =IFERROR(INDEX(問合せ・差戻し事例!$G:$G,MATCH(F5,問合せ・差戻し事例!$A:$A,0)),"") -> 4 | K5: =IFERROR(INDEX(問合せ・差戻し事例!$H:$H,MATCH(F5,問合せ・差戻し事例!$A:$A,0)),"") -> ・データソース及び抽出条件が分かる資料（画面コピーなど）の送付をお願いします ・網羅性が確認できる資料（試算表との一致確認）の送付をお願いします
A6: 5 | B6: 1 | C6: =IFERROR(INDEX(チェックポイント!$D:$D,MATCH(B6,チェックポイント!$A:$A,0)),"") -> 15 | D6: =IFERROR(INDEX(チェックポイント!$E:$E,MATCH(B6,チェックポイント!$A:$A,0)),"") -> 売掛金明細・試算表の一致 | E6: =IFERROR(INDEX(チェックポイント!$F:$F,MATCH(B6,チェックポイント!$A:$A,0)),"") -> 成果物の作成に用いたデータソースと抽出条件（手順）の記録（画面コピー等）が提出されているか。 | F6: 70 | G6: =IFERROR(INDEX(問合せ・差戻し事例!$F:$F,MATCH(F6,問合せ・差戻し事例!$A:$A,0)),"") -> エア・ウォーター東日本(株) | H6: =IFERROR(INDEX(問合せ・差戻し事例!$E:$E,MATCH(F6,問合せ・差戻し事例!$A:$A,0)),"") -> (株)環境技術センター | I6: =IFERROR(INDEX(問合せ・差戻し事例!$D:$D,MATCH(F6,問合せ・差戻し事例!$A:$A,0)),"") -> 230101 | J6: =IFERROR(INDEX(問合せ・差戻し事例!$G:$G,MATCH(F6,問合せ・差戻し事例!$A:$A,0)),"") -> 4 | K6: =IFERROR(INDEX(問合せ・差戻し事例!$H:$H,MATCH(F6,問合せ・差戻し事例!$A:$A,0)),"") -> ・データソース及び抽出条件が分かる資料（画面コピーなど）の提出してください ・網羅性が確認できる資料（試算表との一致確認）の提出してください
A7: 6 | B7: 1 | C7: =IFERROR(INDEX(チェックポイント!$D:$D,MATCH(B7,チェックポイント!$A:$A,0)),"") -> 15 | D7: =IFERROR(INDEX(チェックポイント!$E:$E,MATCH(B7,チェックポイント!$A:$A,0)),"") -> 売掛金明細・試算表の一致 | E7: =IFERROR(INDEX(チェックポイント!$F:$F,MATCH(B7,チェックポイント!$A:$A,0)),"") -> 成果物の作成に用いたデータソースと抽出条件（手順）の記録（画面コピー等）が提出されているか。 | F7: 79 | G7: =IFERROR(INDEX(問合せ・差戻し事例!$F:$F,MATCH(F7,問合せ・差戻し事例!$A:$A,0)),"") -> エア・ウォーター東日本(株) | H7: =IFERROR(INDEX(問合せ・差戻し事例!$E:$E,MATCH(F7,問合せ・差戻し事例!$A:$A,0)),"") -> エア・ウォーター・スマイル(株) | I7: =IFERROR(INDEX(問合せ・差戻し事例!$D:$D,MATCH(F7,問合せ・差戻し事例!$A:$A,0)),"") -> 230200 | J7: =IFERROR(INDEX(問合せ・差戻し事例!$G:$G,MATCH(F7,問合せ・差戻し事例!$A:$A,0)),"") -> 4 | K7: =IFERROR(INDEX(問合せ・差戻し事例!$H:$H,MATCH(F7,問合せ・差戻し事例!$A:$A,0)),"") -> ・データソース及び抽出条件が分かる資料（画面コピーなど）の提出してください ・網羅性が確認できる資料（試算表との一致確認）の提出してください ・回収が遅延している債権全てにつき、回収遅延理由の記載をお願いします
A8: 7 | B8: 1 | C8: =IFERROR(INDEX(チェックポイント!$D:$D,MATCH(B8,チェックポイント!$A:$A,0)),"") -> 15 | D8: =IFERROR(INDEX(チェックポイント!$E:$E,MATCH(B8,チェックポイント!$A:$A,0)),"") -> 売掛金明細・試算表の一致 | E8: =IFERROR(INDEX(チェックポイント!$F:$F,MATCH(B8,チェックポイント!$A:$A,0)),"") -> 成果物の作成に用いたデータソースと抽出条件（手順）の記録（画面コピー等）が提出されているか。 | F8: 83 | G8: =IFERROR(INDEX(問合せ・差戻し事例!$F:$F,MATCH(F8,問合せ・差戻し事例!$A:$A,0)),"") -> エア・ウォーター東日本(株) | H8: =IFERROR(INDEX(問合せ・差戻し事例!$E:$E,MATCH(F8,問合せ・差戻し事例!$A:$A,0)),"") -> 竹中運輸(株) | I8: =IFERROR(INDEX(問合せ・差戻し事例!$D:$D,MATCH(F8,問合せ・差戻し事例!$A:$A,0)),"") -> 230103 | J8: =IFERROR(INDEX(問合せ・差戻し事例!$G:$G,MATCH(F8,問合せ・差戻し事例!$A:$A,0)),"") -> 4 | K8: =IFERROR(INDEX(問合せ・差戻し事例!$H:$H,MATCH(F8,問合せ・差戻し事例!$A:$A,0)),"") -> ・データソース及び抽出条件が分かる資料（画面コピーなど）の提出してください
A9: 8 | B9: 1 | C9: =IFERROR(INDEX(チェックポイント!$D:$D,MATCH(B9,チェックポイント!$A:$A,0)),"") -> 15 | D9: =IFERROR(INDEX(チェックポイント!$E:$E,MATCH(B9,チェックポイント!$A:$A,0)),"") -> 売掛金明細・試算表の一致 | E9: =IFERROR(INDEX(チェックポイント!$F:$F,MATCH(B9,チェックポイント!$A:$A,0)),"") -> 成果物の作成に用いたデータソースと抽出条件（手順）の記録（画面コピー等）が提出されているか。 | F9: 93 | G9: =IFERROR(INDEX(問合せ・差戻し事例!$F:$F,MATCH(F9,問合せ・差戻し事例!$A:$A,0)),"") -> エア・ウォーター東日本(株) | H9: =IFERROR(INDEX(問合せ・差戻し事例!$E:$E,MATCH(F9,問合せ・差戻し事例!$A:$A,0)),"") -> エア・ウォーター東日本メディエス(株) | I9: =IFERROR(INDEX(問合せ・差戻し事例!$D:$D,MATCH(F9,問合せ・差戻し事例!$A:$A,0)),"") -> 230300 | J9: =IFERROR(INDEX(問合せ・差戻し事例!$G:$G,MATCH(F9,問合せ・差戻し事例!$A:$A,0)),"") -> 4 | K9: =IFERROR(INDEX(問合せ・差戻し事例!$H:$H,MATCH(F9,問合せ・差戻し事例!$A:$A,0)),"") -> ・データソース及び抽出条件が分かる資料（画面コピーなど）の提出してください
A10: 9 | B10: 1 | C10: =IFERROR(INDEX(チェックポイント!$D:$D,MATCH(B10,チェックポイント!$A:$A,0)),"") -> 15 | D10: =IFERROR(INDEX(チェックポイント!$E:$E,MATCH(B10,チェックポイント!$A:$A,0)),"") -> 売掛金明細・試算表の一致 | E10: =IFERROR(INDEX(チェックポイント!$F:$F,MATCH(B10,チェックポイント!$A:$A,0)),"") -> 成果物の作成に用いたデータソースと抽出条件（手順）の記録（画面コピー等）が提出されているか。 | F10: 104 | G10: =IFERROR(INDEX(問合せ・差戻し事例!$F:$F,MATCH(F10,問合せ・差戻し事例!$A:$A,0)),"") -> エア・ウォーター東日本(株) | H10: =IFERROR(INDEX(問合せ・差戻し事例!$E:$E,MATCH(F10,問合せ・差戻し事例!$A:$A,0)),"") -> (株)関茂助商店 | I10: =IFERROR(INDEX(問合せ・差戻し事例!$D:$D,MATCH(F10,問合せ・差戻し事例!$A:$A,0)),"") -> 230102 | J10: =IFERROR(INDEX(問合せ・差戻し事例!$G:$G,MATCH(F10,問合せ・差戻し事例!$A:$A,0)),"") -> 4 | K10: =IFERROR(INDEX(問合せ・差戻し事例!$H:$H,MATCH(F10,問合せ・差戻し事例!$A:$A,0)),"") -> ・データソース及び抽出条件が分かる資料（画面コピーなど）の提出してください ・網羅性が確認できる資料（試算表との一致確認）の提出してください
A11: 10 | B11: 1 | C11: =IFERROR(INDEX(チェックポイント!$D:$D,MATCH(B11,チェックポイント!$A:$A,0)),"") -> 15 | D11: =IFERROR(INDEX(チェックポイント!$E:$E,MATCH(B11,チェックポイント!$A:$A,0)),"") -> 売掛金明細・試算表の一致 | E11: =IFERROR(INDEX(チェックポイント!$F:$F,MATCH(B11,チェックポイント!$A:$A,0)),"") -> 成果物の作成に用いたデータソースと抽出条件（手順）の記録（画面コピー等）が提出されているか。 | F11: 107 | G11: =IFERROR(INDEX(問合せ・差戻し事例!$F:$F,MATCH(F11,問合せ・差戻し事例!$A:$A,0)),"") -> エア・ウォーター東日本(株) | H11: =IFERROR(INDEX(問合せ・差戻し事例!$E:$E,MATCH(F11,問合せ・差戻し事例!$A:$A,0)),"") -> エア・ウォーター・ミライ(株) | I11: =IFERROR(INDEX(問合せ・差戻し事例!$D:$D,MATCH(F11,問合せ・差戻し事例!$A:$A,0)),"") -> 230400 | J11: =IFERROR(INDEX(問合せ・差戻し事例!$G:$G,MATCH(F11,問合せ・差戻し事例!$A:$A,0)),"") -> 4 | K11: =IFERROR(INDEX(問合せ・差戻し事例!$H:$H,MATCH(F11,問合せ・差戻し事例!$A:$A,0)),"") -> ・データソース及び抽出条件が分かる資料（画面コピーなど）の提出してください ・網羅性が確認できる資料（試算表との一致確認）の提出してください ・回収が遅延している債権全てにつき、回収遅延理由の記載をお願いします ・回収遅延理由について、部門責任者等の適切な承認者の承認を得てください
A12: 11 | B12: 1 | C12: =IFERROR(INDEX(チェックポイント!$D:$D,MATCH(B12,チェックポイント!$A:$A,0)),"") -> 15 | D12: =IFERROR(INDEX(チェックポイント!$E:$E,MATCH(B12,チェックポイント!$A:$A,0)),"") -> 売掛金明細・試算表の一致 | E12: =IFERROR(INDEX(チェックポイント!$F:$F,MATCH(B12,チェックポイント!$A:$A,0)),"") -> 成果物の作成に用いたデータソースと抽出条件（手順）の記録（画面コピー等）が提出されているか。 | F12: 176 | G12: =IFERROR(INDEX(問合せ・差戻し事例!$F:$F,MATCH(F12,問合せ・差戻し事例!$A:$A,0)),"") -> エア・ウォーター北海道(株) | H12: =IFERROR(INDEX(問合せ・差戻し事例!$E:$E,MATCH(F12,問合せ・差戻し事例!$A:$A,0)),"") -> (株)北海道総合ガスセンター | I12: =IFERROR(INDEX(問合せ・差戻し事例!$D:$D,MATCH(F12,問合せ・差戻し事例!$A:$A,0)),"") -> 220600 | J12: =IFERROR(INDEX(問合せ・差戻し事例!$G:$G,MATCH(F12,問合せ・差戻し事例!$A:$A,0)),"") -> 4 | K12: =IFERROR(INDEX(問合せ・差戻し事例!$H:$H,MATCH(F12,問合せ・差戻し事例!$A:$A,0)),"") -> ・データソース及び抽出条件が分かる資料（画面コピーなど）の送付をお願いします ・網羅性が確認できる資料（試算表との一致確認）の送付をお願いします
A13: 12 | B13: 1 | C13: =IFERROR(INDEX(チェックポイント!$D:$D,MATCH(B13,チェックポイント!$A:$A,0)),"") -> 15 | D13: =IFERROR(INDEX(チェックポイント!$E:$E,MATCH(B13,チェックポイント!$A:$A,0)),"") -> 売掛金明細・試算表の一致 | E13: =IFERROR(INDEX(チェックポイント!$F:$F,MATCH(B13,チェックポイント!$A:$A,0)),"") -> 成果物の作成に用いたデータソースと抽出条件（手順）の記録（画面コピー等）が提出されているか。 | F13: 234 | G13: =IFERROR(INDEX(問合せ・差戻し事例!$F:$F,MATCH(F13,問合せ・差戻し事例!$A:$A,0)),"") -> 飲料ユニット | H13: =IFERROR(INDEX(問合せ・差戻し事例!$E:$E,MATCH(F13,問合せ・差戻し事例!$A:$A,0)),"") -> ゴールドパック(株) | I13: =IFERROR(INDEX(問合せ・差戻し事例!$D:$D,MATCH(F13,問合せ・差戻し事例!$A:$A,0)),"") -> 130100 | J13: =IFERROR(INDEX(問合せ・差戻し事例!$G:$G,MATCH(F13,問合せ・差戻し事例!$A:$A,0)),"") -> 4 | K13: =IFERROR(INDEX(問合せ・差戻し事例!$H:$H,MATCH(F13,問合せ・差戻し事例!$A:$A,0)),"") -> ・データソース及び抽出条件が分かる資料（画面コピーなど）の送付をお願いします
... A2442: 2441 | B2442: 188 | C2442: =IFERROR(INDEX(チェックポイント!$D:$D,MATCH(B2442,チェックポイント!$A:$A,0)),"") -> 共通 | D2442: =IFERROR(INDEX(チェックポイント!$E:$E,MATCH(B2442,チェックポイント!$A:$A,0)),"") | E2442: =IFERROR(INDEX(チェックポイント!$F:$F,MATCH(B2442,チェックポイント!$A:$A,0)),"") -> 賞与引当金の見積金額の根拠資料（繰入額の計算資料）が提出されているか。 | F2442: 543 | G2442: =IFERROR(INDEX(問合せ・差戻し事例!$F:$F,MATCH(F2442,問合せ・差戻し事例!$A:$A,0)),"") -> デンタルケアユニット | H2442: =IFERROR(INDEX(問合せ・差戻し事例!$E:$E,MATCH(F2442,問合せ・差戻し事例!$A:$A,0)),"") -> (株)デンタルフィット | I2442: =IFERROR(INDEX(問合せ・差戻し事例!$D:$D,MATCH(F2442,問合せ・差戻し事例!$A:$A,0)),"") -> 100204 | J2442: =IFERROR(INDEX(問合せ・差戻し事例!$G:$G,MATCH(F2442,問合せ・差戻し事例!$A:$A,0)),"") -> 26 | K2442: =IFERROR(INDEX(問合せ・差戻し事例!$H:$H,MATCH(F2442,問合せ・差戻し事例!$A:$A,0)),"") -> 追加のご依頼で恐縮ですが、当期中に支払った賞与確定額について、その決定方法及び計算過程のわかる規程及び集計資料をご共有いただけますと幸いです。 （追記） 備考に記載の通り、別途検討の結果、こちら不要となりましたので、ご放念ください。大変失礼いたしました。

Sheet 会社マスタ
A1: 会社管理番号 | B1: 会社名 | C1: 担当ユニット | D1: 構成単位
A2: 00 | B2: エア・ウォーター(株) | C2: AWI本体 | D2: ○
A3: 210100 | B3: (株)松尾ホールディングス | C3: 連結管理室 | D3: ○
A4: 210101 | B4: (株)アーステクノ | C4: 連結管理室
A5: 210102 | B5: (株)オートテック | C5: 連結管理室
A6: 210103 | B6: (株)クレアス | C6: 連結管理室
A7: 210104 | B7: 嶋田工業(株) | C7: 連結管理室
A8: 210105 | B8: (株)松尾組 | C8: 連結管理室
A9: 210106 | B9: (株)松尾都市開発 | C9: 連結管理室
A10: 210107 | B10: (株)松尾道路 | C10: 連結管理室
A11: 210108 | B11: (株)松尾環境 | C11: 連結管理室
A12: 100100 | B12: デンケン・ハイデンタル(株) | C12: デンタルケアユニット | D12: ○
A13: 100101 | B13: KDF U.S., Inc. | C13: デンタルケアユニット
A14: 100200 | B14: (株)歯愛メディカル | C14: デンタルケアユニット | D14: ○
A15: 100201 | B15: (株)サクラ歯研 | C15: デンタルケアユニット
A16: 100202 | B16: (株)Ciロジスティクスセンター | C16: デンタルケアユニット
A17: 100203 | B17: (株)デミライン | C17: デンタルケアユニット
A18: 100204 | B18: (株)デンタルフィット | C18: デンタルケアユニット
A19: 100205 | B19: (株)ナイキ歯研 | C19: デンタルケアユニット
A20: 100206 | B20: (株)ニッセン | C20: デンタルケアユニット | D20: ○
A21: 100207 | B21: (株)ニッセンホールディングス | C21: デンタルケアユニット
A22: 100208 | B22: (株)ニッセンライフ | C22: デンタルケアユニット
A23: 100209 | B23: (株)ニッセンLINX | C23: デンタルケアユニット
A24: 100210 | B24: (株)マロンスタイル | C24: デンタルケアユニット
A25: 100211 | B25: (株)RayVision | C25: デンタルケアユニット
A26: 100212 | B26: (株)白鳩 | C26: デンタルケアユニット | D26: ○
A27: 100213 | B27: (株)TDS | C27: デンタルケアユニット
A28: 100214 | B28: (株)クラブメディア | C28: デンタルケアユニット
A29: 100215 | B29: (株)Ciエナジー | C29: デンタルケアユニット
A30: 100216 | B30: (株)u&n | C30: デンタルケアユニット
A31: 100217 | B31: 上海妮尚商貿有限公司 | C31: デンタルケアユニット
A32: 100218 | B32: Ci Korea Co., Ltd | C32: デンタルケアユニット
A33: 100219 | B33: ニッセン・クレジットサービス(株) | C33: デンタルケアユニット
A34: 240000 | B34: エア・ウォーター西日本(株) | C34: エア・ウォーター西日本(株) | D34: ○
A35: 240100 | B35: エア・ウォーター西日本メディエス(株) | C35: エア・ウォーター西日本(株)
A36: 240200 | B36: (株)エコテック | C36: エア・ウォーター西日本(株)
A37: 240300 | B37: 福山液酸(株) | C37: エア・ウォーター西日本(株)
A38: 240400 | B38: 松山酸素(株) | C38: エア・ウォーター西日本(株) | D38: ○
A39: 240500 | B39: 沖縄エア・ウォーター(株) | C39: エア・ウォーター西日本(株)
A40: 240600 | B40: 熊本液酸(株) | C40: エア・ウォーター西日本(株)
A41: 240700 | B41: 長崎液酸(株) | C41: エア・ウォーター西日本(株)
A42: 240800 | B42: (株)日本医療環境サービス | C42: エア・ウォーター西日本(株) | D42: ○
A43: 240900 | B43: (株)ニライカナイ | C43: エア・ウォーター西日本(株)
A44: 241000 | B44: (株)南九州ガスセンター | C44: エア・ウォーター西日本(株)
A45: 241100 | B45: (株)アイ・ジー・エム | C45: エア・ウォーター西日本(株)
A46: 241200 | B46: (株)大牟田高圧ガスセンター | C46: エア・ウォーター西日本(株)
A47: 241300 | B47: ステリフィリング九州(株) | C47: エア・ウォーター西日本(株)
A48: 241400 | B48: 大平産業(株) | C48: エア・ウォーター西日本(株)
A49: 241500 | B49: (株)鳥取若葉台窒素ガスセンター | C49: エア・ウォーター西日本(株)
A50: 241600 | B50: 舞鶴大同ガス(株) | C50: エア・ウォーター西日本(株)
A51: 241700 | B51: 森脇産業(株) | C51: エア・ウォーター西日本(株)
A52: 240201 | B52: Hyogo Gas Supply Center(株) | C52: エア・ウォーター西日本(株)
A53: 240401 | B53: (株)イナートガスセンター | C53: エア・ウォーター西日本(株)
A54: 230000 | B54: エア・ウォーター東日本(株) | C54: エア・ウォーター東日本(株) | D54: ○
A55: 230100 | B55: エア・ウォーター東日本マネジメント(株) | C55: エア・ウォーター東日本(株)
A56: 230200 | B56: エア・ウォーター・スマイル(株) | C56: エア・ウォーター東日本(株)
A57: 230300 | B57: エア・ウォーター東日本メディエス(株) | C57: エア・ウォーター東日本(株)
A58: 230400 | B58: エア・ウォーター・ミライ(株) | C58: エア・ウォーター東日本(株)
A59: 230500 | B59: 岩手液酸(株) | C59: エア・ウォーター東日本(株)
A60: 230600 | B60: (株)大森器械店 | C60: エア・ウォーター東日本(株) | D60: ○
A61: 230700 | B61: 亀山液酸(株) | C61: エア・ウォーター東日本(株)
A62: 230800 | B62: 相模原液酸(株) | C62: エア・ウォーター東日本(株)
A63: 230900 | B63: 静岡液酸(株) | C63: エア・ウォーター東日本(株)
A64: 231000 | B64: 東海液酸(株) | C64: エア・ウォーター東日本(株)
A65: 231100 | B65: 新潟液酸(株) | C65: エア・ウォーター東日本(株)
A66: 231200 | B66: 福島液酸(株) | C66: エア・ウォーター東日本(株)
A67: 231300 | B67: 山形液酸(株) | C67: エア・ウォーター東日本(株)
A68: 231400 | B68: (株)元気 | C68: エア・ウォーター東日本(株)
A69: 231500 | B69: (株)関東ガスサービス | C69: エア・ウォーター東日本(株)
A70: 231600 | B70: (株)伊勢ガスセンター | C70: エア・ウォーター東日本(株)
A71: 231700 | B71: (株)エイチ・エー・ダブリュー・ガスセンター | C71: エア・ウォーター東日本(株)
A72: 231800 | B72: 岐阜エア・ウォーター(株) | C72: エア・ウォーター東日本(株)
... A86: 231401 | B86: 青果流通機構(株) | C86: エア・ウォーター東日本(株)
A87: 220000 | B87: エア・ウォーター北海道(株) | C87: エア・ウォーター北海道(株) | D87: ○
A88: 220100 | B88: エア・ウォーター産業・医療ガス（株） | C88: エア・ウォーター北海道(株) | D88: ○
A89: 220200 | B89: エア・ウォーター・ライフソリューション(株) | C89: エア・ウォーター北海道(株) | D89: ○
A90: 220300 | B90: エア・ウォーター・ラボアンドフーズ(株) | C90: エア・ウォーター北海道(株)
A91: 220400 | B91: (株)札幌デンタル・ラボラトリー | C91: デンタルケアユニット | D91: ○
A92: 220500 | B92: (株)ホクエイ | C92: エア・ウォーター北海道(株) | D92: ○
A93: 220600 | B93: (株)北海道総合ガスセンター | C93: エア・ウォーター北海道(株)
A94: 220700 | B94: 小樽ガスセンター(株) | C94: エア・ウォーター北海道(株)
A95: 220800 | B95: (株)オートガスステーション札幌(解散中) | C95: エア・ウォーター北海道(株)
A96: 220101 | B96: 伊並産業(株) | C96: エア・ウォーター北海道(株)
A97: 220201 | B97: 旭川エナジック(株) | C97: エア・ウォーター北海道(株)
A98: 220202 | B98: 空知エナジック(株) | C98: エア・ウォーター北海道(株)
A99: 220203 | B99: 滝川ガス(株) | C99: エア・ウォーター北海道(株)
A100: 220204 | B100: 函館エナジック(株) | C100: エア・ウォーター北海道(株)
A101: 040100 | B101: エア・ウォーター・エンジニアリング(株) | C101: グローバルエンジニアリングユニット | D101: ○
A102: 040200 | B102: AIR WATER INDIA PRIVATE LIMITED | C102: グローバルエンジニアリングユニット | D102: ○
A103: 040300 | B103: AIR WATER VIETNAM CO., LTD. | C103: グローバルエンジニアリングユニット | D103: ○
A104: 040400 | B104: AIR WATER AMERICA INC. | C104: グローバルエンジニアリングユニット | D104: ○
A105: 040600 | B105: Power Partners Private Limited | C105: グローバルエンジニアリングユニット | D105: ○
A106: 040700 | B106: M1 Engineering Holdings Limited | C106: グローバルエンジニアリングユニット
A107: 040800 | B107: Taylor-Wharton Malaysia Sdn. Bhd. | C107: グローバルエンジニアリングユニット | D107: ○
A108: 040900 | B108: 爱沃特气体 (厦门) 有限公司 | C108: グローバルエンジニアリングユニット
A109: 040401 | B109: AIR WATER GAS SOLUTIONS INC. | C109: グローバルエンジニアリングユニット | D109: ○
A110: 040402 | B110: American Gas Products, Inc. | C110: グローバルエンジニアリングユニット | D110: ○
A111: 040406 | B111: Arizona Air Pro, LLC | C111: グローバルエンジニアリングユニット
A112: 040403 | B112: Noble Gas Solutions, LLC | C112: グローバルエンジニアリングユニット | D112: ○
A113: 040405 | B113: Phoenix Welding Supply LLC | C113: グローバルエンジニアリングユニット | D113: ○
...

Sheet 成果物イメージ_No.4
K1: 単位：百万円
A2: Sample | B2: 売掛金明細 | F2: 追記箇所
A3: No. | B3: 取引先コード | C3: 取引先名 | D3: 繰越残高 | E3: 残高 | F3: 通常回収サイト | G3: 取引発生日 | H3: 回収予定日 | I3: 滞留 | J3: 最新の回収予定日 | K3: 回収遅延理由（合理的でない場合、売上の妥当性をコメント）
A4: 1 | B4: 1 | C4: A社 | D4: 100 | E4: 100 | F4: 2か月 | G4: 45933 | H4: 46022 | I4: ○ | J4: 46173 | K4: 取引No.1001に係る債権が滞留している。回収遅延理由は、先方の指定書式での必須提出書類の漏れにより請求ができていなかったためである。なお、当該理由については部門責任者の承認を得ている。 この点、対象取引の契約書、注文書、納品書にて、取引発生日や取引金額の一致を確認し、売上計上の妥当性に問題はないと判断した。
A5: 2 | B5: 2 | C5: B社 | D5: 200 | E5: 200 | F5: 4か月 | G5: 46005 | H5: 46142
A6: 3 | B6: 3 | C6: C社 | D6: 100 | E6: 100 | F6: 3か月 | G6: 46047 | H6: 46142
A7: 4 | B7: 4 | C7: D社 | D7: 500 | E7: 500 | F7: 1か月 | G7: 46080 | H7: 46112 | I7: ○ | J7: 46142 | K7: 取引No.1023に係る債権が滞留している。回収遅延理由は月末付近の取引であったことから請求書の到着が遅延したためである。なお、当該理由については部門責任者の承認を得ている。 この点、既に請求書を発送しており、4/30に回収予定であることから問題ないと判断した。
A8: 5 | B8: 5 | C8: E社 | D8: 0 | E8: 90 | F8: 3か月 | G8: 46105 | H8: 46203
D9: 合計 | E9: 990
D10: 試算表金額 | E10: 990
D11: 差異 | E11: 0

Sheet 成果物イメージ_No.5
A1: Sample No. | B1: 取引先名 | C1: 案件名 | D1: 伝票番号 | E1: 計上日 | F1: 売上金額 | G1: 検証コメント | H1: 会計処理の顛末
A2: 1 | B2: Tフーズ株式会社 | C2: 冷凍倉庫監視システム | D2: SL2510-0400 | E2: 45955 | F2: 18000000
A3: 2 | B3: V商事株式会社 | C3: サーバーラック 10台 | D3: SL2511-0300 | E3: 45971 | F3: 5000000 | G3: 計上から5日後に一部金額が取り消されている。調査の結果、納品した10台のうち2台に輸送中の破損があり、顧客検収時に返品されたことが判明。返品受入報告書および顧客との協議メールを確認 | H3: 破損した2台分（1,000,000円）の売上を11/15付で取り消す修正仕訳（No. SL2511-0350）を起票。事業上合理的な取引と判断
A4: 3 | B4: V商事株式会社 | C4: サーバーラック 10台 | D4: SL2511-0350 | E4: 45976 | F4: -1000000 | G4: （上記 SL2511-0300 の一部取消仕訳） | H4: （同上）
A5: 4 | B5: V商事株式会社 | C5: ソフトウェアライセンス | D5: SL2602-0150 | E5: 46073 | F5: 7500000
A6: 5 | B6: W建設株式会社 | C6: 建設資材（セメント）納品 | D6: SL2601-0880 | E6: 46052 | F6: 23000000
A7: 6 | B7: Y工業株式会社 | C7: プラント保守部品 | D7: SL2512-0480 | E7: 46006 | F7: 8000000 | G7: 計上から5日後に全額が取り消されている。顧客Y工業への確認および返品受入報告書の照合により、「納品部品の仕様違いによる返品」であることが確認された | H7: 顧客との合意に基づき、12/20付で売上取消の修正仕訳（No. SL2512-0511）を起票。代替品は翌月に納品・売上計上済みであり、事業上合理的な取引と判断
A8: 7 | B8: Y工業株式会社 | C8: プラント保守部品 | D8: SL2512-0511 | E8: 46011 | F8: -8000000 | G8: （上記 SL2512-0480 の取消仕訳） | H8: （同上）
A9: 8 | B9: Y工業株式会社 | C9: プラント保守部品 | D9: SL2601-0151 | E9: 46047 | F9: 8000000 | G9: （上記 SL2512-0480 の再計上） | H9: （同上）
A10: 9 | B10: 株式会社Z | C10: システム保守サービス | D10: SL2509-0210 | E10: 45915 | F10: 12000000

Sheet 成果物イメージ_No.6
A1: 月 | B1: 【26/3】 売上 (百万円) | C1: 【26/3】 粗利 (百万円) | D1: 【25/3】 売上 (百万円) | E1: 【25/3】 粗利 (百万円) | F1: 増減コメント | H1: Sample No. | I1: 月 | J1: 【26/3】 売上 (百万円) | K1: 【26/3】 粗利 (百万円) | L1: 【25/3】 売上 (百万円) | M1: 【25/3】 粗利 (百万円) | N1: 売上前月比 | O1: 粗利前月比 | P1: 売上前年 同月比 | Q1: 粗利前年 同月比 | R1: 増減分析コメント】
A2: 4月 | B2: 215 | C2: 52 | D2: 200 | E2: 53.8 | H2: 1 | I2: 4月 | J2: 215 | K2: 53.8 | L2: 200 | M2: 52 | N2: - | O2: - | P2: 1.08 | Q2: 1.03
A3: 5月 | B3: 230 | C3: 52.5 | D3: 210 | E3: 59.8 | H3: 2 | I3: 5月 | J3: 260 | K3: 72.8 | L3: 205 | M3: 51.3 | N3: 1.21 | O3: 1.3531599 | P3: 1.27 | Q3: 1.42 | R3: ・【前年比/前月比】4月に発表した高付加価値の新製品『△△』の初回ロット出荷が集中し、売上・粗利率ともに大きく伸長（+50M）
A4: 6月 | B4: 350 | C4: 82.5 | D4: 330 | E4: 84 | F4: ・上半期（4-9月）の販売目標達成に向け、営業部門が主要顧客への先行納品やキャンペーンを6月に集中させたことで、売上が増加した（100M） | H4: 3 | I4: 6月 | J4: 350 | K4: 84 | L4: 330 | M4: 82.5 | N4: 1.35 | O4: 1.1538462 | P4: 1.06 | Q4: 1.02 | R4: ・【前月比】主要代理店からの四半期末発注（駆け込み需要）が集中（+85M） ・前年同様のトレンド
A5: 7月 | B5: 245 | C5: 62.1 | D5: 230 | E5: 68.6 | H5: 4 | I5: 7月 | J5: 245 | K5: 68.6 | L5: 230 | M5: 62.1 | N5: 0.7 | O5: 0.81666667 | P5: 1.07 | Q5: 1.1 | R5: ・前年同様のトレンド
A6: 8月 | B6: 225 | C6: 60.2 | D6: 215 | E6: 60.8 | H6: 5 | I6: 8月 | J6: 225 | K6: 60.8 | L6: 215 | M6: 60.2 | N6: 0.92 | O6: 0.88629738 | P6: 1.05 | Q6: 1.01
A7: 9月 | B7: 380 | C7: 86.4 | D7: 360 | E7: 87.4 | F7: ・設備投資予算の消化を目的とした大口発注が中間決算期に集中した（50M） ・下期から本格稼働する大規模な建設プロジェクトや設備更新案件に関する部材受注により、9月の売上が増加した（100M） | H7: 6 | I7: 9月 | J7: 380 | K7: 87.4 | L7: 360 | M7: 86.4 | N7: 1.69 | O7: 1.4375 | P7: 1.06 | Q7: 1.01 | R7: ・【前月比】大口顧客A社向けプラント設備の中間納品が計画通り行われ、売上が増加（+150M）
A8: 10月 | B8: 280 | C8: 75.6 | D8: 270 | E8: 81.2 | H8: 7 | I8: 10月 | J8: 220 | K8: 52.8 | L8: 270 | M8: 75.6 | N8: 0.58 | O8: 0.60411899 | P8: 0.81 | Q8: 0.7 | R8: ・【前年比/前月比】半導体部品のサプライヤーからの納入が世界的に遅延した影響で、主力製品『〇〇』の生産が滞り、出荷が一部翌月以降にずれ込み（-15M）
A9: 11月 | B9: 310 | C9: 78.3 | D9: 290 | E9: 80.6 | H9: 8 | I9: 11月 | J9: 310 | K9: 80.6 | L9: 290 | M9: 78.3 | N9: 1.41 | O9: 1.5265152 | P9: 1.07 | Q9: 1.03 | R9: ・【前月比】前月の部品供給遅延による生産遅延が解消し、10月からの繰り越し分を含めて出荷が回復（+80M）
